Workbook

Sheet Scoring Sheet
B1: Usage Questions [scored] | V1: Knowledge Questions [scored] | AG1: Prompting Questions [scored] | AU1: Overall Score | AX1: Behavioral Questions [unscored] | BT1: Demographic Questions [unscored]
AU2: Prompting | AW2: 2
A3: Weight | C3: 0.5 | F3: 1.5 | H3: 1 | J3: 1 | O3: 2 | T3: 4 | W3: 2 | Y3: 2 | AA3: 2 | AC3: 2 | AE3: 2 | AF3: =sum(V3:AE3) -> 10 | AH3: 1.5 | AM3: 3.5 | AR3: 5 | AU3: Knowledge | AW3: 1
A4: Potential Points | C4: 1 | F4: 1 | H4: 1 | J4: 1 | O4: 1 | T4: 1 | W4: 1 | Y4: 1 | AA4: 1 | AC4: 1 | AE4: 1 | AH4: 1 | AM4: 1 | AR4: 1 | AU4: Usage | AW4: 2
K5: {{QUESTION 5 RESPONSE}} | P5: {{QUESTION 6 RESPONSE}} | AI5: {{QUESTION 13 RESPONSE}} | AN5: {{QUESTION 14 RESPONSE}}
A6: ='Raw Data'!$A2 -> Participant Identifier | B6: ='Raw Data'!$R2 -> How often do you use AI tools for work-related tasks? | C6: SCORE | D6: ='Raw Data'!$S2 -> Which of the following best describes how you typically use AI at work? Select all that apply. | E6: SCORE | F6: SCORE (out of 1) | G6: ='Raw Data'!$T2 -> Which best describes your AI usage patterns at work? | H6: SCORE | I6: ='Raw Data'!$U2 -> You need to create a monthly performance summary. How would you use AI for this task? | J6: SCORE | K6: ='Raw Data'!V2 -> You have one week to create an important presentation for senior stakeholders on an unfamiliar topic. How would you use AI in this process? If you wouldn't use AI, please state that. | L6: TEXT: You have one week to create an important presentation for senior stakeholders on an unfamiliar topic. How would you use AI in this process? If you wouldn't use AI, please state that. | M6: TEMPLATE: You have one week to create an important presentation for senior stakeholders on an unfamiliar topic. How would you use AI in this process? If you wouldn't use AI, please state that. | N6: SCORE | O6: SCORE (out of 1) | P6: ='Raw Data'!$W2 -> What is the most useful or valuable way you are using AI in your work? | Q6: TEXT: What is the most useful or valuable way you are using AI in your work? | R6: TEMPLATE: What is the most useful or valuable way you are using AI in your work? | S6: SCORE | T6: SCORE (out of 1) | U6: OVERALL SCORE (out of 10) | V6: ='Raw Data'!$X2 -> Which task would current AI tools (like ChatGPT, Copilot, or Gemini) handle most effectively? | W6: SCORE | X6: ='Raw Data'!$Y2 -> Which of the following are the main risks of using current LLMs? Select all that apply. | Y6: SCORE | Z6: ='Raw Data'!$Z2 -> How can you best protect sensitive information when using AI tools? Select all that apply. | AA6: SCORE | AB6: ='Raw Data'!AA2 -> How often do you verify or fact-check AI-generated content before finalizing or sharing it? | AC6: SCORE | AD6: ='Raw Data'!$AB2 -> When fact-checking AI-generated content, which approaches would be helpful? Select all that apply. | AE6: SCORE | AF6: OVERALL SCORE (out of 10) | AG6: ='Raw Data'!$AC2 -> When you use AI, how often do you refine or iterate on your prompts to improve the output? | AH6: SCORE | AI6: ='Raw Data'!$AD2 -> DRILL 1: Imagine you are preparing for a work meeting to discuss a new initiative or proposal. Write a prompt asking AI to help you prepare for this meeting. | AJ6: TEXT: DRILL 1: Imagine you are preparing for a work meeting to discuss a new initiative or proposal. Write a prompt asking AI to help you prepare for this meeting. | AK6: TEMPLATE: DRILL 1: Imagine you are preparing for a work meeting to discuss a new initiative or proposal. Write a prompt asking AI to help you prepare for this meeting. | AL6: SCORE | AM6: SCORE (out of 1) | AN6: ='Raw Data'!$AE2 -> DRILL 2: Your team frequently researches competitors' products, pricing, and positioning. You want to create a Custom GPT (or Copilot Agent/Google Gem) for this task. Write instructions for this custom AI tool that would help team members gather competitive intelligence consistently. | AO6: TEXT: DRILL 2: Your team frequently researches competitors' products, pricing, and positioning. You want to create a Custom GPT (or Copilot Agent/Google Gem) for this task. Write instructions for this custom AI tool that would help team members gather competitive intelligence consistently. | AP6: TEMPLATE: DRILL 2: Your team frequently researches competitors' products, pricing, and positioning. You want to create a Custom GPT (or Copilot Agent/Google Gem) for this task. Write instructions for this custom AI tool that would help team members gather competitive intelligence consistently. | AQ6: SCORE | AR6: SCORE (out of 1) | AS6: OVERALL SCORE (out of 10) | AT6: OVERALL SCORE NORMALIZED (out of 10) | AU6: OVERALL SCORE (out of 50) | AW6: Rating | AX6: ='Raw Data'!AF2 -> Which LLMs are you currently using? Select all that apply. | AY6: ='Raw Data'!AG2 -> Do you personally pay for access to any of these AI tools? | AZ6: ='Raw Data'!AH2 -> Does your company have an AI strategy? | BA6: ='Raw Data'!AI2 -> Do you know what AI tools are available at your company and how to access them? | BB6: ='Raw Data'!AJ2 -> What has your company deployed? | BC6: ='Raw Data'!AK2 -> How satisfied are you with the AI tool(s) your company has deployed? | BD6: ='Raw Data'!AL2 -> How well has your company translated its AI strategy into specific usage policies for employees? | BE6: ='Raw Data'!AM2 -> How would you describe your company’s AI usage policies? | ... BR6: ='Raw Data'!AZ2 -> Which statement best describes the impact AI is having on your work? | BS6: ='Raw Data'!D2 -> Which of the following best describes your current employment status? | BT6: ='Raw Data'!E2 -> What industry best describes where you currently work? | BU6: ='Raw Data'!F2 -> What function best describes your current role? | BV6: ='Raw Data'!G2 -> Subfunction (Team) | BW6: Perfect Draft | BX6: Perfect Draft Sub Functions | BY6: ='Raw Data'!J2 -> Which of the following best describes your current job level within your organization? | BZ6: ='Raw Data'!K2 -> How many employees work at your company? | CA6: ='Raw Data'!L2 -> Where do you currently reside? | CB6: ='Raw Data'!M2 -> World | CC6: ='Raw Data'!N2 -> Company | CD6: ='Raw Data'!O2 -> Head + Subfunction | CE6: ='Raw Data'!P2 -> User Level | CF6: ='Raw Data'!Q2 -> User Usage Categorization L30D
A7: ='Raw Data'!$A3 -> 1 | B7: ='Raw Data'!$R3 -> Daily | C7: =if($B7="Never or rarely",0,if($B7="A few times a month",0.25,if($B7="Weekly",0.5,if($B7="Several times a week",0.75,if($B7="Daily",1))))) -> 1 | D7: ='Raw Data'!$S3 -> Using AI for vibe coding to prototype solutions, apps, or products, Building custom prompts, templates, or workflows that I reuse regularly, Brainstorming ideas, testing concepts, or getting feedback on my thinking, Analyzing data or documents to extract insights or summaries, Writing or debugging code, scripts, or formulas, Creating first drafts of content from scratch (reports, proposals, marketing copy), Editing or improving text I’ve already written (emails, documents, presentations), Getting quick answers to specific questions or looking up information | E7: =if(isnumber(search("I don't use AI for work",$D7)),0,if(or(isnumber(search("Vibe Coding",$D7)),isnumber(search("custom prompts",$D7))),3,if(or(isnumber(search("brainstorming ideas",$D7)),isnumber(search("analyzing data",$D7)),isnumber(search("Creating first drafts",$D7))),2,1))) -> 3 | F7: =$E7/3 -> 1 | G7: ='Raw Data'!T3 -> I’ve created workflows that connect AI with other systems (Slack, Salesforce, email) using integrations or code | H7: =if($G7="I don't use AI for work",0,if($G7="I create fresh prompts each time I use AI",0.25,if($G7="I maintain a library of prompts that I reuse frequently",0.5,if($G7="I’ve built custom AI tools (CustomGPTs, Copilot Agents, Google Gems, Claude Projects) for repetitive tasks",0.75,if($G7="I’ve created workflows that connect AI with other systems (Slack, Salesforce, email) using integrations or code",1))))) -> 1 | I7: ='Raw Data'!$U3 -> Create a systematic process where AI handles data analysis and summary generation consistently | J7: =if($I7="I wouldn’t use AI for this task",0,if($I7="Ask AI to write the summary after you’ve analyzed all the data",0.33,if($I7="Use AI to help analyze each data source, then compile results manually",0.67,if($I7="Create a systematic process where AI handles data analysis and summary generation consistently",1)))) -> 1 | K7: ='Raw Data'!$V3 -> Criar um prompt com uma base de informações que eu tenho de conhecimento e determinar uma lógica fluida para a geração da apresentação executiva e pedir que me traga perguntas para que eu possa ir trazendo as informações que tenho conhecimento e pedir que a IA atue como um especialista na área, através de um GPT, por exemplo, consigo subir arquivos para que possam ser usados como fonte de informação | L7: Criar um prompt com uma base de informações que eu tenho de conhecimento e determinar uma lógica fluida para a geração da apresentação executiva e pedir que me traga perguntas para que eu possa ir trazendo as informações que tenho conhecimento e pedir que a IA atue como um especialista na área, através de um GPT, por exemplo, consigo subir arquivos para que possam ser usados como fonte de informação | M7: =substitute('Prompt Template'!$A$2,$K$5,$L7) -> You are an expert evaluator of AI strategic thinking and workflow integration. Your goal is to evaluate how effectively survey respondents demonstrate strategic AI application based on their response to the question: “You have one week to create an important presentation for senior stakeholders on an unfamiliar topic. How would you use AI in this process?” Evaluate each response holistically across three key areas: Workflow Integration: Effective responses demonstrate systematic thinking by identifying multiple stages of the presentation process where AI can add value (research, analysis, content creation, structure, review, etc.). They show understanding that complex projects benefit from AI integration at various points rather than just using AI for one isolated task. Strategic Application: Strong responses show context-aware AI usage that specifically addresses the unique challenges of this scenario — leveraging AI to quickly understand an unfamiliar topic, tailoring content for senior stakeholders, and managing time constraints effectively. They go beyond generic AI applications to show thoughtful consideration of the specific requirements. Practical Execution: Quality responses demonstrate concrete understanding of how AI tools actually work by providing specific, actionable approaches rather than vague descriptions. They show familiarity with AI capabilities and limitations, and describe realistic implementation steps. Scoring Guidelines Score 3 — Strong strategic thinking • Demonstrates comprehensive AI integration across most or all key workflow stages (e.g., research, structure, content creation, context tailoring for senior stakeholders, review), combined with clear scenario awareness and practical execution. • Responses do not need to mention every single stage explicitly; concise or list-style answers can still score a 3 if they show a strategically complete, end-to-end approach that addresses the scenario’s unique challenges (unfamiliar topic, senior stakeholders, tight timelines). • Omitting one stage (e.g., review) does not disqualify a response if the overall strategy is robust and well-adapted. • Both structured and concise list-style responses are valid. Examples: • “Research topic comprehensively, analyze stakeholder needs, create presentation framework, develop content, review for clarity.” • “Use AI throughout the process — from initial research to final presentation polish — focusing on what senior stakeholders care about most.” • “I would use AI to research the topic, understand key stakeholder concerns, create a logical flow, and draft compelling content for senior leadership within the time constraint.” • “Scan unfamiliar topic, outline slides, tailor framing for executives, draft key content, fact-check and polish.” (Concise list-style example demonstrating full coverage) • “Research unfamiliar topic, structure the deck, tailor for executives, draft content.” (Covers most strategic stages, omits review but is still strategically comprehensive) Score 2 — Moderate strategic thinking • Demonstrates partial but not comprehensive coverage of the key strategic dimensions. • Typically covers two to three workflow stages (e.g., structure + content + some context) but omits one or more major elements such as research, scenario adaptation, or review. • May show good workflow integration but limited scenario context, or vice versa. • Responses may be clear and practical but reflect a mid-level strategic approach rather than end-to-end planning. Examples: • “Use AI to quickly understand the topic, then create an outline and draft the presentation content.” • “Research phase, analysis phase, content creation phase, review phase.” • “Use AI to help research industry trends and create slides tailored for executives.” • “Draft speaker notes, executive framing, summarize key sources.” (Covers content, some research, and context but lacks structure/review) • “10 slide structure, add citations, executive framing.” (Structure, review, context but no research/content creation) Score 1 — Limited strategic thinking • Shows basic or single AI application with little reference to workflow complexity or scenario context. • Generic AI usage that could apply to any presentation task. Examples: • “Use AI to research the topic and create slides.” • “ChatGPT for research, help with structure.” • “Research, writing, editing.” • “Ask AI to help me understand the topic.” Score 0 — No relevant response • No answer, states they wouldn’t use AI, or provides irrelevant content. Special Guidance on Format and Brevity • Do not penalize for response format or brevity. • Evaluate list-style or terse responses based on substance, not phrasing. • A concise response that clearly addresses all key strategic dimensions can score a 3. • Responses that address only part of the workflow or omit key scenario considerations should score a 2, even if clearly written. • Brevity alone should not lower a score. Output: For your response, ONLY output the single score (0–3). Do not include any explanation. Here is the user’s input: <user_input>Criar um prompt com uma base de informações que eu tenho de conhecimento e determinar uma lógica fluida para a geração da apresentação executiva e pedir que me traga perguntas para que eu possa ir trazendo as informações que tenho conhecimento e pedir que a IA atue como um especialista na área, através de um GPT, por exemplo, consigo subir arquivos para que possam ser usados como fonte de informação</user_input> | N7: {=index('Response Scoring'!$C:$C,match($A7,'Response Scoring'!$A:$A,0))} -> 2 | O7: =$N7/3 -> 0.66666667 | P7: ='Raw Data'!$W3 -> Construir soluções de vibe coding que possam ser utilizadas internamente na cia para atender necessidade da melhoria da maturidade dos times de produto e design | Q7: Construir soluções de vibe coding que possam ser utilizadas internamente na cia para atender necessidade da melhoria da maturidade dos times de produto e design | R7: =substitute('Prompt Template'!$B$2,$P$5,$Q7) -> You are an expert evaluator of practical AI value creation in work contexts. Your goal is to evaluate how effectively survey respondents demonstrate valuable AI usage based on their response to the question: ‘What is the most useful or valuable way you are using AI in your work?’ Valuable AI usage enables higher speed and/or quality work outputs with measurable impact on workflow pain points or business objectives. Strong responses demonstrate AI integration that transforms how core work gets done, rather than providing minor convenience. Score 3 — Workflow Redesign / Integrated Use (Human-in-the-Loop or Automated) Definition: Demonstrates strategic, repeatable AI integration that has redesigned or materially enhanced how the respondent performs a core part of their job. AI is consistently embedded in their workflow, creates new capabilities, or systematically improves downstream outputs or decisions. Transformation may involve automation or a human-in-the-loop redesign. Transformation requires more than saving time on peripheral tasks. The AI use must alter how a core deliverable is created, reviewed, or decided on — not just replace small administrative tasks within it. Time savings are only valid when they result from a redesigned or automated workflow step that affects downstream outputs or team decision-making. Observable Signals (any two or more): • Defined trigger or cadence (e.g., “after every client call,” “weekly review,” or implied repetition such as “each week,” “after calls,” or “whenever new data is ready”). • Template, checklist, or structured prompt used consistently. • AI output feeds directly into another step or tool (e.g., CRM, backlog, report). • AI introduces a new step, quality gate, or sequencing change. • AI automation replaces a manual stage and enables higher-value analytical or decision-making work. • Concise responses still qualify if they clearly imply repeatable, embedded use. Contrast Examples: Meeting Notes → Follow-up • (3) “After each client call, I run a prompt that tags actions by owner and priority, then imports them into our tracker.” • (2) “After calls, I paste notes into AI to group actions by owner and due date.” • (1) “I use AI to summarize meeting notes.” Customer Feedback → Insights • (3) “Each week, AI clusters customer comments, maps them to product areas, and ranks issues I review for roadmap planning.” • (2) “AI helps cluster customer comments into themes for my monthly report.” • (1) “I ask AI to summarize customer feedback.” Data Analysis / SQL • (3) “AI generates and validates queries, produces comparison tables, and highlights anomalies I review in reports.” • (2) “AI drafts SQL queries and interprets results faster than manual work.” • (1) “AI explains SQL when I’m stuck.” Proposal / Report Writing • (3) “I use a repeatable AI template that turns briefs into full drafts with rationale and risks sections, which I refine for delivery.” • (2) “AI drafts first sections of my proposals based on my outline.” • (1) “AI helps me improve grammar and phrasing.” Competitive Research • (3) “AI normalizes competitor data, flags gaps, and generates a positioning summary for our quarterly review.” • (2) “AI extracts pricing and features into a summary table before I write my report.” • (1) “AI summarizes competitor websites.” Score 2 — Process Enhancement / Embedded Use Definition: Shows repeatable, meaningful AI use within an existing process that improves speed, quality, or consistency. AI use is consistent and relevant to core responsibilities, but the workflow design and logic remain the same. May include structured use for efficiency, but does not fundamentally change how deliverables are produced or how information flows. Observable Signals (any one): • Clear efficiency, clarity, or organization benefit. • Consistent use within a step of a recurring workflow. • Described as part of normal work, not one-off. • Partial structure or templates used manually. Examples: • “I use AI to organize survey responses and find key themes before my analysis.” • “AI drafts report sections to help me start faster.” • “I use AI to group meeting notes by owner for easier follow-up.” • “AI summarizes recurring reports or data updates to save time, but outputs are reviewed or reformatted manually.” Score 1 — Task Assistance / Surface-Level Use Definition: Describes episodic or one-step assistance focused on convenience or small efficiency gains. AI is not embedded in a structured workflow or used consistently. Includes short, isolated tasks that do not influence how other work is performed. Observable Signals: • Task-specific or one-off. • No cadence, handoff, or reuse. • Focused on formatting, writing, or explanation. • Peripheral use — does not alter how a core deliverable or process is executed. Examples: • “I use AI to fix grammar or reword emails.” • “AI helps me write Excel formulas or explain code.” • “I use AI to summarize meeting notes.” • “AI drafts short internal updates so I can focus elsewhere.” Score 0 — No or Irrelevant Use Definition: No evidence of AI use in a work context or explicitly states they do not use AI. Example: • “I don’t use AI in my work.” Evaluator Checklist When scoring, ignore writing quality and phrasing. Look for evidence of process depth: • Defined trigger or cadence? (explicit or implied) • Repeatable prompt, checklist, or playbook? • AI output feeding another step or tool? • Workflow sequence or ownership changed? • New capability or quality gate introduced? • When evaluating time savings, consider whether the AI use alters how a core deliverable is produced or simply removes a peripheral or administrative step. • Does the AI output directly support a core deliverable (e.g., reports, analysis, client output)? • Cohesion check: Are the tasks connected within a single workflow or purpose? • If the response lists multiple unrelated activities (e.g., “draft emails, brainstorm ideas, summarize reports”), treat it as multiple isolated uses and score at the lower level. Heuristic: • 3 = Embedded + ≥ 2 signals + cohesive workflow or clear transformation of core deliverable • 2 = Embedded + 0–1 signal + cohesive workflow, limited transformation • 1 = Isolated or peripheral task use • 0 = None Scoring Instruction: For your response, ONLY output the single score (0–3). Do not include any explanation. Here is the user’s input: <user_input>Construir soluções de vibe coding que possam ser utilizadas internamente na cia para atender necessidade da melhoria da maturidade dos times de produto e design</user_input> | S7: {=index('Response Scoring'!$E:$E,match($A7,'Response Scoring'!$A:$A,0))} -> 2 | T7: =$S7/3 -> 0.66666667 | U7: =sumproduct($B7:$T7,$B$4:$T$4) -> 5.3333333 | V7: ='Raw Data'!$X3 -> Analyzing presentation slides to evaluate both the visual design and written content for consistency | W7: =if($V7="Analyzing presentation slides to evaluate both the visual design and written content for consistency",1,0) -> 1 | X7: ='Raw Data'!$Y3 -> Hallucinations (generating false or misleading information), Biases in answers, Data privacy concerns when information is shared with an LLM, Vulnerability to manipulation by bad actors | Y7: =if(isnumber(search("Hallucinations",$X7)),0.25)+if(isnumber(search("Biases in answers",$X7)),0.25,0)+if(isnumber(search("Data privacy concerns",$X7)),0.25)+if(isnumber(search("Vulnerability",$X7)),0.25) -> 1 | Z7: ='Raw Data'!$Z3 -> Avoid using AI tools for anything work-related, Use secure company instances or enterprise plans when available, Anonymize information by removing identifying details | AA7: =if(or(isnumber(search("Avoid using AI tools",$Z7)),isnumber(search("Verify that the AI tool",$Z7))),0,(if(isnumber(SEARCH("Anonymize information",$Z7)),0.5)+if(isnumber(search("Use secure company instances",$Z7)),0.5))) -> 0 | AB7: ='Raw Data'!$AA3 -> Always: I routinely cross-check AI outputs with reliable sources | AC7: =if($AB7="Never: I typically trust the output as is",0,if($AB7="Rarely: I only verify if something doesn’t sound right",0.33,if($AB7="Sometimes: I do a quick check against known data or references",0.67,if($AB7="Always: I routinely cross-check AI outputs with reliable sources",1)))) -> 1 | AD7: ='Raw Data'!$AB3 -> Cross-reference key claims with reliable external sources, Verify any calculations or data analysis independently, Ask the same AI tool to double-check its work for accuracy | AE7: =if(or(isnumber(search("Check if the response uses confident language",$AD7)),isnumber(search("Look for professional formatting",$AD7))),0,(if(isnumber(search("Use a different AI tool",$AD7)),0.25)+if(isnumber(search("Cross-reference key claims",$AD7)),0.25)+if(isnumber(search("Verify any calculations",$AD7)),0.25)+if(isnumber(search("Ask the same AI tool",$AD7)),0.25))) -> 0.75 | AF7: 6.83 | AG7: ='Raw Data'!$AC3 -> Frequently: I systematically refine prompts until I’m satisfied | AH7: =if($AG7="Never: I usually just ask once and accept the first response",0,if($AG7="Rarely: I only tweak the prompt if something feels obviously off",0.33,if($AG7="Sometimes: I iterate 2–3 times to reach a good result",0.67,if($AG7="Frequently: I systematically refine prompts until I’m satisfied",1)))) -> 1 | AI7: ='Raw Data'!$AD3 -> Quero que você atue como um especialista na área relacionada a essa iniciativa, oferecendo análises técnicas, sugestões estratégicas e orientações práticas. Preciso me preparar para uma reunião de trabalho em que vou apresentar e discutir uma nova iniciativa/proposta. Me ajude a: 1. estruturar uma apresentação clara e convincente; 2. organizar os principais argumentos; 3. antecipar perguntas, dúvidas e objeções da equipe; 4.sugerir respostas sólidas e embasadas; Identificar possíveis riscos e oportunidades. Também preciso de um resumo objetivo da iniciativa e recomendações sobre como conduzir a reunião de forma eficiente. Posso te enviar mais detalhes, se precisar. | AJ7: Quero que você atue como um especialista na área relacionada a essa iniciativa, oferecendo análises técnicas, sugestões estratégicas e orientações práticas. Preciso me preparar para uma reunião de trabalho em que vou apresentar e discutir uma nova iniciativa/proposta. Me ajude a: 1. estruturar uma apresentação clara e convincente; 2. organizar os principais argumentos; 3. antecipar perguntas, dúvidas e objeções da equipe; 4.sugerir respostas sólidas e embasadas; Identificar possíveis riscos e oportunidades. Também preciso de um resumo objetivo da iniciativa e recomendações sobre como conduzir a reunião de forma eficiente. Posso te enviar mais detalhes, se precisar. | AK7: =substitute('Prompt Template'!$C$2,$AI$5,$AJ7) -> You are an expert prompt engineer. Your goal is to evaluate the effectiveness of the prompt below. Less effective prompts are too vague, open-ended, and do not give clear instructions. More effective prompts provide background, clear instructions, and are well structured. Since you are tasked with evaluating true effectiveness of the prompt, you can give scores of 1. This is for an AI Readiness Survey that will assess individuals' proficiency when using AI. <task>Write a prompt asking AI to help you prepare for a work meeting to discuss a new initiative or proposal</task> <prompt>Quero que você atue como um especialista na área relacionada a essa iniciativa, oferecendo análises técnicas, sugestões estratégicas e orientações práticas. Preciso me preparar para uma reunião de trabalho em que vou apresentar e discutir uma nova iniciativa/proposta. Me ajude a: 1. estruturar uma apresentação clara e convincente; 2. organizar os principais argumentos; 3. antecipar perguntas, dúvidas e objeções da equipe; 4.sugerir respostas sólidas e embasadas; Identificar possíveis riscos e oportunidades. Também preciso de um resumo objetivo da iniciativa e recomendações sobre como conduzir a reunião de forma eficiente. Posso te enviar mais detalhes, se precisar.</prompt> A score of 1 prompt example: "Help me prepare for my work meeting" Rate the effectiveness on a scale of 1-5. Only respond with a single number from 1-5. If the person states they do not know how to prompt or their prompt isn't relevant to the task, give them a 0. Use the following criteria: Clarity and Specificity: A good prompt should be clear, specific, and focused. It should provide enough context and detail to guide the AI towards generating a relevant and useful response. Vague, open-ended, or ambiguous prompts make it difficult for the AI to understand the user's intent and can lead to generic or irrelevant outputs. Completeness and Sufficiency: An effective prompt should include all the necessary information and requirements to enable the AI to complete the requested task or answer the question thoroughly. It should anticipate what details the AI might need and proactively provide them. Incomplete prompts that leave out critical facts or constraints will likely result in suboptimal responses that fail to fully address the user's needs. Structure and Organization: A well-crafted prompt should be logically structured and organized. It should break down complex requests into clear steps or components, making it easier for the AI to process and respond to each part systematically. Using formatting techniques like bullet points, numbering, or sectioning can help improve the prompt's clarity and readability. Conciseness and Precision: While a good prompt should be detailed and informative, it should also strive to be as concise and precise as possible. Overly wordy or rambling prompts can obscure the key points and make it harder for the AI to identify the essential requirements. An effective prompt finds the right balance between providing necessary context and avoiding extraneous or redundant information. Here is the user's input: <user_input>Quero que você atue como um especialista na área relacionada a essa iniciativa, oferecendo análises técnicas, sugestões estratégicas e orientações práticas. Preciso me preparar para uma reunião de trabalho em que vou apresentar e discutir uma nova iniciativa/proposta. Me ajude a: 1. estruturar uma apresentação clara e convincente; 2. organizar os principais argumentos; 3. antecipar perguntas, dúvidas e objeções da equipe; 4.sugerir respostas sólidas e embasadas; Identificar possíveis riscos e oportunidades. Também preciso de um resumo objetivo da iniciativa e recomendações sobre como conduzir a reunião de forma eficiente. Posso te enviar mais detalhes, se precisar.</user_input> | AL7: {=index('Response Scoring'!$G:$G,match($A7,'Response Scoring'!$A:$A,0))} -> 4 | AM7: =$AL7/5 -> 0.8 | AN7: ='Raw Data'!$AE3 -> Nome do agente: Competitive Intelligence GPT Missão: Apoiar a equipe na coleta e análise de informações sobre concorrentes — produtos, preços, lançamentos e posicionamento — para embasar decisões estratégicas de marca e portfólio. Persona Você é um analista de inteligência competitiva meticuloso, estratégico e orientado por dados. Seu papel é coletar, comparar e sintetizar informações públicas sobre o mercado e concorrentes de forma clara, ética e acionável. Você escreve de modo profissional, objetivo e analítico, evitando opiniões subjetivas. Seu foco é transformar dados em insights úteis para decisões de negócio. Instruções de comportamento Use somente fontes públicas confiáveis: sites oficiais, e-commerces, redes sociais, notícias e relatórios. Nunca utilize dados privados, rumores ou inferências sem base. Sempre cite fonte e data das informações encontradas. Padronize preços (ex: BRL) e organize comparações de forma clara. Destaque tendências, oportunidades e riscos para nossa marca. 🧩 Estrutura das respostas Sempre apresente as análises no seguinte formato: Concorrente: Fontes consultadas: Portfólio e lançamentos: Preços e promoções: Posicionamento e diferenciais: Estratégia digital e canais: Reputação e feedback do consumidor: Insights e oportunidades: Finalize cada resposta com um resumo executivo destacando os principais aprendizados e implicações estratégicas. Estilo de comunicação Tom: profissional, consultivo e neutro Linguagem: clara, concisa e orientada à decisão Estrutura: tabelas, tópicos e resumos curtos sempre que possível Exemplos de solicitações “Compare o posicionamento e preços da Budweiser e da Heineken no Brasil.” “Liste lançamentos de cervejas sem álcool nos últimos 6 meses.” “Analise campanhas digitais recentes da Stella Artois.” “Crie um relatório competitivo sobre o segmento de hard seltzers.” | AO7: Nome do agente: Competitive Intelligence GPT Missão: Apoiar a equipe na coleta e análise de informações sobre concorrentes — produtos, preços, lançamentos e posicionamento — para embasar decisões estratégicas de marca e portfólio. Persona Você é um analista de inteligência competitiva meticuloso, estratégico e orientado por dados. Seu papel é coletar, comparar e sintetizar informações públicas sobre o mercado e concorrentes de forma clara, ética e acionável. Você escreve de modo profissional, objetivo e analítico, evitando opiniões subjetivas. Seu foco é transformar dados em insights úteis para decisões de negócio. Instruções de comportamento Use somente fontes públicas confiáveis: sites oficiais, e-commerces, redes sociais, notícias e relatórios. Nunca utilize dados privados, rumores ou inferências sem base. Sempre cite fonte e data das informações encontradas. Padronize preços (ex: BRL) e organize comparações de forma clara. Destaque tendências, oportunidades e riscos para nossa marca. 🧩 Estrutura das respostas Sempre apresente as análises no seguinte formato: Concorrente: Fontes consultadas: Portfólio e lançamentos: Preços e promoções: Posicionamento e diferenciais: Estratégia digital e canais: Reputação e feedback do consumidor: Insights e oportunidades: Finalize cada resposta com um resumo executivo destacando os principais aprendizados e implicações estratégicas. Estilo de comunicação Tom: profissional, consultivo e neutro Linguagem: clara, concisa e orientada à decisão Estrutura: tabelas, tópicos e resumos curtos sempre que possível Exemplos de solicitações “Compare o posicionamento e preços da Budweiser e da Heineken no Brasil.” “Liste lançamentos de cervejas sem álcool nos últimos 6 meses.” “Analise campanhas digitais recentes da Stella Artois.” “Crie um relatório competitivo sobre o segmento de hard seltzers.” | AP7: =substitute('Prompt Template'!$D$2,$AN$5,$AO7) -> You are an expert evaluator of AI instruction design and CustomGPT configuration. Your goal is to evaluate how effectively a respondent demonstrates their ability to write high-quality AI instructions — the kind used to configure tools like CustomGPTs, Copilot Agents, or Google Gems. The test question asks respondents to: ‘Write instructions for a Custom GPT that would help team members gather competitive intelligence consistently.’ This scenario is used only as a familiar example. Do not evaluate their knowledge of competitive analysis — only the clarity, structure, and effectiveness of their AI instruction design. The competitive intelligence context is a stand-in for any business task. Scoring Overview Rate each response on a scale of 0–5. • 5 = System-ready, strong demonstration of instruction design skill. • 0 = Irrelevant or no response. Focus on instructional quality, not topic expertise or formatting aesthetics. Evaluation Dimensions 1. Structural Design Effective instructions clearly define the inputs, process/steps, and outputs. They show logical sequencing (e.g., research → organize → summarize) and reflect understanding of how AI interprets procedural tasks. 2. Instructional Precision Steps and directives are specific, actionable, and testable by an AI. Avoids vague terms like “analyze competitors” without specifying how to do so or what output is expected. 3. Boundary and Role Definition Strong instructions establish clear context for the AI — defining its role, scope, and constraints. They guide what to include/exclude and how to handle ambiguity or conflicting data. 4. Reusability and Scalability Good instructions can be reused consistently by others. They define consistent formatting, data structures, or repeatable logic that ensures stable results across users or scenarios. 5. Outcome Alignment The best instructions would realistically result in a functioning CustomGPT that performs the intended task accurately and consistently. Weak ones would produce inconsistent or low-quality behavior. Scoring Guidelines Score 5 – System-Ready • Instructions could be pasted directly into a CustomGPT/Copilot and perform effectively. • They demonstrate full system readiness — meaning the AI could execute the intended behavior repeatedly and autonomously, without additional clarification. • Includes: • Defined role and purpose (who/what the AI is). • Clear inputs (what information or user query it receives). • Explicit steps/process (how the AI should perform the task). • Defined outputs (format, tone, or structure of response). • Constraints/quality controls (rules, caveats, or handling instructions). • Demonstrates awareness of how to build a reusable, consistent AI behavior. Example 1: “Role: Competitive Intelligence Assistant. Purpose: Gather structured competitor data from reliable sources. Inputs: Company/product names. Process: 1) Identify top 5 competitors, 2) Extract features/pricing, 3) Summarize differences in a table. Output: Comparative matrix. Guardrails: Only use credible, verifiable sources.” Example 2 (Natural-Language Equivalent): “This CustomGPT should act as our internal research analyst. When given a company or product name, it identifies credible sources like official websites, press releases, and reviews. It compares product features, pricing, and messaging across competitors and summarizes the results in a consistent table and a short written overview with citations. The report should flag any information that seems outdated or unverified and maintain a uniform format for reuse across projects.” Note: Responses may use either explicit headings (Role/Inputs/Process/Output) or fluent natural language. Both are valid if they include equivalent components and could realistically produce consistent, reusable results. Score 4 – Strong but Missing Refinements • Structured and actionable; includes most components (e.g., steps, outputs, and some constraints). • Missing minor refinements such as input specificity, error handling, or reusability mechanisms. • AI could perform the task, but inconsistently. Example 1: “Gather information on competitors’ products, features, and pricing. Summarize in a table. Cite reliable sources.” (Functional but missing full structure or clear constraints.) Example 2: “Create a CustomGPT that collects information from competitor websites, reviews, and announcements. Summarize pricing, features, and positioning in a table, then highlight new updates. Include dates and brief notes on source credibility.” (Strong structure, but lacks clear inputs and reusability framing.) Score 3 – Structured but Shallow • Provides a reasonable outline or list of tasks but lacks cohesion or precision. • Mentions the goal but misses how to operationalize it in a repeatable, system-friendly way. • AI would need to infer too much to work reliably. Example 1: “Research competitors and summarize key findings about pricing and positioning.” (Has intent but lacks sequencing or defined outputs.) Example 2: “The GPT should find information about our competitors’ pricing and products, summarize what’s different, and give a short write-up each week.” (Clear intent, but underspecified logic — reads more like a to-do list than executable instructions.) Score 2 – Fragmented or Vague • Mentions competitive research but provides minimal or disconnected guidance. • Steps are generic, unsequenced, or too ambiguous to drive consistent AI behavior. Example elements: “Look up competitors and gather details.” “Find competitor info and summarize.” (Too vague to translate into functioning instructions.) Score 1 – Minimal or Misunderstood • Shows fundamental misunderstanding of AI instruction design. • Generic, incomplete, or irrelevant content that couldn’t guide an AI system at all. Example elements: “Just tell GPT to look up competitors.” “I’d ask it to find info about other companies.” “Use ChatGPT to do competitive research for us.” “Help me understand what our competitors do better.” “Search online for competitor products and summarize.” (Shows surface-level familiarity with AI but no system thinking.) Score 0 – No Response or Irrelevant • Empty, “I don’t know,” or unrelated answer. Example elements: “Not sure what to put here.” “I don’t use GPT for that.” “I’d rather do that myself.” “No idea how to write that.” (Shows confusion or complete lack of task understanding.) Evaluator Checklist When scoring, focus on functional design quality, not formatting or topic expertise. Ask yourself: • Does the response clearly define the AI’s role, inputs, process, and outputs? • Are instructions specific, sequenced, and testable? • Do they include boundaries or quality controls? • Could the AI perform the task consistently and autonomously if these instructions were used? • Is the response written at a configuration level (system prompt) rather than a one-off user command? Heuristic: • 5 = Fully structured, system-ready, reusable. • 4 = Strong, nearly system-ready, missing refinements. • 3 = Structured but shallow. • 2 = Fragmented or vague. • 1 = Minimal or misunderstood. • 0 = None/irrelevant. Scoring Instruction: For your response, ONLY output the single score (0–5). Do not include any explanation. Here is the user’s input: <user_input>Nome do agente: Competitive Intelligence GPT Missão: Apoiar a equipe na coleta e análise de informações sobre concorrentes — produtos, preços, lançamentos e posicionamento — para embasar decisões estratégicas de marca e portfólio. Persona Você é um analista de inteligência competitiva meticuloso, estratégico e orientado por dados. Seu papel é coletar, comparar e sintetizar informações públicas sobre o mercado e concorrentes de forma clara, ética e acionável. Você escreve de modo profissional, objetivo e analítico, evitando opiniões subjetivas. Seu foco é transformar dados em insights úteis para decisões de negócio. Instruções de comportamento Use somente fontes públicas confiáveis: sites oficiais, e-commerces, redes sociais, notícias e relatórios. Nunca utilize dados privados, rumores ou inferências sem base. Sempre cite fonte e data das informações encontradas. Padronize preços (ex: BRL) e organize comparações de forma clara. Destaque tendências, oportunidades e riscos para nossa marca. 🧩 Estrutura das respostas Sempre apresente as análises no seguinte formato: Concorrente: Fontes consultadas: Portfólio e lançamentos: Preços e promoções: Posicionamento e diferenciais: Estratégia digital e canais: Reputação e feedback do consumidor: Insights e oportunidades: Finalize cada resposta com um resumo executivo destacando os principais aprendizados e implicações estratégicas. Estilo de comunicação Tom: profissional, consultivo e neutro Linguagem: clara, concisa e orientada à decisão Estrutura: tabelas, tópicos e resumos curtos sempre que possível Exemplos de solicitações “Compare o posicionamento e preços da Budweiser e da Heineken no Brasil.” “Liste lançamentos de cervejas sem álcool nos últimos 6 meses.” “Analise campanhas digitais recentes da Stella Artois.” “Crie um relatório competitivo sobre o segmento de hard seltzers.”</user_input> | AQ7: {=index('Response Scoring'!$I:$I,match($A7,'Response Scoring'!$A:$A,0))} -> 5 | AR7: =$AQ7/5 -> 1 | AS7: =sumproduct($AG7:$AR7,$AG$3:$AR$3) -> 9.3 | AT7: =($AH7*2)+(AM7*8) -> 8.4 | AU7: =($U7*$AW$4)+($AF7*$AW$3)+($AS7*$AW$2) -> 36.096667 | AV7: =$AU7*2 -> 72.193333 | AW7: =IF($AV7>=80,"AI Expert",if($AV7>=60,"AI Practitioner",IF(AND($AV7<60,$AV7>=25),"AI Experimenter",if(and($AV7<25,$AV7>=0),"AI Novice")))) -> AI Practitioner | AX7: ='Raw Data'!AF3 -> ChatGPT, CoPilot, Claude, Gemini | AY7: ='Raw Data'!AG3 -> Yes | AZ7: ='Raw Data'!AH3 | BA7: ='Raw Data'!AI3 | BB7: ='Raw Data'!AJ3 | BC7: ='Raw Data'!AK3 | BD7: ='Raw Data'!AL3 | BE7: ='Raw Data'!AM3 | ... BR7: ='Raw Data'!AZ3 | BS7: ='Raw Data'!D3 | BT7: ='Raw Data'!E3 | BU7: ='Raw Data'!F3 -> DTC GHQ | BV7: ='Raw Data'!G3 -> Product Design | BW7: =if(BV7='Demographic Analysis'!$A$22,"Yes","No") -> #REF! | BX7: ='Raw Data'!I3 -> N/A | BY7: ='Raw Data'!J3 | BZ7: ='Raw Data'!K3 | CA7: ='Raw Data'!L3 -> Brazil | CB7: ='Raw Data'!M3 -> Growth Group | CC7: ='Raw Data'!N3 -> AB Inbev | CD7: ='Raw Data'!O3 -> Fernanda Faria - Product Design | CE7: ='Raw Data'!P3 -> Heavy User | CF7: ='Raw Data'!Q3 -> Weekly
A8: ='Raw Data'!$A4 -> 2 | B8: ='Raw Data'!$R4 -> Daily | C8: =if($B8="Never or rarely",0,if($B8="A few times a month",0.25,if($B8="Weekly",0.5,if($B8="Several times a week",0.75,if($B8="Daily",1))))) -> 1 | D8: ='Raw Data'!$S4 -> Building custom prompts, templates, or workflows that I reuse regularly, Writing or debugging code, scripts, or formulas, Editing or improving text I’ve already written (emails, documents, presentations), Getting quick answers to specific questions or looking up information, Analyzing data or documents to extract insights or summaries, Using AI for vibe coding to prototype solutions, apps, or products | E8: =if(isnumber(search("I don't use AI for work",$D8)),0,if(or(isnumber(search("Vibe Coding",$D8)),isnumber(search("custom prompts",$D8))),3,if(or(isnumber(search("brainstorming ideas",$D8)),isnumber(search("analyzing data",$D8)),isnumber(search("Creating first drafts",$D8))),2,1))) -> 3 | F8: =$E8/3 -> 1 | G8: ='Raw Data'!T4 -> I’ve built custom AI tools (CustomGPTs, Copilot Agents, Google Gems, Claude Projects) for repetitive tasks | H8: =if($G8="I don't use AI for work",0,if($G8="I create fresh prompts each time I use AI",0.25,if($G8="I maintain a library of prompts that I reuse frequently",0.5,if($G8="I’ve built custom AI tools (CustomGPTs, Copilot Agents, Google Gems, Claude Projects) for repetitive tasks",0.75,if($G8="I’ve created workflows that connect AI with other systems (Slack, Salesforce, email) using integrations or code",1))))) -> 0.75 | I8: ='Raw Data'!$U4 -> Create a systematic process where AI handles data analysis and summary generation consistently | J8: =if($I8="I wouldn’t use AI for this task",0,if($I8="Ask AI to write the summary after you’ve analyzed all the data",0.33,if($I8="Use AI to help analyze each data source, then compile results manually",0.67,if($I8="Create a systematic process where AI handles data analysis and summary generation consistently",1)))) -> 1 | K8: ='Raw Data'!$V4 -> I would Ai to help me learn about topic, create an mind-map with main information about the topic, organized an short discovery and bullet points to start create presentation | L8: I would Ai to help me learn about topic, create an mind-map with main information about the topic, organized an short discovery and bullet points to start create presentation | M8: =substitute('Prompt Template'!$A$2,$K$5,$L8) -> You are an expert evaluator of AI strategic thinking and workflow integration. Your goal is to evaluate how effectively survey respondents demonstrate strategic AI application based on their response to the question: “You have one week to create an important presentation for senior stakeholders on an unfamiliar topic. How would you use AI in this process?” Evaluate each response holistically across three key areas: Workflow Integration: Effective responses demonstrate systematic thinking by identifying multiple stages of the presentation process where AI can add value (research, analysis, content creation, structure, review, etc.). They show understanding that complex projects benefit from AI integration at various points rather than just using AI for one isolated task. Strategic Application: Strong responses show context-aware AI usage that specifically addresses the unique challenges of this scenario — leveraging AI to quickly understand an unfamiliar topic, tailoring content for senior stakeholders, and managing time constraints effectively. They go beyond generic AI applications to show thoughtful consideration of the specific requirements. Practical Execution: Quality responses demonstrate concrete understanding of how AI tools actually work by providing specific, actionable approaches rather than vague descriptions. They show familiarity with AI capabilities and limitations, and describe realistic implementation steps. Scoring Guidelines Score 3 — Strong strategic thinking • Demonstrates comprehensive AI integration across most or all key workflow stages (e.g., research, structure, content creation, context tailoring for senior stakeholders, review), combined with clear scenario awareness and practical execution. • Responses do not need to mention every single stage explicitly; concise or list-style answers can still score a 3 if they show a strategically complete, end-to-end approach that addresses the scenario’s unique challenges (unfamiliar topic, senior stakeholders, tight timelines). • Omitting one stage (e.g., review) does not disqualify a response if the overall strategy is robust and well-adapted. • Both structured and concise list-style responses are valid. Examples: • “Research topic comprehensively, analyze stakeholder needs, create presentation framework, develop content, review for clarity.” • “Use AI throughout the process — from initial research to final presentation polish — focusing on what senior stakeholders care about most.” • “I would use AI to research the topic, understand key stakeholder concerns, create a logical flow, and draft compelling content for senior leadership within the time constraint.” • “Scan unfamiliar topic, outline slides, tailor framing for executives, draft key content, fact-check and polish.” (Concise list-style example demonstrating full coverage) • “Research unfamiliar topic, structure the deck, tailor for executives, draft content.” (Covers most strategic stages, omits review but is still strategically comprehensive) Score 2 — Moderate strategic thinking • Demonstrates partial but not comprehensive coverage of the key strategic dimensions. • Typically covers two to three workflow stages (e.g., structure + content + some context) but omits one or more major elements such as research, scenario adaptation, or review. • May show good workflow integration but limited scenario context, or vice versa. • Responses may be clear and practical but reflect a mid-level strategic approach rather than end-to-end planning. Examples: • “Use AI to quickly understand the topic, then create an outline and draft the presentation content.” • “Research phase, analysis phase, content creation phase, review phase.” • “Use AI to help research industry trends and create slides tailored for executives.” • “Draft speaker notes, executive framing, summarize key sources.” (Covers content, some research, and context but lacks structure/review) • “10 slide structure, add citations, executive framing.” (Structure, review, context but no research/content creation) Score 1 — Limited strategic thinking • Shows basic or single AI application with little reference to workflow complexity or scenario context. • Generic AI usage that could apply to any presentation task. Examples: • “Use AI to research the topic and create slides.” • “ChatGPT for research, help with structure.” • “Research, writing, editing.” • “Ask AI to help me understand the topic.” Score 0 — No relevant response • No answer, states they wouldn’t use AI, or provides irrelevant content. Special Guidance on Format and Brevity • Do not penalize for response format or brevity. • Evaluate list-style or terse responses based on substance, not phrasing. • A concise response that clearly addresses all key strategic dimensions can score a 3. • Responses that address only part of the workflow or omit key scenario considerations should score a 2, even if clearly written. • Brevity alone should not lower a score. Output: For your response, ONLY output the single score (0–3). Do not include any explanation. Here is the user’s input: <user_input>I would Ai to help me learn about topic, create an mind-map with main information about the topic, organized an short discovery and bullet points to start create presentation</user_input> | N8: {=index('Response Scoring'!$C:$C,match($A8,'Response Scoring'!$A:$A,0))} -> 2 | O8: =$N8/3 -> 0.66666667 | P8: ='Raw Data'!$W4 -> I use Ai to be my partner, creating personas, tools to generate dashboards, analyse Datas and study improveemnts on the Squads that i work I create a dashboard to provide a EM main information's about delivery evolution of their squads | Q8: I use Ai to be my partner, creating personas, tools to generate dashboards, analyse Datas and study improveemnts on the Squads that i work I create a dashboard to provide a EM main information's about delivery evolution of their squads | R8: =substitute('Prompt Template'!$B$2,$P$5,$Q8) -> You are an expert evaluator of practical AI value creation in work contexts. Your goal is to evaluate how effectively survey respondents demonstrate valuable AI usage based on their response to the question: ‘What is the most useful or valuable way you are using AI in your work?’ Valuable AI usage enables higher speed and/or quality work outputs with measurable impact on workflow pain points or business objectives. Strong responses demonstrate AI integration that transforms how core work gets done, rather than providing minor convenience. Score 3 — Workflow Redesign / Integrated Use (Human-in-the-Loop or Automated) Definition: Demonstrates strategic, repeatable AI integration that has redesigned or materially enhanced how the respondent performs a core part of their job. AI is consistently embedded in their workflow, creates new capabilities, or systematically improves downstream outputs or decisions. Transformation may involve automation or a human-in-the-loop redesign. Transformation requires more than saving time on peripheral tasks. The AI use must alter how a core deliverable is created, reviewed, or decided on — not just replace small administrative tasks within it. Time savings are only valid when they result from a redesigned or automated workflow step that affects downstream outputs or team decision-making. Observable Signals (any two or more): • Defined trigger or cadence (e.g., “after every client call,” “weekly review,” or implied repetition such as “each week,” “after calls,” or “whenever new data is ready”). • Template, checklist, or structured prompt used consistently. • AI output feeds directly into another step or tool (e.g., CRM, backlog, report). • AI introduces a new step, quality gate, or sequencing change. • AI automation replaces a manual stage and enables higher-value analytical or decision-making work. • Concise responses still qualify if they clearly imply repeatable, embedded use. Contrast Examples: Meeting Notes → Follow-up • (3) “After each client call, I run a prompt that tags actions by owner and priority, then imports them into our tracker.” • (2) “After calls, I paste notes into AI to group actions by owner and due date.” • (1) “I use AI to summarize meeting notes.” Customer Feedback → Insights • (3) “Each week, AI clusters customer comments, maps them to product areas, and ranks issues I review for roadmap planning.” • (2) “AI helps cluster customer comments into themes for my monthly report.” • (1) “I ask AI to summarize customer feedback.” Data Analysis / SQL • (3) “AI generates and validates queries, produces comparison tables, and highlights anomalies I review in reports.” • (2) “AI drafts SQL queries and interprets results faster than manual work.” • (1) “AI explains SQL when I’m stuck.” Proposal / Report Writing • (3) “I use a repeatable AI template that turns briefs into full drafts with rationale and risks sections, which I refine for delivery.” • (2) “AI drafts first sections of my proposals based on my outline.” • (1) “AI helps me improve grammar and phrasing.” Competitive Research • (3) “AI normalizes competitor data, flags gaps, and generates a positioning summary for our quarterly review.” • (2) “AI extracts pricing and features into a summary table before I write my report.” • (1) “AI summarizes competitor websites.” Score 2 — Process Enhancement / Embedded Use Definition: Shows repeatable, meaningful AI use within an existing process that improves speed, quality, or consistency. AI use is consistent and relevant to core responsibilities, but the workflow design and logic remain the same. May include structured use for efficiency, but does not fundamentally change how deliverables are produced or how information flows. Observable Signals (any one): • Clear efficiency, clarity, or organization benefit. • Consistent use within a step of a recurring workflow. • Described as part of normal work, not one-off. • Partial structure or templates used manually. Examples: • “I use AI to organize survey responses and find key themes before my analysis.” • “AI drafts report sections to help me start faster.” • “I use AI to group meeting notes by owner for easier follow-up.” • “AI summarizes recurring reports or data updates to save time, but outputs are reviewed or reformatted manually.” Score 1 — Task Assistance / Surface-Level Use Definition: Describes episodic or one-step assistance focused on convenience or small efficiency gains. AI is not embedded in a structured workflow or used consistently. Includes short, isolated tasks that do not influence how other work is performed. Observable Signals: • Task-specific or one-off. • No cadence, handoff, or reuse. • Focused on formatting, writing, or explanation. • Peripheral use — does not alter how a core deliverable or process is executed. Examples: • “I use AI to fix grammar or reword emails.” • “AI helps me write Excel formulas or explain code.” • “I use AI to summarize meeting notes.” • “AI drafts short internal updates so I can focus elsewhere.” Score 0 — No or Irrelevant Use Definition: No evidence of AI use in a work context or explicitly states they do not use AI. Example: • “I don’t use AI in my work.” Evaluator Checklist When scoring, ignore writing quality and phrasing. Look for evidence of process depth: • Defined trigger or cadence? (explicit or implied) • Repeatable prompt, checklist, or playbook? • AI output feeding another step or tool? • Workflow sequence or ownership changed? • New capability or quality gate introduced? • When evaluating time savings, consider whether the AI use alters how a core deliverable is produced or simply removes a peripheral or administrative step. • Does the AI output directly support a core deliverable (e.g., reports, analysis, client output)? • Cohesion check: Are the tasks connected within a single workflow or purpose? • If the response lists multiple unrelated activities (e.g., “draft emails, brainstorm ideas, summarize reports”), treat it as multiple isolated uses and score at the lower level. Heuristic: • 3 = Embedded + ≥ 2 signals + cohesive workflow or clear transformation of core deliverable • 2 = Embedded + 0–1 signal + cohesive workflow, limited transformation • 1 = Isolated or peripheral task use • 0 = None Scoring Instruction: For your response, ONLY output the single score (0–3). Do not include any explanation. Here is the user’s input: <user_input>I use Ai to be my partner, creating personas, tools to generate dashboards, analyse Datas and study improveemnts on the Squads that i work I create a dashboard to provide a EM main information's about delivery evolution of their squads</user_input> | S8: {=index('Response Scoring'!$E:$E,match($A8,'Response Scoring'!$A:$A,0))} -> 3 | T8: =$S8/3 -> 1 | U8: =sumproduct($B8:$T8,$B$4:$T$4) -> 5.4166667 | V8: ='Raw Data'!$X4 -> Analyzing presentation slides to evaluate both the visual design and written content for consistency | W8: =if($V8="Analyzing presentation slides to evaluate both the visual design and written content for consistency",1,0) -> 1 | X8: ='Raw Data'!$Y4 -> Biases in answers | Y8: =if(isnumber(search("Hallucinations",$X8)),0.25)+if(isnumber(search("Biases in answers",$X8)),0.25,0)+if(isnumber(search("Data privacy concerns",$X8)),0.25)+if(isnumber(search("Vulnerability",$X8)),0.25) -> 0.25 | Z8: ='Raw Data'!$Z4 -> Use secure company instances or enterprise plans when available, Anonymize information by removing identifying details, Only share information that you would be comfortable sharing internally with a colleague, Verify that the AI tool has SSL/HTTPS encryption before using it, Avoid using AI tools for anything work-related | AA8: =if(or(isnumber(search("Avoid using AI tools",$Z8)),isnumber(search("Verify that the AI tool",$Z8))),0,(if(isnumber(SEARCH("Anonymize information",$Z8)),0.5)+if(isnumber(search("Use secure company instances",$Z8)),0.5))) -> 0 | AB8: ='Raw Data'!$AA4 -> Always: I routinely cross-check AI outputs with reliable sources | AC8: =if($AB8="Never: I typically trust the output as is",0,if($AB8="Rarely: I only verify if something doesn’t sound right",0.33,if($AB8="Sometimes: I do a quick check against known data or references",0.67,if($AB8="Always: I routinely cross-check AI outputs with reliable sources",1)))) -> 1 | AD8: ='Raw Data'!$AB4 -> Check if the response uses confident language and specific details, Use a different AI tool to review and verify the content, Cross-reference key claims with reliable external sources, Ask the same AI tool to double-check its work for accuracy | AE8: =if(or(isnumber(search("Check if the response uses confident language",$AD8)),isnumber(search("Look for professional formatting",$AD8))),0,(if(isnumber(search("Use a different AI tool",$AD8)),0.25)+if(isnumber(search("Cross-reference key claims",$AD8)),0.25)+if(isnumber(search("Verify any calculations",$AD8)),0.25)+if(isnumber(search("Ask the same AI tool",$AD8)),0.25))) -> 0 | AF8: 8.8 | AG8: ='Raw Data'!$AC4 -> Frequently: I systematically refine prompts until I’m satisfied | AH8: =if($AG8="Never: I usually just ask once and accept the first response",0,if($AG8="Rarely: I only tweak the prompt if something feels obviously off",0.33,if($AG8="Sometimes: I iterate 2–3 times to reach a good result",0.67,if($AG8="Frequently: I systematically refine prompts until I’m satisfied",1)))) -> 1 | AI8: ='Raw Data'!$AD4 -> Help me prepare for an upcoming work meeting where I will discuss a new initiative proposal. I need assistance with the following: Outline: Create an outline of key points I should cover during the presentation. Supporting Data: Suggest relevant data or statistics that could strengthen my proposal. Anticipate Questions: List potential questions or concerns that attendees might have, along with suggested responses. Visual Aids: Recommend any visual aids or materials that would enhance my presentation. Meeting Agenda: Draft a concise agenda for the meeting to keep the discussion focused. | AJ8: Help me prepare for an upcoming work meeting where I will discuss a new initiative proposal. I need assistance with the following: Outline: Create an outline of key points I should cover during the presentation. Supporting Data: Suggest relevant data or statistics that could strengthen my proposal. Anticipate Questions: List potential questions or concerns that attendees might have, along with suggested responses. Visual Aids: Recommend any visual aids or materials that would enhance my presentation. Meeting Agenda: Draft a concise agenda for the meeting to keep the discussion focused. | AK8: =substitute('Prompt Template'!$C$2,$AI$5,$AJ8) -> You are an expert prompt engineer. Your goal is to evaluate the effectiveness of the prompt below. Less effective prompts are too vague, open-ended, and do not give clear instructions. More effective prompts provide background, clear instructions, and are well structured. Since you are tasked with evaluating true effectiveness of the prompt, you can give scores of 1. This is for an AI Readiness Survey that will assess individuals' proficiency when using AI. <task>Write a prompt asking AI to help you prepare for a work meeting to discuss a new initiative or proposal</task> <prompt>Help me prepare for an upcoming work meeting where I will discuss a new initiative proposal. I need assistance with the following: Outline: Create an outline of key points I should cover during the presentation. Supporting Data: Suggest relevant data or statistics that could strengthen my proposal. Anticipate Questions: List potential questions or concerns that attendees might have, along with suggested responses. Visual Aids: Recommend any visual aids or materials that would enhance my presentation. Meeting Agenda: Draft a concise agenda for the meeting to keep the discussion focused.</prompt> A score of 1 prompt example: "Help me prepare for my work meeting" Rate the effectiveness on a scale of 1-5. Only respond with a single number from 1-5. If the person states they do not know how to prompt or their prompt isn't relevant to the task, give them a 0. Use the following criteria: Clarity and Specificity: A good prompt should be clear, specific, and focused. It should provide enough context and detail to guide the AI towards generating a relevant and useful response. Vague, open-ended, or ambiguous prompts make it difficult for the AI to understand the user's intent and can lead to generic or irrelevant outputs. Completeness and Sufficiency: An effective prompt should include all the necessary information and requirements to enable the AI to complete the requested task or answer the question thoroughly. It should anticipate what details the AI might need and proactively provide them. Incomplete prompts that leave out critical facts or constraints will likely result in suboptimal responses that fail to fully address the user's needs. Structure and Organization: A well-crafted prompt should be logically structured and organized. It should break down complex requests into clear steps or components, making it easier for the AI to process and respond to each part systematically. Using formatting techniques like bullet points, numbering, or sectioning can help improve the prompt's clarity and readability. Conciseness and Precision: While a good prompt should be detailed and informative, it should also strive to be as concise and precise as possible. Overly wordy or rambling prompts can obscure the key points and make it harder for the AI to identify the essential requirements. An effective prompt finds the right balance between providing necessary context and avoiding extraneous or redundant information. Here is the user's input: <user_input>Help me prepare for an upcoming work meeting where I will discuss a new initiative proposal. I need assistance with the following: Outline: Create an outline of key points I should cover during the presentation. Supporting Data: Suggest relevant data or statistics that could strengthen my proposal. Anticipate Questions: List potential questions or concerns that attendees might have, along with suggested responses. Visual Aids: Recommend any visual aids or materials that would enhance my presentation. Meeting Agenda: Draft a concise agenda for the meeting to keep the discussion focused.</user_input> | AL8: {=index('Response Scoring'!$G:$G,match($A8,'Response Scoring'!$A:$A,0))} -> 4 | AM8: =$AL8/5 -> 0.8 | AN8: ='Raw Data'!$AE4 -> 1. User Commands and Queries Product Research: Command: "Provide an overview of [Competitor Name]'s latest product offerings." Command: "What are the key features of [Competitor Name]'s [specific product]?" Pricing Analysis: Command: "List the pricing strategies used by [Competitor Name] for [specific product/category]." Command: "How does [Competitor Name]'s pricing compare to ours?" Market Positioning: Command: "Explain how [Competitor Name] positions itself in the market." Command: "What are the unique selling propositions (USPs) of [Competitor Name]?" SWOT Analysis: Command: "Perform a SWOT analysis for [Competitor Name]." Command: "Identify strengths and weaknesses of [Competitor Name]'s product line." Customer Sentiment: Command: "Summarize customer reviews and feedback for [Competitor Name]'s [specific product]." Command: "What are common customer complaints about [Competitor Name]?" | AO8: 1. User Commands and Queries Product Research: Command: "Provide an overview of [Competitor Name]'s latest product offerings." Command: "What are the key features of [Competitor Name]'s [specific product]?" Pricing Analysis: Command: "List the pricing strategies used by [Competitor Name] for [specific product/category]." Command: "How does [Competitor Name]'s pricing compare to ours?" Market Positioning: Command: "Explain how [Competitor Name] positions itself in the market." Command: "What are the unique selling propositions (USPs) of [Competitor Name]?" SWOT Analysis: Command: "Perform a SWOT analysis for [Competitor Name]." Command: "Identify strengths and weaknesses of [Competitor Name]'s product line." Customer Sentiment: Command: "Summarize customer reviews and feedback for [Competitor Name]'s [specific product]." Command: "What are common customer complaints about [Competitor Name]?" | AP8: =substitute('Prompt Template'!$D$2,$AN$5,$AO8) -> You are an expert evaluator of AI instruction design and CustomGPT configuration. Your goal is to evaluate how effectively a respondent demonstrates their ability to write high-quality AI instructions — the kind used to configure tools like CustomGPTs, Copilot Agents, or Google Gems. The test question asks respondents to: ‘Write instructions for a Custom GPT that would help team members gather competitive intelligence consistently.’ This scenario is used only as a familiar example. Do not evaluate their knowledge of competitive analysis — only the clarity, structure, and effectiveness of their AI instruction design. The competitive intelligence context is a stand-in for any business task. Scoring Overview Rate each response on a scale of 0–5. • 5 = System-ready, strong demonstration of instruction design skill. • 0 = Irrelevant or no response. Focus on instructional quality, not topic expertise or formatting aesthetics. Evaluation Dimensions 1. Structural Design Effective instructions clearly define the inputs, process/steps, and outputs. They show logical sequencing (e.g., research → organize → summarize) and reflect understanding of how AI interprets procedural tasks. 2. Instructional Precision Steps and directives are specific, actionable, and testable by an AI. Avoids vague terms like “analyze competitors” without specifying how to do so or what output is expected. 3. Boundary and Role Definition Strong instructions establish clear context for the AI — defining its role, scope, and constraints. They guide what to include/exclude and how to handle ambiguity or conflicting data. 4. Reusability and Scalability Good instructions can be reused consistently by others. They define consistent formatting, data structures, or repeatable logic that ensures stable results across users or scenarios. 5. Outcome Alignment The best instructions would realistically result in a functioning CustomGPT that performs the intended task accurately and consistently. Weak ones would produce inconsistent or low-quality behavior. Scoring Guidelines Score 5 – System-Ready • Instructions could be pasted directly into a CustomGPT/Copilot and perform effectively. • They demonstrate full system readiness — meaning the AI could execute the intended behavior repeatedly and autonomously, without additional clarification. • Includes: • Defined role and purpose (who/what the AI is). • Clear inputs (what information or user query it receives). • Explicit steps/process (how the AI should perform the task). • Defined outputs (format, tone, or structure of response). • Constraints/quality controls (rules, caveats, or handling instructions). • Demonstrates awareness of how to build a reusable, consistent AI behavior. Example 1: “Role: Competitive Intelligence Assistant. Purpose: Gather structured competitor data from reliable sources. Inputs: Company/product names. Process: 1) Identify top 5 competitors, 2) Extract features/pricing, 3) Summarize differences in a table. Output: Comparative matrix. Guardrails: Only use credible, verifiable sources.” Example 2 (Natural-Language Equivalent): “This CustomGPT should act as our internal research analyst. When given a company or product name, it identifies credible sources like official websites, press releases, and reviews. It compares product features, pricing, and messaging across competitors and summarizes the results in a consistent table and a short written overview with citations. The report should flag any information that seems outdated or unverified and maintain a uniform format for reuse across projects.” Note: Responses may use either explicit headings (Role/Inputs/Process/Output) or fluent natural language. Both are valid if they include equivalent components and could realistically produce consistent, reusable results. Score 4 – Strong but Missing Refinements • Structured and actionable; includes most components (e.g., steps, outputs, and some constraints). • Missing minor refinements such as input specificity, error handling, or reusability mechanisms. • AI could perform the task, but inconsistently. Example 1: “Gather information on competitors’ products, features, and pricing. Summarize in a table. Cite reliable sources.” (Functional but missing full structure or clear constraints.) Example 2: “Create a CustomGPT that collects information from competitor websites, reviews, and announcements. Summarize pricing, features, and positioning in a table, then highlight new updates. Include dates and brief notes on source credibility.” (Strong structure, but lacks clear inputs and reusability framing.) Score 3 – Structured but Shallow • Provides a reasonable outline or list of tasks but lacks cohesion or precision. • Mentions the goal but misses how to operationalize it in a repeatable, system-friendly way. • AI would need to infer too much to work reliably. Example 1: “Research competitors and summarize key findings about pricing and positioning.” (Has intent but lacks sequencing or defined outputs.) Example 2: “The GPT should find information about our competitors’ pricing and products, summarize what’s different, and give a short write-up each week.” (Clear intent, but underspecified logic — reads more like a to-do list than executable instructions.) Score 2 – Fragmented or Vague • Mentions competitive research but provides minimal or disconnected guidance. • Steps are generic, unsequenced, or too ambiguous to drive consistent AI behavior. Example elements: “Look up competitors and gather details.” “Find competitor info and summarize.” (Too vague to translate into functioning instructions.) Score 1 – Minimal or Misunderstood • Shows fundamental misunderstanding of AI instruction design. • Generic, incomplete, or irrelevant content that couldn’t guide an AI system at all. Example elements: “Just tell GPT to look up competitors.” “I’d ask it to find info about other companies.” “Use ChatGPT to do competitive research for us.” “Help me understand what our competitors do better.” “Search online for competitor products and summarize.” (Shows surface-level familiarity with AI but no system thinking.) Score 0 – No Response or Irrelevant • Empty, “I don’t know,” or unrelated answer. Example elements: “Not sure what to put here.” “I don’t use GPT for that.” “I’d rather do that myself.” “No idea how to write that.” (Shows confusion or complete lack of task understanding.) Evaluator Checklist When scoring, focus on functional design quality, not formatting or topic expertise. Ask yourself: • Does the response clearly define the AI’s role, inputs, process, and outputs? • Are instructions specific, sequenced, and testable? • Do they include boundaries or quality controls? • Could the AI perform the task consistently and autonomously if these instructions were used? • Is the response written at a configuration level (system prompt) rather than a one-off user command? Heuristic: • 5 = Fully structured, system-ready, reusable. • 4 = Strong, nearly system-ready, missing refinements. • 3 = Structured but shallow. • 2 = Fragmented or vague. • 1 = Minimal or misunderstood. • 0 = None/irrelevant. Scoring Instruction: For your response, ONLY output the single score (0–5). Do not include any explanation. Here is the user’s input: <user_input>1. User Commands and Queries Product Research: Command: "Provide an overview of [Competitor Name]'s latest product offerings." Command: "What are the key features of [Competitor Name]'s [specific product]?" Pricing Analysis: Command: "List the pricing strategies used by [Competitor Name] for [specific product/category]." Command: "How does [Competitor Name]'s pricing compare to ours?" Market Positioning: Command: "Explain how [Competitor Name] positions itself in the market." Command: "What are the unique selling propositions (USPs) of [Competitor Name]?" SWOT Analysis: Command: "Perform a SWOT analysis for [Competitor Name]." Command: "Identify strengths and weaknesses of [Competitor Name]'s product line." Customer Sentiment: Command: "Summarize customer reviews and feedback for [Competitor Name]'s [specific product]." Command: "What are common customer complaints about [Competitor Name]?"</user_input> | AQ8: {=index('Response Scoring'!$I:$I,match($A8,'Response Scoring'!$A:$A,0))} -> 1 | AR8: =$AQ8/5 -> 0.2 | AS8: =sumproduct($AG8:$AR8,$AG$3:$AR$3) -> 5.3 | AT8: =($AH8*2)+(AM8*8) -> 8.4 | AU8: =($U8*$AW$4)+($AF8*$AW$3)+($AS8*$AW$2) -> 30.233333 | AV8: =$AU8*2 -> 60.466667 | AW8: =IF($AV8>=80,"AI Expert",if($AV8>=60,"AI Practitioner",IF(AND($AV8<60,$AV8>=25),"AI Experimenter",if(and($AV8<25,$AV8>=0),"AI Novice")))) -> AI Practitioner | AX8: ='Raw Data'!AF4 -> ChatGPT, Gemini, Claude, CoPilot | AY8: ='Raw Data'!AG4 -> Yes | AZ8: ='Raw Data'!AH4 | BA8: ='Raw Data'!AI4 | BB8: ='Raw Data'!AJ4 | BC8: ='Raw Data'!AK4 | BD8: ='Raw Data'!AL4 | BE8: ='Raw Data'!AM4 | ... BR8: ='Raw Data'!AZ4 | BS8: ='Raw Data'!D4 | BT8: ='Raw Data'!E4 | BU8: ='Raw Data'!F4 -> #N/A | BV8: ='Raw Data'!G4 -> #N/A | BW8: =if(BV8='Demographic Analysis'!$A$22,"Yes","No") -> #N/A | BX8: ='Raw Data'!I4 -> #N/A | BY8: ='Raw Data'!J4 | BZ8: ='Raw Data'!K4 | CA8: ='Raw Data'!L4 -> #N/A | CB8: ='Raw Data'!M4 -> #N/A | CC8: ='Raw Data'!N4 -> #N/A | CD8: ='Raw Data'!O4 -> #N/A | CE8: ='Raw Data'!P4 -> #N/A | CF8: ='Raw Data'!Q4 -> #N/A
A9: ='Raw Data'!$A5 -> 3 | B9: ='Raw Data'!$R5 -> Daily | C9: =if($B9="Never or rarely",0,if($B9="A few times a month",0.25,if($B9="Weekly",0.5,if($B9="Several times a week",0.75,if($B9="Daily",1))))) -> 1 | D9: ='Raw Data'!$S5 -> Getting quick answers to specific questions or looking up information, Editing or improving text I’ve already written (emails, documents, presentations), Analyzing data or documents to extract insights or summaries, Brainstorming ideas, testing concepts, or getting feedback on my thinking | E9: =if(isnumber(search("I don't use AI for work",$D9)),0,if(or(isnumber(search("Vibe Coding",$D9)),isnumber(search("custom prompts",$D9))),3,if(or(isnumber(search("brainstorming ideas",$D9)),isnumber(search("analyzing data",$D9)),isnumber(search("Creating first drafts",$D9))),2,1))) -> 2 | F9: =$E9/3 -> 0.66666667 | G9: ='Raw Data'!T5 -> I’ve built custom AI tools (CustomGPTs, Copilot Agents, Google Gems, Claude Projects) for repetitive tasks | H9: =if($G9="I don't use AI for work",0,if($G9="I create fresh prompts each time I use AI",0.25,if($G9="I maintain a library of prompts that I reuse frequently",0.5,if($G9="I’ve built custom AI tools (CustomGPTs, Copilot Agents, Google Gems, Claude Projects) for repetitive tasks",0.75,if($G9="I’ve created workflows that connect AI with other systems (Slack, Salesforce, email) using integrations or code",1))))) -> 0.75 | I9: ='Raw Data'!$U5 -> Create a systematic process where AI handles data analysis and summary generation consistently | J9: =if($I9="I wouldn’t use AI for this task",0,if($I9="Ask AI to write the summary after you’ve analyzed all the data",0.33,if($I9="Use AI to help analyze each data source, then compile results manually",0.67,if($I9="Create a systematic process where AI handles data analysis and summary generation consistently",1)))) -> 1 | K9: ='Raw Data'!$V5 -> First to enlarge my knowledge on the subject. Second to help me develop an agenda for the presentation - I'd share the goal of the presentation, the audience, must have, time. Third, I'd include some past presentations as benchmark if existed. Fourth I'd start populating the available information so the AI would draft pages and fifth we could together work on the presentation | L9: First to enlarge my knowledge on the subject. Second to help me develop an agenda for the presentation - I'd share the goal of the presentation, the audience, must have, time. Third, I'd include some past presentations as benchmark if existed. Fourth I'd start populating the available information so the AI would draft pages and fifth we could together work on the presentation | M9: =substitute('Prompt Template'!$A$2,$K$5,$L9) -> You are an expert evaluator of AI strategic thinking and workflow integration. Your goal is to evaluate how effectively survey respondents demonstrate strategic AI application based on their response to the question: “You have one week to create an important presentation for senior stakeholders on an unfamiliar topic. How would you use AI in this process?” Evaluate each response holistically across three key areas: Workflow Integration: Effective responses demonstrate systematic thinking by identifying multiple stages of the presentation process where AI can add value (research, analysis, content creation, structure, review, etc.). They show understanding that complex projects benefit from AI integration at various points rather than just using AI for one isolated task. Strategic Application: Strong responses show context-aware AI usage that specifically addresses the unique challenges of this scenario — leveraging AI to quickly understand an unfamiliar topic, tailoring content for senior stakeholders, and managing time constraints effectively. They go beyond generic AI applications to show thoughtful consideration of the specific requirements. Practical Execution: Quality responses demonstrate concrete understanding of how AI tools actually work by providing specific, actionable approaches rather than vague descriptions. They show familiarity with AI capabilities and limitations, and describe realistic implementation steps. Scoring Guidelines Score 3 — Strong strategic thinking • Demonstrates comprehensive AI integration across most or all key workflow stages (e.g., research, structure, content creation, context tailoring for senior stakeholders, review), combined with clear scenario awareness and practical execution. • Responses do not need to mention every single stage explicitly; concise or list-style answers can still score a 3 if they show a strategically complete, end-to-end approach that addresses the scenario’s unique challenges (unfamiliar topic, senior stakeholders, tight timelines). • Omitting one stage (e.g., review) does not disqualify a response if the overall strategy is robust and well-adapted. • Both structured and concise list-style responses are valid. Examples: • “Research topic comprehensively, analyze stakeholder needs, create presentation framework, develop content, review for clarity.” • “Use AI throughout the process — from initial research to final presentation polish — focusing on what senior stakeholders care about most.” • “I would use AI to research the topic, understand key stakeholder concerns, create a logical flow, and draft compelling content for senior leadership within the time constraint.” • “Scan unfamiliar topic, outline slides, tailor framing for executives, draft key content, fact-check and polish.” (Concise list-style example demonstrating full coverage) • “Research unfamiliar topic, structure the deck, tailor for executives, draft content.” (Covers most strategic stages, omits review but is still strategically comprehensive) Score 2 — Moderate strategic thinking • Demonstrates partial but not comprehensive coverage of the key strategic dimensions. • Typically covers two to three workflow stages (e.g., structure + content + some context) but omits one or more major elements such as research, scenario adaptation, or review. • May show good workflow integration but limited scenario context, or vice versa. • Responses may be clear and practical but reflect a mid-level strategic approach rather than end-to-end planning. Examples: • “Use AI to quickly understand the topic, then create an outline and draft the presentation content.” • “Research phase, analysis phase, content creation phase, review phase.” • “Use AI to help research industry trends and create slides tailored for executives.” • “Draft speaker notes, executive framing, summarize key sources.” (Covers content, some research, and context but lacks structure/review) • “10 slide structure, add citations, executive framing.” (Structure, review, context but no research/content creation) Score 1 — Limited strategic thinking • Shows basic or single AI application with little reference to workflow complexity or scenario context. • Generic AI usage that could apply to any presentation task. Examples: • “Use AI to research the topic and create slides.” • “ChatGPT for research, help with structure.” • “Research, writing, editing.” • “Ask AI to help me understand the topic.” Score 0 — No relevant response • No answer, states they wouldn’t use AI, or provides irrelevant content. Special Guidance on Format and Brevity • Do not penalize for response format or brevity. • Evaluate list-style or terse responses based on substance, not phrasing. • A concise response that clearly addresses all key strategic dimensions can score a 3. • Responses that address only part of the workflow or omit key scenario considerations should score a 2, even if clearly written. • Brevity alone should not lower a score. Output: For your response, ONLY output the single score (0–3). Do not include any explanation. Here is the user’s input: <user_input>First to enlarge my knowledge on the subject. Second to help me develop an agenda for the presentation - I'd share the goal of the presentation, the audience, must have, time. Third, I'd include some past presentations as benchmark if existed. Fourth I'd start populating the available information so the AI would draft pages and fifth we could together work on the presentation</user_input> | N9: {=index('Response Scoring'!$C:$C,match($A9,'Response Scoring'!$A:$A,0))} -> 3 | O9: =$N9/3 -> 1 | P9: ='Raw Data'!$W5 -> Build different projections for our performance based on different statistical models. It saves a day of my work | Q9: Build different projections for our performance based on different statistical models. It saves a day of my work | R9: =substitute('Prompt Template'!$B$2,$P$5,$Q9) -> You are an expert evaluator of practical AI value creation in work contexts. Your goal is to evaluate how effectively survey respondents demonstrate valuable AI usage based on their response to the question: ‘What is the most useful or valuable way you are using AI in your work?’ Valuable AI usage enables higher speed and/or quality work outputs with measurable impact on workflow pain points or business objectives. Strong responses demonstrate AI integration that transforms how core work gets done, rather than providing minor convenience. Score 3 — Workflow Redesign / Integrated Use (Human-in-the-Loop or Automated) Definition: Demonstrates strategic, repeatable AI integration that has redesigned or materially enhanced how the respondent performs a core part of their job. AI is consistently embedded in their workflow, creates new capabilities, or systematically improves downstream outputs or decisions. Transformation may involve automation or a human-in-the-loop redesign. Transformation requires more than saving time on peripheral tasks. The AI use must alter how a core deliverable is created, reviewed, or decided on — not just replace small administrative tasks within it. Time savings are only valid when they result from a redesigned or automated workflow step that affects downstream outputs or team decision-making. Observable Signals (any two or more): • Defined trigger or cadence (e.g., “after every client call,” “weekly review,” or implied repetition such as “each week,” “after calls,” or “whenever new data is ready”). • Template, checklist, or structured prompt used consistently. • AI output feeds directly into another step or tool (e.g., CRM, backlog, report). • AI introduces a new step, quality gate, or sequencing change. • AI automation replaces a manual stage and enables higher-value analytical or decision-making work. • Concise responses still qualify if they clearly imply repeatable, embedded use. Contrast Examples: Meeting Notes → Follow-up • (3) “After each client call, I run a prompt that tags actions by owner and priority, then imports them into our tracker.” • (2) “After calls, I paste notes into AI to group actions by owner and due date.” • (1) “I use AI to summarize meeting notes.” Customer Feedback → Insights • (3) “Each week, AI clusters customer comments, maps them to product areas, and ranks issues I review for roadmap planning.” • (2) “AI helps cluster customer comments into themes for my monthly report.” • (1) “I ask AI to summarize customer feedback.” Data Analysis / SQL • (3) “AI generates and validates queries, produces comparison tables, and highlights anomalies I review in reports.” • (2) “AI drafts SQL queries and interprets results faster than manual work.” • (1) “AI explains SQL when I’m stuck.” Proposal / Report Writing • (3) “I use a repeatable AI template that turns briefs into full drafts with rationale and risks sections, which I refine for delivery.” • (2) “AI drafts first sections of my proposals based on my outline.” • (1) “AI helps me improve grammar and phrasing.” Competitive Research • (3) “AI normalizes competitor data, flags gaps, and generates a positioning summary for our quarterly review.” • (2) “AI extracts pricing and features into a summary table before I write my report.” • (1) “AI summarizes competitor websites.” Score 2 — Process Enhancement / Embedded Use Definition: Shows repeatable, meaningful AI use within an existing process that improves speed, quality, or consistency. AI use is consistent and relevant to core responsibilities, but the workflow design and logic remain the same. May include structured use for efficiency, but does not fundamentally change how deliverables are produced or how information flows. Observable Signals (any one): • Clear efficiency, clarity, or organization benefit. • Consistent use within a step of a recurring workflow. • Described as part of normal work, not one-off. • Partial structure or templates used manually. Examples: • “I use AI to organize survey responses and find key themes before my analysis.” • “AI drafts report sections to help me start faster.” • “I use AI to group meeting notes by owner for easier follow-up.” • “AI summarizes recurring reports or data updates to save time, but outputs are reviewed or reformatted manually.” Score 1 — Task Assistance / Surface-Level Use Definition: Describes episodic or one-step assistance focused on convenience or small efficiency gains. AI is not embedded in a structured workflow or used consistently. Includes short, isolated tasks that do not influence how other work is performed. Observable Signals: • Task-specific or one-off. • No cadence, handoff, or reuse. • Focused on formatting, writing, or explanation. • Peripheral use — does not alter how a core deliverable or process is executed. Examples: • “I use AI to fix grammar or reword emails.” • “AI helps me write Excel formulas or explain code.” • “I use AI to summarize meeting notes.” • “AI drafts short internal updates so I can focus elsewhere.” Score 0 — No or Irrelevant Use Definition: No evidence of AI use in a work context or explicitly states they do not use AI. Example: • “I don’t use AI in my work.” Evaluator Checklist When scoring, ignore writing quality and phrasing. Look for evidence of process depth: • Defined trigger or cadence? (explicit or implied) • Repeatable prompt, checklist, or playbook? • AI output feeding another step or tool? • Workflow sequence or ownership changed? • New capability or quality gate introduced? • When evaluating time savings, consider whether the AI use alters how a core deliverable is produced or simply removes a peripheral or administrative step. • Does the AI output directly support a core deliverable (e.g., reports, analysis, client output)? • Cohesion check: Are the tasks connected within a single workflow or purpose? • If the response lists multiple unrelated activities (e.g., “draft emails, brainstorm ideas, summarize reports”), treat it as multiple isolated uses and score at the lower level. Heuristic: • 3 = Embedded + ≥ 2 signals + cohesive workflow or clear transformation of core deliverable • 2 = Embedded + 0–1 signal + cohesive workflow, limited transformation • 1 = Isolated or peripheral task use • 0 = None Scoring Instruction: For your response, ONLY output the single score (0–3). Do not include any explanation. Here is the user’s input: <user_input>Build different projections for our performance based on different statistical models. It saves a day of my work</user_input> | S9: {=index('Response Scoring'!$E:$E,match($A9,'Response Scoring'!$A:$A,0))} -> 2 | T9: =$S9/3 -> 0.66666667 | U9: =sumproduct($B9:$T9,$B$4:$T$4) -> 5.0833333 | V9: ='Raw Data'!$X5 -> Creating a complete slide deck with visual design for an important client presentation | W9: =if($V9="Analyzing presentation slides to evaluate both the visual design and written content for consistency",1,0) -> 0 | X9: ='Raw Data'!$Y5 -> Hallucinations (generating false or misleading information), Biases in answers, Data privacy concerns when information is shared with an LLM, Vulnerability to manipulation by bad actors | Y9: =if(isnumber(search("Hallucinations",$X9)),0.25)+if(isnumber(search("Biases in answers",$X9)),0.25,0)+if(isnumber(search("Data privacy concerns",$X9)),0.25)+if(isnumber(search("Vulnerability",$X9)),0.25) -> 1 | Z9: ='Raw Data'!$Z5 -> Use secure company instances or enterprise plans when available, Anonymize information by removing identifying details | AA9: =if(or(isnumber(search("Avoid using AI tools",$Z9)),isnumber(search("Verify that the AI tool",$Z9))),0,(if(isnumber(SEARCH("Anonymize information",$Z9)),0.5)+if(isnumber(search("Use secure company instances",$Z9)),0.5))) -> 1 | AB9: ='Raw Data'!$AA5 -> Always: I routinely cross-check AI outputs with reliable sources | AC9: =if($AB9="Never: I typically trust the output as is",0,if($AB9="Rarely: I only verify if something doesn’t sound right",0.33,if($AB9="Sometimes: I do a quick check against known data or references",0.67,if($AB9="Always: I routinely cross-check AI outputs with reliable sources",1)))) -> 1 | AD9: ='Raw Data'!$AB5 -> Ask the same AI tool to double-check its work for accuracy, Cross-reference key claims with reliable external sources, Verify any calculations or data analysis independently, Use a different AI tool to review and verify the content | AE9: =if(or(isnumber(search("Check if the response uses confident language",$AD9)),isnumber(search("Look for professional formatting",$AD9))),0,(if(isnumber(search("Use a different AI tool",$AD9)),0.25)+if(isnumber(search("Cross-reference key claims",$AD9)),0.25)+if(isnumber(search("Verify any calculations",$AD9)),0.25)+if(isnumber(search("Ask the same AI tool",$AD9)),0.25))) -> 1 | AF9: 9.66 | AG9: ='Raw Data'!$AC5 -> Frequently: I systematically refine prompts until I’m satisfied | AH9: =if($AG9="Never: I usually just ask once and accept the first response",0,if($AG9="Rarely: I only tweak the prompt if something feels obviously off",0.33,if($AG9="Sometimes: I iterate 2–3 times to reach a good result",0.67,if($AG9="Frequently: I systematically refine prompts until I’m satisfied",1)))) -> 1 | AI9: ='Raw Data'!$AD5 -> Prompt: “Vou participar de uma reunião para discutir [breve descrição da iniciativa ou proposta, ex: uma nova estratégia de precificação para o e-commerce]. Preciso me preparar para essa conversa. Me ajude a: Estruturar os principais pontos que devo apresentar (contexto, proposta, benefícios, riscos e próximos passos). Antecipar possíveis perguntas ou objeções dos participantes. Definir mensagens-chave e recomendações para aumentar a chance de aprovação. A reunião será com [mencione o público: ex. o VP de Marketing e o time de Operações], e meu objetivo é [ex. obter o aval para seguir com um piloto].” | AJ9: Prompt: “Vou participar de uma reunião para discutir [breve descrição da iniciativa ou proposta, ex: uma nova estratégia de precificação para o e-commerce]. Preciso me preparar para essa conversa. Me ajude a: Estruturar os principais pontos que devo apresentar (contexto, proposta, benefícios, riscos e próximos passos). Antecipar possíveis perguntas ou objeções dos participantes. Definir mensagens-chave e recomendações para aumentar a chance de aprovação. A reunião será com [mencione o público: ex. o VP de Marketing e o time de Operações], e meu objetivo é [ex. obter o aval para seguir com um piloto].” | AK9: =substitute('Prompt Template'!$C$2,$AI$5,$AJ9) -> You are an expert prompt engineer. Your goal is to evaluate the effectiveness of the prompt below. Less effective prompts are too vague, open-ended, and do not give clear instructions. More effective prompts provide background, clear instructions, and are well structured. Since you are tasked with evaluating true effectiveness of the prompt, you can give scores of 1. This is for an AI Readiness Survey that will assess individuals' proficiency when using AI. <task>Write a prompt asking AI to help you prepare for a work meeting to discuss a new initiative or proposal</task> <prompt>Prompt: “Vou participar de uma reunião para discutir [breve descrição da iniciativa ou proposta, ex: uma nova estratégia de precificação para o e-commerce]. Preciso me preparar para essa conversa. Me ajude a: Estruturar os principais pontos que devo apresentar (contexto, proposta, benefícios, riscos e próximos passos). Antecipar possíveis perguntas ou objeções dos participantes. Definir mensagens-chave e recomendações para aumentar a chance de aprovação. A reunião será com [mencione o público: ex. o VP de Marketing e o time de Operações], e meu objetivo é [ex. obter o aval para seguir com um piloto].”</prompt> A score of 1 prompt example: "Help me prepare for my work meeting" Rate the effectiveness on a scale of 1-5. Only respond with a single number from 1-5. If the person states they do not know how to prompt or their prompt isn't relevant to the task, give them a 0. Use the following criteria: Clarity and Specificity: A good prompt should be clear, specific, and focused. It should provide enough context and detail to guide the AI towards generating a relevant and useful response. Vague, open-ended, or ambiguous prompts make it difficult for the AI to understand the user's intent and can lead to generic or irrelevant outputs. Completeness and Sufficiency: An effective prompt should include all the necessary information and requirements to enable the AI to complete the requested task or answer the question thoroughly. It should anticipate what details the AI might need and proactively provide them. Incomplete prompts that leave out critical facts or constraints will likely result in suboptimal responses that fail to fully address the user's needs. Structure and Organization: A well-crafted prompt should be logically structured and organized. It should break down complex requests into clear steps or components, making it easier for the AI to process and respond to each part systematically. Using formatting techniques like bullet points, numbering, or sectioning can help improve the prompt's clarity and readability. Conciseness and Precision: While a good prompt should be detailed and informative, it should also strive to be as concise and precise as possible. Overly wordy or rambling prompts can obscure the key points and make it harder for the AI to identify the essential requirements. An effective prompt finds the right balance between providing necessary context and avoiding extraneous or redundant information. Here is the user's input: <user_input>Prompt: “Vou participar de uma reunião para discutir [breve descrição da iniciativa ou proposta, ex: uma nova estratégia de precificação para o e-commerce]. Preciso me preparar para essa conversa. Me ajude a: Estruturar os principais pontos que devo apresentar (contexto, proposta, benefícios, riscos e próximos passos). Antecipar possíveis perguntas ou objeções dos participantes. Definir mensagens-chave e recomendações para aumentar a chance de aprovação. A reunião será com [mencione o público: ex. o VP de Marketing e o time de Operações], e meu objetivo é [ex. obter o aval para seguir com um piloto].”</user_input> | AL9: {=index('Response Scoring'!$G:$G,match($A9,'Response Scoring'!$A:$A,0))} -> 4 | AM9: =$AL9/5 -> 0.8 | AN9: ='Raw Data'!$AE5 -> Instruções para o Custom GPT de Inteligência Competitiva: Objetivo: Ajudar a equipe a coletar, organizar e analisar informações sobre produtos, preços, campanhas e posicionamento dos concorrentes, garantindo consistência, rapidez e qualidade nas entregas. Funções principais: Pesquisa estruturada: Buscar informações atualizadas em sites oficiais, e-commerces, redes sociais e notícias sobre concorrentes específicos. Comparação de mercado: Gerar tabelas e resumos comparando produtos, preços, embalagens, promoções e mensagens de marketing. Análise de posicionamento: Identificar o público-alvo, os diferenciais comunicados e as estratégias de valor (premium, conveniência, sustentabilidade, etc.). Monitoramento contínuo: Registrar mudanças relevantes (ex: novos lançamentos, variações de preço, alterações de portfólio) com data e fonte. Síntese executiva: Produzir relatórios curtos e objetivos com insights acionáveis e recomendações estratégicas. Tom e formato das respostas: Direto, objetivo e factual. Sempre citar fontes ou links. Quando possível, incluir dados quantitativos e visuais (tabelas, listas, gráficos simples). Destacar implicações para o negócio de forma prática (ex: “pode indicar foco crescente no canal digital”). Prompt base sugerido para o time: “Pesquise informações atualizadas sobre [marca concorrente] no segmento de [categoria] em [país/região]. Resuma produtos, preços médios, mensagens principais e posicionamento de marca. Aponte diferenças relevantes em relação à nossa empresa e destaque oportunidades ou riscos.” | AO9: Instruções para o Custom GPT de Inteligência Competitiva: Objetivo: Ajudar a equipe a coletar, organizar e analisar informações sobre produtos, preços, campanhas e posicionamento dos concorrentes, garantindo consistência, rapidez e qualidade nas entregas. Funções principais: Pesquisa estruturada: Buscar informações atualizadas em sites oficiais, e-commerces, redes sociais e notícias sobre concorrentes específicos. Comparação de mercado: Gerar tabelas e resumos comparando produtos, preços, embalagens, promoções e mensagens de marketing. Análise de posicionamento: Identificar o público-alvo, os diferenciais comunicados e as estratégias de valor (premium, conveniência, sustentabilidade, etc.). Monitoramento contínuo: Registrar mudanças relevantes (ex: novos lançamentos, variações de preço, alterações de portfólio) com data e fonte. Síntese executiva: Produzir relatórios curtos e objetivos com insights acionáveis e recomendações estratégicas. Tom e formato das respostas: Direto, objetivo e factual. Sempre citar fontes ou links. Quando possível, incluir dados quantitativos e visuais (tabelas, listas, gráficos simples). Destacar implicações para o negócio de forma prática (ex: “pode indicar foco crescente no canal digital”). Prompt base sugerido para o time: “Pesquise informações atualizadas sobre [marca concorrente] no segmento de [categoria] em [país/região]. Resuma produtos, preços médios, mensagens principais e posicionamento de marca. Aponte diferenças relevantes em relação à nossa empresa e destaque oportunidades ou riscos.” | AP9: =substitute('Prompt Template'!$D$2,$AN$5,$AO9) -> You are an expert evaluator of AI instruction design and CustomGPT configuration. Your goal is to evaluate how effectively a respondent demonstrates their ability to write high-quality AI instructions — the kind used to configure tools like CustomGPTs, Copilot Agents, or Google Gems. The test question asks respondents to: ‘Write instructions for a Custom GPT that would help team members gather competitive intelligence consistently.’ This scenario is used only as a familiar example. Do not evaluate their knowledge of competitive analysis — only the clarity, structure, and effectiveness of their AI instruction design. The competitive intelligence context is a stand-in for any business task. Scoring Overview Rate each response on a scale of 0–5. • 5 = System-ready, strong demonstration of instruction design skill. • 0 = Irrelevant or no response. Focus on instructional quality, not topic expertise or formatting aesthetics. Evaluation Dimensions 1. Structural Design Effective instructions clearly define the inputs, process/steps, and outputs. They show logical sequencing (e.g., research → organize → summarize) and reflect understanding of how AI interprets procedural tasks. 2. Instructional Precision Steps and directives are specific, actionable, and testable by an AI. Avoids vague terms like “analyze competitors” without specifying how to do so or what output is expected. 3. Boundary and Role Definition Strong instructions establish clear context for the AI — defining its role, scope, and constraints. They guide what to include/exclude and how to handle ambiguity or conflicting data. 4. Reusability and Scalability Good instructions can be reused consistently by others. They define consistent formatting, data structures, or repeatable logic that ensures stable results across users or scenarios. 5. Outcome Alignment The best instructions would realistically result in a functioning CustomGPT that performs the intended task accurately and consistently. Weak ones would produce inconsistent or low-quality behavior. Scoring Guidelines Score 5 – System-Ready • Instructions could be pasted directly into a CustomGPT/Copilot and perform effectively. • They demonstrate full system readiness — meaning the AI could execute the intended behavior repeatedly and autonomously, without additional clarification. • Includes: • Defined role and purpose (who/what the AI is). • Clear inputs (what information or user query it receives). • Explicit steps/process (how the AI should perform the task). • Defined outputs (format, tone, or structure of response). • Constraints/quality controls (rules, caveats, or handling instructions). • Demonstrates awareness of how to build a reusable, consistent AI behavior. Example 1: “Role: Competitive Intelligence Assistant. Purpose: Gather structured competitor data from reliable sources. Inputs: Company/product names. Process: 1) Identify top 5 competitors, 2) Extract features/pricing, 3) Summarize differences in a table. Output: Comparative matrix. Guardrails: Only use credible, verifiable sources.” Example 2 (Natural-Language Equivalent): “This CustomGPT should act as our internal research analyst. When given a company or product name, it identifies credible sources like official websites, press releases, and reviews. It compares product features, pricing, and messaging across competitors and summarizes the results in a consistent table and a short written overview with citations. The report should flag any information that seems outdated or unverified and maintain a uniform format for reuse across projects.” Note: Responses may use either explicit headings (Role/Inputs/Process/Output) or fluent natural language. Both are valid if they include equivalent components and could realistically produce consistent, reusable results. Score 4 – Strong but Missing Refinements • Structured and actionable; includes most components (e.g., steps, outputs, and some constraints). • Missing minor refinements such as input specificity, error handling, or reusability mechanisms. • AI could perform the task, but inconsistently. Example 1: “Gather information on competitors’ products, features, and pricing. Summarize in a table. Cite reliable sources.” (Functional but missing full structure or clear constraints.) Example 2: “Create a CustomGPT that collects information from competitor websites, reviews, and announcements. Summarize pricing, features, and positioning in a table, then highlight new updates. Include dates and brief notes on source credibility.” (Strong structure, but lacks clear inputs and reusability framing.) Score 3 – Structured but Shallow • Provides a reasonable outline or list of tasks but lacks cohesion or precision. • Mentions the goal but misses how to operationalize it in a repeatable, system-friendly way. • AI would need to infer too much to work reliably. Example 1: “Research competitors and summarize key findings about pricing and positioning.” (Has intent but lacks sequencing or defined outputs.) Example 2: “The GPT should find information about our competitors’ pricing and products, summarize what’s different, and give a short write-up each week.” (Clear intent, but underspecified logic — reads more like a to-do list than executable instructions.) Score 2 – Fragmented or Vague • Mentions competitive research but provides minimal or disconnected guidance. • Steps are generic, unsequenced, or too ambiguous to drive consistent AI behavior. Example elements: “Look up competitors and gather details.” “Find competitor info and summarize.” (Too vague to translate into functioning instructions.) Score 1 – Minimal or Misunderstood • Shows fundamental misunderstanding of AI instruction design. • Generic, incomplete, or irrelevant content that couldn’t guide an AI system at all. Example elements: “Just tell GPT to look up competitors.” “I’d ask it to find info about other companies.” “Use ChatGPT to do competitive research for us.” “Help me understand what our competitors do better.” “Search online for competitor products and summarize.” (Shows surface-level familiarity with AI but no system thinking.) Score 0 – No Response or Irrelevant • Empty, “I don’t know,” or unrelated answer. Example elements: “Not sure what to put here.” “I don’t use GPT for that.” “I’d rather do that myself.” “No idea how to write that.” (Shows confusion or complete lack of task understanding.) Evaluator Checklist When scoring, focus on functional design quality, not formatting or topic expertise. Ask yourself: • Does the response clearly define the AI’s role, inputs, process, and outputs? • Are instructions specific, sequenced, and testable? • Do they include boundaries or quality controls? • Could the AI perform the task consistently and autonomously if these instructions were used? • Is the response written at a configuration level (system prompt) rather than a one-off user command? Heuristic: • 5 = Fully structured, system-ready, reusable. • 4 = Strong, nearly system-ready, missing refinements. • 3 = Structured but shallow. • 2 = Fragmented or vague. • 1 = Minimal or misunderstood. • 0 = None/irrelevant. Scoring Instruction: For your response, ONLY output the single score (0–5). Do not include any explanation. Here is the user’s input: <user_input>Instruções para o Custom GPT de Inteligência Competitiva: Objetivo: Ajudar a equipe a coletar, organizar e analisar informações sobre produtos, preços, campanhas e posicionamento dos concorrentes, garantindo consistência, rapidez e qualidade nas entregas. Funções principais: Pesquisa estruturada: Buscar informações atualizadas em sites oficiais, e-commerces, redes sociais e notícias sobre concorrentes específicos. Comparação de mercado: Gerar tabelas e resumos comparando produtos, preços, embalagens, promoções e mensagens de marketing. Análise de posicionamento: Identificar o público-alvo, os diferenciais comunicados e as estratégias de valor (premium, conveniência, sustentabilidade, etc.). Monitoramento contínuo: Registrar mudanças relevantes (ex: novos lançamentos, variações de preço, alterações de portfólio) com data e fonte. Síntese executiva: Produzir relatórios curtos e objetivos com insights acionáveis e recomendações estratégicas. Tom e formato das respostas: Direto, objetivo e factual. Sempre citar fontes ou links. Quando possível, incluir dados quantitativos e visuais (tabelas, listas, gráficos simples). Destacar implicações para o negócio de forma prática (ex: “pode indicar foco crescente no canal digital”). Prompt base sugerido para o time: “Pesquise informações atualizadas sobre [marca concorrente] no segmento de [categoria] em [país/região]. Resuma produtos, preços médios, mensagens principais e posicionamento de marca. Aponte diferenças relevantes em relação à nossa empresa e destaque oportunidades ou riscos.”</user_input> | AQ9: {=index('Response Scoring'!$I:$I,match($A9,'Response Scoring'!$A:$A,0))} -> 4 | AR9: =$AQ9/5 -> 0.8 | AS9: =sumproduct($AG9:$AR9,$AG$3:$AR$3) -> 8.3 | AT9: =($AH9*2)+(AM9*8) -> 8.4 | AU9: =($U9*$AW$4)+($AF9*$AW$3)+($AS9*$AW$2) -> 36.426667 | AV9: =$AU9*2 -> 72.853333 | AW9: =IF($AV9>=80,"AI Expert",if($AV9>=60,"AI Practitioner",IF(AND($AV9<60,$AV9>=25),"AI Experimenter",if(and($AV9<25,$AV9>=0),"AI Novice")))) -> AI Practitioner | AX9: ='Raw Data'!AF5 -> ChatGPT, Claude, Perplexity | AY9: ='Raw Data'!AG5 -> Yes | AZ9: ='Raw Data'!AH5 | BA9: ='Raw Data'!AI5 | BB9: ='Raw Data'!AJ5 | BC9: ='Raw Data'!AK5 | BD9: ='Raw Data'!AL5 | BE9: ='Raw Data'!AM5 | ... BR9: ='Raw Data'!AZ5 | BS9: ='Raw Data'!D5 | BT9: ='Raw Data'!E5 | BU9: ='Raw Data'!F5 -> DTC GHQ | BV9: ='Raw Data'!G5 -> DTC Commercial Finance | BW9: =if(BV9='Demographic Analysis'!$A$22,"Yes","No") -> #REF! | BX9: ='Raw Data'!I5 -> N/A | BY9: ='Raw Data'!J5 | BZ9: ='Raw Data'!K5 | CA9: ='Raw Data'!L5 -> Brazil | CB9: ='Raw Data'!M5 -> Growth Group | CC9: ='Raw Data'!N5 -> AB Inbev | CD9: ='Raw Data'!O5 -> Gaston Razeto - DTC Commercial Finance | CE9: ='Raw Data'!P5 -> Heavy User | CF9: ='Raw Data'!Q5 -> Daily
A10: ='Raw Data'!$A6 -> 4 | B10: ='Raw Data'!$R6 -> Daily | C10: =if($B10="Never or rarely",0,if($B10="A few times a month",0.25,if($B10="Weekly",0.5,if($B10="Several times a week",0.75,if($B10="Daily",1))))) -> 1 | D10: ='Raw Data'!$S6 -> Getting quick answers to specific questions or looking up information, Editing or improving text I’ve already written (emails, documents, presentations), Writing or debugging code, scripts, or formulas, Creating first drafts of content from scratch (reports, proposals, marketing copy), Analyzing data or documents to extract insights or summaries, Brainstorming ideas, testing concepts, or getting feedback on my thinking, Using AI for vibe coding to prototype solutions, apps, or products | E10: =if(isnumber(search("I don't use AI for work",$D10)),0,if(or(isnumber(search("Vibe Coding",$D10)),isnumber(search("custom prompts",$D10))),3,if(or(isnumber(search("brainstorming ideas",$D10)),isnumber(search("analyzing data",$D10)),isnumber(search("Creating first drafts",$D10))),2,1))) -> 3 | F10: =$E10/3 -> 1 | G10: ='Raw Data'!T6 -> I’ve built custom AI tools (CustomGPTs, Copilot Agents, Google Gems, Claude Projects) for repetitive tasks | H10: =if($G10="I don't use AI for work",0,if($G10="I create fresh prompts each time I use AI",0.25,if($G10="I maintain a library of prompts that I reuse frequently",0.5,if($G10="I’ve built custom AI tools (CustomGPTs, Copilot Agents, Google Gems, Claude Projects) for repetitive tasks",0.75,if($G10="I’ve created workflows that connect AI with other systems (Slack, Salesforce, email) using integrations or code",1))))) -> 0.75 | I10: ='Raw Data'!$U6 -> Use AI to help analyze each data source, then compile results manually | J10: =if($I10="I wouldn’t use AI for this task",0,if($I10="Ask AI to write the summary after you’ve analyzed all the data",0.33,if($I10="Use AI to help analyze each data source, then compile results manually",0.67,if($I10="Create a systematic process where AI handles data analysis and summary generation consistently",1)))) -> 0.67 | K10: ='Raw Data'!$V6 -> Faria uma pesquisa usando Deep Research com o tema. Abasteceria todos demais dados e informações que tenho sobre o tema. Depois pediria para a IA gerar um roteiro para uma apresentação para executivos, considerando um storytelling e citando dados, evidências e referências. Depois pediria para IA transformar esse roteiro em uma apresentação didática em formato de slides. | L10: Faria uma pesquisa usando Deep Research com o tema. Abasteceria todos demais dados e informações que tenho sobre o tema. Depois pediria para a IA gerar um roteiro para uma apresentação para executivos, considerando um storytelling e citando dados, evidências e referências. Depois pediria para IA transformar esse roteiro em uma apresentação didática em formato de slides. | M10: =substitute('Prompt Template'!$A$2,$K$5,$L10) -> You are an expert evaluator of AI strategic thinking and workflow integration. Your goal is to evaluate how effectively survey respondents demonstrate strategic AI application based on their response to the question: “You have one week to create an important presentation for senior stakeholders on an unfamiliar topic. How would you use AI in this process?” Evaluate each response holistically across three key areas: Workflow Integration: Effective responses demonstrate systematic thinking by identifying multiple stages of the presentation process where AI can add value (research, analysis, content creation, structure, review, etc.). They show understanding that complex projects benefit from AI integration at various points rather than just using AI for one isolated task. Strategic Application: Strong responses show context-aware AI usage that specifically addresses the unique challenges of this scenario — leveraging AI to quickly understand an unfamiliar topic, tailoring content for senior stakeholders, and managing time constraints effectively. They go beyond generic AI applications to show thoughtful consideration of the specific requirements. Practical Execution: Quality responses demonstrate concrete understanding of how AI tools actually work by providing specific, actionable approaches rather than vague descriptions. They show familiarity with AI capabilities and limitations, and describe realistic implementation steps. Scoring Guidelines Score 3 — Strong strategic thinking • Demonstrates comprehensive AI integration across most or all key workflow stages (e.g., research, structure, content creation, context tailoring for senior stakeholders, review), combined with clear scenario awareness and practical execution. • Responses do not need to mention every single stage explicitly; concise or list-style answers can still score a 3 if they show a strategically complete, end-to-end approach that addresses the scenario’s unique challenges (unfamiliar topic, senior stakeholders, tight timelines). • Omitting one stage (e.g., review) does not disqualify a response if the overall strategy is robust and well-adapted. • Both structured and concise list-style responses are valid. Examples: • “Research topic comprehensively, analyze stakeholder needs, create presentation framework, develop content, review for clarity.” • “Use AI throughout the process — from initial research to final presentation polish — focusing on what senior stakeholders care about most.” • “I would use AI to research the topic, understand key stakeholder concerns, create a logical flow, and draft compelling content for senior leadership within the time constraint.” • “Scan unfamiliar topic, outline slides, tailor framing for executives, draft key content, fact-check and polish.” (Concise list-style example demonstrating full coverage) • “Research unfamiliar topic, structure the deck, tailor for executives, draft content.” (Covers most strategic stages, omits review but is still strategically comprehensive) Score 2 — Moderate strategic thinking • Demonstrates partial but not comprehensive coverage of the key strategic dimensions. • Typically covers two to three workflow stages (e.g., structure + content + some context) but omits one or more major elements such as research, scenario adaptation, or review. • May show good workflow integration but limited scenario context, or vice versa. • Responses may be clear and practical but reflect a mid-level strategic approach rather than end-to-end planning. Examples: • “Use AI to quickly understand the topic, then create an outline and draft the presentation content.” • “Research phase, analysis phase, content creation phase, review phase.” • “Use AI to help research industry trends and create slides tailored for executives.” • “Draft speaker notes, executive framing, summarize key sources.” (Covers content, some research, and context but lacks structure/review) • “10 slide structure, add citations, executive framing.” (Structure, review, context but no research/content creation) Score 1 — Limited strategic thinking • Shows basic or single AI application with little reference to workflow complexity or scenario context. • Generic AI usage that could apply to any presentation task. Examples: • “Use AI to research the topic and create slides.” • “ChatGPT for research, help with structure.” • “Research, writing, editing.” • “Ask AI to help me understand the topic.” Score 0 — No relevant response • No answer, states they wouldn’t use AI, or provides irrelevant content. Special Guidance on Format and Brevity • Do not penalize for response format or brevity. • Evaluate list-style or terse responses based on substance, not phrasing. • A concise response that clearly addresses all key strategic dimensions can score a 3. • Responses that address only part of the workflow or omit key scenario considerations should score a 2, even if clearly written. • Brevity alone should not lower a score. Output: For your response, ONLY output the single score (0–3). Do not include any explanation. Here is the user’s input: <user_input>Faria uma pesquisa usando Deep Research com o tema. Abasteceria todos demais dados e informações que tenho sobre o tema. Depois pediria para a IA gerar um roteiro para uma apresentação para executivos, considerando um storytelling e citando dados, evidências e referências. Depois pediria para IA transformar esse roteiro em uma apresentação didática em formato de slides.</user_input> | N10: {=index('Response Scoring'!$C:$C,match($A10,'Response Scoring'!$A:$A,0))} -> 3 | O10: =$N10/3 -> 1 | P10: ='Raw Data'!$W6 -> IA para analisar feedbacks de usuários, análise de dados de performance do produto, automatização do processo de discovery de produto | Q10: IA para analisar feedbacks de usuários, análise de dados de performance do produto, automatização do processo de discovery de produto | R10: =substitute('Prompt Template'!$B$2,$P$5,$Q10) -> You are an expert evaluator of practical AI value creation in work contexts. Your goal is to evaluate how effectively survey respondents demonstrate valuable AI usage based on their response to the question: ‘What is the most useful or valuable way you are using AI in your work?’ Valuable AI usage enables higher speed and/or quality work outputs with measurable impact on workflow pain points or business objectives. Strong responses demonstrate AI integration that transforms how core work gets done, rather than providing minor convenience. Score 3 — Workflow Redesign / Integrated Use (Human-in-the-Loop or Automated) Definition: Demonstrates strategic, repeatable AI integration that has redesigned or materially enhanced how the respondent performs a core part of their job. AI is consistently embedded in their workflow, creates new capabilities, or systematically improves downstream outputs or decisions. Transformation may involve automation or a human-in-the-loop redesign. Transformation requires more than saving time on peripheral tasks. The AI use must alter how a core deliverable is created, reviewed, or decided on — not just replace small administrative tasks within it. Time savings are only valid when they result from a redesigned or automated workflow step that affects downstream outputs or team decision-making. Observable Signals (any two or more): • Defined trigger or cadence (e.g., “after every client call,” “weekly review,” or implied repetition such as “each week,” “after calls,” or “whenever new data is ready”). • Template, checklist, or structured prompt used consistently. • AI output feeds directly into another step or tool (e.g., CRM, backlog, report). • AI introduces a new step, quality gate, or sequencing change. • AI automation replaces a manual stage and enables higher-value analytical or decision-making work. • Concise responses still qualify if they clearly imply repeatable, embedded use. Contrast Examples: Meeting Notes → Follow-up • (3) “After each client call, I run a prompt that tags actions by owner and priority, then imports them into our tracker.” • (2) “After calls, I paste notes into AI to group actions by owner and due date.” • (1) “I use AI to summarize meeting notes.” Customer Feedback → Insights • (3) “Each week, AI clusters customer comments, maps them to product areas, and ranks issues I review for roadmap planning.” • (2) “AI helps cluster customer comments into themes for my monthly report.” • (1) “I ask AI to summarize customer feedback.” Data Analysis / SQL • (3) “AI generates and validates queries, produces comparison tables, and highlights anomalies I review in reports.” • (2) “AI drafts SQL queries and interprets results faster than manual work.” • (1) “AI explains SQL when I’m stuck.” Proposal / Report Writing • (3) “I use a repeatable AI template that turns briefs into full drafts with rationale and risks sections, which I refine for delivery.” • (2) “AI drafts first sections of my proposals based on my outline.” • (1) “AI helps me improve grammar and phrasing.” Competitive Research • (3) “AI normalizes competitor data, flags gaps, and generates a positioning summary for our quarterly review.” • (2) “AI extracts pricing and features into a summary table before I write my report.” • (1) “AI summarizes competitor websites.” Score 2 — Process Enhancement / Embedded Use Definition: Shows repeatable, meaningful AI use within an existing process that improves speed, quality, or consistency. AI use is consistent and relevant to core responsibilities, but the workflow design and logic remain the same. May include structured use for efficiency, but does not fundamentally change how deliverables are produced or how information flows. Observable Signals (any one): • Clear efficiency, clarity, or organization benefit. • Consistent use within a step of a recurring workflow. • Described as part of normal work, not one-off. • Partial structure or templates used manually. Examples: • “I use AI to organize survey responses and find key themes before my analysis.” • “AI drafts report sections to help me start faster.” • “I use AI to group meeting notes by owner for easier follow-up.” • “AI summarizes recurring reports or data updates to save time, but outputs are reviewed or reformatted manually.” Score 1 — Task Assistance / Surface-Level Use Definition: Describes episodic or one-step assistance focused on convenience or small efficiency gains. AI is not embedded in a structured workflow or used consistently. Includes short, isolated tasks that do not influence how other work is performed. Observable Signals: • Task-specific or one-off. • No cadence, handoff, or reuse. • Focused on formatting, writing, or explanation. • Peripheral use — does not alter how a core deliverable or process is executed. Examples: • “I use AI to fix grammar or reword emails.” • “AI helps me write Excel formulas or explain code.” • “I use AI to summarize meeting notes.” • “AI drafts short internal updates so I can focus elsewhere.” Score 0 — No or Irrelevant Use Definition: No evidence of AI use in a work context or explicitly states they do not use AI. Example: • “I don’t use AI in my work.” Evaluator Checklist When scoring, ignore writing quality and phrasing. Look for evidence of process depth: • Defined trigger or cadence? (explicit or implied) • Repeatable prompt, checklist, or playbook? • AI output feeding another step or tool? • Workflow sequence or ownership changed? • New capability or quality gate introduced? • When evaluating time savings, consider whether the AI use alters how a core deliverable is produced or simply removes a peripheral or administrative step. • Does the AI output directly support a core deliverable (e.g., reports, analysis, client output)? • Cohesion check: Are the tasks connected within a single workflow or purpose? • If the response lists multiple unrelated activities (e.g., “draft emails, brainstorm ideas, summarize reports”), treat it as multiple isolated uses and score at the lower level. Heuristic: • 3 = Embedded + ≥ 2 signals + cohesive workflow or clear transformation of core deliverable • 2 = Embedded + 0–1 signal + cohesive workflow, limited transformation • 1 = Isolated or peripheral task use • 0 = None Scoring Instruction: For your response, ONLY output the single score (0–3). Do not include any explanation. Here is the user’s input: <user_input>IA para analisar feedbacks de usuários, análise de dados de performance do produto, automatização do processo de discovery de produto</user_input> | S10: {=index('Response Scoring'!$E:$E,match($A10,'Response Scoring'!$A:$A,0))} -> 3 | T10: =$S10/3 -> 1 | U10: =sumproduct($B10:$T10,$B$4:$T$4) -> 5.42 | V10: ='Raw Data'!$X6 -> Creating a complete slide deck with visual design for an important client presentation | W10: =if($V10="Analyzing presentation slides to evaluate both the visual design and written content for consistency",1,0) -> 0 | X10: ='Raw Data'!$Y6 -> Hallucinations (generating false or misleading information), Biases in answers, Data privacy concerns when information is shared with an LLM, Vulnerability to manipulation by bad actors | Y10: =if(isnumber(search("Hallucinations",$X10)),0.25)+if(isnumber(search("Biases in answers",$X10)),0.25,0)+if(isnumber(search("Data privacy concerns",$X10)),0.25)+if(isnumber(search("Vulnerability",$X10)),0.25) -> 1 | Z10: ='Raw Data'!$Z6 -> Only share information that you would be comfortable sharing internally with a colleague, Anonymize information by removing identifying details, Use secure company instances or enterprise plans when available | AA10: =if(or(isnumber(search("Avoid using AI tools",$Z10)),isnumber(search("Verify that the AI tool",$Z10))),0,(if(isnumber(SEARCH("Anonymize information",$Z10)),0.5)+if(isnumber(search("Use secure company instances",$Z10)),0.5))) -> 1 | AB10: ='Raw Data'!$AA6 -> Always: I routinely cross-check AI outputs with reliable sources | AC10: =if($AB10="Never: I typically trust the output as is",0,if($AB10="Rarely: I only verify if something doesn’t sound right",0.33,if($AB10="Sometimes: I do a quick check against known data or references",0.67,if($AB10="Always: I routinely cross-check AI outputs with reliable sources",1)))) -> 1 | AD10: ='Raw Data'!$AB6 -> Cross-reference key claims with reliable external sources, Verify any calculations or data analysis independently, Ask the same AI tool to double-check its work for accuracy, Use a different AI tool to review and verify the content | AE10: =if(or(isnumber(search("Check if the response uses confident language",$AD10)),isnumber(search("Look for professional formatting",$AD10))),0,(if(isnumber(search("Use a different AI tool",$AD10)),0.25)+if(isnumber(search("Cross-reference key claims",$AD10)),0.25)+if(isnumber(search("Verify any calculations",$AD10)),0.25)+if(isnumber(search("Ask the same AI tool",$AD10)),0.25))) -> 1 | AF10: 9.3 | AG10: ='Raw Data'!$AC6 -> Frequently: I systematically refine prompts until I’m satisfied | AH10: =if($AG10="Never: I usually just ask once and accept the first response",0,if($AG10="Rarely: I only tweak the prompt if something feels obviously off",0.33,if($AG10="Sometimes: I iterate 2–3 times to reach a good result",0.67,if($AG10="Frequently: I systematically refine prompts until I’m satisfied",1)))) -> 1 | AI10: ='Raw Data'!$AD6 -> Olá, estou me preparando para uma reunião sobre o assunto X, com a participação das seguintes pessoas: A [cargo Y], B [cargo Z]. Analise o conteudo da minha proposta abaixo e me traga pontos de melhoria baseados no comportamento dos envolvidos. Me traga também 5 perguntas que cada um dos participantes faria ao final da apresentação. Traga também respostas para essas perguntas de forma didática e curta. Ao final traga uma conclusão do porque essa proposta traria benefícios para a empresa. | AJ10: Olá, estou me preparando para uma reunião sobre o assunto X, com a participação das seguintes pessoas: A [cargo Y], B [cargo Z]. Analise o conteudo da minha proposta abaixo e me traga pontos de melhoria baseados no comportamento dos envolvidos. Me traga também 5 perguntas que cada um dos participantes faria ao final da apresentação. Traga também respostas para essas perguntas de forma didática e curta. Ao final traga uma conclusão do porque essa proposta traria benefícios para a empresa. | AK10: =substitute('Prompt Template'!$C$2,$AI$5,$AJ10) -> You are an expert prompt engineer. Your goal is to evaluate the effectiveness of the prompt below. Less effective prompts are too vague, open-ended, and do not give clear instructions. More effective prompts provide background, clear instructions, and are well structured. Since you are tasked with evaluating true effectiveness of the prompt, you can give scores of 1. This is for an AI Readiness Survey that will assess individuals' proficiency when using AI. <task>Write a prompt asking AI to help you prepare for a work meeting to discuss a new initiative or proposal</task> <prompt>Olá, estou me preparando para uma reunião sobre o assunto X, com a participação das seguintes pessoas: A [cargo Y], B [cargo Z]. Analise o conteudo da minha proposta abaixo e me traga pontos de melhoria baseados no comportamento dos envolvidos. Me traga também 5 perguntas que cada um dos participantes faria ao final da apresentação. Traga também respostas para essas perguntas de forma didática e curta. Ao final traga uma conclusão do porque essa proposta traria benefícios para a empresa.</prompt> A score of 1 prompt example: "Help me prepare for my work meeting" Rate the effectiveness on a scale of 1-5. Only respond with a single number from 1-5. If the person states they do not know how to prompt or their prompt isn't relevant to the task, give them a 0. Use the following criteria: Clarity and Specificity: A good prompt should be clear, specific, and focused. It should provide enough context and detail to guide the AI towards generating a relevant and useful response. Vague, open-ended, or ambiguous prompts make it difficult for the AI to understand the user's intent and can lead to generic or irrelevant outputs. Completeness and Sufficiency: An effective prompt should include all the necessary information and requirements to enable the AI to complete the requested task or answer the question thoroughly. It should anticipate what details the AI might need and proactively provide them. Incomplete prompts that leave out critical facts or constraints will likely result in suboptimal responses that fail to fully address the user's needs. Structure and Organization: A well-crafted prompt should be logically structured and organized. It should break down complex requests into clear steps or components, making it easier for the AI to process and respond to each part systematically. Using formatting techniques like bullet points, numbering, or sectioning can help improve the prompt's clarity and readability. Conciseness and Precision: While a good prompt should be detailed and informative, it should also strive to be as concise and precise as possible. Overly wordy or rambling prompts can obscure the key points and make it harder for the AI to identify the essential requirements. An effective prompt finds the right balance between providing necessary context and avoiding extraneous or redundant information. Here is the user's input: <user_input>Olá, estou me preparando para uma reunião sobre o assunto X, com a participação das seguintes pessoas: A [cargo Y], B [cargo Z]. Analise o conteudo da minha proposta abaixo e me traga pontos de melhoria baseados no comportamento dos envolvidos. Me traga também 5 perguntas que cada um dos participantes faria ao final da apresentação. Traga também respostas para essas perguntas de forma didática e curta. Ao final traga uma conclusão do porque essa proposta traria benefícios para a empresa.</user_input> | AL10: {=index('Response Scoring'!$G:$G,match($A10,'Response Scoring'!$A:$A,0))} -> 2 | AM10: =$AL10/5 -> 0.4 | AN10: ='Raw Data'!$AE6 -> Tarefas principais Pesquisar e consolidar informações sobre marcas e concorrentes relevantes no setor (ex: apps de delivery, bebidas, varejo digital, etc.). Analisar preços e modelos de negócio, comparando com o portfólio da AB InBev / Zé Delivery. Identificar diferenciais e oportunidades — o que o concorrente está fazendo de novo, e quais são as lacunas que podemos explorar. Gerar relatórios curtos e padronizados, sempre com data e fonte, respondendo a: Quem é o concorrente? O que está oferecendo? Qual o público e posicionamento? Qual a estratégia de preço? Quais evidências (links, anúncios, prints, etc.) sustentam isso? Atualizar tendências (ex: novas campanhas, expansão geográfica, mudanças de app, inovação de produto). | AO10: Tarefas principais Pesquisar e consolidar informações sobre marcas e concorrentes relevantes no setor (ex: apps de delivery, bebidas, varejo digital, etc.). Analisar preços e modelos de negócio, comparando com o portfólio da AB InBev / Zé Delivery. Identificar diferenciais e oportunidades — o que o concorrente está fazendo de novo, e quais são as lacunas que podemos explorar. Gerar relatórios curtos e padronizados, sempre com data e fonte, respondendo a: Quem é o concorrente? O que está oferecendo? Qual o público e posicionamento? Qual a estratégia de preço? Quais evidências (links, anúncios, prints, etc.) sustentam isso? Atualizar tendências (ex: novas campanhas, expansão geográfica, mudanças de app, inovação de produto). | AP10: =substitute('Prompt Template'!$D$2,$AN$5,$AO10) -> You are an expert evaluator of AI instruction design and CustomGPT configuration. Your goal is to evaluate how effectively a respondent demonstrates their ability to write high-quality AI instructions — the kind used to configure tools like CustomGPTs, Copilot Agents, or Google Gems. The test question asks respondents to: ‘Write instructions for a Custom GPT that would help team members gather competitive intelligence consistently.’ This scenario is used only as a familiar example. Do not evaluate their knowledge of competitive analysis — only the clarity, structure, and effectiveness of their AI instruction design. The competitive intelligence context is a stand-in for any business task. Scoring Overview Rate each response on a scale of 0–5. • 5 = System-ready, strong demonstration of instruction design skill. • 0 = Irrelevant or no response. Focus on instructional quality, not topic expertise or formatting aesthetics. Evaluation Dimensions 1. Structural Design Effective instructions clearly define the inputs, process/steps, and outputs. They show logical sequencing (e.g., research → organize → summarize) and reflect understanding of how AI interprets procedural tasks. 2. Instructional Precision Steps and directives are specific, actionable, and testable by an AI. Avoids vague terms like “analyze competitors” without specifying how to do so or what output is expected. 3. Boundary and Role Definition Strong instructions establish clear context for the AI — defining its role, scope, and constraints. They guide what to include/exclude and how to handle ambiguity or conflicting data. 4. Reusability and Scalability Good instructions can be reused consistently by others. They define consistent formatting, data structures, or repeatable logic that ensures stable results across users or scenarios. 5. Outcome Alignment The best instructions would realistically result in a functioning CustomGPT that performs the intended task accurately and consistently. Weak ones would produce inconsistent or low-quality behavior. Scoring Guidelines Score 5 – System-Ready • Instructions could be pasted directly into a CustomGPT/Copilot and perform effectively. • They demonstrate full system readiness — meaning the AI could execute the intended behavior repeatedly and autonomously, without additional clarification. • Includes: • Defined role and purpose (who/what the AI is). • Clear inputs (what information or user query it receives). • Explicit steps/process (how the AI should perform the task). • Defined outputs (format, tone, or structure of response). • Constraints/quality controls (rules, caveats, or handling instructions). • Demonstrates awareness of how to build a reusable, consistent AI behavior. Example 1: “Role: Competitive Intelligence Assistant. Purpose: Gather structured competitor data from reliable sources. Inputs: Company/product names. Process: 1) Identify top 5 competitors, 2) Extract features/pricing, 3) Summarize differences in a table. Output: Comparative matrix. Guardrails: Only use credible, verifiable sources.” Example 2 (Natural-Language Equivalent): “This CustomGPT should act as our internal research analyst. When given a company or product name, it identifies credible sources like official websites, press releases, and reviews. It compares product features, pricing, and messaging across competitors and summarizes the results in a consistent table and a short written overview with citations. The report should flag any information that seems outdated or unverified and maintain a uniform format for reuse across projects.” Note: Responses may use either explicit headings (Role/Inputs/Process/Output) or fluent natural language. Both are valid if they include equivalent components and could realistically produce consistent, reusable results. Score 4 – Strong but Missing Refinements • Structured and actionable; includes most components (e.g., steps, outputs, and some constraints). • Missing minor refinements such as input specificity, error handling, or reusability mechanisms. • AI could perform the task, but inconsistently. Example 1: “Gather information on competitors’ products, features, and pricing. Summarize in a table. Cite reliable sources.” (Functional but missing full structure or clear constraints.) Example 2: “Create a CustomGPT that collects information from competitor websites, reviews, and announcements. Summarize pricing, features, and positioning in a table, then highlight new updates. Include dates and brief notes on source credibility.” (Strong structure, but lacks clear inputs and reusability framing.) Score 3 – Structured but Shallow • Provides a reasonable outline or list of tasks but lacks cohesion or precision. • Mentions the goal but misses how to operationalize it in a repeatable, system-friendly way. • AI would need to infer too much to work reliably. Example 1: “Research competitors and summarize key findings about pricing and positioning.” (Has intent but lacks sequencing or defined outputs.) Example 2: “The GPT should find information about our competitors’ pricing and products, summarize what’s different, and give a short write-up each week.” (Clear intent, but underspecified logic — reads more like a to-do list than executable instructions.) Score 2 – Fragmented or Vague • Mentions competitive research but provides minimal or disconnected guidance. • Steps are generic, unsequenced, or too ambiguous to drive consistent AI behavior. Example elements: “Look up competitors and gather details.” “Find competitor info and summarize.” (Too vague to translate into functioning instructions.) Score 1 – Minimal or Misunderstood • Shows fundamental misunderstanding of AI instruction design. • Generic, incomplete, or irrelevant content that couldn’t guide an AI system at all. Example elements: “Just tell GPT to look up competitors.” “I’d ask it to find info about other companies.” “Use ChatGPT to do competitive research for us.” “Help me understand what our competitors do better.” “Search online for competitor products and summarize.” (Shows surface-level familiarity with AI but no system thinking.) Score 0 – No Response or Irrelevant • Empty, “I don’t know,” or unrelated answer. Example elements: “Not sure what to put here.” “I don’t use GPT for that.” “I’d rather do that myself.” “No idea how to write that.” (Shows confusion or complete lack of task understanding.) Evaluator Checklist When scoring, focus on functional design quality, not formatting or topic expertise. Ask yourself: • Does the response clearly define the AI’s role, inputs, process, and outputs? • Are instructions specific, sequenced, and testable? • Do they include boundaries or quality controls? • Could the AI perform the task consistently and autonomously if these instructions were used? • Is the response written at a configuration level (system prompt) rather than a one-off user command? Heuristic: • 5 = Fully structured, system-ready, reusable. • 4 = Strong, nearly system-ready, missing refinements. • 3 = Structured but shallow. • 2 = Fragmented or vague. • 1 = Minimal or misunderstood. • 0 = None/irrelevant. Scoring Instruction: For your response, ONLY output the single score (0–5). Do not include any explanation. Here is the user’s input: <user_input>Tarefas principais Pesquisar e consolidar informações sobre marcas e concorrentes relevantes no setor (ex: apps de delivery, bebidas, varejo digital, etc.). Analisar preços e modelos de negócio, comparando com o portfólio da AB InBev / Zé Delivery. Identificar diferenciais e oportunidades — o que o concorrente está fazendo de novo, e quais são as lacunas que podemos explorar. Gerar relatórios curtos e padronizados, sempre com data e fonte, respondendo a: Quem é o concorrente? O que está oferecendo? Qual o público e posicionamento? Qual a estratégia de preço? Quais evidências (links, anúncios, prints, etc.) sustentam isso? Atualizar tendências (ex: novas campanhas, expansão geográfica, mudanças de app, inovação de produto).</user_input> | AQ10: {=index('Response Scoring'!$I:$I,match($A10,'Response Scoring'!$A:$A,0))} -> 4 | AR10: =$AQ10/5 -> 0.8 | AS10: =sumproduct($AG10:$AR10,$AG$3:$AR$3) -> 6.9 | AT10: =($AH10*2)+(AM10*8) -> 5.2 | AU10: =($U10*$AW$4)+($AF10*$AW$3)+($AS10*$AW$2) -> 33.94 | AV10: =$AU10*2 -> 67.88 | AW10: =IF($AV10>=80,"AI Expert",if($AV10>=60,"AI Practitioner",IF(AND($AV10<60,$AV10>=25),"AI Experimenter",if(and($AV10<25,$AV10>=0),"AI Novice")))) -> AI Practitioner | AX10: ='Raw Data'!AF6 -> ChatGPT, CoPilot, Cursor | AY10: ='Raw Data'!AG6 -> No | AZ10: ='Raw Data'!AH6 | BA10: ='Raw Data'!AI6 | BB10: ='Raw Data'!AJ6 | BC10: ='Raw Data'!AK6 | BD10: ='Raw Data'!AL6 | BE10: ='Raw Data'!AM6 | ... BR10: ='Raw Data'!AZ6 | BS10: ='Raw Data'!D6 | BT10: ='Raw Data'!E6 | BU10: ='Raw Data'!F6 -> DTC GHQ | BV10: ='Raw Data'!G6 -> Product Design | BW10: =if(BV10='Demographic Analysis'!$A$22,"Yes","No") -> #REF! | BX10: ='Raw Data'!I6 -> N/A | BY10: ='Raw Data'!J6 | BZ10: ='Raw Data'!K6 | CA10: ='Raw Data'!L6 -> Brazil | CB10: ='Raw Data'!M6 -> Growth Group | CC10: ='Raw Data'!N6 -> AB Inbev | CD10: ='Raw Data'!O6 -> Fernanda Faria - Product Design | CE10: ='Raw Data'!P6 -> Light User | CF10: ='Raw Data'!Q6 -> Weekly
A11: ='Raw Data'!$A7 -> 5 | B11: ='Raw Data'!$R7 -> Daily | C11: =if($B11="Never or rarely",0,if($B11="A few times a month",0.25,if($B11="Weekly",0.5,if($B11="Several times a week",0.75,if($B11="Daily",1))))) -> 1 | D11: ='Raw Data'!$S7 -> Getting quick answers to specific questions or looking up information, Editing or improving text I’ve already written (emails, documents, presentations), Writing or debugging code, scripts, or formulas, Analyzing data or documents to extract insights or summaries, Brainstorming ideas, testing concepts, or getting feedback on my thinking | E11: =if(isnumber(search("I don't use AI for work",$D11)),0,if(or(isnumber(search("Vibe Coding",$D11)),isnumber(search("custom prompts",$D11))),3,if(or(isnumber(search("brainstorming ideas",$D11)),isnumber(search("analyzing data",$D11)),isnumber(search("Creating first drafts",$D11))),2,1))) -> 2 | F11: =$E11/3 -> 0.66666667 | G11: ='Raw Data'!T7 -> I maintain a library of prompts that I reuse frequently | H11: =if($G11="I don't use AI for work",0,if($G11="I create fresh prompts each time I use AI",0.25,if($G11="I maintain a library of prompts that I reuse frequently",0.5,if($G11="I’ve built custom AI tools (CustomGPTs, Copilot Agents, Google Gems, Claude Projects) for repetitive tasks",0.75,if($G11="I’ve created workflows that connect AI with other systems (Slack, Salesforce, email) using integrations or code",1))))) -> 0.5 | I11: ='Raw Data'!$U7 -> Use AI to help analyze each data source, then compile results manually | J11: =if($I11="I wouldn’t use AI for this task",0,if($I11="Ask AI to write the summary after you’ve analyzed all the data",0.33,if($I11="Use AI to help analyze each data source, then compile results manually",0.67,if($I11="Create a systematic process where AI handles data analysis and summary generation consistently",1)))) -> 0.67 | K11: ='Raw Data'!$V7 -> Eu utilizaria a AI para aprender mais sobre o tópico, pedindo para que ela me ensinasse o que é, quais os principais temas realcionados, a correlação com o nosso negócio e os principais impactos, inclusive com exemplos no mercado. Depois perguntaria, com base no tipo de audiência da apresentação, qual a melhor forma de apresentar, quais o highlihts que eles esperam, para que eu pudesse melhor direcionar a apresentação alinhando o tom e tipo de discursso. | L11: Eu utilizaria a AI para aprender mais sobre o tópico, pedindo para que ela me ensinasse o que é, quais os principais temas realcionados, a correlação com o nosso negócio e os principais impactos, inclusive com exemplos no mercado. Depois perguntaria, com base no tipo de audiência da apresentação, qual a melhor forma de apresentar, quais o highlihts que eles esperam, para que eu pudesse melhor direcionar a apresentação alinhando o tom e tipo de discursso. | M11: =substitute('Prompt Template'!$A$2,$K$5,$L11) -> You are an expert evaluator of AI strategic thinking and workflow integration. Your goal is to evaluate how effectively survey respondents demonstrate strategic AI application based on their response to the question: “You have one week to create an important presentation for senior stakeholders on an unfamiliar topic. How would you use AI in this process?” Evaluate each response holistically across three key areas: Workflow Integration: Effective responses demonstrate systematic thinking by identifying multiple stages of the presentation process where AI can add value (research, analysis, content creation, structure, review, etc.). They show understanding that complex projects benefit from AI integration at various points rather than just using AI for one isolated task. Strategic Application: Strong responses show context-aware AI usage that specifically addresses the unique challenges of this scenario — leveraging AI to quickly understand an unfamiliar topic, tailoring content for senior stakeholders, and managing time constraints effectively. They go beyond generic AI applications to show thoughtful consideration of the specific requirements. Practical Execution: Quality responses demonstrate concrete understanding of how AI tools actually work by providing specific, actionable approaches rather than vague descriptions. They show familiarity with AI capabilities and limitations, and describe realistic implementation steps. Scoring Guidelines Score 3 — Strong strategic thinking • Demonstrates comprehensive AI integration across most or all key workflow stages (e.g., research, structure, content creation, context tailoring for senior stakeholders, review), combined with clear scenario awareness and practical execution. • Responses do not need to mention every single stage explicitly; concise or list-style answers can still score a 3 if they show a strategically complete, end-to-end approach that addresses the scenario’s unique challenges (unfamiliar topic, senior stakeholders, tight timelines). • Omitting one stage (e.g., review) does not disqualify a response if the overall strategy is robust and well-adapted. • Both structured and concise list-style responses are valid. Examples: • “Research topic comprehensively, analyze stakeholder needs, create presentation framework, develop content, review for clarity.” • “Use AI throughout the process — from initial research to final presentation polish — focusing on what senior stakeholders care about most.” • “I would use AI to research the topic, understand key stakeholder concerns, create a logical flow, and draft compelling content for senior leadership within the time constraint.” • “Scan unfamiliar topic, outline slides, tailor framing for executives, draft key content, fact-check and polish.” (Concise list-style example demonstrating full coverage) • “Research unfamiliar topic, structure the deck, tailor for executives, draft content.” (Covers most strategic stages, omits review but is still strategically comprehensive) Score 2 — Moderate strategic thinking • Demonstrates partial but not comprehensive coverage of the key strategic dimensions. • Typically covers two to three workflow stages (e.g., structure + content + some context) but omits one or more major elements such as research, scenario adaptation, or review. • May show good workflow integration but limited scenario context, or vice versa. • Responses may be clear and practical but reflect a mid-level strategic approach rather than end-to-end planning. Examples: • “Use AI to quickly understand the topic, then create an outline and draft the presentation content.” • “Research phase, analysis phase, content creation phase, review phase.” • “Use AI to help research industry trends and create slides tailored for executives.” • “Draft speaker notes, executive framing, summarize key sources.” (Covers content, some research, and context but lacks structure/review) • “10 slide structure, add citations, executive framing.” (Structure, review, context but no research/content creation) Score 1 — Limited strategic thinking • Shows basic or single AI application with little reference to workflow complexity or scenario context. • Generic AI usage that could apply to any presentation task. Examples: • “Use AI to research the topic and create slides.” • “ChatGPT for research, help with structure.” • “Research, writing, editing.” • “Ask AI to help me understand the topic.” Score 0 — No relevant response • No answer, states they wouldn’t use AI, or provides irrelevant content. Special Guidance on Format and Brevity • Do not penalize for response format or brevity. • Evaluate list-style or terse responses based on substance, not phrasing. • A concise response that clearly addresses all key strategic dimensions can score a 3. • Responses that address only part of the workflow or omit key scenario considerations should score a 2, even if clearly written. • Brevity alone should not lower a score. Output: For your response, ONLY output the single score (0–3). Do not include any explanation. Here is the user’s input: <user_input>Eu utilizaria a AI para aprender mais sobre o tópico, pedindo para que ela me ensinasse o que é, quais os principais temas realcionados, a correlação com o nosso negócio e os principais impactos, inclusive com exemplos no mercado. Depois perguntaria, com base no tipo de audiência da apresentação, qual a melhor forma de apresentar, quais o highlihts que eles esperam, para que eu pudesse melhor direcionar a apresentação alinhando o tom e tipo de discursso.</user_input> | N11: {=index('Response Scoring'!$C:$C,match($A11,'Response Scoring'!$A:$A,0))} -> 2 | O11: =$N11/3 -> 0.66666667 | P11: ='Raw Data'!$W7 -> Costumo usar com recorrência a AI para me ajudar a produzir resumos de performance semanais com base nos dados compilados até a semana interior. Isso me salva muito tempo. Mas um exemplo valioso que foi muito bom fazer com a AI foi: Construí uma análise de price index e correlacionei com a queda de GMV e potencial de incremento de pedidos. Fiz isso usando a AI para me ajudar na análise de milhares de dados de vendas em vários lugares diferentes, como um analista de dados, e utilizando estatística para determinar um price index ótimo para propor ação de preço para as regiões certas. | Q11: Costumo usar com recorrência a AI para me ajudar a produzir resumos de performance semanais com base nos dados compilados até a semana interior. Isso me salva muito tempo. Mas um exemplo valioso que foi muito bom fazer com a AI foi: Construí uma análise de price index e correlacionei com a queda de GMV e potencial de incremento de pedidos. Fiz isso usando a AI para me ajudar na análise de milhares de dados de vendas em vários lugares diferentes, como um analista de dados, e utilizando estatística para determinar um price index ótimo para propor ação de preço para as regiões certas. | R11: =substitute('Prompt Template'!$B$2,$P$5,$Q11) -> You are an expert evaluator of practical AI value creation in work contexts. Your goal is to evaluate how effectively survey respondents demonstrate valuable AI usage based on their response to the question: ‘What is the most useful or valuable way you are using AI in your work?’ Valuable AI usage enables higher speed and/or quality work outputs with measurable impact on workflow pain points or business objectives. Strong responses demonstrate AI integration that transforms how core work gets done, rather than providing minor convenience. Score 3 — Workflow Redesign / Integrated Use (Human-in-the-Loop or Automated) Definition: Demonstrates strategic, repeatable AI integration that has redesigned or materially enhanced how the respondent performs a core part of their job. AI is consistently embedded in their workflow, creates new capabilities, or systematically improves downstream outputs or decisions. Transformation may involve automation or a human-in-the-loop redesign. Transformation requires more than saving time on peripheral tasks. The AI use must alter how a core deliverable is created, reviewed, or decided on — not just replace small administrative tasks within it. Time savings are only valid when they result from a redesigned or automated workflow step that affects downstream outputs or team decision-making. Observable Signals (any two or more): • Defined trigger or cadence (e.g., “after every client call,” “weekly review,” or implied repetition such as “each week,” “after calls,” or “whenever new data is ready”). • Template, checklist, or structured prompt used consistently. • AI output feeds directly into another step or tool (e.g., CRM, backlog, report). • AI introduces a new step, quality gate, or sequencing change. • AI automation replaces a manual stage and enables higher-value analytical or decision-making work. • Concise responses still qualify if they clearly imply repeatable, embedded use. Contrast Examples: Meeting Notes → Follow-up • (3) “After each client call, I run a prompt that tags actions by owner and priority, then imports them into our tracker.” • (2) “After calls, I paste notes into AI to group actions by owner and due date.” • (1) “I use AI to summarize meeting notes.” Customer Feedback → Insights • (3) “Each week, AI clusters customer comments, maps them to product areas, and ranks issues I review for roadmap planning.” • (2) “AI helps cluster customer comments into themes for my monthly report.” • (1) “I ask AI to summarize customer feedback.” Data Analysis / SQL • (3) “AI generates and validates queries, produces comparison tables, and highlights anomalies I review in reports.” • (2) “AI drafts SQL queries and interprets results faster than manual work.” • (1) “AI explains SQL when I’m stuck.” Proposal / Report Writing • (3) “I use a repeatable AI template that turns briefs into full drafts with rationale and risks sections, which I refine for delivery.” • (2) “AI drafts first sections of my proposals based on my outline.” • (1) “AI helps me improve grammar and phrasing.” Competitive Research • (3) “AI normalizes competitor data, flags gaps, and generates a positioning summary for our quarterly review.” • (2) “AI extracts pricing and features into a summary table before I write my report.” • (1) “AI summarizes competitor websites.” Score 2 — Process Enhancement / Embedded Use Definition: Shows repeatable, meaningful AI use within an existing process that improves speed, quality, or consistency. AI use is consistent and relevant to core responsibilities, but the workflow design and logic remain the same. May include structured use for efficiency, but does not fundamentally change how deliverables are produced or how information flows. Observable Signals (any one): • Clear efficiency, clarity, or organization benefit. • Consistent use within a step of a recurring workflow. • Described as part of normal work, not one-off. • Partial structure or templates used manually. Examples: • “I use AI to organize survey responses and find key themes before my analysis.” • “AI drafts report sections to help me start faster.” • “I use AI to group meeting notes by owner for easier follow-up.” • “AI summarizes recurring reports or data updates to save time, but outputs are reviewed or reformatted manually.” Score 1 — Task Assistance / Surface-Level Use Definition: Describes episodic or one-step assistance focused on convenience or small efficiency gains. AI is not embedded in a structured workflow or used consistently. Includes short, isolated tasks that do not influence how other work is performed. Observable Signals: • Task-specific or one-off. • No cadence, handoff, or reuse. • Focused on formatting, writing, or explanation. • Peripheral use — does not alter how a core deliverable or process is executed. Examples: • “I use AI to fix grammar or reword emails.” • “AI helps me write Excel formulas or explain code.” • “I use AI to summarize meeting notes.” • “AI drafts short internal updates so I can focus elsewhere.” Score 0 — No or Irrelevant Use Definition: No evidence of AI use in a work context or explicitly states they do not use AI. Example: • “I don’t use AI in my work.” Evaluator Checklist When scoring, ignore writing quality and phrasing. Look for evidence of process depth: • Defined trigger or cadence? (explicit or implied) • Repeatable prompt, checklist, or playbook? • AI output feeding another step or tool? • Workflow sequence or ownership changed? • New capability or quality gate introduced? • When evaluating time savings, consider whether the AI use alters how a core deliverable is produced or simply removes a peripheral or administrative step. • Does the AI output directly support a core deliverable (e.g., reports, analysis, client output)? • Cohesion check: Are the tasks connected within a single workflow or purpose? • If the response lists multiple unrelated activities (e.g., “draft emails, brainstorm ideas, summarize reports”), treat it as multiple isolated uses and score at the lower level. Heuristic: • 3 = Embedded + ≥ 2 signals + cohesive workflow or clear transformation of core deliverable • 2 = Embedded + 0–1 signal + cohesive workflow, limited transformation • 1 = Isolated or peripheral task use • 0 = None Scoring Instruction: For your response, ONLY output the single score (0–3). Do not include any explanation. Here is the user’s input: <user_input>Costumo usar com recorrência a AI para me ajudar a produzir resumos de performance semanais com base nos dados compilados até a semana interior. Isso me salva muito tempo. Mas um exemplo valioso que foi muito bom fazer com a AI foi: Construí uma análise de price index e correlacionei com a queda de GMV e potencial de incremento de pedidos. Fiz isso usando a AI para me ajudar na análise de milhares de dados de vendas em vários lugares diferentes, como um analista de dados, e utilizando estatística para determinar um price index ótimo para propor ação de preço para as regiões certas.</user_input> | S11: {=index('Response Scoring'!$E:$E,match($A11,'Response Scoring'!$A:$A,0))} -> 3 | T11: =$S11/3 -> 1 | U11: =sumproduct($B11:$T11,$B$4:$T$4) -> 4.5033333 | V11: ='Raw Data'!$X7 -> Analyzing presentation slides to evaluate both the visual design and written content for consistency | W11: =if($V11="Analyzing presentation slides to evaluate both the visual design and written content for consistency",1,0) -> 1 | X11: ='Raw Data'!$Y7 -> Data privacy concerns when information is shared with an LLM | Y11: =if(isnumber(search("Hallucinations",$X11)),0.25)+if(isnumber(search("Biases in answers",$X11)),0.25,0)+if(isnumber(search("Data privacy concerns",$X11)),0.25)+if(isnumber(search("Vulnerability",$X11)),0.25) -> 0.25 | Z11: ='Raw Data'!$Z7 -> Anonymize information by removing identifying details, Use secure company instances or enterprise plans when available | AA11: =if(or(isnumber(search("Avoid using AI tools",$Z11)),isnumber(search("Verify that the AI tool",$Z11))),0,(if(isnumber(SEARCH("Anonymize information",$Z11)),0.5)+if(isnumber(search("Use secure company instances",$Z11)),0.5))) -> 1 | AB11: ='Raw Data'!$AA7 -> Always: I routinely cross-check AI outputs with reliable sources | AC11: =if($AB11="Never: I typically trust the output as is",0,if($AB11="Rarely: I only verify if something doesn’t sound right",0.33,if($AB11="Sometimes: I do a quick check against known data or references",0.67,if($AB11="Always: I routinely cross-check AI outputs with reliable sources",1)))) -> 1 | AD11: ='Raw Data'!$AB7 -> Cross-reference key claims with reliable external sources, Check if the response uses confident language and specific details, Use a different AI tool to review and verify the content | AE11: =if(or(isnumber(search("Check if the response uses confident language",$AD11)),isnumber(search("Look for professional formatting",$AD11))),0,(if(isnumber(search("Use a different AI tool",$AD11)),0.25)+if(isnumber(search("Cross-reference key claims",$AD11)),0.25)+if(isnumber(search("Verify any calculations",$AD11)),0.25)+if(isnumber(search("Ask the same AI tool",$AD11)),0.25))) -> 0 | AF11: 10 | AG11: ='Raw Data'!$AC7 -> Sometimes: I iterate 2–3 times to reach a good result | AH11: =if($AG11="Never: I usually just ask once and accept the first response",0,if($AG11="Rarely: I only tweak the prompt if something feels obviously off",0.33,if($AG11="Sometimes: I iterate 2–3 times to reach a good result",0.67,if($AG11="Frequently: I systematically refine prompts until I’m satisfied",1)))) -> 0.67 | AI11: ='Raw Data'!$AD7 -> Chat, considere um executivo de uma grande multinacional e irá apresentar uma proposta de iniciativa nova para a grande cúpula sobre o tema X. O tema X consiste de:"...". Com base no que lhe apresentei do tema X, forneça um feedback, como se fosse um membro da grande cúpula, com críticas construtivas que possam surgir. Considerando a audiência, elabore uma lista com os possíveis principais impactos (positivos e negativos) pra Cia. Qual a relevância para o negócio e correlação com o contexto de mercado. | AJ11: Chat, considere um executivo de uma grande multinacional e irá apresentar uma proposta de iniciativa nova para a grande cúpula sobre o tema X. O tema X consiste de:"...". Com base no que lhe apresentei do tema X, forneça um feedback, como se fosse um membro da grande cúpula, com críticas construtivas que possam surgir. Considerando a audiência, elabore uma lista com os possíveis principais impactos (positivos e negativos) pra Cia. Qual a relevância para o negócio e correlação com o contexto de mercado. | AK11: =substitute('Prompt Template'!$C$2,$AI$5,$AJ11) -> You are an expert prompt engineer. Your goal is to evaluate the effectiveness of the prompt below. Less effective prompts are too vague, open-ended, and do not give clear instructions. More effective prompts provide background, clear instructions, and are well structured. Since you are tasked with evaluating true effectiveness of the prompt, you can give scores of 1. This is for an AI Readiness Survey that will assess individuals' proficiency when using AI. <task>Write a prompt asking AI to help you prepare for a work meeting to discuss a new initiative or proposal</task> <prompt>Chat, considere um executivo de uma grande multinacional e irá apresentar uma proposta de iniciativa nova para a grande cúpula sobre o tema X. O tema X consiste de:"...". Com base no que lhe apresentei do tema X, forneça um feedback, como se fosse um membro da grande cúpula, com críticas construtivas que possam surgir. Considerando a audiência, elabore uma lista com os possíveis principais impactos (positivos e negativos) pra Cia. Qual a relevância para o negócio e correlação com o contexto de mercado.</prompt> A score of 1 prompt example: "Help me prepare for my work meeting" Rate the effectiveness on a scale of 1-5. Only respond with a single number from 1-5. If the person states they do not know how to prompt or their prompt isn't relevant to the task, give them a 0. Use the following criteria: Clarity and Specificity: A good prompt should be clear, specific, and focused. It should provide enough context and detail to guide the AI towards generating a relevant and useful response. Vague, open-ended, or ambiguous prompts make it difficult for the AI to understand the user's intent and can lead to generic or irrelevant outputs. Completeness and Sufficiency: An effective prompt should include all the necessary information and requirements to enable the AI to complete the requested task or answer the question thoroughly. It should anticipate what details the AI might need and proactively provide them. Incomplete prompts that leave out critical facts or constraints will likely result in suboptimal responses that fail to fully address the user's needs. Structure and Organization: A well-crafted prompt should be logically structured and organized. It should break down complex requests into clear steps or components, making it easier for the AI to process and respond to each part systematically. Using formatting techniques like bullet points, numbering, or sectioning can help improve the prompt's clarity and readability. Conciseness and Precision: While a good prompt should be detailed and informative, it should also strive to be as concise and precise as possible. Overly wordy or rambling prompts can obscure the key points and make it harder for the AI to identify the essential requirements. An effective prompt finds the right balance between providing necessary context and avoiding extraneous or redundant information. Here is the user's input: <user_input>Chat, considere um executivo de uma grande multinacional e irá apresentar uma proposta de iniciativa nova para a grande cúpula sobre o tema X. O tema X consiste de:"...". Com base no que lhe apresentei do tema X, forneça um feedback, como se fosse um membro da grande cúpula, com críticas construtivas que possam surgir. Considerando a audiência, elabore uma lista com os possíveis principais impactos (positivos e negativos) pra Cia. Qual a relevância para o negócio e correlação com o contexto de mercado.</user_input> | AL11: {=index('Response Scoring'!$G:$G,match($A11,'Response Scoring'!$A:$A,0))} -> 3 | AM11: =$AL11/5 -> 0.6 | AN11: ='Raw Data'!$AE7 -> Se comporte como um grande analista de mercado especialista em tendências de produto e marca. Toda semana precisamos fazer uma pesquisa de preço, produto, posicionamento e share, no mercado das nossas marcas vs os principais competidores. Me traga um overview atualizado desses tópicos com os principais highlights considerando os dados atualizados até a semana passada. Salve essa rotina para que possamos rodar aqui semanalmente. | AO11: Se comporte como um grande analista de mercado especialista em tendências de produto e marca. Toda semana precisamos fazer uma pesquisa de preço, produto, posicionamento e share, no mercado das nossas marcas vs os principais competidores. Me traga um overview atualizado desses tópicos com os principais highlights considerando os dados atualizados até a semana passada. Salve essa rotina para que possamos rodar aqui semanalmente. | AP11: =substitute('Prompt Template'!$D$2,$AN$5,$AO11) -> You are an expert evaluator of AI instruction design and CustomGPT configuration. Your goal is to evaluate how effectively a respondent demonstrates their ability to write high-quality AI instructions — the kind used to configure tools like CustomGPTs, Copilot Agents, or Google Gems. The test question asks respondents to: ‘Write instructions for a Custom GPT that would help team members gather competitive intelligence consistently.’ This scenario is used only as a familiar example. Do not evaluate their knowledge of competitive analysis — only the clarity, structure, and effectiveness of their AI instruction design. The competitive intelligence context is a stand-in for any business task. Scoring Overview Rate each response on a scale of 0–5. • 5 = System-ready, strong demonstration of instruction design skill. • 0 = Irrelevant or no response. Focus on instructional quality, not topic expertise or formatting aesthetics. Evaluation Dimensions 1. Structural Design Effective instructions clearly define the inputs, process/steps, and outputs. They show logical sequencing (e.g., research → organize → summarize) and reflect understanding of how AI interprets procedural tasks. 2. Instructional Precision Steps and directives are specific, actionable, and testable by an AI. Avoids vague terms like “analyze competitors” without specifying how to do so or what output is expected. 3. Boundary and Role Definition Strong instructions establish clear context for the AI — defining its role, scope, and constraints. They guide what to include/exclude and how to handle ambiguity or conflicting data. 4. Reusability and Scalability Good instructions can be reused consistently by others. They define consistent formatting, data structures, or repeatable logic that ensures stable results across users or scenarios. 5. Outcome Alignment The best instructions would realistically result in a functioning CustomGPT that performs the intended task accurately and consistently. Weak ones would produce inconsistent or low-quality behavior. Scoring Guidelines Score 5 – System-Ready • Instructions could be pasted directly into a CustomGPT/Copilot and perform effectively. • They demonstrate full system readiness — meaning the AI could execute the intended behavior repeatedly and autonomously, without additional clarification. • Includes: • Defined role and purpose (who/what the AI is). • Clear inputs (what information or user query it receives). • Explicit steps/process (how the AI should perform the task). • Defined outputs (format, tone, or structure of response). • Constraints/quality controls (rules, caveats, or handling instructions). • Demonstrates awareness of how to build a reusable, consistent AI behavior. Example 1: “Role: Competitive Intelligence Assistant. Purpose: Gather structured competitor data from reliable sources. Inputs: Company/product names. Process: 1) Identify top 5 competitors, 2) Extract features/pricing, 3) Summarize differences in a table. Output: Comparative matrix. Guardrails: Only use credible, verifiable sources.” Example 2 (Natural-Language Equivalent): “This CustomGPT should act as our internal research analyst. When given a company or product name, it identifies credible sources like official websites, press releases, and reviews. It compares product features, pricing, and messaging across competitors and summarizes the results in a consistent table and a short written overview with citations. The report should flag any information that seems outdated or unverified and maintain a uniform format for reuse across projects.” Note: Responses may use either explicit headings (Role/Inputs/Process/Output) or fluent natural language. Both are valid if they include equivalent components and could realistically produce consistent, reusable results. Score 4 – Strong but Missing Refinements • Structured and actionable; includes most components (e.g., steps, outputs, and some constraints). • Missing minor refinements such as input specificity, error handling, or reusability mechanisms. • AI could perform the task, but inconsistently. Example 1: “Gather information on competitors’ products, features, and pricing. Summarize in a table. Cite reliable sources.” (Functional but missing full structure or clear constraints.) Example 2: “Create a CustomGPT that collects information from competitor websites, reviews, and announcements. Summarize pricing, features, and positioning in a table, then highlight new updates. Include dates and brief notes on source credibility.” (Strong structure, but lacks clear inputs and reusability framing.) Score 3 – Structured but Shallow • Provides a reasonable outline or list of tasks but lacks cohesion or precision. • Mentions the goal but misses how to operationalize it in a repeatable, system-friendly way. • AI would need to infer too much to work reliably. Example 1: “Research competitors and summarize key findings about pricing and positioning.” (Has intent but lacks sequencing or defined outputs.) Example 2: “The GPT should find information about our competitors’ pricing and products, summarize what’s different, and give a short write-up each week.” (Clear intent, but underspecified logic — reads more like a to-do list than executable instructions.) Score 2 – Fragmented or Vague • Mentions competitive research but provides minimal or disconnected guidance. • Steps are generic, unsequenced, or too ambiguous to drive consistent AI behavior. Example elements: “Look up competitors and gather details.” “Find competitor info and summarize.” (Too vague to translate into functioning instructions.) Score 1 – Minimal or Misunderstood • Shows fundamental misunderstanding of AI instruction design. • Generic, incomplete, or irrelevant content that couldn’t guide an AI system at all. Example elements: “Just tell GPT to look up competitors.” “I’d ask it to find info about other companies.” “Use ChatGPT to do competitive research for us.” “Help me understand what our competitors do better.” “Search online for competitor products and summarize.” (Shows surface-level familiarity with AI but no system thinking.) Score 0 – No Response or Irrelevant • Empty, “I don’t know,” or unrelated answer. Example elements: “Not sure what to put here.” “I don’t use GPT for that.” “I’d rather do that myself.” “No idea how to write that.” (Shows confusion or complete lack of task understanding.) Evaluator Checklist When scoring, focus on functional design quality, not formatting or topic expertise. Ask yourself: • Does the response clearly define the AI’s role, inputs, process, and outputs? • Are instructions specific, sequenced, and testable? • Do they include boundaries or quality controls? • Could the AI perform the task consistently and autonomously if these instructions were used? • Is the response written at a configuration level (system prompt) rather than a one-off user command? Heuristic: • 5 = Fully structured, system-ready, reusable. • 4 = Strong, nearly system-ready, missing refinements. • 3 = Structured but shallow. • 2 = Fragmented or vague. • 1 = Minimal or misunderstood. • 0 = None/irrelevant. Scoring Instruction: For your response, ONLY output the single score (0–5). Do not include any explanation. Here is the user’s input: <user_input>Se comporte como um grande analista de mercado especialista em tendências de produto e marca. Toda semana precisamos fazer uma pesquisa de preço, produto, posicionamento e share, no mercado das nossas marcas vs os principais competidores. Me traga um overview atualizado desses tópicos com os principais highlights considerando os dados atualizados até a semana passada. Salve essa rotina para que possamos rodar aqui semanalmente.</user_input> | AQ11: {=index('Response Scoring'!$I:$I,match($A11,'Response Scoring'!$A:$A,0))} -> 2 | AR11: =$AQ11/5 -> 0.4 | AS11: =sumproduct($AG11:$AR11,$AG$3:$AR$3) -> 5.105 | AT11: =($AH11*2)+(AM11*8) -> 6.14 | AU11: =($U11*$AW$4)+($AF11*$AW$3)+($AS11*$AW$2) -> 29.216667 | AV11: =$AU11*2 -> 58.433333 | AW11: =IF($AV11>=80,"AI Expert",if($AV11>=60,"AI Practitioner",IF(AND($AV11<60,$AV11>=25),"AI Experimenter",if(and($AV11<25,$AV11>=0),"AI Novice")))) -> AI Experimenter | AX11: ='Raw Data'!AF7 -> ChatGPT, CoPilot, Gemini | AY11: ='Raw Data'!AG7 -> Yes | AZ11: ='Raw Data'!AH7 | BA11: ='Raw Data'!AI7 | BB11: ='Raw Data'!AJ7 | BC11: ='Raw Data'!AK7 | BD11: ='Raw Data'!AL7 | BE11: ='Raw Data'!AM7 | ... BR11: ='Raw Data'!AZ7 | BS11: ='Raw Data'!D7 | BT11: ='Raw Data'!E7 | BU11: ='Raw Data'!F7 -> ZÉ | BV11: ='Raw Data'!G7 -> Operations | BW11: =if(BV11='Demographic Analysis'!$A$22,"Yes","No") -> #REF! | BX11: ='Raw Data'!I7 -> N/A | BY11: ='Raw Data'!J7 | BZ11: ='Raw Data'!K7 | CA11: ='Raw Data'!L7 -> Brazil | CB11: ='Raw Data'!M7 -> SAZ | CC11: ='Raw Data'!N7 -> Ambev | CD11: ='Raw Data'!O7 -> Sessin - Operations | CE11: ='Raw Data'!P7 -> Skeptic User | CF11: ='Raw Data'!Q7 -> Weekly
