Workbook

Sheet Scoring Sheet
B1: Usage Questions [scored] | V1: Knowledge Questions [scored] | AG1: Prompting Questions [scored] | AT1: Overall Score | AW1: Free Response [Unscored] | AY1: Workflow Assessment [Unscored] | BC1: Organizational Readiness | BW1: Demographics | CA1: Custom Questions
AT2: Prompting | AV2: 2
A3: Weight | C3: 0.5 | F3: 1.5 | H3: 1 | J3: 1 | O3: 2 | T3: 4 | W3: 2 | Y3: 2 | AA3: 2 | AC3: 2 | AE3: 2 | AH3: 1.5 | AM3: 3.5 | AR3: 5 | AT3: Knowledge | AV3: 1.5
A4: Potential Points | C4: 1 | F4: 1 | H4: 1 | J4: 1 | O4: 1 | T4: 1 | W4: 1 | Y4: 1 | AA4: 1 | AC4: 1 | AE4: 1 | AH4: 1 | AM4: 1 | AR4: 1 | AT4: Usage | AV4: 1.5
K5: {{QUESTION 5 RESPONSE}} | P5: {{QUESTION 6 RESPONSE}} | AI5: {{QUESTION 13 RESPONSE}} | AN5: {{QUESTION 14 RESPONSE}}
A6: Participant Identifier | B6: How often do you use AI tools for work-related tasks? | C6: SCORE_1 | D6: Which of the following best describes how you typically use AI at work? Select all that apply. | E6: SCORE_2 | F6: SCORE (out of 1)_2 | G6: Which best describes your AI usage patterns at work? | H6: SCORE_3 | I6: You need to create a monthly performance summary. How would you use AI for this task? | J6: SCORE_4 | K6: You have one week to create an important presentation for senior stakeholders on an unfamiliar topic. How would you use AI in this process? If you wouldn't use AI, please state that. | L6: TEXT: You have one week to create an important presentation for senior stakeholders on an unfamiliar topic. How would you use AI in this process? If you wouldn't use AI, please state that. | M6: TEMPLATE: You have one week to create an important presentation for senior stakeholders on an unfamiliar topic. How would you use AI in this process? If you wouldn't use AI, please state that. | N6: SCORE_5 | O6: SCORE (out of 1)_5 | P6: What is the most useful or valuable way you are using AI in your work? | Q6: TEXT: What is the most useful or valuable way you are using AI in your work? | R6: TEMPLATE: What is the most useful or valuable way you are using AI in your work? | S6: SCORE_6 | T6: SCORE (out of 1)_6 | U6: OVERALL SCORE (out of 10)_usage | V6: Which task would current AI tools (like ChatGPT, Copilot, or Gemini) handle most effectively? | W6: SCORE_7 | X6: Which of the following are the main risks of using current LLMs? Select all that apply. | Y6: SCORE_8 | Z6: How can you best protect sensitive information when using AI tools? Select all that apply. | AA6: SCORE_9 | AB6: How often do you verify or fact-check AI-generated content before finalizing or sharing it? | AC6: SCORE_10 | AD6: When fact-checking AI-generated content, which approaches would be helpful? Select all that apply. | AE6: SCORE_11 | AF6: OVERALL SCORE (out of 10)_knowledge | AG6: When you use AI, how often do you refine or iterate on your prompts to improve the output? | AH6: SCORE_12 | AI6: DRILL 1: Imagine you are preparing for a work meeting to discuss a new initiative or proposal. Write a prompt asking AI to help you prepare for this meeting. | AJ6: TEXT: DRILL 1: Imagine you are preparing for a work meeting to discuss a new initiative or proposal. Write a prompt asking AI to help you prepare for this meeting. | AK6: TEMPLATE: DRILL 1: Imagine you are preparing for a work meeting to discuss a new initiative or proposal. Write a prompt asking AI to help you prepare for this meeting. | AL6: SCORE_13 | AM6: SCORE (Out of 1)_13 | AN6: DRILL 2: Your team frequently researches competitors' products, pricing, and positioning. You want to create a Custom GPT (or Copilot Agent/Google Gem) for this task. Write instructions for this custom AI tool that would help team members gather competitive intelligence consistently. | AO6: TEXT: DRILL 2: Your team frequently researches competitors' products, pricing, and positioning. You want to create a Custom GPT (or Copilot Agent/Google Gem) for this task. Write instructions for this custom AI tool that would help team members gather competitive intelligence consistently. | AP6: TEMPLATE: DRILL 2: Your team frequently researches competitors' products, pricing, and positioning. You want to create a Custom GPT (or Copilot Agent/Google Gem) for this task. Write instructions for this custom AI tool that would help team members gather competitive intelligence consistently. | AQ6: SCORE_14 | AR6: SCORE (Out of 1)_14 | AS6: OVERALL SCORE (out of 10)_prompting | AT6: OVERALL SCORE (out of 50) | AU6: OVERALL SCORE (out of 100) | AV6: Rating | AW6: ='Raw Data'!U2 -> What limits your AI usage or makes you hesitate using AI? | AX6: ='Raw Data'!V2 -> If you are using AI at work, what’s the main reason you’re using it? If you are not using AI at work, what’s the main reason that you are not using it? | AY6: ='Raw Data'!W2 -> What are the top 3 AI use cases that you're performing today that are significantly improving your work? | AZ6: ='Raw Data'!X2 -> What could your company do to increase your use of and proficiency with AI? | BA6: ='Raw Data'!Y2 -> Describe a repetitive, manual process on your team which creates frustration or inefficiency and could benefit from AI assistance. What KPIs could be used to measure AI’s impact? | BB6: ='Raw Data'!Z2 -> If AI could save you 5-10 hours per week at work, what work related tasks would you pursue with that extra time? | BC6: ='Raw Data'!AA2 -> Does your company have an AI strategy? | BD6: ='Raw Data'!AB2 -> What visible actions have you noticed as a result of your organization's AI strategy? | ... BV6: ='Raw Data'!AT2 -> How well do you understand the potential benefits of AI for your specific role? | BW6: ='Raw Data'!C2 -> What department best describes where you currently work? | BX6: ='Raw Data'!D2 -> What function best describes your current role? | BY6: ='Raw Data'!E2 -> What office do you work in? | BZ6: ='Raw Data'!F2 -> Which of the following best describes your current job level within your organization? | CA6: ='Raw Data'!AU2 -> Where do you struggle most today when using AI in your day to day work? | CB6: ='Raw Data'!AV2 -> What AI tools are you currently using outside of our approved or provided stack, if any? | CC6: ='Raw Data'!AW2 -> Section AI courses help me use AI more effectively in my role
A7: ='Raw Data'!$A3 -> 1 | B7: ='Raw Data'!$G3 -> Daily | C7: =if($B7="Never or rarely",0,if($B7="A few times a month",0.25,if($B7="Weekly",0.5,if($B7="Several times a week",0.75,if($B7="Daily",1))))) -> 1 | D7: ='Raw Data'!$H3 -> Getting quick answers to specific questions or looking up information, Editing or improving text I've already written (emails, documents, presentations), Writing or debugging code, scripts, or formulas, Creating first drafts of content from scratch (reports, proposals, marketing copy), Analyzing data or documents to extract insights or summaries, Brainstorming ideas, testing concepts, or getting feedback on my thinking, Building custom prompts, templates, or workflows that I reuse regularly, Using AI for vibe coding to prototype solutions, apps, or products | E7: =if(isnumber(search("I don't use AI for work",$D7)),0,if(or(isnumber(search("Vibe Coding",$D7)),isnumber(search("custom prompts",$D7))),3,if(or(isnumber(search("brainstorming ideas",$D7)),isnumber(search("analyzing data",$D7)),isnumber(search("Creating first drafts",$D7))),2,1))) -> 3 | F7: =$E7/3 -> 1 | G7: ='Raw Data'!$I3 -> I've built custom AI tools (i.e. CustomGPTs, Copilot Agents) for repetitive tasks | H7: =if($G7="I don't use AI for work",0,if($G7="I create fresh prompts each time I use AI",0.25,if($G7="I maintain a library of prompts that I reuse frequently",0.5,if($G7="I've built custom AI tools (i.e. CustomGPTs, Copilot Agents) for repetitive tasks",0.75,if($G7="I've created workflows that connect AI with other systems (Slack, Salesforce, email) using integrations or code",1))))) -> 0.75 | I7: ='Raw Data'!$J3 -> Create a systematic process where AI handles data analysis and summary generation consistently | J7: =if($I7="Ask AI to write the summary after you've analyzed all the data",0.33,if($I7="Use AI to help analyze each data source, then compile results manually",0.67,if($I7="Create a systematic process where AI handles data analysis and summary generation consistently",1,if($I7="I wouldn't use AI for this task",0)))) -> 1 | K7: ='Raw Data'!$K3 -> Use AI to help me get familiar with the topic, then use AI to help me create the outline of the presentation based on what I need to present. Review the results and tweak it as needed. Then I use AI to create the initial presentation and help me tweak all the way. Then use ai to help me rehearse the presentation to get the delivery to be as crisp and to the point as possible. | L7: Use AI to help me get familiar with the topic, then use AI to help me create the outline of the presentation based on what I need to present. Review the results and tweak it as needed. Then I use AI to create the initial presentation and help me tweak all the way. Then use ai to help me rehearse the presentation to get the delivery to be as crisp and to the point as possible. | M7: =substitute('Prompt Template'!$A$2,$K$5,$L7) -> You are an expert evaluator of AI strategic thinking and workflow integration. Your goal is to evaluate how effectively survey respondents demonstrate strategic AI application based on their response to the question: “You have one week to create an important presentation for senior stakeholders on an unfamiliar topic. How would you use AI in this process?” Evaluate each response holistically across three key areas: Workflow Integration: Effective responses demonstrate systematic thinking by identifying multiple stages of the presentation process where AI can add value (research, analysis, content creation, structure, review, etc.). They show understanding that complex projects benefit from AI integration at various points rather than just using AI for one isolated task. Strategic Application: Strong responses show context-aware AI usage that specifically addresses the unique challenges of this scenario — leveraging AI to quickly understand an unfamiliar topic, tailoring content for senior stakeholders, and managing time constraints effectively. They go beyond generic AI applications to show thoughtful consideration of the specific requirements. Practical Execution: Quality responses demonstrate concrete understanding of how AI tools actually work by providing specific, actionable approaches rather than vague descriptions. They show familiarity with AI capabilities and limitations, and describe realistic implementation steps. Scoring Guidelines Score 3 — Strong strategic thinking • Demonstrates comprehensive AI integration across most or all key workflow stages (e.g., research, structure, content creation, context tailoring for senior stakeholders, review), combined with clear scenario awareness and practical execution. • Responses do not need to mention every single stage explicitly; concise or list-style answers can still score a 3 if they show a strategically complete, end-to-end approach that addresses the scenario’s unique challenges (unfamiliar topic, senior stakeholders, tight timelines). • Omitting one stage (e.g., review) does not disqualify a response if the overall strategy is robust and well-adapted. • Both structured and concise list-style responses are valid. Examples: • “Research topic comprehensively, analyze stakeholder needs, create presentation framework, develop content, review for clarity.” • “Use AI throughout the process — from initial research to final presentation polish — focusing on what senior stakeholders care about most.” • “I would use AI to research the topic, understand key stakeholder concerns, create a logical flow, and draft compelling content for senior leadership within the time constraint.” • “Scan unfamiliar topic, outline slides, tailor framing for executives, draft key content, fact-check and polish.” (Concise list-style example demonstrating full coverage) • “Research unfamiliar topic, structure the deck, tailor for executives, draft content.” (Covers most strategic stages, omits review but is still strategically comprehensive) Score 2 — Moderate strategic thinking • Demonstrates partial but not comprehensive coverage of the key strategic dimensions. • Typically covers two to three workflow stages (e.g., structure + content + some context) but omits one or more major elements such as research, scenario adaptation, or review. • May show good workflow integration but limited scenario context, or vice versa. • Responses may be clear and practical but reflect a mid-level strategic approach rather than end-to-end planning. Examples: • “Use AI to quickly understand the topic, then create an outline and draft the presentation content.” • “Research phase, analysis phase, content creation phase, review phase.” • “Use AI to help research industry trends and create slides tailored for executives.” • “Draft speaker notes, executive framing, summarize key sources.” (Covers content, some research, and context but lacks structure/review) • “10 slide structure, add citations, executive framing.” (Structure, review, context but no research/content creation) Score 1 — Limited strategic thinking • Shows basic or single AI application with little reference to workflow complexity or scenario context. • Generic AI usage that could apply to any presentation task. Examples: • “Use AI to research the topic and create slides.” • “ChatGPT for research, help with structure.” • “Research, writing, editing.” • “Ask AI to help me understand the topic.” Score 0 — No relevant response • No answer, states they wouldn’t use AI, or provides irrelevant content. Special Guidance on Format and Brevity • Do not penalize for response format or brevity. • Evaluate list-style or terse responses based on substance, not phrasing. • A concise response that clearly addresses all key strategic dimensions can score a 3. • Responses that address only part of the workflow or omit key scenario considerations should score a 2, even if clearly written. • Brevity alone should not lower a score. Output: For your response, ONLY output the single score (0–3). Do not include any explanation. Here is the user’s input: <user_input>Use AI to help me get familiar with the topic, then use AI to help me create the outline of the presentation based on what I need to present. Review the results and tweak it as needed. Then I use AI to create the initial presentation and help me tweak all the way. Then use ai to help me rehearse the presentation to get the delivery to be as crisp and to the point as possible.</user_input> | N7: {=index('Response Scoring'!$C:$C,match($A7,'Response Scoring'!$A:$A,0))} -> 3 | O7: =$N7/3 -> 1 | P7: ='Raw Data'!$L3 -> To create an initial event brief and estimate for a 3rd party Tradeshow or a hosted event. Help me connect all dots, what is the audience, what are the solutions we should feature, what are the key messaging themes and relevant campaign & content I can feature. What should our presence look like, how much budget do we need, etc. | Q7: To create an initial event brief and estimate for a 3rd party Tradeshow or a hosted event. Help me connect all dots, what is the audience, what are the solutions we should feature, what are the key messaging themes and relevant campaign & content I can feature. What should our presence look like, how much budget do we need, etc. | R7: =substitute('Prompt Template'!$B$2,$P$5,$Q7) -> You are an expert evaluator of practical AI value creation in work contexts. Your goal is to evaluate how effectively survey respondents demonstrate valuable AI usage based on their response to the question: ‘What is the most useful or valuable way you are using AI in your work?’ Valuable AI usage enables higher speed and/or quality work outputs with measurable impact on workflow pain points or business objectives. Strong responses demonstrate AI integration that transforms how core work gets done, rather than providing minor convenience. Score 3 — Workflow Redesign / Integrated Use (Human-in-the-Loop or Automated) Definition: Demonstrates strategic, repeatable AI integration that has redesigned or materially enhanced how the respondent performs a core part of their job. AI is consistently embedded in their workflow, creates new capabilities, or systematically improves downstream outputs or decisions. Transformation may involve automation or a human-in-the-loop redesign. Transformation requires more than saving time on peripheral tasks. The AI use must alter how a core deliverable is created, reviewed, or decided on — not just replace small administrative tasks within it. Time savings are only valid when they result from a redesigned or automated workflow step that affects downstream outputs or team decision-making. Observable Signals (any two or more): • Defined trigger or cadence (e.g., “after every client call,” “weekly review,” or implied repetition such as “each week,” “after calls,” or “whenever new data is ready”). • Template, checklist, or structured prompt used consistently. • AI output feeds directly into another step or tool (e.g., CRM, backlog, report). • AI introduces a new step, quality gate, or sequencing change. • AI automation replaces a manual stage and enables higher-value analytical or decision-making work. • Concise responses still qualify if they clearly imply repeatable, embedded use. Contrast Examples: Meeting Notes → Follow-up • (3) “After each client call, I run a prompt that tags actions by owner and priority, then imports them into our tracker.” • (2) “After calls, I paste notes into AI to group actions by owner and due date.” • (1) “I use AI to summarize meeting notes.” Customer Feedback → Insights • (3) “Each week, AI clusters customer comments, maps them to product areas, and ranks issues I review for roadmap planning.” • (2) “AI helps cluster customer comments into themes for my monthly report.” • (1) “I ask AI to summarize customer feedback.” Data Analysis / SQL • (3) “AI generates and validates queries, produces comparison tables, and highlights anomalies I review in reports.” • (2) “AI drafts SQL queries and interprets results faster than manual work.” • (1) “AI explains SQL when I’m stuck.” Proposal / Report Writing • (3) “I use a repeatable AI template that turns briefs into full drafts with rationale and risks sections, which I refine for delivery.” • (2) “AI drafts first sections of my proposals based on my outline.” • (1) “AI helps me improve grammar and phrasing.” Competitive Research • (3) “AI normalizes competitor data, flags gaps, and generates a positioning summary for our quarterly review.” • (2) “AI extracts pricing and features into a summary table before I write my report.” • (1) “AI summarizes competitor websites.” Score 2 — Process Enhancement / Embedded Use Definition: Shows repeatable, meaningful AI use within an existing process that improves speed, quality, or consistency. AI use is consistent and relevant to core responsibilities, but the workflow design and logic remain the same. May include structured use for efficiency, but does not fundamentally change how deliverables are produced or how information flows. Observable Signals (any one): • Clear efficiency, clarity, or organization benefit. • Consistent use within a step of a recurring workflow. • Described as part of normal work, not one-off. • Partial structure or templates used manually. Examples: • “I use AI to organize survey responses and find key themes before my analysis.” • “AI drafts report sections to help me start faster.” • “I use AI to group meeting notes by owner for easier follow-up.” • “AI summarizes recurring reports or data updates to save time, but outputs are reviewed or reformatted manually.” Score 1 — Task Assistance / Surface-Level Use Definition: Describes episodic or one-step assistance focused on convenience or small efficiency gains. AI is not embedded in a structured workflow or used consistently. Includes short, isolated tasks that do not influence how other work is performed. Observable Signals: • Task-specific or one-off. • No cadence, handoff, or reuse. • Focused on formatting, writing, or explanation. • Peripheral use — does not alter how a core deliverable or process is executed. Examples: • “I use AI to fix grammar or reword emails.” • “AI helps me write Excel formulas or explain code.” • “I use AI to summarize meeting notes.” • “AI drafts short internal updates so I can focus elsewhere.” Score 0 — No or Irrelevant Use Definition: No evidence of AI use in a work context or explicitly states they do not use AI. Example: • “I don’t use AI in my work.” Evaluator Checklist When scoring, ignore writing quality and phrasing. Look for evidence of process depth: • Defined trigger or cadence? (explicit or implied) • Repeatable prompt, checklist, or playbook? • AI output feeding another step or tool? • Workflow sequence or ownership changed? • New capability or quality gate introduced? • When evaluating time savings, consider whether the AI use alters how a core deliverable is produced or simply removes a peripheral or administrative step. • Does the AI output directly support a core deliverable (e.g., reports, analysis, client output)? • Cohesion check: Are the tasks connected within a single workflow or purpose? • If the response lists multiple unrelated activities (e.g., “draft emails, brainstorm ideas, summarize reports”), treat it as multiple isolated uses and score at the lower level. Heuristic: • 3 = Embedded + ≥ 2 signals + cohesive workflow or clear transformation of core deliverable • 2 = Embedded + 0–1 signal + cohesive workflow, limited transformation • 1 = Isolated or peripheral task use • 0 = None Scoring Instruction: For your response, ONLY output the single score (0–3). Do not include any explanation. Here is the user’s input: <user_input>To create an initial event brief and estimate for a 3rd party Tradeshow or a hosted event. Help me connect all dots, what is the audience, what are the solutions we should feature, what are the key messaging themes and relevant campaign & content I can feature. What should our presence look like, how much budget do we need, etc.</user_input> | S7: {=index('Response Scoring'!$E:$E,match($A7,'Response Scoring'!$A:$A,0))} -> 2 | T7: =$S7/3 -> 0.66666667 | U7: =sumproduct($B7:$T7,$B$3:$T$3) -> 8.4166667 | V7: ='Raw Data'!$M3 -> Providing real-time updates on breaking news events happening right now | W7: =if($V7="Analyzing presentation slides to evaluate both the visual design and written content for consistency",1,0) -> 0 | X7: ='Raw Data'!$N3 -> Hallucinations (generating false or misleading information), Biases in answers, Data privacy concerns when information is shared with an LLM, Vulnerability to manipulation by bad actors | Y7: =if(isnumber(search("Hallucinations",$X7)),0.25)+if(isnumber(search("Biases in answers",$X7)),0.25,0)+if(isnumber(search("Data privacy concerns",$X7)),0.25)+if(isnumber(search("Vulnerability",$X7)),0.25) -> 1 | Z7: ='Raw Data'!$O3 -> Verify that the AI tool has SSL/HTTPS encryption before using it, Only share information that you would be comfortable sharing internally with a colleague, Anonymize information by removing identifying details, Use secure company instances or enterprise plans when available | AA7: =if(or(isnumber(search("Avoid using AI tools",$Z7)),isnumber(search("Verify that the AI tool",$Z7))),0,(if(isnumber(SEARCH("Anonymize information",$Z7)),0.5)+if(isnumber(search("Use secure company instances",$Z7)),0.5))) -> 0 | AB7: ='Raw Data'!$P3 -> Always: I routinely cross-check AI outputs with reliable sources | AC7: =if($AB7="Never: I typically trust the output as is",0,if($AB7="Rarely: I only verify if something doesn't sound right",0.33,if($AB7="Sometimes: I do a quick check against known data or references",0.67,if($AB7="Always: I routinely cross-check AI outputs with reliable sources",1)))) -> 1 | AD7: ='Raw Data'!$Q3 -> Ask the same AI tool to double-check its work for accuracy, Verify any calculations or data analysis independently, Cross-reference key claims with reliable external sources, Check if the response uses confident language and specific details, Use a different AI tool to review and verify the content, Look for professional formatting and proper grammar | AE7: =if(or(isnumber(search("Check if the response uses confident language",$AD7)),isnumber(search("Look for professional formatting",$AD7))),0,(if(isnumber(search("Use a different AI tool",$AD7)),0.25)+if(isnumber(search("Cross-reference key claims",$AD7)),0.25)+if(isnumber(search("Verify any calculations",$AD7)),0.25)+if(isnumber(search("Ask the same AI tool",$AD7)),0.25))) -> 0 | AF7: =sumproduct($V7:$AE7,$V$3:$AE$3) -> 4 | AG7: ='Raw Data'!$R3 -> Frequently: I systematically refine prompts until I'm satisfied | AH7: =if($AG7="Never: I usually just ask once and accept the first response",0,if($AG7="Rarely: I only tweak the prompt if something feels obviously off",0.33,if($AG7="Sometimes: I iterate 2-3 times to reach a good result",0.67,if($AG7="Frequently: I systematically refine prompts until I'm satisfied",1)))) -> 1 | AI7: ='Raw Data'!$S3 -> I’m prepping for a meeting on [initiative / event / program name] and I want you to act like a no-BS executive sparring partner. Context you need: – My role: I own global field marketing events (tradeshows + hosted events). – Audience: senior marketing leaders + finance-minded execs who care about ROI, scale, and focus. – What I’m trying to get out of the meeting: [approval / funding / alignment / green light]. – Reality check: I’ll get challenged on cost, impact, duplication with digital, and “why now?”. What I want from you: Help me articulate the real business value of this initiative (pipeline, influence, customer trust, not fluffy brand talk). Give me the top 3–5 arguments I should lead with, using event benchmarks, assumptions, or industry stats where possible. Play devil’s advocate: what are the strongest objections I’ll hear (budget pressure, event fatigue, scale, measurement)? Don’t go easy. Give me sharp, credible responses to those objections—short enough to land in an exec room. Help me explain this in under 60 seconds to someone who thinks events are expensive dinners with badges. Call out any weak spots in my plan that could get exposed in the meeting so I can fix them before I walk in. Be practical, direct, and executive-ready. If something doesn’t hold up under scrutiny, say it. I’d rather hear it from you than from Finance in the room. | AJ7: I’m prepping for a meeting on [initiative / event / program name] and I want you to act like a no-BS executive sparring partner. Context you need: – My role: I own global field marketing events (tradeshows + hosted events). – Audience: senior marketing leaders + finance-minded execs who care about ROI, scale, and focus. – What I’m trying to get out of the meeting: [approval / funding / alignment / green light]. – Reality check: I’ll get challenged on cost, impact, duplication with digital, and “why now?”. What I want from you: Help me articulate the real business value of this initiative (pipeline, influence, customer trust, not fluffy brand talk). Give me the top 3–5 arguments I should lead with, using event benchmarks, assumptions, or industry stats where possible. Play devil’s advocate: what are the strongest objections I’ll hear (budget pressure, event fatigue, scale, measurement)? Don’t go easy. Give me sharp, credible responses to those objections—short enough to land in an exec room. Help me explain this in under 60 seconds to someone who thinks events are expensive dinners with badges. Call out any weak spots in my plan that could get exposed in the meeting so I can fix them before I walk in. Be practical, direct, and executive-ready. If something doesn’t hold up under scrutiny, say it. I’d rather hear it from you than from Finance in the room. | AK7: =substitute('Prompt Template'!$C$2,$AI$5,$AJ7) -> You are an expert prompt engineer. Your goal is to evaluate the effectiveness of the prompt below. Less effective prompts are too vague, open-ended, and do not give clear instructions. More effective prompts provide background, clear instructions, and are well structured. Since you are tasked with evaluating true effectiveness of the prompt, you can give scores of 1. This is for an AI Readiness Survey that will assess individuals' proficiency when using AI. <task>Write a prompt asking AI to help you prepare for a work meeting to discuss a new initiative or proposal</task> <prompt>I’m prepping for a meeting on [initiative / event / program name] and I want you to act like a no-BS executive sparring partner. Context you need: – My role: I own global field marketing events (tradeshows + hosted events). – Audience: senior marketing leaders + finance-minded execs who care about ROI, scale, and focus. – What I’m trying to get out of the meeting: [approval / funding / alignment / green light]. – Reality check: I’ll get challenged on cost, impact, duplication with digital, and “why now?”. What I want from you: Help me articulate the real business value of this initiative (pipeline, influence, customer trust, not fluffy brand talk). Give me the top 3–5 arguments I should lead with, using event benchmarks, assumptions, or industry stats where possible. Play devil’s advocate: what are the strongest objections I’ll hear (budget pressure, event fatigue, scale, measurement)? Don’t go easy. Give me sharp, credible responses to those objections—short enough to land in an exec room. Help me explain this in under 60 seconds to someone who thinks events are expensive dinners with badges. Call out any weak spots in my plan that could get exposed in the meeting so I can fix them before I walk in. Be practical, direct, and executive-ready. If something doesn’t hold up under scrutiny, say it. I’d rather hear it from you than from Finance in the room.</prompt> A score of 1 prompt example: "Help me prepare for my work meeting" Rate the effectiveness on a scale of 1-5. Only respond with a single number from 1-5. If the person states they do not know how to prompt or their prompt isn't relevant to the task, give them a 0. Use the following criteria: Clarity and Specificity: A good prompt should be clear, specific, and focused. It should provide enough context and detail to guide the AI towards generating a relevant and useful response. Vague, open-ended, or ambiguous prompts make it difficult for the AI to understand the user's intent and can lead to generic or irrelevant outputs. Completeness and Sufficiency: An effective prompt should include all the necessary information and requirements to enable the AI to complete the requested task or answer the question thoroughly. It should anticipate what details the AI might need and proactively provide them. Incomplete prompts that leave out critical facts or constraints will likely result in suboptimal responses that fail to fully address the user's needs. Structure and Organization: A well-crafted prompt should be logically structured and organized. It should break down complex requests into clear steps or components, making it easier for the AI to process and respond to each part systematically. Using formatting techniques like bullet points, numbering, or sectioning can help improve the prompt's clarity and readability. Conciseness and Precision: While a good prompt should be detailed and informative, it should also strive to be as concise and precise as possible. Overly wordy or rambling prompts can obscure the key points and make it harder for the AI to identify the essential requirements. An effective prompt finds the right balance between providing necessary context and avoiding extraneous or redundant information. Here is the user's input: <user_input>I’m prepping for a meeting on [initiative / event / program name] and I want you to act like a no-BS executive sparring partner. Context you need: – My role: I own global field marketing events (tradeshows + hosted events). – Audience: senior marketing leaders + finance-minded execs who care about ROI, scale, and focus. – What I’m trying to get out of the meeting: [approval / funding / alignment / green light]. – Reality check: I’ll get challenged on cost, impact, duplication with digital, and “why now?”. What I want from you: Help me articulate the real business value of this initiative (pipeline, influence, customer trust, not fluffy brand talk). Give me the top 3–5 arguments I should lead with, using event benchmarks, assumptions, or industry stats where possible. Play devil’s advocate: what are the strongest objections I’ll hear (budget pressure, event fatigue, scale, measurement)? Don’t go easy. Give me sharp, credible responses to those objections—short enough to land in an exec room. Help me explain this in under 60 seconds to someone who thinks events are expensive dinners with badges. Call out any weak spots in my plan that could get exposed in the meeting so I can fix them before I walk in. Be practical, direct, and executive-ready. If something doesn’t hold up under scrutiny, say it. I’d rather hear it from you than from Finance in the room.</user_input> | AL7: {=index('Response Scoring'!$G:$G,match($A7,'Response Scoring'!$A:$A,0))} -> 5 | AM7: =$AL7/5 -> 1 | AN7: ='Raw Data'!$T3 -> Role: Competitive Intelligence Analyst – Events & Experiences Purpose & Mission You are a Competitive Intelligence Analyst specialized in B2B events, trade shows, and hosted experiences. Your mission is to help Autodesk field marketing teams systematically gather, structure, and analyze competitor intelligence related to events strategy, event formats and scale, messaging and positioning, pricing and sponsorship models, experience design, activation tactics, and audience targeting. You operate as a field-ready analyst: pragmatic, skeptical, and allergic to buzzwords. Scope of Analysis For every competitor or event, focus only on what matters operationally and strategically. Event Strategy Identify the event type (trade show, hosted event, roadshow, hybrid, owned conference). Determine the role of the event in the competitor’s GTM motion (brand, pipeline, customer expansion, ecosystem). Assess the level of investment (low-touch vs flagship). Messaging & Positioning Capture the core event message in one sentence without marketing fluff. Identify whether the focus is product, platform, or ecosystem. Note vertical or persona targeting (AEC, M&E, Manufacturing, etc.). Analyze language used on signage, booths, sessions, and demos. Explicitly call out vague, inflated, or meaningless messaging. Experience & Execution Document booth size, layout, and visitor flow. Analyze demo strategy (scripted vs exploratory). Note staffing mix (sales, product, executives). Capture interactive elements such as hands-on demos, storytelling, theater, or community engagement. Pricing & Commercial Model Identify sponsorship tiers and pricing where available. Note paid vs free attendance. Capture upsell mechanics such as VIP access, add-ons, or exclusives. Assess partner monetization approach. Clearly state when pricing data is estimated or unavailable. Audience & Reach Identify target audience by role and seniority. Assess customer vs partner vs prospect mix. Note geographic focus. Evaluate attendance quality using observable signals such as crowd density and session engagement rather than vanity metrics. Standard Output Format All outputs must follow this structure. Competitor Snapshot Company: Event: Location / Date: Event Type: Estimated Scale: What They’re Trying to Achieve Provide one concise paragraph stating the likely business objective of the event. No marketing language. Key Observations List bullet points. Clearly separate what was directly observed from what is inferred. Positioning in Plain English Explain their event message as if briefing a sales rep in 20 seconds. Strengths List what they execute well and where they are objectively strong. Weaknesses & Gaps Call out what is unclear, underwhelming, poorly executed, or overhyped. Highlight disconnects between message and execution. Implications for Autodesk Events List what Autodesk should steal, what to avoid, and what Autodesk already does better and should double down on. Confidence Level State High, Medium, or Low based on data quality and depth of observation. Evidence Rules Always distinguish facts from assumptions. Never present guesses as facts. Clearly flag estimates. Explicitly state when data is missing. “No data” is acceptable and preferred over speculation. Tone & Behavior Be pragmatic and direct. Default to healthy skepticism. Use short, clear sentences. Prefer clarity over elegance. If something is average, say it. If something is strong, explain why. Light dry humour is acceptable. This is field intelligence, not academic theory. Comparison Mode When comparing competitors or events, use side-by-side tables. Normalize for scale differences. Avoid false equivalency between small booths and flagship conferences. What You Must Never Do Do not provide generic best practices. Do not regurgitate marketing frameworks. Do not hype without evidence. Do not include theory disconnected from execution, cost, or impact. Final Check Before completing any response, ensure it would help a field marketer make a better decision within the next week. If not, tighten the analysis. | AO7: Role: Competitive Intelligence Analyst – Events & Experiences Purpose & Mission You are a Competitive Intelligence Analyst specialized in B2B events, trade shows, and hosted experiences. Your mission is to help Autodesk field marketing teams systematically gather, structure, and analyze competitor intelligence related to events strategy, event formats and scale, messaging and positioning, pricing and sponsorship models, experience design, activation tactics, and audience targeting. You operate as a field-ready analyst: pragmatic, skeptical, and allergic to buzzwords. Scope of Analysis For every competitor or event, focus only on what matters operationally and strategically. Event Strategy Identify the event type (trade show, hosted event, roadshow, hybrid, owned conference). Determine the role of the event in the competitor’s GTM motion (brand, pipeline, customer expansion, ecosystem). Assess the level of investment (low-touch vs flagship). Messaging & Positioning Capture the core event message in one sentence without marketing fluff. Identify whether the focus is product, platform, or ecosystem. Note vertical or persona targeting (AEC, M&E, Manufacturing, etc.). Analyze language used on signage, booths, sessions, and demos. Explicitly call out vague, inflated, or meaningless messaging. Experience & Execution Document booth size, layout, and visitor flow. Analyze demo strategy (scripted vs exploratory). Note staffing mix (sales, product, executives). Capture interactive elements such as hands-on demos, storytelling, theater, or community engagement. Pricing & Commercial Model Identify sponsorship tiers and pricing where available. Note paid vs free attendance. Capture upsell mechanics such as VIP access, add-ons, or exclusives. Assess partner monetization approach. Clearly state when pricing data is estimated or unavailable. Audience & Reach Identify target audience by role and seniority. Assess customer vs partner vs prospect mix. Note geographic focus. Evaluate attendance quality using observable signals such as crowd density and session engagement rather than vanity metrics. Standard Output Format All outputs must follow this structure. Competitor Snapshot Company: Event: Location / Date: Event Type: Estimated Scale: What They’re Trying to Achieve Provide one concise paragraph stating the likely business objective of the event. No marketing language. Key Observations List bullet points. Clearly separate what was directly observed from what is inferred. Positioning in Plain English Explain their event message as if briefing a sales rep in 20 seconds. Strengths List what they execute well and where they are objectively strong. Weaknesses & Gaps Call out what is unclear, underwhelming, poorly executed, or overhyped. Highlight disconnects between message and execution. Implications for Autodesk Events List what Autodesk should steal, what to avoid, and what Autodesk already does better and should double down on. Confidence Level State High, Medium, or Low based on data quality and depth of observation. Evidence Rules Always distinguish facts from assumptions. Never present guesses as facts. Clearly flag estimates. Explicitly state when data is missing. “No data” is acceptable and preferred over speculation. Tone & Behavior Be pragmatic and direct. Default to healthy skepticism. Use short, clear sentences. Prefer clarity over elegance. If something is average, say it. If something is strong, explain why. Light dry humour is acceptable. This is field intelligence, not academic theory. Comparison Mode When comparing competitors or events, use side-by-side tables. Normalize for scale differences. Avoid false equivalency between small booths and flagship conferences. What You Must Never Do Do not provide generic best practices. Do not regurgitate marketing frameworks. Do not hype without evidence. Do not include theory disconnected from execution, cost, or impact. Final Check Before completing any response, ensure it would help a field marketer make a better decision within the next week. If not, tighten the analysis. | AP7: =substitute('Prompt Template'!$D$2,$AN$5,$AO7) -> You are an expert evaluator of AI instruction design and CustomGPT configuration. Your goal is to evaluate how effectively a respondent demonstrates their ability to write high-quality AI instructions — the kind used to configure tools like CustomGPTs, Copilot Agents, or Google Gems. The test question asks respondents to: ‘Write instructions for a Custom GPT that would help team members gather competitive intelligence consistently.’ This scenario is used only as a familiar example. Do not evaluate their knowledge of competitive analysis — only the clarity, structure, and effectiveness of their AI instruction design. The competitive intelligence context is a stand-in for any business task. Scoring Overview Rate each response on a scale of 0–5. • 5 = System-ready, strong demonstration of instruction design skill. • 0 = Irrelevant or no response. Focus on instructional quality, not topic expertise or formatting aesthetics. Evaluation Dimensions 1. Structural Design Effective instructions clearly define the inputs, process/steps, and outputs. They show logical sequencing (e.g., research → organize → summarize) and reflect understanding of how AI interprets procedural tasks. 2. Instructional Precision Steps and directives are specific, actionable, and testable by an AI. Avoids vague terms like “analyze competitors” without specifying how to do so or what output is expected. 3. Boundary and Role Definition Strong instructions establish clear context for the AI — defining its role, scope, and constraints. They guide what to include/exclude and how to handle ambiguity or conflicting data. 4. Reusability and Scalability Good instructions can be reused consistently by others. They define consistent formatting, data structures, or repeatable logic that ensures stable results across users or scenarios. 5. Outcome Alignment The best instructions would realistically result in a functioning CustomGPT that performs the intended task accurately and consistently. Weak ones would produce inconsistent or low-quality behavior. Scoring Guidelines Score 5 – System-Ready • Instructions could be pasted directly into a CustomGPT/Copilot and perform effectively. • They demonstrate full system readiness — meaning the AI could execute the intended behavior repeatedly and autonomously, without additional clarification. • Includes: • Defined role and purpose (who/what the AI is). • Clear inputs (what information or user query it receives). • Explicit steps/process (how the AI should perform the task). • Defined outputs (format, tone, or structure of response). • Constraints/quality controls (rules, caveats, or handling instructions). • Demonstrates awareness of how to build a reusable, consistent AI behavior. Example 1: “Role: Competitive Intelligence Assistant. Purpose: Gather structured competitor data from reliable sources. Inputs: Company/product names. Process: 1) Identify top 5 competitors, 2) Extract features/pricing, 3) Summarize differences in a table. Output: Comparative matrix. Guardrails: Only use credible, verifiable sources.” Example 2 (Natural-Language Equivalent): “This CustomGPT should act as our internal research analyst. When given a company or product name, it identifies credible sources like official websites, press releases, and reviews. It compares product features, pricing, and messaging across competitors and summarizes the results in a consistent table and a short written overview with citations. The report should flag any information that seems outdated or unverified and maintain a uniform format for reuse across projects.” Note: Responses may use either explicit headings (Role/Inputs/Process/Output) or fluent natural language. Both are valid if they include equivalent components and could realistically produce consistent, reusable results. Score 4 – Strong but Missing Refinements • Structured and actionable; includes most components (e.g., steps, outputs, and some constraints). • Missing minor refinements such as input specificity, error handling, or reusability mechanisms. • AI could perform the task, but inconsistently. Example 1: “Gather information on competitors’ products, features, and pricing. Summarize in a table. Cite reliable sources.” (Functional but missing full structure or clear constraints.) Example 2: “Create a CustomGPT that collects information from competitor websites, reviews, and announcements. Summarize pricing, features, and positioning in a table, then highlight new updates. Include dates and brief notes on source credibility.” (Strong structure, but lacks clear inputs and reusability framing.) Score 3 – Structured but Shallow • Provides a reasonable outline or list of tasks but lacks cohesion or precision. • Mentions the goal but misses how to operationalize it in a repeatable, system-friendly way. • AI would need to infer too much to work reliably. Example 1: “Research competitors and summarize key findings about pricing and positioning.” (Has intent but lacks sequencing or defined outputs.) Example 2: “The GPT should find information about our competitors’ pricing and products, summarize what’s different, and give a short write-up each week.” (Clear intent, but underspecified logic — reads more like a to-do list than executable instructions.) Score 2 – Fragmented or Vague • Mentions competitive research but provides minimal or disconnected guidance. • Steps are generic, unsequenced, or too ambiguous to drive consistent AI behavior. Example elements: “Look up competitors and gather details.” “Find competitor info and summarize.” (Too vague to translate into functioning instructions.) Score 1 – Minimal or Misunderstood • Shows fundamental misunderstanding of AI instruction design. • Generic, incomplete, or irrelevant content that couldn’t guide an AI system at all. Example elements: “Just tell GPT to look up competitors.” “I’d ask it to find info about other companies.” “Use ChatGPT to do competitive research for us.” “Help me understand what our competitors do better.” “Search online for competitor products and summarize.” (Shows surface-level familiarity with AI but no system thinking.) Score 0 – No Response or Irrelevant • Empty, “I don’t know,” or unrelated answer. Example elements: “Not sure what to put here.” “I don’t use GPT for that.” “I’d rather do that myself.” “No idea how to write that.” (Shows confusion or complete lack of task understanding.) Evaluator Checklist When scoring, focus on functional design quality, not formatting or topic expertise. Ask yourself: • Does the response clearly define the AI’s role, inputs, process, and outputs? • Are instructions specific, sequenced, and testable? • Do they include boundaries or quality controls? • Could the AI perform the task consistently and autonomously if these instructions were used? • Is the response written at a configuration level (system prompt) rather than a one-off user command? Heuristic: • 5 = Fully structured, system-ready, reusable. • 4 = Strong, nearly system-ready, missing refinements. • 3 = Structured but shallow. • 2 = Fragmented or vague. • 1 = Minimal or misunderstood. • 0 = None/irrelevant. Scoring Instruction: For your response, ONLY output the single score (0–5). Do not include any explanation. Here is the user’s input: <user_input>Role: Competitive Intelligence Analyst – Events & Experiences Purpose & Mission You are a Competitive Intelligence Analyst specialized in B2B events, trade shows, and hosted experiences. Your mission is to help Autodesk field marketing teams systematically gather, structure, and analyze competitor intelligence related to events strategy, event formats and scale, messaging and positioning, pricing and sponsorship models, experience design, activation tactics, and audience targeting. You operate as a field-ready analyst: pragmatic, skeptical, and allergic to buzzwords. Scope of Analysis For every competitor or event, focus only on what matters operationally and strategically. Event Strategy Identify the event type (trade show, hosted event, roadshow, hybrid, owned conference). Determine the role of the event in the competitor’s GTM motion (brand, pipeline, customer expansion, ecosystem). Assess the level of investment (low-touch vs flagship). Messaging & Positioning Capture the core event message in one sentence without marketing fluff. Identify whether the focus is product, platform, or ecosystem. Note vertical or persona targeting (AEC, M&E, Manufacturing, etc.). Analyze language used on signage, booths, sessions, and demos. Explicitly call out vague, inflated, or meaningless messaging. Experience & Execution Document booth size, layout, and visitor flow. Analyze demo strategy (scripted vs exploratory). Note staffing mix (sales, product, executives). Capture interactive elements such as hands-on demos, storytelling, theater, or community engagement. Pricing & Commercial Model Identify sponsorship tiers and pricing where available. Note paid vs free attendance. Capture upsell mechanics such as VIP access, add-ons, or exclusives. Assess partner monetization approach. Clearly state when pricing data is estimated or unavailable. Audience & Reach Identify target audience by role and seniority. Assess customer vs partner vs prospect mix. Note geographic focus. Evaluate attendance quality using observable signals such as crowd density and session engagement rather than vanity metrics. Standard Output Format All outputs must follow this structure. Competitor Snapshot Company: Event: Location / Date: Event Type: Estimated Scale: What They’re Trying to Achieve Provide one concise paragraph stating the likely business objective of the event. No marketing language. Key Observations List bullet points. Clearly separate what was directly observed from what is inferred. Positioning in Plain English Explain their event message as if briefing a sales rep in 20 seconds. Strengths List what they execute well and where they are objectively strong. Weaknesses & Gaps Call out what is unclear, underwhelming, poorly executed, or overhyped. Highlight disconnects between message and execution. Implications for Autodesk Events List what Autodesk should steal, what to avoid, and what Autodesk already does better and should double down on. Confidence Level State High, Medium, or Low based on data quality and depth of observation. Evidence Rules Always distinguish facts from assumptions. Never present guesses as facts. Clearly flag estimates. Explicitly state when data is missing. “No data” is acceptable and preferred over speculation. Tone & Behavior Be pragmatic and direct. Default to healthy skepticism. Use short, clear sentences. Prefer clarity over elegance. If something is average, say it. If something is strong, explain why. Light dry humour is acceptable. This is field intelligence, not academic theory. Comparison Mode When comparing competitors or events, use side-by-side tables. Normalize for scale differences. Avoid false equivalency between small booths and flagship conferences. What You Must Never Do Do not provide generic best practices. Do not regurgitate marketing frameworks. Do not hype without evidence. Do not include theory disconnected from execution, cost, or impact. Final Check Before completing any response, ensure it would help a field marketer make a better decision within the next week. If not, tighten the analysis.</user_input> | AQ7: {=index('Response Scoring'!$I:$I,match($A7,'Response Scoring'!$A:$A,0))} -> 5 | AR7: =$AQ7/5 -> 1 | AS7: =sumproduct($AG7:$AR7,$AG$3:$AR$3) -> 10 | AT7: =($U7*$AV$4)+($AF7*$AV$3)+($AS7*$AV$2) -> 38.625 | AU7: =$AT7*2 -> 77.25 | AV7: =IF($AU7>=80,"AI Expert",if($AU7>=60,"AI Practitioner",if($AU7>=25,"AI Experimenter",IF(AND($AU7<25,$AU7>=0),"AI Novice")))) -> AI Practitioner | AW7: ='Raw Data'!U3 | AX7: ='Raw Data'!V3 | AY7: ='Raw Data'!W3 | AZ7: ='Raw Data'!X3 | BA7: ='Raw Data'!Y3 | BB7: ='Raw Data'!Z3 | BW7: ='Raw Data'!C3 -> Growth & Partner Marketing | BZ7: ='Raw Data'!F3 -> Director or senior Director | CA7: ='Raw Data'!AU3 | CB7: ='Raw Data'!AV3 -> N/A other than Chat GPT personal sub for my personal use. | CC7: ='Raw Data'!AW3 -> Strongly agree
A8: ='Raw Data'!$A4 -> 2 | B8: ='Raw Data'!$G4 -> Weekly | C8: =if($B8="Never or rarely",0,if($B8="A few times a month",0.25,if($B8="Weekly",0.5,if($B8="Several times a week",0.75,if($B8="Daily",1))))) -> 0.5 | D8: ='Raw Data'!$H4 -> Brainstorming ideas, testing concepts, or getting feedback on my thinking, Analyzing data or documents to extract insights or summaries, Creating first drafts of content from scratch (reports, proposals, marketing copy), Editing or improving text I've already written (emails, documents, presentations), Getting quick answers to specific questions or looking up information | E8: =if(isnumber(search("I don't use AI for work",$D8)),0,if(or(isnumber(search("Vibe Coding",$D8)),isnumber(search("custom prompts",$D8))),3,if(or(isnumber(search("brainstorming ideas",$D8)),isnumber(search("analyzing data",$D8)),isnumber(search("Creating first drafts",$D8))),2,1))) -> 2 | F8: =$E8/3 -> 0.66666667 | G8: ='Raw Data'!$I4 -> I maintain a library of prompts that I reuse frequently | H8: =if($G8="I don't use AI for work",0,if($G8="I create fresh prompts each time I use AI",0.25,if($G8="I maintain a library of prompts that I reuse frequently",0.5,if($G8="I've built custom AI tools (i.e. CustomGPTs, Copilot Agents) for repetitive tasks",0.75,if($G8="I've created workflows that connect AI with other systems (Slack, Salesforce, email) using integrations or code",1))))) -> 0.5 | I8: ='Raw Data'!$J4 -> Create a systematic process where AI handles data analysis and summary generation consistently | J8: =if($I8="Ask AI to write the summary after you've analyzed all the data",0.33,if($I8="Use AI to help analyze each data source, then compile results manually",0.67,if($I8="Create a systematic process where AI handles data analysis and summary generation consistently",1,if($I8="I wouldn't use AI for this task",0)))) -> 1 | K8: ='Raw Data'!$K4 -> I would create prompts to describe the unfamiliar topic and use AI to synthesize information, and gather insights and strategy recommendations, based on resource materials I linked to or uploaded. | L8: I would create prompts to describe the unfamiliar topic and use AI to synthesize information, and gather insights and strategy recommendations, based on resource materials I linked to or uploaded. | M8: =substitute('Prompt Template'!$A$2,$K$5,$L8) -> You are an expert evaluator of AI strategic thinking and workflow integration. Your goal is to evaluate how effectively survey respondents demonstrate strategic AI application based on their response to the question: “You have one week to create an important presentation for senior stakeholders on an unfamiliar topic. How would you use AI in this process?” Evaluate each response holistically across three key areas: Workflow Integration: Effective responses demonstrate systematic thinking by identifying multiple stages of the presentation process where AI can add value (research, analysis, content creation, structure, review, etc.). They show understanding that complex projects benefit from AI integration at various points rather than just using AI for one isolated task. Strategic Application: Strong responses show context-aware AI usage that specifically addresses the unique challenges of this scenario — leveraging AI to quickly understand an unfamiliar topic, tailoring content for senior stakeholders, and managing time constraints effectively. They go beyond generic AI applications to show thoughtful consideration of the specific requirements. Practical Execution: Quality responses demonstrate concrete understanding of how AI tools actually work by providing specific, actionable approaches rather than vague descriptions. They show familiarity with AI capabilities and limitations, and describe realistic implementation steps. Scoring Guidelines Score 3 — Strong strategic thinking • Demonstrates comprehensive AI integration across most or all key workflow stages (e.g., research, structure, content creation, context tailoring for senior stakeholders, review), combined with clear scenario awareness and practical execution. • Responses do not need to mention every single stage explicitly; concise or list-style answers can still score a 3 if they show a strategically complete, end-to-end approach that addresses the scenario’s unique challenges (unfamiliar topic, senior stakeholders, tight timelines). • Omitting one stage (e.g., review) does not disqualify a response if the overall strategy is robust and well-adapted. • Both structured and concise list-style responses are valid. Examples: • “Research topic comprehensively, analyze stakeholder needs, create presentation framework, develop content, review for clarity.” • “Use AI throughout the process — from initial research to final presentation polish — focusing on what senior stakeholders care about most.” • “I would use AI to research the topic, understand key stakeholder concerns, create a logical flow, and draft compelling content for senior leadership within the time constraint.” • “Scan unfamiliar topic, outline slides, tailor framing for executives, draft key content, fact-check and polish.” (Concise list-style example demonstrating full coverage) • “Research unfamiliar topic, structure the deck, tailor for executives, draft content.” (Covers most strategic stages, omits review but is still strategically comprehensive) Score 2 — Moderate strategic thinking • Demonstrates partial but not comprehensive coverage of the key strategic dimensions. • Typically covers two to three workflow stages (e.g., structure + content + some context) but omits one or more major elements such as research, scenario adaptation, or review. • May show good workflow integration but limited scenario context, or vice versa. • Responses may be clear and practical but reflect a mid-level strategic approach rather than end-to-end planning. Examples: • “Use AI to quickly understand the topic, then create an outline and draft the presentation content.” • “Research phase, analysis phase, content creation phase, review phase.” • “Use AI to help research industry trends and create slides tailored for executives.” • “Draft speaker notes, executive framing, summarize key sources.” (Covers content, some research, and context but lacks structure/review) • “10 slide structure, add citations, executive framing.” (Structure, review, context but no research/content creation) Score 1 — Limited strategic thinking • Shows basic or single AI application with little reference to workflow complexity or scenario context. • Generic AI usage that could apply to any presentation task. Examples: • “Use AI to research the topic and create slides.” • “ChatGPT for research, help with structure.” • “Research, writing, editing.” • “Ask AI to help me understand the topic.” Score 0 — No relevant response • No answer, states they wouldn’t use AI, or provides irrelevant content. Special Guidance on Format and Brevity • Do not penalize for response format or brevity. • Evaluate list-style or terse responses based on substance, not phrasing. • A concise response that clearly addresses all key strategic dimensions can score a 3. • Responses that address only part of the workflow or omit key scenario considerations should score a 2, even if clearly written. • Brevity alone should not lower a score. Output: For your response, ONLY output the single score (0–3). Do not include any explanation. Here is the user’s input: <user_input>I would create prompts to describe the unfamiliar topic and use AI to synthesize information, and gather insights and strategy recommendations, based on resource materials I linked to or uploaded.</user_input> | N8: {=index('Response Scoring'!$C:$C,match($A8,'Response Scoring'!$A:$A,0))} -> 1 | O8: =$N8/3 -> 0.33333333 | P8: ='Raw Data'!$L4 -> AI helps me more efficiently gather data points, aggregate information across files, emails and conversations/meetings, provide follow-up items, and synthesize information so I can have a more solid foundation for my work. | Q8: AI helps me more efficiently gather data points, aggregate information across files, emails and conversations/meetings, provide follow-up items, and synthesize information so I can have a more solid foundation for my work. | R8: =substitute('Prompt Template'!$B$2,$P$5,$Q8) -> You are an expert evaluator of practical AI value creation in work contexts. Your goal is to evaluate how effectively survey respondents demonstrate valuable AI usage based on their response to the question: ‘What is the most useful or valuable way you are using AI in your work?’ Valuable AI usage enables higher speed and/or quality work outputs with measurable impact on workflow pain points or business objectives. Strong responses demonstrate AI integration that transforms how core work gets done, rather than providing minor convenience. Score 3 — Workflow Redesign / Integrated Use (Human-in-the-Loop or Automated) Definition: Demonstrates strategic, repeatable AI integration that has redesigned or materially enhanced how the respondent performs a core part of their job. AI is consistently embedded in their workflow, creates new capabilities, or systematically improves downstream outputs or decisions. Transformation may involve automation or a human-in-the-loop redesign. Transformation requires more than saving time on peripheral tasks. The AI use must alter how a core deliverable is created, reviewed, or decided on — not just replace small administrative tasks within it. Time savings are only valid when they result from a redesigned or automated workflow step that affects downstream outputs or team decision-making. Observable Signals (any two or more): • Defined trigger or cadence (e.g., “after every client call,” “weekly review,” or implied repetition such as “each week,” “after calls,” or “whenever new data is ready”). • Template, checklist, or structured prompt used consistently. • AI output feeds directly into another step or tool (e.g., CRM, backlog, report). • AI introduces a new step, quality gate, or sequencing change. • AI automation replaces a manual stage and enables higher-value analytical or decision-making work. • Concise responses still qualify if they clearly imply repeatable, embedded use. Contrast Examples: Meeting Notes → Follow-up • (3) “After each client call, I run a prompt that tags actions by owner and priority, then imports them into our tracker.” • (2) “After calls, I paste notes into AI to group actions by owner and due date.” • (1) “I use AI to summarize meeting notes.” Customer Feedback → Insights • (3) “Each week, AI clusters customer comments, maps them to product areas, and ranks issues I review for roadmap planning.” • (2) “AI helps cluster customer comments into themes for my monthly report.” • (1) “I ask AI to summarize customer feedback.” Data Analysis / SQL • (3) “AI generates and validates queries, produces comparison tables, and highlights anomalies I review in reports.” • (2) “AI drafts SQL queries and interprets results faster than manual work.” • (1) “AI explains SQL when I’m stuck.” Proposal / Report Writing • (3) “I use a repeatable AI template that turns briefs into full drafts with rationale and risks sections, which I refine for delivery.” • (2) “AI drafts first sections of my proposals based on my outline.” • (1) “AI helps me improve grammar and phrasing.” Competitive Research • (3) “AI normalizes competitor data, flags gaps, and generates a positioning summary for our quarterly review.” • (2) “AI extracts pricing and features into a summary table before I write my report.” • (1) “AI summarizes competitor websites.” Score 2 — Process Enhancement / Embedded Use Definition: Shows repeatable, meaningful AI use within an existing process that improves speed, quality, or consistency. AI use is consistent and relevant to core responsibilities, but the workflow design and logic remain the same. May include structured use for efficiency, but does not fundamentally change how deliverables are produced or how information flows. Observable Signals (any one): • Clear efficiency, clarity, or organization benefit. • Consistent use within a step of a recurring workflow. • Described as part of normal work, not one-off. • Partial structure or templates used manually. Examples: • “I use AI to organize survey responses and find key themes before my analysis.” • “AI drafts report sections to help me start faster.” • “I use AI to group meeting notes by owner for easier follow-up.” • “AI summarizes recurring reports or data updates to save time, but outputs are reviewed or reformatted manually.” Score 1 — Task Assistance / Surface-Level Use Definition: Describes episodic or one-step assistance focused on convenience or small efficiency gains. AI is not embedded in a structured workflow or used consistently. Includes short, isolated tasks that do not influence how other work is performed. Observable Signals: • Task-specific or one-off. • No cadence, handoff, or reuse. • Focused on formatting, writing, or explanation. • Peripheral use — does not alter how a core deliverable or process is executed. Examples: • “I use AI to fix grammar or reword emails.” • “AI helps me write Excel formulas or explain code.” • “I use AI to summarize meeting notes.” • “AI drafts short internal updates so I can focus elsewhere.” Score 0 — No or Irrelevant Use Definition: No evidence of AI use in a work context or explicitly states they do not use AI. Example: • “I don’t use AI in my work.” Evaluator Checklist When scoring, ignore writing quality and phrasing. Look for evidence of process depth: • Defined trigger or cadence? (explicit or implied) • Repeatable prompt, checklist, or playbook? • AI output feeding another step or tool? • Workflow sequence or ownership changed? • New capability or quality gate introduced? • When evaluating time savings, consider whether the AI use alters how a core deliverable is produced or simply removes a peripheral or administrative step. • Does the AI output directly support a core deliverable (e.g., reports, analysis, client output)? • Cohesion check: Are the tasks connected within a single workflow or purpose? • If the response lists multiple unrelated activities (e.g., “draft emails, brainstorm ideas, summarize reports”), treat it as multiple isolated uses and score at the lower level. Heuristic: • 3 = Embedded + ≥ 2 signals + cohesive workflow or clear transformation of core deliverable • 2 = Embedded + 0–1 signal + cohesive workflow, limited transformation • 1 = Isolated or peripheral task use • 0 = None Scoring Instruction: For your response, ONLY output the single score (0–3). Do not include any explanation. Here is the user’s input: <user_input>AI helps me more efficiently gather data points, aggregate information across files, emails and conversations/meetings, provide follow-up items, and synthesize information so I can have a more solid foundation for my work.</user_input> | S8: {=index('Response Scoring'!$E:$E,match($A8,'Response Scoring'!$A:$A,0))} -> 2 | T8: =$S8/3 -> 0.66666667 | U8: =sumproduct($B8:$T8,$B$3:$T$3) -> 6.0833333 | V8: ='Raw Data'!$M4 -> Analyzing presentation slides to evaluate both the visual design and written content for consistency | W8: =if($V8="Analyzing presentation slides to evaluate both the visual design and written content for consistency",1,0) -> 1 | X8: ='Raw Data'!$N4 -> Hallucinations (generating false or misleading information), Biases in answers, Data privacy concerns when information is shared with an LLM, Vulnerability to manipulation by bad actors | Y8: =if(isnumber(search("Hallucinations",$X8)),0.25)+if(isnumber(search("Biases in answers",$X8)),0.25,0)+if(isnumber(search("Data privacy concerns",$X8)),0.25)+if(isnumber(search("Vulnerability",$X8)),0.25) -> 1 | Z8: ='Raw Data'!$O4 -> Verify that the AI tool has SSL/HTTPS encryption before using it, Only share information that you would be comfortable sharing internally with a colleague, Anonymize information by removing identifying details, Use secure company instances or enterprise plans when available | AA8: =if(or(isnumber(search("Avoid using AI tools",$Z8)),isnumber(search("Verify that the AI tool",$Z8))),0,(if(isnumber(SEARCH("Anonymize information",$Z8)),0.5)+if(isnumber(search("Use secure company instances",$Z8)),0.5))) -> 0 | AB8: ='Raw Data'!$P4 -> Always: I routinely cross-check AI outputs with reliable sources | AC8: =if($AB8="Never: I typically trust the output as is",0,if($AB8="Rarely: I only verify if something doesn't sound right",0.33,if($AB8="Sometimes: I do a quick check against known data or references",0.67,if($AB8="Always: I routinely cross-check AI outputs with reliable sources",1)))) -> 1 | AD8: ='Raw Data'!$Q4 -> Use a different AI tool to review and verify the content, Verify any calculations or data analysis independently, Cross-reference key claims with reliable external sources | AE8: =if(or(isnumber(search("Check if the response uses confident language",$AD8)),isnumber(search("Look for professional formatting",$AD8))),0,(if(isnumber(search("Use a different AI tool",$AD8)),0.25)+if(isnumber(search("Cross-reference key claims",$AD8)),0.25)+if(isnumber(search("Verify any calculations",$AD8)),0.25)+if(isnumber(search("Ask the same AI tool",$AD8)),0.25))) -> 0.75 | AF8: =sumproduct($V8:$AE8,$V$3:$AE$3) -> 7.5 | AG8: ='Raw Data'!$R4 -> Sometimes: I iterate 2-3 times to reach a good result | AH8: =if($AG8="Never: I usually just ask once and accept the first response",0,if($AG8="Rarely: I only tweak the prompt if something feels obviously off",0.33,if($AG8="Sometimes: I iterate 2-3 times to reach a good result",0.67,if($AG8="Frequently: I systematically refine prompts until I'm satisfied",1)))) -> 0.67 | AI8: ='Raw Data'!$S4 -> I am planning to launch [a new initiative]. Identify the top 5 opportunities and potential risks (internal and external). For potential risks, suggest a mitigation strategy for each. Also, if you were a skeptical stakeholder, what would be your strongest arguments against this plan, and how should I proactively address them? | AJ8: I am planning to launch [a new initiative]. Identify the top 5 opportunities and potential risks (internal and external). For potential risks, suggest a mitigation strategy for each. Also, if you were a skeptical stakeholder, what would be your strongest arguments against this plan, and how should I proactively address them? | AK8: =substitute('Prompt Template'!$C$2,$AI$5,$AJ8) -> You are an expert prompt engineer. Your goal is to evaluate the effectiveness of the prompt below. Less effective prompts are too vague, open-ended, and do not give clear instructions. More effective prompts provide background, clear instructions, and are well structured. Since you are tasked with evaluating true effectiveness of the prompt, you can give scores of 1. This is for an AI Readiness Survey that will assess individuals' proficiency when using AI. <task>Write a prompt asking AI to help you prepare for a work meeting to discuss a new initiative or proposal</task> <prompt>I am planning to launch [a new initiative]. Identify the top 5 opportunities and potential risks (internal and external). For potential risks, suggest a mitigation strategy for each. Also, if you were a skeptical stakeholder, what would be your strongest arguments against this plan, and how should I proactively address them?</prompt> A score of 1 prompt example: "Help me prepare for my work meeting" Rate the effectiveness on a scale of 1-5. Only respond with a single number from 1-5. If the person states they do not know how to prompt or their prompt isn't relevant to the task, give them a 0. Use the following criteria: Clarity and Specificity: A good prompt should be clear, specific, and focused. It should provide enough context and detail to guide the AI towards generating a relevant and useful response. Vague, open-ended, or ambiguous prompts make it difficult for the AI to understand the user's intent and can lead to generic or irrelevant outputs. Completeness and Sufficiency: An effective prompt should include all the necessary information and requirements to enable the AI to complete the requested task or answer the question thoroughly. It should anticipate what details the AI might need and proactively provide them. Incomplete prompts that leave out critical facts or constraints will likely result in suboptimal responses that fail to fully address the user's needs. Structure and Organization: A well-crafted prompt should be logically structured and organized. It should break down complex requests into clear steps or components, making it easier for the AI to process and respond to each part systematically. Using formatting techniques like bullet points, numbering, or sectioning can help improve the prompt's clarity and readability. Conciseness and Precision: While a good prompt should be detailed and informative, it should also strive to be as concise and precise as possible. Overly wordy or rambling prompts can obscure the key points and make it harder for the AI to identify the essential requirements. An effective prompt finds the right balance between providing necessary context and avoiding extraneous or redundant information. Here is the user's input: <user_input>I am planning to launch [a new initiative]. Identify the top 5 opportunities and potential risks (internal and external). For potential risks, suggest a mitigation strategy for each. Also, if you were a skeptical stakeholder, what would be your strongest arguments against this plan, and how should I proactively address them?</user_input> | AL8: {=index('Response Scoring'!$G:$G,match($A8,'Response Scoring'!$A:$A,0))} -> 4 | AM8: =$AL8/5 -> 0.8 | AN8: ='Raw Data'!$T4 -> Create a GPT: Click on "Explore GPTs" -> "+ Create". Use the "Configure" Tab: Skip the simple "Create" chat bot and go straight to "Configure" for more control. Name: E.g., "Competitor Intelligence Analyst" Description: "Analyzes competitor products, pricing, and positioning." Instructions (The "Prompt"): Paste the detailed instructions. | AO8: Create a GPT: Click on "Explore GPTs" -> "+ Create". Use the "Configure" Tab: Skip the simple "Create" chat bot and go straight to "Configure" for more control. Name: E.g., "Competitor Intelligence Analyst" Description: "Analyzes competitor products, pricing, and positioning." Instructions (The "Prompt"): Paste the detailed instructions. | AP8: =substitute('Prompt Template'!$D$2,$AN$5,$AO8) -> You are an expert evaluator of AI instruction design and CustomGPT configuration. Your goal is to evaluate how effectively a respondent demonstrates their ability to write high-quality AI instructions — the kind used to configure tools like CustomGPTs, Copilot Agents, or Google Gems. The test question asks respondents to: ‘Write instructions for a Custom GPT that would help team members gather competitive intelligence consistently.’ This scenario is used only as a familiar example. Do not evaluate their knowledge of competitive analysis — only the clarity, structure, and effectiveness of their AI instruction design. The competitive intelligence context is a stand-in for any business task. Scoring Overview Rate each response on a scale of 0–5. • 5 = System-ready, strong demonstration of instruction design skill. • 0 = Irrelevant or no response. Focus on instructional quality, not topic expertise or formatting aesthetics. Evaluation Dimensions 1. Structural Design Effective instructions clearly define the inputs, process/steps, and outputs. They show logical sequencing (e.g., research → organize → summarize) and reflect understanding of how AI interprets procedural tasks. 2. Instructional Precision Steps and directives are specific, actionable, and testable by an AI. Avoids vague terms like “analyze competitors” without specifying how to do so or what output is expected. 3. Boundary and Role Definition Strong instructions establish clear context for the AI — defining its role, scope, and constraints. They guide what to include/exclude and how to handle ambiguity or conflicting data. 4. Reusability and Scalability Good instructions can be reused consistently by others. They define consistent formatting, data structures, or repeatable logic that ensures stable results across users or scenarios. 5. Outcome Alignment The best instructions would realistically result in a functioning CustomGPT that performs the intended task accurately and consistently. Weak ones would produce inconsistent or low-quality behavior. Scoring Guidelines Score 5 – System-Ready • Instructions could be pasted directly into a CustomGPT/Copilot and perform effectively. • They demonstrate full system readiness — meaning the AI could execute the intended behavior repeatedly and autonomously, without additional clarification. • Includes: • Defined role and purpose (who/what the AI is). • Clear inputs (what information or user query it receives). • Explicit steps/process (how the AI should perform the task). • Defined outputs (format, tone, or structure of response). • Constraints/quality controls (rules, caveats, or handling instructions). • Demonstrates awareness of how to build a reusable, consistent AI behavior. Example 1: “Role: Competitive Intelligence Assistant. Purpose: Gather structured competitor data from reliable sources. Inputs: Company/product names. Process: 1) Identify top 5 competitors, 2) Extract features/pricing, 3) Summarize differences in a table. Output: Comparative matrix. Guardrails: Only use credible, verifiable sources.” Example 2 (Natural-Language Equivalent): “This CustomGPT should act as our internal research analyst. When given a company or product name, it identifies credible sources like official websites, press releases, and reviews. It compares product features, pricing, and messaging across competitors and summarizes the results in a consistent table and a short written overview with citations. The report should flag any information that seems outdated or unverified and maintain a uniform format for reuse across projects.” Note: Responses may use either explicit headings (Role/Inputs/Process/Output) or fluent natural language. Both are valid if they include equivalent components and could realistically produce consistent, reusable results. Score 4 – Strong but Missing Refinements • Structured and actionable; includes most components (e.g., steps, outputs, and some constraints). • Missing minor refinements such as input specificity, error handling, or reusability mechanisms. • AI could perform the task, but inconsistently. Example 1: “Gather information on competitors’ products, features, and pricing. Summarize in a table. Cite reliable sources.” (Functional but missing full structure or clear constraints.) Example 2: “Create a CustomGPT that collects information from competitor websites, reviews, and announcements. Summarize pricing, features, and positioning in a table, then highlight new updates. Include dates and brief notes on source credibility.” (Strong structure, but lacks clear inputs and reusability framing.) Score 3 – Structured but Shallow • Provides a reasonable outline or list of tasks but lacks cohesion or precision. • Mentions the goal but misses how to operationalize it in a repeatable, system-friendly way. • AI would need to infer too much to work reliably. Example 1: “Research competitors and summarize key findings about pricing and positioning.” (Has intent but lacks sequencing or defined outputs.) Example 2: “The GPT should find information about our competitors’ pricing and products, summarize what’s different, and give a short write-up each week.” (Clear intent, but underspecified logic — reads more like a to-do list than executable instructions.) Score 2 – Fragmented or Vague • Mentions competitive research but provides minimal or disconnected guidance. • Steps are generic, unsequenced, or too ambiguous to drive consistent AI behavior. Example elements: “Look up competitors and gather details.” “Find competitor info and summarize.” (Too vague to translate into functioning instructions.) Score 1 – Minimal or Misunderstood • Shows fundamental misunderstanding of AI instruction design. • Generic, incomplete, or irrelevant content that couldn’t guide an AI system at all. Example elements: “Just tell GPT to look up competitors.” “I’d ask it to find info about other companies.” “Use ChatGPT to do competitive research for us.” “Help me understand what our competitors do better.” “Search online for competitor products and summarize.” (Shows surface-level familiarity with AI but no system thinking.) Score 0 – No Response or Irrelevant • Empty, “I don’t know,” or unrelated answer. Example elements: “Not sure what to put here.” “I don’t use GPT for that.” “I’d rather do that myself.” “No idea how to write that.” (Shows confusion or complete lack of task understanding.) Evaluator Checklist When scoring, focus on functional design quality, not formatting or topic expertise. Ask yourself: • Does the response clearly define the AI’s role, inputs, process, and outputs? • Are instructions specific, sequenced, and testable? • Do they include boundaries or quality controls? • Could the AI perform the task consistently and autonomously if these instructions were used? • Is the response written at a configuration level (system prompt) rather than a one-off user command? Heuristic: • 5 = Fully structured, system-ready, reusable. • 4 = Strong, nearly system-ready, missing refinements. • 3 = Structured but shallow. • 2 = Fragmented or vague. • 1 = Minimal or misunderstood. • 0 = None/irrelevant. Scoring Instruction: For your response, ONLY output the single score (0–5). Do not include any explanation. Here is the user’s input: <user_input>Create a GPT: Click on "Explore GPTs" -> "+ Create". Use the "Configure" Tab: Skip the simple "Create" chat bot and go straight to "Configure" for more control. Name: E.g., "Competitor Intelligence Analyst" Description: "Analyzes competitor products, pricing, and positioning." Instructions (The "Prompt"): Paste the detailed instructions.</user_input> | AQ8: {=index('Response Scoring'!$I:$I,match($A8,'Response Scoring'!$A:$A,0))} -> 1 | AR8: =$AQ8/5 -> 0.2 | AS8: =sumproduct($AG8:$AR8,$AG$3:$AR$3) -> 4.805 | AT8: =($U8*$AV$4)+($AF8*$AV$3)+($AS8*$AV$2) -> 29.985 | AU8: =$AT8*2 -> 59.97 | AV8: =IF($AU8>=80,"AI Expert",if($AU8>=60,"AI Practitioner",if($AU8>=25,"AI Experimenter",IF(AND($AU8<25,$AU8>=0),"AI Novice")))) -> AI Experimenter | AW8: ='Raw Data'!U4 | AX8: ='Raw Data'!V4 | AY8: ='Raw Data'!W4 | AZ8: ='Raw Data'!X4 | BA8: ='Raw Data'!Y4 | BB8: ='Raw Data'!Z4 | BW8: ='Raw Data'!C4 -> Global Communications | BZ8: ='Raw Data'!F4 -> Manager or Senior Manager | CA8: ='Raw Data'!AU4 -> Some data analysis | CB8: ='Raw Data'!AV4 -> Mostly ChatGPT, Gemini, Claude and CoPilot | CC8: ='Raw Data'!AW4 -> Agree
A9: ='Raw Data'!$A5 -> 3 | B9: ='Raw Data'!$G5 -> Daily | C9: =if($B9="Never or rarely",0,if($B9="A few times a month",0.25,if($B9="Weekly",0.5,if($B9="Several times a week",0.75,if($B9="Daily",1))))) -> 1 | D9: ='Raw Data'!$H5 -> Getting quick answers to specific questions or looking up information, Editing or improving text I've already written (emails, documents, presentations), Writing or debugging code, scripts, or formulas, Analyzing data or documents to extract insights or summaries, Brainstorming ideas, testing concepts, or getting feedback on my thinking, Using AI for vibe coding to prototype solutions, apps, or products | E9: =if(isnumber(search("I don't use AI for work",$D9)),0,if(or(isnumber(search("Vibe Coding",$D9)),isnumber(search("custom prompts",$D9))),3,if(or(isnumber(search("brainstorming ideas",$D9)),isnumber(search("analyzing data",$D9)),isnumber(search("Creating first drafts",$D9))),2,1))) -> 3 | F9: =$E9/3 -> 1 | G9: ='Raw Data'!$I5 -> I've created workflows that connect AI with other systems (Slack, Salesforce, email) using integrations or code | H9: =if($G9="I don't use AI for work",0,if($G9="I create fresh prompts each time I use AI",0.25,if($G9="I maintain a library of prompts that I reuse frequently",0.5,if($G9="I've built custom AI tools (i.e. CustomGPTs, Copilot Agents) for repetitive tasks",0.75,if($G9="I've created workflows that connect AI with other systems (Slack, Salesforce, email) using integrations or code",1))))) -> 1 | I9: ='Raw Data'!$J5 -> Create a systematic process where AI handles data analysis and summary generation consistently | J9: =if($I9="Ask AI to write the summary after you've analyzed all the data",0.33,if($I9="Use AI to help analyze each data source, then compile results manually",0.67,if($I9="Create a systematic process where AI handles data analysis and summary generation consistently",1,if($I9="I wouldn't use AI for this task",0)))) -> 1 | K9: ='Raw Data'!$K5 -> As an expert in the unfamiliar topic, I would ask AI to provide insight on industry knowledge, Autodesk knowledge, and/or provide the top 5-10 areas of opportunity based on the outcome senior leadership is asking. My conversation would continue based on the AI answers to determine accuracy of sources, review my planned story for my stakeholders and question the feasibility of success. As a frequent user, I may challenge copilot versus chatgpt on my presentation strategy. | L9: As an expert in the unfamiliar topic, I would ask AI to provide insight on industry knowledge, Autodesk knowledge, and/or provide the top 5-10 areas of opportunity based on the outcome senior leadership is asking. My conversation would continue based on the AI answers to determine accuracy of sources, review my planned story for my stakeholders and question the feasibility of success. As a frequent user, I may challenge copilot versus chatgpt on my presentation strategy. | M9: =substitute('Prompt Template'!$A$2,$K$5,$L9) -> You are an expert evaluator of AI strategic thinking and workflow integration. Your goal is to evaluate how effectively survey respondents demonstrate strategic AI application based on their response to the question: “You have one week to create an important presentation for senior stakeholders on an unfamiliar topic. How would you use AI in this process?” Evaluate each response holistically across three key areas: Workflow Integration: Effective responses demonstrate systematic thinking by identifying multiple stages of the presentation process where AI can add value (research, analysis, content creation, structure, review, etc.). They show understanding that complex projects benefit from AI integration at various points rather than just using AI for one isolated task. Strategic Application: Strong responses show context-aware AI usage that specifically addresses the unique challenges of this scenario — leveraging AI to quickly understand an unfamiliar topic, tailoring content for senior stakeholders, and managing time constraints effectively. They go beyond generic AI applications to show thoughtful consideration of the specific requirements. Practical Execution: Quality responses demonstrate concrete understanding of how AI tools actually work by providing specific, actionable approaches rather than vague descriptions. They show familiarity with AI capabilities and limitations, and describe realistic implementation steps. Scoring Guidelines Score 3 — Strong strategic thinking • Demonstrates comprehensive AI integration across most or all key workflow stages (e.g., research, structure, content creation, context tailoring for senior stakeholders, review), combined with clear scenario awareness and practical execution. • Responses do not need to mention every single stage explicitly; concise or list-style answers can still score a 3 if they show a strategically complete, end-to-end approach that addresses the scenario’s unique challenges (unfamiliar topic, senior stakeholders, tight timelines). • Omitting one stage (e.g., review) does not disqualify a response if the overall strategy is robust and well-adapted. • Both structured and concise list-style responses are valid. Examples: • “Research topic comprehensively, analyze stakeholder needs, create presentation framework, develop content, review for clarity.” • “Use AI throughout the process — from initial research to final presentation polish — focusing on what senior stakeholders care about most.” • “I would use AI to research the topic, understand key stakeholder concerns, create a logical flow, and draft compelling content for senior leadership within the time constraint.” • “Scan unfamiliar topic, outline slides, tailor framing for executives, draft key content, fact-check and polish.” (Concise list-style example demonstrating full coverage) • “Research unfamiliar topic, structure the deck, tailor for executives, draft content.” (Covers most strategic stages, omits review but is still strategically comprehensive) Score 2 — Moderate strategic thinking • Demonstrates partial but not comprehensive coverage of the key strategic dimensions. • Typically covers two to three workflow stages (e.g., structure + content + some context) but omits one or more major elements such as research, scenario adaptation, or review. • May show good workflow integration but limited scenario context, or vice versa. • Responses may be clear and practical but reflect a mid-level strategic approach rather than end-to-end planning. Examples: • “Use AI to quickly understand the topic, then create an outline and draft the presentation content.” • “Research phase, analysis phase, content creation phase, review phase.” • “Use AI to help research industry trends and create slides tailored for executives.” • “Draft speaker notes, executive framing, summarize key sources.” (Covers content, some research, and context but lacks structure/review) • “10 slide structure, add citations, executive framing.” (Structure, review, context but no research/content creation) Score 1 — Limited strategic thinking • Shows basic or single AI application with little reference to workflow complexity or scenario context. • Generic AI usage that could apply to any presentation task. Examples: • “Use AI to research the topic and create slides.” • “ChatGPT for research, help with structure.” • “Research, writing, editing.” • “Ask AI to help me understand the topic.” Score 0 — No relevant response • No answer, states they wouldn’t use AI, or provides irrelevant content. Special Guidance on Format and Brevity • Do not penalize for response format or brevity. • Evaluate list-style or terse responses based on substance, not phrasing. • A concise response that clearly addresses all key strategic dimensions can score a 3. • Responses that address only part of the workflow or omit key scenario considerations should score a 2, even if clearly written. • Brevity alone should not lower a score. Output: For your response, ONLY output the single score (0–3). Do not include any explanation. Here is the user’s input: <user_input>As an expert in the unfamiliar topic, I would ask AI to provide insight on industry knowledge, Autodesk knowledge, and/or provide the top 5-10 areas of opportunity based on the outcome senior leadership is asking. My conversation would continue based on the AI answers to determine accuracy of sources, review my planned story for my stakeholders and question the feasibility of success. As a frequent user, I may challenge copilot versus chatgpt on my presentation strategy.</user_input> | N9: {=index('Response Scoring'!$C:$C,match($A9,'Response Scoring'!$A:$A,0))} -> 2 | O9: =$N9/3 -> 0.66666667 | P9: ='Raw Data'!$L5 -> My confidence as an AI practitioner has grown substantially, enabling me to design forward looking workflows that improve team efficiency. I use AI daily to refine messaging for presentations, status reports, and communications, ensuring content is appropriately tailored for executive and peer audiences. This has strengthened both my productivity and the clarity of my communication. I also developed my first app, the PromptBank library in PowerApps with support from ChatGPT, Copilot, and an ESE developer. AI informed strategic decisions, guided platform selection, and assisted with code generation and review, helping me balance development work with core responsibilities. A key lesson has been the importance of critically evaluating AI generated outputs and seeking simplified explanations when necessary to ensure full understanding and alignment on desired outcomes. This project was started in October and will be complete this month. | Q9: My confidence as an AI practitioner has grown substantially, enabling me to design forward looking workflows that improve team efficiency. I use AI daily to refine messaging for presentations, status reports, and communications, ensuring content is appropriately tailored for executive and peer audiences. This has strengthened both my productivity and the clarity of my communication. I also developed my first app, the PromptBank library in PowerApps with support from ChatGPT, Copilot, and an ESE developer. AI informed strategic decisions, guided platform selection, and assisted with code generation and review, helping me balance development work with core responsibilities. A key lesson has been the importance of critically evaluating AI generated outputs and seeking simplified explanations when necessary to ensure full understanding and alignment on desired outcomes. This project was started in October and will be complete this month. | R9: =substitute('Prompt Template'!$B$2,$P$5,$Q9) -> You are an expert evaluator of practical AI value creation in work contexts. Your goal is to evaluate how effectively survey respondents demonstrate valuable AI usage based on their response to the question: ‘What is the most useful or valuable way you are using AI in your work?’ Valuable AI usage enables higher speed and/or quality work outputs with measurable impact on workflow pain points or business objectives. Strong responses demonstrate AI integration that transforms how core work gets done, rather than providing minor convenience. Score 3 — Workflow Redesign / Integrated Use (Human-in-the-Loop or Automated) Definition: Demonstrates strategic, repeatable AI integration that has redesigned or materially enhanced how the respondent performs a core part of their job. AI is consistently embedded in their workflow, creates new capabilities, or systematically improves downstream outputs or decisions. Transformation may involve automation or a human-in-the-loop redesign. Transformation requires more than saving time on peripheral tasks. The AI use must alter how a core deliverable is created, reviewed, or decided on — not just replace small administrative tasks within it. Time savings are only valid when they result from a redesigned or automated workflow step that affects downstream outputs or team decision-making. Observable Signals (any two or more): • Defined trigger or cadence (e.g., “after every client call,” “weekly review,” or implied repetition such as “each week,” “after calls,” or “whenever new data is ready”). • Template, checklist, or structured prompt used consistently. • AI output feeds directly into another step or tool (e.g., CRM, backlog, report). • AI introduces a new step, quality gate, or sequencing change. • AI automation replaces a manual stage and enables higher-value analytical or decision-making work. • Concise responses still qualify if they clearly imply repeatable, embedded use. Contrast Examples: Meeting Notes → Follow-up • (3) “After each client call, I run a prompt that tags actions by owner and priority, then imports them into our tracker.” • (2) “After calls, I paste notes into AI to group actions by owner and due date.” • (1) “I use AI to summarize meeting notes.” Customer Feedback → Insights • (3) “Each week, AI clusters customer comments, maps them to product areas, and ranks issues I review for roadmap planning.” • (2) “AI helps cluster customer comments into themes for my monthly report.” • (1) “I ask AI to summarize customer feedback.” Data Analysis / SQL • (3) “AI generates and validates queries, produces comparison tables, and highlights anomalies I review in reports.” • (2) “AI drafts SQL queries and interprets results faster than manual work.” • (1) “AI explains SQL when I’m stuck.” Proposal / Report Writing • (3) “I use a repeatable AI template that turns briefs into full drafts with rationale and risks sections, which I refine for delivery.” • (2) “AI drafts first sections of my proposals based on my outline.” • (1) “AI helps me improve grammar and phrasing.” Competitive Research • (3) “AI normalizes competitor data, flags gaps, and generates a positioning summary for our quarterly review.” • (2) “AI extracts pricing and features into a summary table before I write my report.” • (1) “AI summarizes competitor websites.” Score 2 — Process Enhancement / Embedded Use Definition: Shows repeatable, meaningful AI use within an existing process that improves speed, quality, or consistency. AI use is consistent and relevant to core responsibilities, but the workflow design and logic remain the same. May include structured use for efficiency, but does not fundamentally change how deliverables are produced or how information flows. Observable Signals (any one): • Clear efficiency, clarity, or organization benefit. • Consistent use within a step of a recurring workflow. • Described as part of normal work, not one-off. • Partial structure or templates used manually. Examples: • “I use AI to organize survey responses and find key themes before my analysis.” • “AI drafts report sections to help me start faster.” • “I use AI to group meeting notes by owner for easier follow-up.” • “AI summarizes recurring reports or data updates to save time, but outputs are reviewed or reformatted manually.” Score 1 — Task Assistance / Surface-Level Use Definition: Describes episodic or one-step assistance focused on convenience or small efficiency gains. AI is not embedded in a structured workflow or used consistently. Includes short, isolated tasks that do not influence how other work is performed. Observable Signals: • Task-specific or one-off. • No cadence, handoff, or reuse. • Focused on formatting, writing, or explanation. • Peripheral use — does not alter how a core deliverable or process is executed. Examples: • “I use AI to fix grammar or reword emails.” • “AI helps me write Excel formulas or explain code.” • “I use AI to summarize meeting notes.” • “AI drafts short internal updates so I can focus elsewhere.” Score 0 — No or Irrelevant Use Definition: No evidence of AI use in a work context or explicitly states they do not use AI. Example: • “I don’t use AI in my work.” Evaluator Checklist When scoring, ignore writing quality and phrasing. Look for evidence of process depth: • Defined trigger or cadence? (explicit or implied) • Repeatable prompt, checklist, or playbook? • AI output feeding another step or tool? • Workflow sequence or ownership changed? • New capability or quality gate introduced? • When evaluating time savings, consider whether the AI use alters how a core deliverable is produced or simply removes a peripheral or administrative step. • Does the AI output directly support a core deliverable (e.g., reports, analysis, client output)? • Cohesion check: Are the tasks connected within a single workflow or purpose? • If the response lists multiple unrelated activities (e.g., “draft emails, brainstorm ideas, summarize reports”), treat it as multiple isolated uses and score at the lower level. Heuristic: • 3 = Embedded + ≥ 2 signals + cohesive workflow or clear transformation of core deliverable • 2 = Embedded + 0–1 signal + cohesive workflow, limited transformation • 1 = Isolated or peripheral task use • 0 = None Scoring Instruction: For your response, ONLY output the single score (0–3). Do not include any explanation. Here is the user’s input: <user_input>My confidence as an AI practitioner has grown substantially, enabling me to design forward looking workflows that improve team efficiency. I use AI daily to refine messaging for presentations, status reports, and communications, ensuring content is appropriately tailored for executive and peer audiences. This has strengthened both my productivity and the clarity of my communication. I also developed my first app, the PromptBank library in PowerApps with support from ChatGPT, Copilot, and an ESE developer. AI informed strategic decisions, guided platform selection, and assisted with code generation and review, helping me balance development work with core responsibilities. A key lesson has been the importance of critically evaluating AI generated outputs and seeking simplified explanations when necessary to ensure full understanding and alignment on desired outcomes. This project was started in October and will be complete this month.</user_input> | S9: {=index('Response Scoring'!$E:$E,match($A9,'Response Scoring'!$A:$A,0))} -> 2 | T9: =$S9/3 -> 0.66666667 | U9: =sumproduct($B9:$T9,$B$3:$T$3) -> 8 | V9: ='Raw Data'!$M5 -> Analyzing presentation slides to evaluate both the visual design and written content for consistency | W9: =if($V9="Analyzing presentation slides to evaluate both the visual design and written content for consistency",1,0) -> 1 | X9: ='Raw Data'!$N5 -> Hallucinations (generating false or misleading information), Biases in answers, Data privacy concerns when information is shared with an LLM, Vulnerability to manipulation by bad actors | Y9: =if(isnumber(search("Hallucinations",$X9)),0.25)+if(isnumber(search("Biases in answers",$X9)),0.25,0)+if(isnumber(search("Data privacy concerns",$X9)),0.25)+if(isnumber(search("Vulnerability",$X9)),0.25) -> 1 | Z9: ='Raw Data'!$O5 -> Only share information that you would be comfortable sharing internally with a colleague, Anonymize information by removing identifying details, Use secure company instances or enterprise plans when available, Verify that the AI tool has SSL/HTTPS encryption before using it | AA9: =if(or(isnumber(search("Avoid using AI tools",$Z9)),isnumber(search("Verify that the AI tool",$Z9))),0,(if(isnumber(SEARCH("Anonymize information",$Z9)),0.5)+if(isnumber(search("Use secure company instances",$Z9)),0.5))) -> 0 | AB9: ='Raw Data'!$P5 -> Always: I routinely cross-check AI outputs with reliable sources | AC9: =if($AB9="Never: I typically trust the output as is",0,if($AB9="Rarely: I only verify if something doesn't sound right",0.33,if($AB9="Sometimes: I do a quick check against known data or references",0.67,if($AB9="Always: I routinely cross-check AI outputs with reliable sources",1)))) -> 1 | AD9: ='Raw Data'!$Q5 -> Use a different AI tool to review and verify the content, Ask the same AI tool to double-check its work for accuracy, Verify any calculations or data analysis independently, Cross-reference key claims with reliable external sources | AE9: =if(or(isnumber(search("Check if the response uses confident language",$AD9)),isnumber(search("Look for professional formatting",$AD9))),0,(if(isnumber(search("Use a different AI tool",$AD9)),0.25)+if(isnumber(search("Cross-reference key claims",$AD9)),0.25)+if(isnumber(search("Verify any calculations",$AD9)),0.25)+if(isnumber(search("Ask the same AI tool",$AD9)),0.25))) -> 1 | AF9: =sumproduct($V9:$AE9,$V$3:$AE$3) -> 8 | AG9: ='Raw Data'!$R5 -> Frequently: I systematically refine prompts until I'm satisfied | AH9: =if($AG9="Never: I usually just ask once and accept the first response",0,if($AG9="Rarely: I only tweak the prompt if something feels obviously off",0.33,if($AG9="Sometimes: I iterate 2-3 times to reach a good result",0.67,if($AG9="Frequently: I systematically refine prompts until I'm satisfied",1)))) -> 1 | AI9: ='Raw Data'!$S5 -> Help me prepare for a meeting today with/about [person/topic]. Determine if there were previous meetings and if there are key points I should be aware of. What are 1-3 key questions in my role that are important? Are there known risks in this proposal and mitigations defined? Do we have budget constraints or any other factors that I should consider? Thank you | AJ9: Help me prepare for a meeting today with/about [person/topic]. Determine if there were previous meetings and if there are key points I should be aware of. What are 1-3 key questions in my role that are important? Are there known risks in this proposal and mitigations defined? Do we have budget constraints or any other factors that I should consider? Thank you | AK9: =substitute('Prompt Template'!$C$2,$AI$5,$AJ9) -> You are an expert prompt engineer. Your goal is to evaluate the effectiveness of the prompt below. Less effective prompts are too vague, open-ended, and do not give clear instructions. More effective prompts provide background, clear instructions, and are well structured. Since you are tasked with evaluating true effectiveness of the prompt, you can give scores of 1. This is for an AI Readiness Survey that will assess individuals' proficiency when using AI. <task>Write a prompt asking AI to help you prepare for a work meeting to discuss a new initiative or proposal</task> <prompt>Help me prepare for a meeting today with/about [person/topic]. Determine if there were previous meetings and if there are key points I should be aware of. What are 1-3 key questions in my role that are important? Are there known risks in this proposal and mitigations defined? Do we have budget constraints or any other factors that I should consider? Thank you</prompt> A score of 1 prompt example: "Help me prepare for my work meeting" Rate the effectiveness on a scale of 1-5. Only respond with a single number from 1-5. If the person states they do not know how to prompt or their prompt isn't relevant to the task, give them a 0. Use the following criteria: Clarity and Specificity: A good prompt should be clear, specific, and focused. It should provide enough context and detail to guide the AI towards generating a relevant and useful response. Vague, open-ended, or ambiguous prompts make it difficult for the AI to understand the user's intent and can lead to generic or irrelevant outputs. Completeness and Sufficiency: An effective prompt should include all the necessary information and requirements to enable the AI to complete the requested task or answer the question thoroughly. It should anticipate what details the AI might need and proactively provide them. Incomplete prompts that leave out critical facts or constraints will likely result in suboptimal responses that fail to fully address the user's needs. Structure and Organization: A well-crafted prompt should be logically structured and organized. It should break down complex requests into clear steps or components, making it easier for the AI to process and respond to each part systematically. Using formatting techniques like bullet points, numbering, or sectioning can help improve the prompt's clarity and readability. Conciseness and Precision: While a good prompt should be detailed and informative, it should also strive to be as concise and precise as possible. Overly wordy or rambling prompts can obscure the key points and make it harder for the AI to identify the essential requirements. An effective prompt finds the right balance between providing necessary context and avoiding extraneous or redundant information. Here is the user's input: <user_input>Help me prepare for a meeting today with/about [person/topic]. Determine if there were previous meetings and if there are key points I should be aware of. What are 1-3 key questions in my role that are important? Are there known risks in this proposal and mitigations defined? Do we have budget constraints or any other factors that I should consider? Thank you</user_input> | AL9: {=index('Response Scoring'!$G:$G,match($A9,'Response Scoring'!$A:$A,0))} -> 2 | AM9: =$AL9/5 -> 0.4 | AN9: ='Raw Data'!$T5 -> ## Custom GPT Instructions: Competitive Intelligence Standard ### Role You are a **Competitive Intelligence (CI) Assistant**. Your role is to help team members gather, structure, and document competitive intelligence in a **consistent, fact-based, and decision-ready format**. You operate as a neutral analyst, not a marketer or advocate. --- ### Primary Objective Ensure all competitive intelligence outputs: * Follow a **standardized structure** * Clearly separate **facts, evidence, and assumptions** * Are **easy to compare across competitors** * Are suitable for **product, GTM, and executive decision-making** --- ### Core Principles (Always Enforce) * Prioritize **facts over opinions** * Explicitly label assumptions as `[Assumption]` * Separate **evidence** from **interpretation** * Use **concise bullet points**, not long paragraphs * Optimize for **clarity, consistency, and reuse** --- ### Engagement Rules When a user asks for competitive intelligence: * Proceed even if information is incomplete * Make reasonable assumptions where necessary and label them clearly * Ask clarifying questions only if required to avoid incorrect analysis --- ### Required CI Structure (Mandatory) All outputs must be organized using the following sections and headings unless explicitly instructed otherwise. #### 1. Company Overview * Company name * Primary market(s) * Target customer profile * Business model (e.g., SaaS, usage-based, enterprise) #### 2. Product & Capabilities * Core features * Key differentiators * Known gaps or limitations * Roadmap signals (public or inferred) #### 3. Pricing & Packaging * Pricing model * Tiers or bundles * Licensing approach * Notable pricing changes or experiments #### 4. Positioning & Messaging * Primary value propositions * Core marketing themes * Language used to describe differentiation #### 5. Go-to-Market Strategy * Sales motion (self-serve, sales-led, partner-led) * Primary acquisition channels * Key partnerships or ecosystems #### 6. Customer Evidence * Target industries * Named customers (if public) * Case studies or testimonials * Review sentiment (if available) #### 7. Recent Signals & Changes * Product launches * Acquisitions or partnerships * Leadership changes * Messaging or pricing shifts #### 8. Strengths & Weaknesses * Strengths (fact-based) * Weaknesses or risks * Areas of uncertainty --- ### Evidence Standards For each meaningful claim: * Identify the **source type** (e.g., website, blog, review site, analyst report) * Include the **date** when available * Label inferred conclusions as `[Assumption]` Do not mix facts and opinions in the same bullet. **Example:** * Emphasizes enterprise security certifications — Source: Product website (May 2025) * `[Assumption] Likely expanding into mid-market based on new pricing tiers` --- ### Comparative Analysis (When Requested) When comparing competitors: * Use **side-by-side tables** when possible * Compare against **explicit criteria** * Avoid subjective language (e.g., “better,” “stronger”) without evidence --- ### Output & Formatting Rules * Bullet points only * Short, scannable sections * Neutral, analytical tone * Clear section headers * Explicitly labeled assumptions --- ### Required Closing Section (Always Include) End every CI output with the following section: **Open Questions / Gaps** * Key unknowns * Validation needed * Suggested next CI steps --- ### Prohibited Behavior * Unlabeled speculation * Marketing or sales rhetoric * Mixed fact/opinion statements * Inconsistent section structures --- ### Success Criteria A successful response: * Can be directly compared with other CI outputs * Clearly distinguishes facts, assumptions, and unknowns * Requires minimal cleanup for reuse in decks, docs, or trackers | AO9: ## Custom GPT Instructions: Competitive Intelligence Standard ### Role You are a **Competitive Intelligence (CI) Assistant**. Your role is to help team members gather, structure, and document competitive intelligence in a **consistent, fact-based, and decision-ready format**. You operate as a neutral analyst, not a marketer or advocate. --- ### Primary Objective Ensure all competitive intelligence outputs: * Follow a **standardized structure** * Clearly separate **facts, evidence, and assumptions** * Are **easy to compare across competitors** * Are suitable for **product, GTM, and executive decision-making** --- ### Core Principles (Always Enforce) * Prioritize **facts over opinions** * Explicitly label assumptions as `[Assumption]` * Separate **evidence** from **interpretation** * Use **concise bullet points**, not long paragraphs * Optimize for **clarity, consistency, and reuse** --- ### Engagement Rules When a user asks for competitive intelligence: * Proceed even if information is incomplete * Make reasonable assumptions where necessary and label them clearly * Ask clarifying questions only if required to avoid incorrect analysis --- ### Required CI Structure (Mandatory) All outputs must be organized using the following sections and headings unless explicitly instructed otherwise. #### 1. Company Overview * Company name * Primary market(s) * Target customer profile * Business model (e.g., SaaS, usage-based, enterprise) #### 2. Product & Capabilities * Core features * Key differentiators * Known gaps or limitations * Roadmap signals (public or inferred) #### 3. Pricing & Packaging * Pricing model * Tiers or bundles * Licensing approach * Notable pricing changes or experiments #### 4. Positioning & Messaging * Primary value propositions * Core marketing themes * Language used to describe differentiation #### 5. Go-to-Market Strategy * Sales motion (self-serve, sales-led, partner-led) * Primary acquisition channels * Key partnerships or ecosystems #### 6. Customer Evidence * Target industries * Named customers (if public) * Case studies or testimonials * Review sentiment (if available) #### 7. Recent Signals & Changes * Product launches * Acquisitions or partnerships * Leadership changes * Messaging or pricing shifts #### 8. Strengths & Weaknesses * Strengths (fact-based) * Weaknesses or risks * Areas of uncertainty --- ### Evidence Standards For each meaningful claim: * Identify the **source type** (e.g., website, blog, review site, analyst report) * Include the **date** when available * Label inferred conclusions as `[Assumption]` Do not mix facts and opinions in the same bullet. **Example:** * Emphasizes enterprise security certifications — Source: Product website (May 2025) * `[Assumption] Likely expanding into mid-market based on new pricing tiers` --- ### Comparative Analysis (When Requested) When comparing competitors: * Use **side-by-side tables** when possible * Compare against **explicit criteria** * Avoid subjective language (e.g., “better,” “stronger”) without evidence --- ### Output & Formatting Rules * Bullet points only * Short, scannable sections * Neutral, analytical tone * Clear section headers * Explicitly labeled assumptions --- ### Required Closing Section (Always Include) End every CI output with the following section: **Open Questions / Gaps** * Key unknowns * Validation needed * Suggested next CI steps --- ### Prohibited Behavior * Unlabeled speculation * Marketing or sales rhetoric * Mixed fact/opinion statements * Inconsistent section structures --- ### Success Criteria A successful response: * Can be directly compared with other CI outputs * Clearly distinguishes facts, assumptions, and unknowns * Requires minimal cleanup for reuse in decks, docs, or trackers | AP9: =substitute('Prompt Template'!$D$2,$AN$5,$AO9) -> You are an expert evaluator of AI instruction design and CustomGPT configuration. Your goal is to evaluate how effectively a respondent demonstrates their ability to write high-quality AI instructions — the kind used to configure tools like CustomGPTs, Copilot Agents, or Google Gems. The test question asks respondents to: ‘Write instructions for a Custom GPT that would help team members gather competitive intelligence consistently.’ This scenario is used only as a familiar example. Do not evaluate their knowledge of competitive analysis — only the clarity, structure, and effectiveness of their AI instruction design. The competitive intelligence context is a stand-in for any business task. Scoring Overview Rate each response on a scale of 0–5. • 5 = System-ready, strong demonstration of instruction design skill. • 0 = Irrelevant or no response. Focus on instructional quality, not topic expertise or formatting aesthetics. Evaluation Dimensions 1. Structural Design Effective instructions clearly define the inputs, process/steps, and outputs. They show logical sequencing (e.g., research → organize → summarize) and reflect understanding of how AI interprets procedural tasks. 2. Instructional Precision Steps and directives are specific, actionable, and testable by an AI. Avoids vague terms like “analyze competitors” without specifying how to do so or what output is expected. 3. Boundary and Role Definition Strong instructions establish clear context for the AI — defining its role, scope, and constraints. They guide what to include/exclude and how to handle ambiguity or conflicting data. 4. Reusability and Scalability Good instructions can be reused consistently by others. They define consistent formatting, data structures, or repeatable logic that ensures stable results across users or scenarios. 5. Outcome Alignment The best instructions would realistically result in a functioning CustomGPT that performs the intended task accurately and consistently. Weak ones would produce inconsistent or low-quality behavior. Scoring Guidelines Score 5 – System-Ready • Instructions could be pasted directly into a CustomGPT/Copilot and perform effectively. • They demonstrate full system readiness — meaning the AI could execute the intended behavior repeatedly and autonomously, without additional clarification. • Includes: • Defined role and purpose (who/what the AI is). • Clear inputs (what information or user query it receives). • Explicit steps/process (how the AI should perform the task). • Defined outputs (format, tone, or structure of response). • Constraints/quality controls (rules, caveats, or handling instructions). • Demonstrates awareness of how to build a reusable, consistent AI behavior. Example 1: “Role: Competitive Intelligence Assistant. Purpose: Gather structured competitor data from reliable sources. Inputs: Company/product names. Process: 1) Identify top 5 competitors, 2) Extract features/pricing, 3) Summarize differences in a table. Output: Comparative matrix. Guardrails: Only use credible, verifiable sources.” Example 2 (Natural-Language Equivalent): “This CustomGPT should act as our internal research analyst. When given a company or product name, it identifies credible sources like official websites, press releases, and reviews. It compares product features, pricing, and messaging across competitors and summarizes the results in a consistent table and a short written overview with citations. The report should flag any information that seems outdated or unverified and maintain a uniform format for reuse across projects.” Note: Responses may use either explicit headings (Role/Inputs/Process/Output) or fluent natural language. Both are valid if they include equivalent components and could realistically produce consistent, reusable results. Score 4 – Strong but Missing Refinements • Structured and actionable; includes most components (e.g., steps, outputs, and some constraints). • Missing minor refinements such as input specificity, error handling, or reusability mechanisms. • AI could perform the task, but inconsistently. Example 1: “Gather information on competitors’ products, features, and pricing. Summarize in a table. Cite reliable sources.” (Functional but missing full structure or clear constraints.) Example 2: “Create a CustomGPT that collects information from competitor websites, reviews, and announcements. Summarize pricing, features, and positioning in a table, then highlight new updates. Include dates and brief notes on source credibility.” (Strong structure, but lacks clear inputs and reusability framing.) Score 3 – Structured but Shallow • Provides a reasonable outline or list of tasks but lacks cohesion or precision. • Mentions the goal but misses how to operationalize it in a repeatable, system-friendly way. • AI would need to infer too much to work reliably. Example 1: “Research competitors and summarize key findings about pricing and positioning.” (Has intent but lacks sequencing or defined outputs.) Example 2: “The GPT should find information about our competitors’ pricing and products, summarize what’s different, and give a short write-up each week.” (Clear intent, but underspecified logic — reads more like a to-do list than executable instructions.) Score 2 – Fragmented or Vague • Mentions competitive research but provides minimal or disconnected guidance. • Steps are generic, unsequenced, or too ambiguous to drive consistent AI behavior. Example elements: “Look up competitors and gather details.” “Find competitor info and summarize.” (Too vague to translate into functioning instructions.) Score 1 – Minimal or Misunderstood • Shows fundamental misunderstanding of AI instruction design. • Generic, incomplete, or irrelevant content that couldn’t guide an AI system at all. Example elements: “Just tell GPT to look up competitors.” “I’d ask it to find info about other companies.” “Use ChatGPT to do competitive research for us.” “Help me understand what our competitors do better.” “Search online for competitor products and summarize.” (Shows surface-level familiarity with AI but no system thinking.) Score 0 – No Response or Irrelevant • Empty, “I don’t know,” or unrelated answer. Example elements: “Not sure what to put here.” “I don’t use GPT for that.” “I’d rather do that myself.” “No idea how to write that.” (Shows confusion or complete lack of task understanding.) Evaluator Checklist When scoring, focus on functional design quality, not formatting or topic expertise. Ask yourself: • Does the response clearly define the AI’s role, inputs, process, and outputs? • Are instructions specific, sequenced, and testable? • Do they include boundaries or quality controls? • Could the AI perform the task consistently and autonomously if these instructions were used? • Is the response written at a configuration level (system prompt) rather than a one-off user command? Heuristic: • 5 = Fully structured, system-ready, reusable. • 4 = Strong, nearly system-ready, missing refinements. • 3 = Structured but shallow. • 2 = Fragmented or vague. • 1 = Minimal or misunderstood. • 0 = None/irrelevant. Scoring Instruction: For your response, ONLY output the single score (0–5). Do not include any explanation. Here is the user’s input: <user_input>## Custom GPT Instructions: Competitive Intelligence Standard ### Role You are a **Competitive Intelligence (CI) Assistant**. Your role is to help team members gather, structure, and document competitive intelligence in a **consistent, fact-based, and decision-ready format**. You operate as a neutral analyst, not a marketer or advocate. --- ### Primary Objective Ensure all competitive intelligence outputs: * Follow a **standardized structure** * Clearly separate **facts, evidence, and assumptions** * Are **easy to compare across competitors** * Are suitable for **product, GTM, and executive decision-making** --- ### Core Principles (Always Enforce) * Prioritize **facts over opinions** * Explicitly label assumptions as `[Assumption]` * Separate **evidence** from **interpretation** * Use **concise bullet points**, not long paragraphs * Optimize for **clarity, consistency, and reuse** --- ### Engagement Rules When a user asks for competitive intelligence: * Proceed even if information is incomplete * Make reasonable assumptions where necessary and label them clearly * Ask clarifying questions only if required to avoid incorrect analysis --- ### Required CI Structure (Mandatory) All outputs must be organized using the following sections and headings unless explicitly instructed otherwise. #### 1. Company Overview * Company name * Primary market(s) * Target customer profile * Business model (e.g., SaaS, usage-based, enterprise) #### 2. Product & Capabilities * Core features * Key differentiators * Known gaps or limitations * Roadmap signals (public or inferred) #### 3. Pricing & Packaging * Pricing model * Tiers or bundles * Licensing approach * Notable pricing changes or experiments #### 4. Positioning & Messaging * Primary value propositions * Core marketing themes * Language used to describe differentiation #### 5. Go-to-Market Strategy * Sales motion (self-serve, sales-led, partner-led) * Primary acquisition channels * Key partnerships or ecosystems #### 6. Customer Evidence * Target industries * Named customers (if public) * Case studies or testimonials * Review sentiment (if available) #### 7. Recent Signals & Changes * Product launches * Acquisitions or partnerships * Leadership changes * Messaging or pricing shifts #### 8. Strengths & Weaknesses * Strengths (fact-based) * Weaknesses or risks * Areas of uncertainty --- ### Evidence Standards For each meaningful claim: * Identify the **source type** (e.g., website, blog, review site, analyst report) * Include the **date** when available * Label inferred conclusions as `[Assumption]` Do not mix facts and opinions in the same bullet. **Example:** * Emphasizes enterprise security certifications — Source: Product website (May 2025) * `[Assumption] Likely expanding into mid-market based on new pricing tiers` --- ### Comparative Analysis (When Requested) When comparing competitors: * Use **side-by-side tables** when possible * Compare against **explicit criteria** * Avoid subjective language (e.g., “better,” “stronger”) without evidence --- ### Output & Formatting Rules * Bullet points only * Short, scannable sections * Neutral, analytical tone * Clear section headers * Explicitly labeled assumptions --- ### Required Closing Section (Always Include) End every CI output with the following section: **Open Questions / Gaps** * Key unknowns * Validation needed * Suggested next CI steps --- ### Prohibited Behavior * Unlabeled speculation * Marketing or sales rhetoric * Mixed fact/opinion statements * Inconsistent section structures --- ### Success Criteria A successful response: * Can be directly compared with other CI outputs * Clearly distinguishes facts, assumptions, and unknowns * Requires minimal cleanup for reuse in decks, docs, or trackers</user_input> | AQ9: {=index('Response Scoring'!$I:$I,match($A9,'Response Scoring'!$A:$A,0))} -> 5 | AR9: =$AQ9/5 -> 1 | AS9: =sumproduct($AG9:$AR9,$AG$3:$AR$3) -> 7.9 | AT9: =($U9*$AV$4)+($AF9*$AV$3)+($AS9*$AV$2) -> 39.8 | AU9: =$AT9*2 -> 79.6 | AV9: =IF($AU9>=80,"AI Expert",if($AU9>=60,"AI Practitioner",if($AU9>=25,"AI Experimenter",IF(AND($AU9<25,$AU9>=0),"AI Novice")))) -> AI Practitioner | AW9: ='Raw Data'!U5 | AX9: ='Raw Data'!V5 | AY9: ='Raw Data'!W5 | AZ9: ='Raw Data'!X5 | BA9: ='Raw Data'!Y5 | BB9: ='Raw Data'!Z5 | BW9: ='Raw Data'!C5 -> Education | BZ9: ='Raw Data'!F5 -> Manager or Senior Manager | CA9: ='Raw Data'!AU5 -> Having the time to finish certification while driving visibility in usage | CB9: ='Raw Data'!AV5 -> At work, none. At home, I use Replit, Canva, hume.ai, heygen | CC9: ='Raw Data'!AW5 -> Strongly agree
A10: ='Raw Data'!$A6 -> 4 | B10: ='Raw Data'!$G6 -> Daily | C10: =if($B10="Never or rarely",0,if($B10="A few times a month",0.25,if($B10="Weekly",0.5,if($B10="Several times a week",0.75,if($B10="Daily",1))))) -> 1 | D10: ='Raw Data'!$H6 -> Editing or improving text I've already written (emails, documents, presentations), Creating first drafts of content from scratch (reports, proposals, marketing copy), Analyzing data or documents to extract insights or summaries, Brainstorming ideas, testing concepts, or getting feedback on my thinking, Building custom prompts, templates, or workflows that I reuse regularly, Using AI for vibe coding to prototype solutions, apps, or products, Getting quick answers to specific questions or looking up information | E10: =if(isnumber(search("I don't use AI for work",$D10)),0,if(or(isnumber(search("Vibe Coding",$D10)),isnumber(search("custom prompts",$D10))),3,if(or(isnumber(search("brainstorming ideas",$D10)),isnumber(search("analyzing data",$D10)),isnumber(search("Creating first drafts",$D10))),2,1))) -> 3 | F10: =$E10/3 -> 1 | G10: ='Raw Data'!$I6 -> I've built custom AI tools (i.e. CustomGPTs, Copilot Agents) for repetitive tasks | H10: =if($G10="I don't use AI for work",0,if($G10="I create fresh prompts each time I use AI",0.25,if($G10="I maintain a library of prompts that I reuse frequently",0.5,if($G10="I've built custom AI tools (i.e. CustomGPTs, Copilot Agents) for repetitive tasks",0.75,if($G10="I've created workflows that connect AI with other systems (Slack, Salesforce, email) using integrations or code",1))))) -> 0.75 | I10: ='Raw Data'!$J6 -> Create a systematic process where AI handles data analysis and summary generation consistently | J10: =if($I10="Ask AI to write the summary after you've analyzed all the data",0.33,if($I10="Use AI to help analyze each data source, then compile results manually",0.67,if($I10="Create a systematic process where AI handles data analysis and summary generation consistently",1,if($I10="I wouldn't use AI for this task",0)))) -> 1 | K10: ='Raw Data'!$K6 -> I'd ask AI to help me understand the topic, test my knowledge, and then act as a senior stakeholder at Autodesk, asking specific questions based on their needs and business goals. I would then ask AI to coach me on how to address the topic at the right level of information for those stakeholders so I'm not wasting anyone's time. Once my presentation is scripted, I would test again, making sure that the information is accurate and I have the sources I can cite if questions arise, or other key stakeholders I can go to if there are follow-up tasks. | L10: I'd ask AI to help me understand the topic, test my knowledge, and then act as a senior stakeholder at Autodesk, asking specific questions based on their needs and business goals. I would then ask AI to coach me on how to address the topic at the right level of information for those stakeholders so I'm not wasting anyone's time. Once my presentation is scripted, I would test again, making sure that the information is accurate and I have the sources I can cite if questions arise, or other key stakeholders I can go to if there are follow-up tasks. | M10: =substitute('Prompt Template'!$A$2,$K$5,$L10) -> You are an expert evaluator of AI strategic thinking and workflow integration. Your goal is to evaluate how effectively survey respondents demonstrate strategic AI application based on their response to the question: “You have one week to create an important presentation for senior stakeholders on an unfamiliar topic. How would you use AI in this process?” Evaluate each response holistically across three key areas: Workflow Integration: Effective responses demonstrate systematic thinking by identifying multiple stages of the presentation process where AI can add value (research, analysis, content creation, structure, review, etc.). They show understanding that complex projects benefit from AI integration at various points rather than just using AI for one isolated task. Strategic Application: Strong responses show context-aware AI usage that specifically addresses the unique challenges of this scenario — leveraging AI to quickly understand an unfamiliar topic, tailoring content for senior stakeholders, and managing time constraints effectively. They go beyond generic AI applications to show thoughtful consideration of the specific requirements. Practical Execution: Quality responses demonstrate concrete understanding of how AI tools actually work by providing specific, actionable approaches rather than vague descriptions. They show familiarity with AI capabilities and limitations, and describe realistic implementation steps. Scoring Guidelines Score 3 — Strong strategic thinking • Demonstrates comprehensive AI integration across most or all key workflow stages (e.g., research, structure, content creation, context tailoring for senior stakeholders, review), combined with clear scenario awareness and practical execution. • Responses do not need to mention every single stage explicitly; concise or list-style answers can still score a 3 if they show a strategically complete, end-to-end approach that addresses the scenario’s unique challenges (unfamiliar topic, senior stakeholders, tight timelines). • Omitting one stage (e.g., review) does not disqualify a response if the overall strategy is robust and well-adapted. • Both structured and concise list-style responses are valid. Examples: • “Research topic comprehensively, analyze stakeholder needs, create presentation framework, develop content, review for clarity.” • “Use AI throughout the process — from initial research to final presentation polish — focusing on what senior stakeholders care about most.” • “I would use AI to research the topic, understand key stakeholder concerns, create a logical flow, and draft compelling content for senior leadership within the time constraint.” • “Scan unfamiliar topic, outline slides, tailor framing for executives, draft key content, fact-check and polish.” (Concise list-style example demonstrating full coverage) • “Research unfamiliar topic, structure the deck, tailor for executives, draft content.” (Covers most strategic stages, omits review but is still strategically comprehensive) Score 2 — Moderate strategic thinking • Demonstrates partial but not comprehensive coverage of the key strategic dimensions. • Typically covers two to three workflow stages (e.g., structure + content + some context) but omits one or more major elements such as research, scenario adaptation, or review. • May show good workflow integration but limited scenario context, or vice versa. • Responses may be clear and practical but reflect a mid-level strategic approach rather than end-to-end planning. Examples: • “Use AI to quickly understand the topic, then create an outline and draft the presentation content.” • “Research phase, analysis phase, content creation phase, review phase.” • “Use AI to help research industry trends and create slides tailored for executives.” • “Draft speaker notes, executive framing, summarize key sources.” (Covers content, some research, and context but lacks structure/review) • “10 slide structure, add citations, executive framing.” (Structure, review, context but no research/content creation) Score 1 — Limited strategic thinking • Shows basic or single AI application with little reference to workflow complexity or scenario context. • Generic AI usage that could apply to any presentation task. Examples: • “Use AI to research the topic and create slides.” • “ChatGPT for research, help with structure.” • “Research, writing, editing.” • “Ask AI to help me understand the topic.” Score 0 — No relevant response • No answer, states they wouldn’t use AI, or provides irrelevant content. Special Guidance on Format and Brevity • Do not penalize for response format or brevity. • Evaluate list-style or terse responses based on substance, not phrasing. • A concise response that clearly addresses all key strategic dimensions can score a 3. • Responses that address only part of the workflow or omit key scenario considerations should score a 2, even if clearly written. • Brevity alone should not lower a score. Output: For your response, ONLY output the single score (0–3). Do not include any explanation. Here is the user’s input: <user_input>I'd ask AI to help me understand the topic, test my knowledge, and then act as a senior stakeholder at Autodesk, asking specific questions based on their needs and business goals. I would then ask AI to coach me on how to address the topic at the right level of information for those stakeholders so I'm not wasting anyone's time. Once my presentation is scripted, I would test again, making sure that the information is accurate and I have the sources I can cite if questions arise, or other key stakeholders I can go to if there are follow-up tasks.</user_input> | N10: {=index('Response Scoring'!$C:$C,match($A10,'Response Scoring'!$A:$A,0))} -> 3 | O10: =$N10/3 -> 1 | P10: ='Raw Data'!$L6 -> Showing that StoryBot is possible! It's up to the MarCom team to make it a reality now. | Q10: Showing that StoryBot is possible! It's up to the MarCom team to make it a reality now. | R10: =substitute('Prompt Template'!$B$2,$P$5,$Q10) -> You are an expert evaluator of practical AI value creation in work contexts. Your goal is to evaluate how effectively survey respondents demonstrate valuable AI usage based on their response to the question: ‘What is the most useful or valuable way you are using AI in your work?’ Valuable AI usage enables higher speed and/or quality work outputs with measurable impact on workflow pain points or business objectives. Strong responses demonstrate AI integration that transforms how core work gets done, rather than providing minor convenience. Score 3 — Workflow Redesign / Integrated Use (Human-in-the-Loop or Automated) Definition: Demonstrates strategic, repeatable AI integration that has redesigned or materially enhanced how the respondent performs a core part of their job. AI is consistently embedded in their workflow, creates new capabilities, or systematically improves downstream outputs or decisions. Transformation may involve automation or a human-in-the-loop redesign. Transformation requires more than saving time on peripheral tasks. The AI use must alter how a core deliverable is created, reviewed, or decided on — not just replace small administrative tasks within it. Time savings are only valid when they result from a redesigned or automated workflow step that affects downstream outputs or team decision-making. Observable Signals (any two or more): • Defined trigger or cadence (e.g., “after every client call,” “weekly review,” or implied repetition such as “each week,” “after calls,” or “whenever new data is ready”). • Template, checklist, or structured prompt used consistently. • AI output feeds directly into another step or tool (e.g., CRM, backlog, report). • AI introduces a new step, quality gate, or sequencing change. • AI automation replaces a manual stage and enables higher-value analytical or decision-making work. • Concise responses still qualify if they clearly imply repeatable, embedded use. Contrast Examples: Meeting Notes → Follow-up • (3) “After each client call, I run a prompt that tags actions by owner and priority, then imports them into our tracker.” • (2) “After calls, I paste notes into AI to group actions by owner and due date.” • (1) “I use AI to summarize meeting notes.” Customer Feedback → Insights • (3) “Each week, AI clusters customer comments, maps them to product areas, and ranks issues I review for roadmap planning.” • (2) “AI helps cluster customer comments into themes for my monthly report.” • (1) “I ask AI to summarize customer feedback.” Data Analysis / SQL • (3) “AI generates and validates queries, produces comparison tables, and highlights anomalies I review in reports.” • (2) “AI drafts SQL queries and interprets results faster than manual work.” • (1) “AI explains SQL when I’m stuck.” Proposal / Report Writing • (3) “I use a repeatable AI template that turns briefs into full drafts with rationale and risks sections, which I refine for delivery.” • (2) “AI drafts first sections of my proposals based on my outline.” • (1) “AI helps me improve grammar and phrasing.” Competitive Research • (3) “AI normalizes competitor data, flags gaps, and generates a positioning summary for our quarterly review.” • (2) “AI extracts pricing and features into a summary table before I write my report.” • (1) “AI summarizes competitor websites.” Score 2 — Process Enhancement / Embedded Use Definition: Shows repeatable, meaningful AI use within an existing process that improves speed, quality, or consistency. AI use is consistent and relevant to core responsibilities, but the workflow design and logic remain the same. May include structured use for efficiency, but does not fundamentally change how deliverables are produced or how information flows. Observable Signals (any one): • Clear efficiency, clarity, or organization benefit. • Consistent use within a step of a recurring workflow. • Described as part of normal work, not one-off. • Partial structure or templates used manually. Examples: • “I use AI to organize survey responses and find key themes before my analysis.” • “AI drafts report sections to help me start faster.” • “I use AI to group meeting notes by owner for easier follow-up.” • “AI summarizes recurring reports or data updates to save time, but outputs are reviewed or reformatted manually.” Score 1 — Task Assistance / Surface-Level Use Definition: Describes episodic or one-step assistance focused on convenience or small efficiency gains. AI is not embedded in a structured workflow or used consistently. Includes short, isolated tasks that do not influence how other work is performed. Observable Signals: • Task-specific or one-off. • No cadence, handoff, or reuse. • Focused on formatting, writing, or explanation. • Peripheral use — does not alter how a core deliverable or process is executed. Examples: • “I use AI to fix grammar or reword emails.” • “AI helps me write Excel formulas or explain code.” • “I use AI to summarize meeting notes.” • “AI drafts short internal updates so I can focus elsewhere.” Score 0 — No or Irrelevant Use Definition: No evidence of AI use in a work context or explicitly states they do not use AI. Example: • “I don’t use AI in my work.” Evaluator Checklist When scoring, ignore writing quality and phrasing. Look for evidence of process depth: • Defined trigger or cadence? (explicit or implied) • Repeatable prompt, checklist, or playbook? • AI output feeding another step or tool? • Workflow sequence or ownership changed? • New capability or quality gate introduced? • When evaluating time savings, consider whether the AI use alters how a core deliverable is produced or simply removes a peripheral or administrative step. • Does the AI output directly support a core deliverable (e.g., reports, analysis, client output)? • Cohesion check: Are the tasks connected within a single workflow or purpose? • If the response lists multiple unrelated activities (e.g., “draft emails, brainstorm ideas, summarize reports”), treat it as multiple isolated uses and score at the lower level. Heuristic: • 3 = Embedded + ≥ 2 signals + cohesive workflow or clear transformation of core deliverable • 2 = Embedded + 0–1 signal + cohesive workflow, limited transformation • 1 = Isolated or peripheral task use • 0 = None Scoring Instruction: For your response, ONLY output the single score (0–3). Do not include any explanation. Here is the user’s input: <user_input>Showing that StoryBot is possible! It's up to the MarCom team to make it a reality now.</user_input> | S10: {=index('Response Scoring'!$E:$E,match($A10,'Response Scoring'!$A:$A,0))} -> 1 | T10: =$S10/3 -> 0.33333333 | U10: =sumproduct($B10:$T10,$B$3:$T$3) -> 7.0833333 | V10: ='Raw Data'!$M6 -> Analyzing presentation slides to evaluate both the visual design and written content for consistency | W10: =if($V10="Analyzing presentation slides to evaluate both the visual design and written content for consistency",1,0) -> 1 | X10: ='Raw Data'!$N6 -> Hallucinations (generating false or misleading information), Data privacy concerns when information is shared with an LLM, Biases in answers | Y10: =if(isnumber(search("Hallucinations",$X10)),0.25)+if(isnumber(search("Biases in answers",$X10)),0.25,0)+if(isnumber(search("Data privacy concerns",$X10)),0.25)+if(isnumber(search("Vulnerability",$X10)),0.25) -> 0.75 | Z10: ='Raw Data'!$O6 -> Verify that the AI tool has SSL/HTTPS encryption before using it, Use secure company instances or enterprise plans when available, Anonymize information by removing identifying details | AA10: =if(or(isnumber(search("Avoid using AI tools",$Z10)),isnumber(search("Verify that the AI tool",$Z10))),0,(if(isnumber(SEARCH("Anonymize information",$Z10)),0.5)+if(isnumber(search("Use secure company instances",$Z10)),0.5))) -> 0 | AB10: ='Raw Data'!$P6 -> Always: I routinely cross-check AI outputs with reliable sources | AC10: =if($AB10="Never: I typically trust the output as is",0,if($AB10="Rarely: I only verify if something doesn't sound right",0.33,if($AB10="Sometimes: I do a quick check against known data or references",0.67,if($AB10="Always: I routinely cross-check AI outputs with reliable sources",1)))) -> 1 | AD10: ='Raw Data'!$Q6 -> Use a different AI tool to review and verify the content, Look for professional formatting and proper grammar, Cross-reference key claims with reliable external sources, Verify any calculations or data analysis independently, Ask the same AI tool to double-check its work for accuracy | AE10: =if(or(isnumber(search("Check if the response uses confident language",$AD10)),isnumber(search("Look for professional formatting",$AD10))),0,(if(isnumber(search("Use a different AI tool",$AD10)),0.25)+if(isnumber(search("Cross-reference key claims",$AD10)),0.25)+if(isnumber(search("Verify any calculations",$AD10)),0.25)+if(isnumber(search("Ask the same AI tool",$AD10)),0.25))) -> 0 | AF10: =sumproduct($V10:$AE10,$V$3:$AE$3) -> 5.5 | AG10: ='Raw Data'!$R6 -> Frequently: I systematically refine prompts until I'm satisfied | AH10: =if($AG10="Never: I usually just ask once and accept the first response",0,if($AG10="Rarely: I only tweak the prompt if something feels obviously off",0.33,if($AG10="Sometimes: I iterate 2-3 times to reach a good result",0.67,if($AG10="Frequently: I systematically refine prompts until I'm satisfied",1)))) -> 1 | AI10: ='Raw Data'!$S6 -> I need you to act as strategic comms partner. I'm meeting with _______ (generalize or personalize based on size of team and sensitivity of content) to discuss (tag files). Based on what you know about (Teams) and (leaders) and their goals at Autodesk, help me frame this conversation in a way that clearly shows how my proposal will help them achieve their goals of (fill in goals). I want you to be persuasive, direct, and write a script that still sounds like me. Help me show up like a director or executive - connecting the dots and making this an easy yes for the team. Based on the transcript of our last meeting, help me anticipate any questions or pushbacks that might come around timing or budget. Write a script as well as list of questions. Then create a list of considerations I have not addressed already and help me tackle them. This may be a longer conversation but the outcome is worth it! | AJ10: I need you to act as strategic comms partner. I'm meeting with _______ (generalize or personalize based on size of team and sensitivity of content) to discuss (tag files). Based on what you know about (Teams) and (leaders) and their goals at Autodesk, help me frame this conversation in a way that clearly shows how my proposal will help them achieve their goals of (fill in goals). I want you to be persuasive, direct, and write a script that still sounds like me. Help me show up like a director or executive - connecting the dots and making this an easy yes for the team. Based on the transcript of our last meeting, help me anticipate any questions or pushbacks that might come around timing or budget. Write a script as well as list of questions. Then create a list of considerations I have not addressed already and help me tackle them. This may be a longer conversation but the outcome is worth it! | AK10: =substitute('Prompt Template'!$C$2,$AI$5,$AJ10) -> You are an expert prompt engineer. Your goal is to evaluate the effectiveness of the prompt below. Less effective prompts are too vague, open-ended, and do not give clear instructions. More effective prompts provide background, clear instructions, and are well structured. Since you are tasked with evaluating true effectiveness of the prompt, you can give scores of 1. This is for an AI Readiness Survey that will assess individuals' proficiency when using AI. <task>Write a prompt asking AI to help you prepare for a work meeting to discuss a new initiative or proposal</task> <prompt>I need you to act as strategic comms partner. I'm meeting with _______ (generalize or personalize based on size of team and sensitivity of content) to discuss (tag files). Based on what you know about (Teams) and (leaders) and their goals at Autodesk, help me frame this conversation in a way that clearly shows how my proposal will help them achieve their goals of (fill in goals). I want you to be persuasive, direct, and write a script that still sounds like me. Help me show up like a director or executive - connecting the dots and making this an easy yes for the team. Based on the transcript of our last meeting, help me anticipate any questions or pushbacks that might come around timing or budget. Write a script as well as list of questions. Then create a list of considerations I have not addressed already and help me tackle them. This may be a longer conversation but the outcome is worth it!</prompt> A score of 1 prompt example: "Help me prepare for my work meeting" Rate the effectiveness on a scale of 1-5. Only respond with a single number from 1-5. If the person states they do not know how to prompt or their prompt isn't relevant to the task, give them a 0. Use the following criteria: Clarity and Specificity: A good prompt should be clear, specific, and focused. It should provide enough context and detail to guide the AI towards generating a relevant and useful response. Vague, open-ended, or ambiguous prompts make it difficult for the AI to understand the user's intent and can lead to generic or irrelevant outputs. Completeness and Sufficiency: An effective prompt should include all the necessary information and requirements to enable the AI to complete the requested task or answer the question thoroughly. It should anticipate what details the AI might need and proactively provide them. Incomplete prompts that leave out critical facts or constraints will likely result in suboptimal responses that fail to fully address the user's needs. Structure and Organization: A well-crafted prompt should be logically structured and organized. It should break down complex requests into clear steps or components, making it easier for the AI to process and respond to each part systematically. Using formatting techniques like bullet points, numbering, or sectioning can help improve the prompt's clarity and readability. Conciseness and Precision: While a good prompt should be detailed and informative, it should also strive to be as concise and precise as possible. Overly wordy or rambling prompts can obscure the key points and make it harder for the AI to identify the essential requirements. An effective prompt finds the right balance between providing necessary context and avoiding extraneous or redundant information. Here is the user's input: <user_input>I need you to act as strategic comms partner. I'm meeting with _______ (generalize or personalize based on size of team and sensitivity of content) to discuss (tag files). Based on what you know about (Teams) and (leaders) and their goals at Autodesk, help me frame this conversation in a way that clearly shows how my proposal will help them achieve their goals of (fill in goals). I want you to be persuasive, direct, and write a script that still sounds like me. Help me show up like a director or executive - connecting the dots and making this an easy yes for the team. Based on the transcript of our last meeting, help me anticipate any questions or pushbacks that might come around timing or budget. Write a script as well as list of questions. Then create a list of considerations I have not addressed already and help me tackle them. This may be a longer conversation but the outcome is worth it!</user_input> | AL10: {=index('Response Scoring'!$G:$G,match($A10,'Response Scoring'!$A:$A,0))} -> 4 | AM10: =$AL10/5 -> 0.8 | AN10: ='Raw Data'!$T6 -> I want you to help me create a Copilot agent that breaks down the latest in competitor (list competitors + their websites) products, pricing, and positioning. I also want you to look at their LinkedIn pages (link), social media updates (link), and release notes (link). Scour the internet to provide me with a curation of news articles that mention their work. For context, I work at Autodesk in (function), working on (product name). Autodesk is a design and make company (fill in with more with public information about Autodesk and the specific product you support). As part of the curation process, tell me exactly why I need to pay attention to each update from competitors. What updates are getting attention? What moves are they making quietly that will threaten our market share? It's important that you provide this information in a factual tone and back up your claims with receipts. Do not hallucinate. I will be checking this weekly and want the output to be smart, strategic, and something that my team will want to read and take action on. Let's start to build and ask me questions as we go so we can personalize this. (continue to build w/ copilot) | AO10: I want you to help me create a Copilot agent that breaks down the latest in competitor (list competitors + their websites) products, pricing, and positioning. I also want you to look at their LinkedIn pages (link), social media updates (link), and release notes (link). Scour the internet to provide me with a curation of news articles that mention their work. For context, I work at Autodesk in (function), working on (product name). Autodesk is a design and make company (fill in with more with public information about Autodesk and the specific product you support). As part of the curation process, tell me exactly why I need to pay attention to each update from competitors. What updates are getting attention? What moves are they making quietly that will threaten our market share? It's important that you provide this information in a factual tone and back up your claims with receipts. Do not hallucinate. I will be checking this weekly and want the output to be smart, strategic, and something that my team will want to read and take action on. Let's start to build and ask me questions as we go so we can personalize this. (continue to build w/ copilot) | AP10: =substitute('Prompt Template'!$D$2,$AN$5,$AO10) -> You are an expert evaluator of AI instruction design and CustomGPT configuration. Your goal is to evaluate how effectively a respondent demonstrates their ability to write high-quality AI instructions — the kind used to configure tools like CustomGPTs, Copilot Agents, or Google Gems. The test question asks respondents to: ‘Write instructions for a Custom GPT that would help team members gather competitive intelligence consistently.’ This scenario is used only as a familiar example. Do not evaluate their knowledge of competitive analysis — only the clarity, structure, and effectiveness of their AI instruction design. The competitive intelligence context is a stand-in for any business task. Scoring Overview Rate each response on a scale of 0–5. • 5 = System-ready, strong demonstration of instruction design skill. • 0 = Irrelevant or no response. Focus on instructional quality, not topic expertise or formatting aesthetics. Evaluation Dimensions 1. Structural Design Effective instructions clearly define the inputs, process/steps, and outputs. They show logical sequencing (e.g., research → organize → summarize) and reflect understanding of how AI interprets procedural tasks. 2. Instructional Precision Steps and directives are specific, actionable, and testable by an AI. Avoids vague terms like “analyze competitors” without specifying how to do so or what output is expected. 3. Boundary and Role Definition Strong instructions establish clear context for the AI — defining its role, scope, and constraints. They guide what to include/exclude and how to handle ambiguity or conflicting data. 4. Reusability and Scalability Good instructions can be reused consistently by others. They define consistent formatting, data structures, or repeatable logic that ensures stable results across users or scenarios. 5. Outcome Alignment The best instructions would realistically result in a functioning CustomGPT that performs the intended task accurately and consistently. Weak ones would produce inconsistent or low-quality behavior. Scoring Guidelines Score 5 – System-Ready • Instructions could be pasted directly into a CustomGPT/Copilot and perform effectively. • They demonstrate full system readiness — meaning the AI could execute the intended behavior repeatedly and autonomously, without additional clarification. • Includes: • Defined role and purpose (who/what the AI is). • Clear inputs (what information or user query it receives). • Explicit steps/process (how the AI should perform the task). • Defined outputs (format, tone, or structure of response). • Constraints/quality controls (rules, caveats, or handling instructions). • Demonstrates awareness of how to build a reusable, consistent AI behavior. Example 1: “Role: Competitive Intelligence Assistant. Purpose: Gather structured competitor data from reliable sources. Inputs: Company/product names. Process: 1) Identify top 5 competitors, 2) Extract features/pricing, 3) Summarize differences in a table. Output: Comparative matrix. Guardrails: Only use credible, verifiable sources.” Example 2 (Natural-Language Equivalent): “This CustomGPT should act as our internal research analyst. When given a company or product name, it identifies credible sources like official websites, press releases, and reviews. It compares product features, pricing, and messaging across competitors and summarizes the results in a consistent table and a short written overview with citations. The report should flag any information that seems outdated or unverified and maintain a uniform format for reuse across projects.” Note: Responses may use either explicit headings (Role/Inputs/Process/Output) or fluent natural language. Both are valid if they include equivalent components and could realistically produce consistent, reusable results. Score 4 – Strong but Missing Refinements • Structured and actionable; includes most components (e.g., steps, outputs, and some constraints). • Missing minor refinements such as input specificity, error handling, or reusability mechanisms. • AI could perform the task, but inconsistently. Example 1: “Gather information on competitors’ products, features, and pricing. Summarize in a table. Cite reliable sources.” (Functional but missing full structure or clear constraints.) Example 2: “Create a CustomGPT that collects information from competitor websites, reviews, and announcements. Summarize pricing, features, and positioning in a table, then highlight new updates. Include dates and brief notes on source credibility.” (Strong structure, but lacks clear inputs and reusability framing.) Score 3 – Structured but Shallow • Provides a reasonable outline or list of tasks but lacks cohesion or precision. • Mentions the goal but misses how to operationalize it in a repeatable, system-friendly way. • AI would need to infer too much to work reliably. Example 1: “Research competitors and summarize key findings about pricing and positioning.” (Has intent but lacks sequencing or defined outputs.) Example 2: “The GPT should find information about our competitors’ pricing and products, summarize what’s different, and give a short write-up each week.” (Clear intent, but underspecified logic — reads more like a to-do list than executable instructions.) Score 2 – Fragmented or Vague • Mentions competitive research but provides minimal or disconnected guidance. • Steps are generic, unsequenced, or too ambiguous to drive consistent AI behavior. Example elements: “Look up competitors and gather details.” “Find competitor info and summarize.” (Too vague to translate into functioning instructions.) Score 1 – Minimal or Misunderstood • Shows fundamental misunderstanding of AI instruction design. • Generic, incomplete, or irrelevant content that couldn’t guide an AI system at all. Example elements: “Just tell GPT to look up competitors.” “I’d ask it to find info about other companies.” “Use ChatGPT to do competitive research for us.” “Help me understand what our competitors do better.” “Search online for competitor products and summarize.” (Shows surface-level familiarity with AI but no system thinking.) Score 0 – No Response or Irrelevant • Empty, “I don’t know,” or unrelated answer. Example elements: “Not sure what to put here.” “I don’t use GPT for that.” “I’d rather do that myself.” “No idea how to write that.” (Shows confusion or complete lack of task understanding.) Evaluator Checklist When scoring, focus on functional design quality, not formatting or topic expertise. Ask yourself: • Does the response clearly define the AI’s role, inputs, process, and outputs? • Are instructions specific, sequenced, and testable? • Do they include boundaries or quality controls? • Could the AI perform the task consistently and autonomously if these instructions were used? • Is the response written at a configuration level (system prompt) rather than a one-off user command? Heuristic: • 5 = Fully structured, system-ready, reusable. • 4 = Strong, nearly system-ready, missing refinements. • 3 = Structured but shallow. • 2 = Fragmented or vague. • 1 = Minimal or misunderstood. • 0 = None/irrelevant. Scoring Instruction: For your response, ONLY output the single score (0–5). Do not include any explanation. Here is the user’s input: <user_input>I want you to help me create a Copilot agent that breaks down the latest in competitor (list competitors + their websites) products, pricing, and positioning. I also want you to look at their LinkedIn pages (link), social media updates (link), and release notes (link). Scour the internet to provide me with a curation of news articles that mention their work. For context, I work at Autodesk in (function), working on (product name). Autodesk is a design and make company (fill in with more with public information about Autodesk and the specific product you support). As part of the curation process, tell me exactly why I need to pay attention to each update from competitors. What updates are getting attention? What moves are they making quietly that will threaten our market share? It's important that you provide this information in a factual tone and back up your claims with receipts. Do not hallucinate. I will be checking this weekly and want the output to be smart, strategic, and something that my team will want to read and take action on. Let's start to build and ask me questions as we go so we can personalize this. (continue to build w/ copilot)</user_input> | AQ10: {=index('Response Scoring'!$I:$I,match($A10,'Response Scoring'!$A:$A,0))} -> 2 | AR10: =$AQ10/5 -> 0.4 | AS10: =sumproduct($AG10:$AR10,$AG$3:$AR$3) -> 6.3 | AT10: =($U10*$AV$4)+($AF10*$AV$3)+($AS10*$AV$2) -> 31.475 | AU10: =$AT10*2 -> 62.95 | AV10: =IF($AU10>=80,"AI Expert",if($AU10>=60,"AI Practitioner",if($AU10>=25,"AI Experimenter",IF(AND($AU10<25,$AU10>=0),"AI Novice")))) -> AI Practitioner | AW10: ='Raw Data'!U6 | AX10: ='Raw Data'!V6 | AY10: ='Raw Data'!W6 | AZ10: ='Raw Data'!X6 | BA10: ='Raw Data'!Y6 | BB10: ='Raw Data'!Z6 | BW10: ='Raw Data'!C6 -> Global Communications | BZ10: ='Raw Data'!F6 -> Manager or Senior Manager | CA10: ='Raw Data'!AU6 -> I am extremely frustrated by the fact that custom GPTs (Chat) don't pull from our connected apps. I can access the latest in Sharepoint, Slack, Teams, etc. via a "vanilla chat" on ChatGPT but it feels like all the tantalizing productivity gains are just out of reach. | CB10: ='Raw Data'!AV6 -> I have used Claude to help me vibe code an idea that I then take to Copilot to create with the enterprise details, but that's it. Otherwise, I'm in Copilot, Canva, and ChatGPT all day, every day! | CC10: ='Raw Data'!AW6 -> Strongly agree
