Workbook

Sheet Scoring Sheet
C1: Usage Questions [scored] | W1: Knowledge Questions [scored] | AH1: Prompting Questions [scored] | AU1: Overall Score | AX1: Behavioral Questions [unscored] | BT1: Demographic Questions [unscored]
AU2: Prompting | AW2: 2
A3: Weight | D3: 0.5 | G3: 1.5 | I3: 1 | K3: 1 | P3: 2 | U3: 4 | X3: 2 | Z3: 2 | AB3: 2 | AD3: 2 | AF3: 2 | AG3: =SUM(W3:AF3) -> 10 | AI3: 1.5 | AN3: 3.5 | AS3: 5 | AU3: Knowledge | AW3: 1
A4: Potential Points | D4: 1 | G4: 1 | I4: 1 | K4: 1 | P4: 1 | U4: 1 | X4: 1 | Z4: 1 | AB4: 1 | AD4: 1 | AF4: 1 | AI4: 1 | AN4: 1 | AS4: 1 | AU4: Usage | AW4: 2
L5: {{QUESTION 5 RESPONSE}} | Q5: {{QUESTION 6 RESPONSE}} | AJ5: {{QUESTION 13 RESPONSE}} | AO5: {{QUESTION 14 RESPONSE}}
A6: Participant Identifier | B6: How often do you use AI tools for work-related tasks? | C6: SCORE_1 | D6: Which of the following best describes how you typically use AI at work? Select all that apply. | E6: SCORE_2 | F6: SCORE (out of 1)_2 | G6: Which best describes your AI usage patterns at work? | H6: SCORE_3 | I6: You need to create a monthly performance summary. How would you use AI for this task? | J6: SCORE_4 | K6: You have one week to create an important presentation for senior stakeholders on an unfamiliar topic. How would you use AI in this process? If you wouldn't use AI, please state that. | L6: TEXT: You have one week to create an important presentation for senior stakeholders on an unfamiliar topic. How would you use AI in this process? If you wouldn't use AI, please state that. | M6: TEMPLATE: You have one week to create an important presentation for senior stakeholders on an unfamiliar topic. How would you use AI in this process? If you wouldn't use AI, please state that. | N6: SCORE_5 | O6: SCORE (out of 1)_5 | P6: What is the most useful or valuable way you are using AI in your work? | Q6: TEXT: What is the most useful or valuable way you are using AI in your work? | R6: TEMPLATE: What is the most useful or valuable way you are using AI in your work? | S6: SCORE_6 | T6: SCORE (out of 1)_6 | U6: OVERALL SCORE (out of 10)_usage | V6: Which task would current AI tools (like ChatGPT, Copilot, or Gemini) handle most effectively? | W6: SCORE_7 | X6: Which of the following are the main risks of using current LLMs? Select all that apply. | Y6: SCORE_8 | Z6: How can you best protect sensitive information when using AI tools? Select all that apply. | AA6: SCORE_9 | AB6: How often do you verify or fact-check AI-generated content before finalizing or sharing it? | AC6: SCORE_10 | AD6: When fact-checking AI-generated content, which approaches would be helpful? Select all that apply. | AE6: SCORE_11 | AF6: OVERALL SCORE (out of 10)_knowledge | AG6: When you use AI, how often do you refine or iterate on your prompts to improve the output? | AH6: SCORE_12 | AI6: DRILL 1: Imagine you are preparing for a work meeting to discuss a new initiative or proposal. Write a prompt asking AI to help you prepare for this meeting. | AJ6: TEXT: DRILL 1: Imagine you are preparing for a work meeting to discuss a new initiative or proposal. Write a prompt asking AI to help you prepare for this meeting. | AK6: TEMPLATE: DRILL 1: Imagine you are preparing for a work meeting to discuss a new initiative or proposal. Write a prompt asking AI to help you prepare for this meeting. | AL6: SCORE_13 | AM6: SCORE (Out of 1)_13 | AN6: DRILL 2: Your team frequently researches competitors' products, pricing, and positioning. You want to create a Custom GPT (or Copilot Agent/Google Gem) for this task. Write instructions for this custom AI tool that would help team members gather competitive intelligence consistently. | AO6: TEXT: DRILL 2: Your team frequently researches competitors' products, pricing, and positioning. You want to create a Custom GPT (or Copilot Agent/Google Gem) for this task. Write instructions for this custom AI tool that would help team members gather competitive intelligence consistently. | AP6: TEMPLATE: DRILL 2: Your team frequently researches competitors' products, pricing, and positioning. You want to create a Custom GPT (or Copilot Agent/Google Gem) for this task. Write instructions for this custom AI tool that would help team members gather competitive intelligence consistently. | AQ6: SCORE_14 | AR6: SCORE (Out of 1)_14 | AS6: SCORE (out of 1) | AT6: OVERALL SCORE (out of 10) | AU6: OVERALL SCORE (out of 50) | AW6: Rating | AX6: ='Raw Data'!Y2 -> Which LLMs are you currently using? Select all that apply. | AY6: ='Raw Data'!Z2 -> Do you personally pay for access to any of these AI tools? | AZ6: ='Raw Data'!AA2 -> Does your company have an AI strategy? | BA6: ='Raw Data'!AB2 -> Do you know what AI tools are available at your company and how to access them? | BB6: ='Raw Data'!AC2 -> What has your company deployed? | BC6: ='Raw Data'!AD2 -> How satisfied are you with the AI tool(s) your company has deployed? | BD6: ='Raw Data'!AE2 -> How well has your company translated its AI strategy into specific usage policies for employees? | BE6: ='Raw Data'!AF2 -> How would you describe your company’s AI usage policies? | ... BR6: ='Raw Data'!AS2 -> Which statement best describes the impact AI is having on your work? | BS6: ='Raw Data'!C2 -> Which of the following best describes your current employment status? | BT6: ='Raw Data'!D2 -> What industry best describes where you currently work? | BU6: ='Raw Data'!E2 -> What function best describes your current role? | BV6: ='Raw Data'!F2 -> Which of the following best describes your current job level within your organization? | BW6: ='Raw Data'!G2 -> How many employees work at your company? | BX6: ='Raw Data'!H2 -> Where do you currently reside? | BY6: ='Raw Data'!I2 -> What is your current age? | BZ6: ='Raw Data'!J2 -> What is your gender identity? | CA6: ='Raw Data'!AT2 -> What limits your AI usage or makes you hesitate using AI? | CB6: ='Raw Data'!AU2 -> If you are using AI at work, what’s the main reason you’re using it? If you are not using AI at work, what’s the main reason that you are not using it? | CC6: ='Raw Data'!AV2 -> What are the top 3 AI use cases that you're performing today that are significantly improving your work? Describe them below including the tools that you are using, the problem you’re solving, and the benefits (i.e. time saved). | CD6: ='Raw Data'!AW2 -> What could your company do to increase your use of and proficiency with AI? | CE6: ='Raw Data'!AX2 -> Describe a repetitive, manual process on your team which creates frustration or inefficiency and could benefit from AI assistance. What KPIs could be used to measure AI’s impact? | CF6: ='Raw Data'!AY2 -> If AI could save you 5-10 hours per week at work, what work related tasks would you pursue with that extra time? | CG6: ='Raw Data'!AZ2 -> Did you complete the AI Maturity Diagnostic when it was first administered in February? | CH6: ='Raw Data'!BB2 -> 0
A7: ='Raw Data'!$A3 -> 1 | C7: ='Raw Data'!$K3 -> A few times a month | D7: =IF($C7="Never or rarely",0,IF($C7="A few times a month",0.25,IF($C7="Weekly",0.5,IF($C7="Several times a week",0.75,IF($C7="Daily",1))))) -> 0.25 | E7: ='Raw Data'!$L3 -> Getting quick answers to specific questions or looking up information, Editing or improving text I've already written (emails, documents, presentations), Brainstorming ideas, testing concepts, or getting feedback on my thinking | F7: =IF(ISNUMBER(SEARCH("I don't use AI for work",$E7)),0,IF(OR(ISNUMBER(SEARCH("Vibe Coding",$E7)),ISNUMBER(SEARCH("custom prompts",$E7))),3,IF(OR(ISNUMBER(SEARCH("brainstorming ideas",$E7)),ISNUMBER(SEARCH("analyzing data",$E7)),ISNUMBER(SEARCH("Creating first drafts",$E7))),2,1))) -> 2 | G7: =$F7/3 -> 0.66666667 | H7: ='Raw Data'!M3 -> I create fresh prompts each time I use AI | I7: =IF($H7="I don't use AI for work",0,IF($H7="I create fresh prompts each time I use AI",0.25,IF($H7="I maintain a library of prompts that I reuse frequently",0.5,IF($H7="I've built custom AI tools (CustomGPTs, Copilot Agents, Google Gems, Claude Projects) for repetitive tasks",0.75,IF($H7="I've created workflows that connect AI with other systems (Slack, Salesforce, email) using integrations or code",1))))) -> 0.25 | J7: ='Raw Data'!$N3 -> Ask AI to write the summary after you've analyzed all the data | K7: =IF($J7="Ask AI to write the summary after you've analyzed all the data",0.33,IF($J7="Use AI to help analyze each data source, then compile results manually",0.67,IF($J7="Create a systematic process where AI handles data analysis and summary generation consistently",1,IF($J7="I wouldn’t use AI for this task",0)))) -> 0.33 | L7: ='Raw Data'!$O3 -> I wouldn't us AI | M7: I wouldn't us AI | N7: =SUBSTITUTE('Prompt Template'!$A$2,$L$5,$M7) -> You are an expert evaluator of AI strategic thinking and workflow integration. Your goal is to evaluate how effectively survey respondents demonstrate strategic AI application based on their response to the question: “You have one week to create an important presentation for senior stakeholders on an unfamiliar topic. How would you use AI in this process?” Evaluate each response holistically across three key areas: Workflow Integration: Effective responses demonstrate systematic thinking by identifying multiple stages of the presentation process where AI can add value (research, analysis, content creation, structure, review, etc.). They show understanding that complex projects benefit from AI integration at various points rather than just using AI for one isolated task. Strategic Application: Strong responses show context-aware AI usage that specifically addresses the unique challenges of this scenario — leveraging AI to quickly understand an unfamiliar topic, tailoring content for senior stakeholders, and managing time constraints effectively. They go beyond generic AI applications to show thoughtful consideration of the specific requirements. Practical Execution: Quality responses demonstrate concrete understanding of how AI tools actually work by providing specific, actionable approaches rather than vague descriptions. They show familiarity with AI capabilities and limitations, and describe realistic implementation steps. Scoring Guidelines Score 3 — Strong strategic thinking • Demonstrates comprehensive AI integration across most or all key workflow stages (e.g., research, structure, content creation, context tailoring for senior stakeholders, review), combined with clear scenario awareness and practical execution. • Responses do not need to mention every single stage explicitly; concise or list-style answers can still score a 3 if they show a strategically complete, end-to-end approach that addresses the scenario’s unique challenges (unfamiliar topic, senior stakeholders, tight timelines). • Omitting one stage (e.g., review) does not disqualify a response if the overall strategy is robust and well-adapted. • Both structured and concise list-style responses are valid. Examples: • “Research topic comprehensively, analyze stakeholder needs, create presentation framework, develop content, review for clarity.” • “Use AI throughout the process — from initial research to final presentation polish — focusing on what senior stakeholders care about most.” • “I would use AI to research the topic, understand key stakeholder concerns, create a logical flow, and draft compelling content for senior leadership within the time constraint.” • “Scan unfamiliar topic, outline slides, tailor framing for executives, draft key content, fact-check and polish.” (Concise list-style example demonstrating full coverage) • “Research unfamiliar topic, structure the deck, tailor for executives, draft content.” (Covers most strategic stages, omits review but is still strategically comprehensive) Score 2 — Moderate strategic thinking • Demonstrates partial but not comprehensive coverage of the key strategic dimensions. • Typically covers two to three workflow stages (e.g., structure + content + some context) but omits one or more major elements such as research, scenario adaptation, or review. • May show good workflow integration but limited scenario context, or vice versa. • Responses may be clear and practical but reflect a mid-level strategic approach rather than end-to-end planning. Examples: • “Use AI to quickly understand the topic, then create an outline and draft the presentation content.” • “Research phase, analysis phase, content creation phase, review phase.” • “Use AI to help research industry trends and create slides tailored for executives.” • “Draft speaker notes, executive framing, summarize key sources.” (Covers content, some research, and context but lacks structure/review) • “10 slide structure, add citations, executive framing.” (Structure, review, context but no research/content creation) Score 1 — Limited strategic thinking • Shows basic or single AI application with little reference to workflow complexity or scenario context. • Generic AI usage that could apply to any presentation task. Examples: • “Use AI to research the topic and create slides.” • “ChatGPT for research, help with structure.” • “Research, writing, editing.” • “Ask AI to help me understand the topic.” Score 0 — No relevant response • No answer, states they wouldn’t use AI, or provides irrelevant content. Special Guidance on Format and Brevity • Do not penalize for response format or brevity. • Evaluate list-style or terse responses based on substance, not phrasing. • A concise response that clearly addresses all key strategic dimensions can score a 3. • Responses that address only part of the workflow or omit key scenario considerations should score a 2, even if clearly written. • Brevity alone should not lower a score. Output: For your response, ONLY output the single score (0–3). Do not include any explanation. Here is the user’s input: <user_input>I wouldn't us AI</user_input> | O7: {=INDEX('Response Scoring'!$C:$C,MATCH($A7,'Response Scoring'!$A:$A,0))} -> 0 | P7: =$O7/3 -> 0 | Q7: ='Raw Data'!$P3 -> Help assist in writing clear communication | R7: Help assist in writing clear communication | S7: =SUBSTITUTE('Prompt Template'!$B$2,$Q$5,$R7) -> You are an expert evaluator of practical AI value creation in work contexts. Your goal is to evaluate how effectively survey respondents demonstrate valuable AI usage based on their response to the question: ‘What is the most useful or valuable way you are using AI in your work?’ Valuable AI usage enables higher speed and/or quality work outputs with measurable impact on workflow pain points or business objectives. Strong responses demonstrate AI integration that transforms how core work gets done, rather than providing minor convenience. Score 3 — Workflow Redesign / Integrated Use (Human-in-the-Loop or Automated) Definition: Demonstrates strategic, repeatable AI integration that has redesigned or materially enhanced how the respondent performs a core part of their job. AI is consistently embedded in their workflow, creates new capabilities, or systematically improves downstream outputs or decisions. Transformation may involve automation or a human-in-the-loop redesign. Transformation requires more than saving time on peripheral tasks. The AI use must alter how a core deliverable is created, reviewed, or decided on — not just replace small administrative tasks within it. Time savings are only valid when they result from a redesigned or automated workflow step that affects downstream outputs or team decision-making. Observable Signals (any two or more): • Defined trigger or cadence (e.g., “after every client call,” “weekly review,” or implied repetition such as “each week,” “after calls,” or “whenever new data is ready”). • Template, checklist, or structured prompt used consistently. • AI output feeds directly into another step or tool (e.g., CRM, backlog, report). • AI introduces a new step, quality gate, or sequencing change. • AI automation replaces a manual stage and enables higher-value analytical or decision-making work. • Concise responses still qualify if they clearly imply repeatable, embedded use. Contrast Examples: Meeting Notes → Follow-up • (3) “After each client call, I run a prompt that tags actions by owner and priority, then imports them into our tracker.” • (2) “After calls, I paste notes into AI to group actions by owner and due date.” • (1) “I use AI to summarize meeting notes.” Customer Feedback → Insights • (3) “Each week, AI clusters customer comments, maps them to product areas, and ranks issues I review for roadmap planning.” • (2) “AI helps cluster customer comments into themes for my monthly report.” • (1) “I ask AI to summarize customer feedback.” Data Analysis / SQL • (3) “AI generates and validates queries, produces comparison tables, and highlights anomalies I review in reports.” • (2) “AI drafts SQL queries and interprets results faster than manual work.” • (1) “AI explains SQL when I’m stuck.” Proposal / Report Writing • (3) “I use a repeatable AI template that turns briefs into full drafts with rationale and risks sections, which I refine for delivery.” • (2) “AI drafts first sections of my proposals based on my outline.” • (1) “AI helps me improve grammar and phrasing.” Competitive Research • (3) “AI normalizes competitor data, flags gaps, and generates a positioning summary for our quarterly review.” • (2) “AI extracts pricing and features into a summary table before I write my report.” • (1) “AI summarizes competitor websites.” Score 2 — Process Enhancement / Embedded Use Definition: Shows repeatable, meaningful AI use within an existing process that improves speed, quality, or consistency. AI use is consistent and relevant to core responsibilities, but the workflow design and logic remain the same. May include structured use for efficiency, but does not fundamentally change how deliverables are produced or how information flows. Observable Signals (any one): • Clear efficiency, clarity, or organization benefit. • Consistent use within a step of a recurring workflow. • Described as part of normal work, not one-off. • Partial structure or templates used manually. Examples: • “I use AI to organize survey responses and find key themes before my analysis.” • “AI drafts report sections to help me start faster.” • “I use AI to group meeting notes by owner for easier follow-up.” • “AI summarizes recurring reports or data updates to save time, but outputs are reviewed or reformatted manually.” Score 1 — Task Assistance / Surface-Level Use Definition: Describes episodic or one-step assistance focused on convenience or small efficiency gains. AI is not embedded in a structured workflow or used consistently. Includes short, isolated tasks that do not influence how other work is performed. Observable Signals: • Task-specific or one-off. • No cadence, handoff, or reuse. • Focused on formatting, writing, or explanation. • Peripheral use — does not alter how a core deliverable or process is executed. Examples: • “I use AI to fix grammar or reword emails.” • “AI helps me write Excel formulas or explain code.” • “I use AI to summarize meeting notes.” • “AI drafts short internal updates so I can focus elsewhere.” Score 0 — No or Irrelevant Use Definition: No evidence of AI use in a work context or explicitly states they do not use AI. Example: • “I don’t use AI in my work.” Evaluator Checklist When scoring, ignore writing quality and phrasing. Look for evidence of process depth: • Defined trigger or cadence? (explicit or implied) • Repeatable prompt, checklist, or playbook? • AI output feeding another step or tool? • Workflow sequence or ownership changed? • New capability or quality gate introduced? • When evaluating time savings, consider whether the AI use alters how a core deliverable is produced or simply removes a peripheral or administrative step. • Does the AI output directly support a core deliverable (e.g., reports, analysis, client output)? • Cohesion check: Are the tasks connected within a single workflow or purpose? • If the response lists multiple unrelated activities (e.g., “draft emails, brainstorm ideas, summarize reports”), treat it as multiple isolated uses and score at the lower level. Heuristic: • 3 = Embedded + ≥ 2 signals + cohesive workflow or clear transformation of core deliverable • 2 = Embedded + 0–1 signal + cohesive workflow, limited transformation • 1 = Isolated or peripheral task use • 0 = None Scoring Instruction: For your response, ONLY output the single score (0–3). Do not include any explanation. Here is the user’s input: <user_input>Help assist in writing clear communication</user_input> | T7: {=INDEX('Response Scoring'!$E:$E,MATCH($A7,'Response Scoring'!$A:$A,0))} -> 1 | U7: =$T7/3 -> 0.33333333 | V7: =SUMPRODUCT($C7:$U7,$C$3:$U$3) -> 3.0383333 | W7: ='Raw Data'!$Q3 -> Analyzing presentation slides to evaluate both the visual design and written content for consistency | X7: =IF($W7="Analyzing presentation slides to evaluate both the visual design and written content for consistency",1,0) -> 1 | Y7: ='Raw Data'!$R3 -> Hallucinations (generating false or misleading information), Data privacy concerns when information is shared with an LLM | Z7: =IF(ISNUMBER(SEARCH("Hallucinations",$Y7)),0.25)+IF(ISNUMBER(SEARCH("Biases in answers",$Y7)),0.25,0)+IF(ISNUMBER(SEARCH("Data privacy concerns",$Y7)),0.25)+IF(ISNUMBER(SEARCH("Vulnerability",$Y7)),0.25) -> 0.5 | AA7: ='Raw Data'!$S3 -> Only share information that you would be comfortable sharing internally with a colleague, Anonymize information by removing identifying details, Verify that the AI tool has SSL/HTTPS encryption before using it | AB7: =IF(OR(ISNUMBER(SEARCH("Avoid using AI tools",$AA7)),ISNUMBER(SEARCH("Verify that the AI tool",$AA7))),0,(IF(ISNUMBER(SEARCH("Anonymize information",$AA7)),0.5)+IF(ISNUMBER(SEARCH("Use secure company instances",$AA7)),0.5))) -> 0 | AC7: ='Raw Data'!$T3 -> Sometimes: I do a quick check against known data or references | AD7: =IF($AC7="Never: I typically trust the output as is",0,IF($AC7="Rarely: I only verify if something doesn't sound right",0.33,IF($AC7="Sometimes: I do a quick check against known data or references",0.67,IF($AC7="Always: I routinely cross-check AI outputs with reliable sources",1)))) -> 0.67 | AE7: ='Raw Data'!$U3 -> Cross-reference key claims with reliable external sources, Verify any calculations or data analysis independently, Use a different AI tool to review and verify the content | AF7: =IF(OR(ISNUMBER(SEARCH("Check if the response uses confident language",$AE7)),ISNUMBER(SEARCH("Look for professional formatting",$AE7))),0,(IF(ISNUMBER(SEARCH("Use a different AI tool",$AE7)),0.25)+IF(ISNUMBER(SEARCH("Cross-reference key claims",$AE7)),0.25)+IF(ISNUMBER(SEARCH("Verify any calculations",$AE7)),0.25)+IF(ISNUMBER(SEARCH("Ask the same AI tool",$AE7)),0.25))) -> 0.75 | AG7: =SUMPRODUCT($W7:$AF7,$W$3:$AF$3) -> 5.84 | AH7: ='Raw Data'!$V3 -> Rarely: I only tweak the prompt if something feels obviously off | AI7: =IF($AH7="Never: I usually just ask once and accept the first response",0,IF($AH7="Rarely: I only tweak the prompt if something feels obviously off",0.33,IF($AH7="Sometimes: I iterate 2-3 times to reach a good result",0.67,IF($AH7="Frequently: I systematically refine prompts until I'm satisfied",1)))) -> 0.33 | AJ7: ='Raw Data'!$W3 -> I don't know how to prompt | AK7: I don't know how to prompt | AL7: =SUBSTITUTE('Prompt Template'!$C$2,$AJ$5,$AK7) -> You are an expert prompt engineer. Your goal is to evaluate the effectiveness of the prompt below. Less effective prompts are too vague, open-ended, and do not give clear instructions. More effective prompts provide background, clear instructions, and are well structured. Since you are tasked with evaluating true effectiveness of the prompt, you can give scores of 1. This is for an AI Readiness Survey that will assess individuals' proficiency when using AI. <task>Write a prompt asking AI to help you prepare for a work meeting to discuss a new initiative or proposal</task> <prompt>I don't know how to prompt</prompt> A score of 1 prompt example: "Help me prepare for my work meeting" Rate the effectiveness on a scale of 1-5. Only respond with a single number from 1-5. If the person states they do not know how to prompt or their prompt isn't relevant to the task, give them a 0. Use the following criteria: Clarity and Specificity: A good prompt should be clear, specific, and focused. It should provide enough context and detail to guide the AI towards generating a relevant and useful response. Vague, open-ended, or ambiguous prompts make it difficult for the AI to understand the user's intent and can lead to generic or irrelevant outputs. Completeness and Sufficiency: An effective prompt should include all the necessary information and requirements to enable the AI to complete the requested task or answer the question thoroughly. It should anticipate what details the AI might need and proactively provide them. Incomplete prompts that leave out critical facts or constraints will likely result in suboptimal responses that fail to fully address the user's needs. Structure and Organization: A well-crafted prompt should be logically structured and organized. It should break down complex requests into clear steps or components, making it easier for the AI to process and respond to each part systematically. Using formatting techniques like bullet points, numbering, or sectioning can help improve the prompt's clarity and readability. Conciseness and Precision: While a good prompt should be detailed and informative, it should also strive to be as concise and precise as possible. Overly wordy or rambling prompts can obscure the key points and make it harder for the AI to identify the essential requirements. An effective prompt finds the right balance between providing necessary context and avoiding extraneous or redundant information. Here is the user's input: <user_input>I don't know how to prompt</user_input> | AM7: {=INDEX('Response Scoring'!$G:$G,MATCH($A7,'Response Scoring'!$A:$A,0))} -> 0 | AN7: =$AM7/5 -> 0 | AO7: ='Raw Data'!$X3 -> I don't know how to create custom AI instructions. | AP7: I don't know how to create custom AI instructions. | AQ7: =SUBSTITUTE('Prompt Template'!$D$2,$AO$5,$AP7) -> You are an expert evaluator of AI instruction design and CustomGPT configuration. Your goal is to evaluate how effectively a respondent demonstrates their ability to write high-quality AI instructions — the kind used to configure tools like CustomGPTs, Copilot Agents, or Google Gems. The test question asks respondents to: ‘Write instructions for a Custom GPT that would help team members gather competitive intelligence consistently.’ This scenario is used only as a familiar example. Do not evaluate their knowledge of competitive analysis — only the clarity, structure, and effectiveness of their AI instruction design. The competitive intelligence context is a stand-in for any business task. Scoring Overview Rate each response on a scale of 0–5. • 5 = System-ready, strong demonstration of instruction design skill. • 0 = Irrelevant or no response. Focus on instructional quality, not topic expertise or formatting aesthetics. Evaluation Dimensions 1. Structural Design Effective instructions clearly define the inputs, process/steps, and outputs. They show logical sequencing (e.g., research → organize → summarize) and reflect understanding of how AI interprets procedural tasks. 2. Instructional Precision Steps and directives are specific, actionable, and testable by an AI. Avoids vague terms like “analyze competitors” without specifying how to do so or what output is expected. 3. Boundary and Role Definition Strong instructions establish clear context for the AI — defining its role, scope, and constraints. They guide what to include/exclude and how to handle ambiguity or conflicting data. 4. Reusability and Scalability Good instructions can be reused consistently by others. They define consistent formatting, data structures, or repeatable logic that ensures stable results across users or scenarios. 5. Outcome Alignment The best instructions would realistically result in a functioning CustomGPT that performs the intended task accurately and consistently. Weak ones would produce inconsistent or low-quality behavior. Scoring Guidelines Score 5 – System-Ready • Instructions could be pasted directly into a CustomGPT/Copilot and perform effectively. • They demonstrate full system readiness — meaning the AI could execute the intended behavior repeatedly and autonomously, without additional clarification. • Includes: • Defined role and purpose (who/what the AI is). • Clear inputs (what information or user query it receives). • Explicit steps/process (how the AI should perform the task). • Defined outputs (format, tone, or structure of response). • Constraints/quality controls (rules, caveats, or handling instructions). • Demonstrates awareness of how to build a reusable, consistent AI behavior. Example 1: “Role: Competitive Intelligence Assistant. Purpose: Gather structured competitor data from reliable sources. Inputs: Company/product names. Process: 1) Identify top 5 competitors, 2) Extract features/pricing, 3) Summarize differences in a table. Output: Comparative matrix. Guardrails: Only use credible, verifiable sources.” Example 2 (Natural-Language Equivalent): “This CustomGPT should act as our internal research analyst. When given a company or product name, it identifies credible sources like official websites, press releases, and reviews. It compares product features, pricing, and messaging across competitors and summarizes the results in a consistent table and a short written overview with citations. The report should flag any information that seems outdated or unverified and maintain a uniform format for reuse across projects.” Note: Responses may use either explicit headings (Role/Inputs/Process/Output) or fluent natural language. Both are valid if they include equivalent components and could realistically produce consistent, reusable results. Score 4 – Strong but Missing Refinements • Structured and actionable; includes most components (e.g., steps, outputs, and some constraints). • Missing minor refinements such as input specificity, error handling, or reusability mechanisms. • AI could perform the task, but inconsistently. Example 1: “Gather information on competitors’ products, features, and pricing. Summarize in a table. Cite reliable sources.” (Functional but missing full structure or clear constraints.) Example 2: “Create a CustomGPT that collects information from competitor websites, reviews, and announcements. Summarize pricing, features, and positioning in a table, then highlight new updates. Include dates and brief notes on source credibility.” (Strong structure, but lacks clear inputs and reusability framing.) Score 3 – Structured but Shallow • Provides a reasonable outline or list of tasks but lacks cohesion or precision. • Mentions the goal but misses how to operationalize it in a repeatable, system-friendly way. • AI would need to infer too much to work reliably. Example 1: “Research competitors and summarize key findings about pricing and positioning.” (Has intent but lacks sequencing or defined outputs.) Example 2: “The GPT should find information about our competitors’ pricing and products, summarize what’s different, and give a short write-up each week.” (Clear intent, but underspecified logic — reads more like a to-do list than executable instructions.) Score 2 – Fragmented or Vague • Mentions competitive research but provides minimal or disconnected guidance. • Steps are generic, unsequenced, or too ambiguous to drive consistent AI behavior. Example elements: “Look up competitors and gather details.” “Find competitor info and summarize.” (Too vague to translate into functioning instructions.) Score 1 – Minimal or Misunderstood • Shows fundamental misunderstanding of AI instruction design. • Generic, incomplete, or irrelevant content that couldn’t guide an AI system at all. Example elements: “Just tell GPT to look up competitors.” “I’d ask it to find info about other companies.” “Use ChatGPT to do competitive research for us.” “Help me understand what our competitors do better.” “Search online for competitor products and summarize.” (Shows surface-level familiarity with AI but no system thinking.) Score 0 – No Response or Irrelevant • Empty, “I don’t know,” or unrelated answer. Example elements: “Not sure what to put here.” “I don’t use GPT for that.” “I’d rather do that myself.” “No idea how to write that.” (Shows confusion or complete lack of task understanding.) Evaluator Checklist When scoring, focus on functional design quality, not formatting or topic expertise. Ask yourself: • Does the response clearly define the AI’s role, inputs, process, and outputs? • Are instructions specific, sequenced, and testable? • Do they include boundaries or quality controls? • Could the AI perform the task consistently and autonomously if these instructions were used? • Is the response written at a configuration level (system prompt) rather than a one-off user command? Heuristic: • 5 = Fully structured, system-ready, reusable. • 4 = Strong, nearly system-ready, missing refinements. • 3 = Structured but shallow. • 2 = Fragmented or vague. • 1 = Minimal or misunderstood. • 0 = None/irrelevant. Scoring Instruction: For your response, ONLY output the single score (0–5). Do not include any explanation. Here is the user’s input: <user_input>I don't know how to create custom AI instructions.</user_input> | AR7: {=INDEX('Response Scoring'!$I:$I,MATCH($A7,'Response Scoring'!$A:$A,0))} -> 0 | AS7: =$AR7/5 -> 0 | AT7: =SUMPRODUCT($AH7:$AS7,$AH$3:$AS$3) -> 0.495 | AU7: =($V7*$AW$4)+($AG7*$AW$3)+($AT7*$AW$2) -> 12.906667 | AV7: =$AU7*2 -> 25.813333 | AW7: =IF($AV7>=80,"AI Expert",IF($AV7>=60,"AI Practitioner",IF(AND($AV7<60,$AV7>=25),"AI Experimenter",IF(AND($AV7<25,$AV7>=0),"AI Novice")))) -> AI Experimenter | AX7: ='Raw Data'!Y3 -> ChatGPT | AY7: ='Raw Data'!Z3 -> FALSE | AZ7: ='Raw Data'!AA3 -> Yes, we have a formal AI strategy | BA7: ='Raw Data'!AB3 -> Tools exist with clear access process | BB7: ='Raw Data'!AC3 -> Other | BC7: ='Raw Data'!AD3 -> Satisfied - meets my needs well | BD7: ='Raw Data'!AE3 -> Some policies exist, but don't clearly connect to our strategy | BE7: ='Raw Data'!AF3 -> We have a clear, actionable policy that effectively guides AI use | ... BR7: ='Raw Data'!AS3 -> Modest help - useful for specific tasks but limited overall impact | BS7: ='Raw Data'!C3 -> 0 | BT7: ='Raw Data'!D3 -> 0 | BU7: ='Raw Data'!E3 -> HR/Finance/Corporate | BV7: ='Raw Data'!F3 -> Specialist/Senior Specialist | BW7: ='Raw Data'!G3 -> 0 | BX7: ='Raw Data'!H3 -> 0 | BY7: ='Raw Data'!I3 -> 0 | BZ7: ='Raw Data'!J3 -> 0 | CA7: ='Raw Data'!AT3 -> N/A | CB7: ='Raw Data'!AU3 -> I only use it to make my words clearer. I may experiment here and there, but that is about it. | CC7: ='Raw Data'!AV3 -> - | CD7: ='Raw Data'!AW3 -> - | CE7: ='Raw Data'!AX3 -> - | CF7: ='Raw Data'!AY3 -> n/a | CG7: ='Raw Data'!AZ3 -> Yes
A8: ='Raw Data'!$A4 -> 2 | C8: ='Raw Data'!$K4 -> Daily | D8: =IF($C8="Never or rarely",0,IF($C8="A few times a month",0.25,IF($C8="Weekly",0.5,IF($C8="Several times a week",0.75,IF($C8="Daily",1))))) -> 1 | E8: ='Raw Data'!$L4 -> Editing or improving text I've already written (emails, documents, presentations), Analyzing data or documents to extract insights or summaries, Building custom prompts, templates, or workflows that I reuse regularly, Getting quick answers to specific questions or looking up information | F8: =IF(ISNUMBER(SEARCH("I don't use AI for work",$E8)),0)+IF(ISNUMBER(SEARCH("Getting quick answers",$E8)),1,0)+IF(ISNUMBER(SEARCH("Editing text",$E8)),1,0)+IF(ISNUMBER(SEARCH("Writing/debugging code",$E8)),1,0)+IF(ISNUMBER(SEARCH("Creating first drafts",$E8)),2,0)+IF(ISNUMBER(SEARCH("Analyzing data/documents",$E8)),2,0)+IF(ISNUMBER(SEARCH("Brainstorming/testing concepts",$E8)),2,0)+IF(ISNUMBER(SEARCH("Building custom workflows",$E8)),3,0)+IF(ISNUMBER(SEARCH("Prototyping solutions",$E8)),3,0) -> 1 | G8: =$F8/3 -> 0.33333333 | H8: ='Raw Data'!M4 -> I create fresh prompts each time I use AI | I8: =IF($H8="I don't use AI for work",0,IF($H8="I create fresh prompts each time I use AI",0.25,IF($H8="I maintain a library of prompts that I reuse frequently",0.5,IF($H8="I've built custom AI tools (CustomGPTs, Copilot Agents, Google Gems, Claude Projects) for repetitive tasks",0.75,IF($H8="I've created workflows that connect AI with other systems (Slack, Salesforce, email) using integrations or code",1))))) -> 0.25 | J8: ='Raw Data'!$N4 -> Ask AI to write the summary after you've analyzed all the data | K8: =IF($J8="Ask AI to write the summary after you've analyzed all the data",0.33,IF($J8="Use AI to help analyze each data source, then compile results manually",0.67,IF($J8="Create a systematic process where AI handles data analysis and summary generation consistently",1,IF($J8="I wouldn’t use AI for this task",0)))) -> 0.33 | L8: ='Raw Data'!$O4 -> I would use AI to help with copywriting, summarizing my main points, and to suggest visuals that could amplify my messaging | M8: I would use AI to help with copywriting, summarizing my main points, and to suggest visuals that could amplify my messaging | N8: =SUBSTITUTE('Prompt Template'!$A$2,$L$5,$M8) -> You are an expert evaluator of AI strategic thinking and workflow integration. Your goal is to evaluate how effectively survey respondents demonstrate strategic AI application based on their response to the question: “You have one week to create an important presentation for senior stakeholders on an unfamiliar topic. How would you use AI in this process?” Evaluate each response holistically across three key areas: Workflow Integration: Effective responses demonstrate systematic thinking by identifying multiple stages of the presentation process where AI can add value (research, analysis, content creation, structure, review, etc.). They show understanding that complex projects benefit from AI integration at various points rather than just using AI for one isolated task. Strategic Application: Strong responses show context-aware AI usage that specifically addresses the unique challenges of this scenario — leveraging AI to quickly understand an unfamiliar topic, tailoring content for senior stakeholders, and managing time constraints effectively. They go beyond generic AI applications to show thoughtful consideration of the specific requirements. Practical Execution: Quality responses demonstrate concrete understanding of how AI tools actually work by providing specific, actionable approaches rather than vague descriptions. They show familiarity with AI capabilities and limitations, and describe realistic implementation steps. Scoring Guidelines Score 3 — Strong strategic thinking • Demonstrates comprehensive AI integration across most or all key workflow stages (e.g., research, structure, content creation, context tailoring for senior stakeholders, review), combined with clear scenario awareness and practical execution. • Responses do not need to mention every single stage explicitly; concise or list-style answers can still score a 3 if they show a strategically complete, end-to-end approach that addresses the scenario’s unique challenges (unfamiliar topic, senior stakeholders, tight timelines). • Omitting one stage (e.g., review) does not disqualify a response if the overall strategy is robust and well-adapted. • Both structured and concise list-style responses are valid. Examples: • “Research topic comprehensively, analyze stakeholder needs, create presentation framework, develop content, review for clarity.” • “Use AI throughout the process — from initial research to final presentation polish — focusing on what senior stakeholders care about most.” • “I would use AI to research the topic, understand key stakeholder concerns, create a logical flow, and draft compelling content for senior leadership within the time constraint.” • “Scan unfamiliar topic, outline slides, tailor framing for executives, draft key content, fact-check and polish.” (Concise list-style example demonstrating full coverage) • “Research unfamiliar topic, structure the deck, tailor for executives, draft content.” (Covers most strategic stages, omits review but is still strategically comprehensive) Score 2 — Moderate strategic thinking • Demonstrates partial but not comprehensive coverage of the key strategic dimensions. • Typically covers two to three workflow stages (e.g., structure + content + some context) but omits one or more major elements such as research, scenario adaptation, or review. • May show good workflow integration but limited scenario context, or vice versa. • Responses may be clear and practical but reflect a mid-level strategic approach rather than end-to-end planning. Examples: • “Use AI to quickly understand the topic, then create an outline and draft the presentation content.” • “Research phase, analysis phase, content creation phase, review phase.” • “Use AI to help research industry trends and create slides tailored for executives.” • “Draft speaker notes, executive framing, summarize key sources.” (Covers content, some research, and context but lacks structure/review) • “10 slide structure, add citations, executive framing.” (Structure, review, context but no research/content creation) Score 1 — Limited strategic thinking • Shows basic or single AI application with little reference to workflow complexity or scenario context. • Generic AI usage that could apply to any presentation task. Examples: • “Use AI to research the topic and create slides.” • “ChatGPT for research, help with structure.” • “Research, writing, editing.” • “Ask AI to help me understand the topic.” Score 0 — No relevant response • No answer, states they wouldn’t use AI, or provides irrelevant content. Special Guidance on Format and Brevity • Do not penalize for response format or brevity. • Evaluate list-style or terse responses based on substance, not phrasing. • A concise response that clearly addresses all key strategic dimensions can score a 3. • Responses that address only part of the workflow or omit key scenario considerations should score a 2, even if clearly written. • Brevity alone should not lower a score. Output: For your response, ONLY output the single score (0–3). Do not include any explanation. Here is the user’s input: <user_input>I would use AI to help with copywriting, summarizing my main points, and to suggest visuals that could amplify my messaging</user_input> | O8: {=INDEX('Response Scoring'!$C:$C,MATCH($A8,'Response Scoring'!$A:$A,0))} -> 2 | P8: =$O8/3 -> 0.66666667 | Q8: ='Raw Data'!$P4 -> To create specific or abstract images that are too difficult or time-consuming to design manually, or that are not able to be found on AdobeStock. | R8: To create specific or abstract images that are too difficult or time-consuming to design manually, or that are not able to be found on AdobeStock. | S8: =SUBSTITUTE('Prompt Template'!$B$2,$Q$5,$R8) -> You are an expert evaluator of practical AI value creation in work contexts. Your goal is to evaluate how effectively survey respondents demonstrate valuable AI usage based on their response to the question: ‘What is the most useful or valuable way you are using AI in your work?’ Valuable AI usage enables higher speed and/or quality work outputs with measurable impact on workflow pain points or business objectives. Strong responses demonstrate AI integration that transforms how core work gets done, rather than providing minor convenience. Score 3 — Workflow Redesign / Integrated Use (Human-in-the-Loop or Automated) Definition: Demonstrates strategic, repeatable AI integration that has redesigned or materially enhanced how the respondent performs a core part of their job. AI is consistently embedded in their workflow, creates new capabilities, or systematically improves downstream outputs or decisions. Transformation may involve automation or a human-in-the-loop redesign. Transformation requires more than saving time on peripheral tasks. The AI use must alter how a core deliverable is created, reviewed, or decided on — not just replace small administrative tasks within it. Time savings are only valid when they result from a redesigned or automated workflow step that affects downstream outputs or team decision-making. Observable Signals (any two or more): • Defined trigger or cadence (e.g., “after every client call,” “weekly review,” or implied repetition such as “each week,” “after calls,” or “whenever new data is ready”). • Template, checklist, or structured prompt used consistently. • AI output feeds directly into another step or tool (e.g., CRM, backlog, report). • AI introduces a new step, quality gate, or sequencing change. • AI automation replaces a manual stage and enables higher-value analytical or decision-making work. • Concise responses still qualify if they clearly imply repeatable, embedded use. Contrast Examples: Meeting Notes → Follow-up • (3) “After each client call, I run a prompt that tags actions by owner and priority, then imports them into our tracker.” • (2) “After calls, I paste notes into AI to group actions by owner and due date.” • (1) “I use AI to summarize meeting notes.” Customer Feedback → Insights • (3) “Each week, AI clusters customer comments, maps them to product areas, and ranks issues I review for roadmap planning.” • (2) “AI helps cluster customer comments into themes for my monthly report.” • (1) “I ask AI to summarize customer feedback.” Data Analysis / SQL • (3) “AI generates and validates queries, produces comparison tables, and highlights anomalies I review in reports.” • (2) “AI drafts SQL queries and interprets results faster than manual work.” • (1) “AI explains SQL when I’m stuck.” Proposal / Report Writing • (3) “I use a repeatable AI template that turns briefs into full drafts with rationale and risks sections, which I refine for delivery.” • (2) “AI drafts first sections of my proposals based on my outline.” • (1) “AI helps me improve grammar and phrasing.” Competitive Research • (3) “AI normalizes competitor data, flags gaps, and generates a positioning summary for our quarterly review.” • (2) “AI extracts pricing and features into a summary table before I write my report.” • (1) “AI summarizes competitor websites.” Score 2 — Process Enhancement / Embedded Use Definition: Shows repeatable, meaningful AI use within an existing process that improves speed, quality, or consistency. AI use is consistent and relevant to core responsibilities, but the workflow design and logic remain the same. May include structured use for efficiency, but does not fundamentally change how deliverables are produced or how information flows. Observable Signals (any one): • Clear efficiency, clarity, or organization benefit. • Consistent use within a step of a recurring workflow. • Described as part of normal work, not one-off. • Partial structure or templates used manually. Examples: • “I use AI to organize survey responses and find key themes before my analysis.” • “AI drafts report sections to help me start faster.” • “I use AI to group meeting notes by owner for easier follow-up.” • “AI summarizes recurring reports or data updates to save time, but outputs are reviewed or reformatted manually.” Score 1 — Task Assistance / Surface-Level Use Definition: Describes episodic or one-step assistance focused on convenience or small efficiency gains. AI is not embedded in a structured workflow or used consistently. Includes short, isolated tasks that do not influence how other work is performed. Observable Signals: • Task-specific or one-off. • No cadence, handoff, or reuse. • Focused on formatting, writing, or explanation. • Peripheral use — does not alter how a core deliverable or process is executed. Examples: • “I use AI to fix grammar or reword emails.” • “AI helps me write Excel formulas or explain code.” • “I use AI to summarize meeting notes.” • “AI drafts short internal updates so I can focus elsewhere.” Score 0 — No or Irrelevant Use Definition: No evidence of AI use in a work context or explicitly states they do not use AI. Example: • “I don’t use AI in my work.” Evaluator Checklist When scoring, ignore writing quality and phrasing. Look for evidence of process depth: • Defined trigger or cadence? (explicit or implied) • Repeatable prompt, checklist, or playbook? • AI output feeding another step or tool? • Workflow sequence or ownership changed? • New capability or quality gate introduced? • When evaluating time savings, consider whether the AI use alters how a core deliverable is produced or simply removes a peripheral or administrative step. • Does the AI output directly support a core deliverable (e.g., reports, analysis, client output)? • Cohesion check: Are the tasks connected within a single workflow or purpose? • If the response lists multiple unrelated activities (e.g., “draft emails, brainstorm ideas, summarize reports”), treat it as multiple isolated uses and score at the lower level. Heuristic: • 3 = Embedded + ≥ 2 signals + cohesive workflow or clear transformation of core deliverable • 2 = Embedded + 0–1 signal + cohesive workflow, limited transformation • 1 = Isolated or peripheral task use • 0 = None Scoring Instruction: For your response, ONLY output the single score (0–3). Do not include any explanation. Here is the user’s input: <user_input>To create specific or abstract images that are too difficult or time-consuming to design manually, or that are not able to be found on AdobeStock.</user_input> | T8: {=INDEX('Response Scoring'!$E:$E,MATCH($A8,'Response Scoring'!$A:$A,0))} -> 1 | U8: =$T8/3 -> 0.33333333 | V8: =SUMPRODUCT($C8:$U8,$C$3:$U$3) -> 4.2466667 | W8: ='Raw Data'!$Q4 -> Analyzing presentation slides to evaluate both the visual design and written content for consistency | X8: =IF($W8="Analyzing presentation slides to evaluate both the visual design and written content for consistency",1,0) -> 1 | Y8: ='Raw Data'!$R4 -> Hallucinations (generating false or misleading information), Biases in answers, Data privacy concerns when information is shared with an LLM, Vulnerability to manipulation by bad actors | Z8: =IF(ISNUMBER(SEARCH("Hallucinations",$Y8)),0.25)+IF(ISNUMBER(SEARCH("Biases in answers",$Y8)),0.25,0)+IF(ISNUMBER(SEARCH("Data privacy concerns",$Y8)),0.25)+IF(ISNUMBER(SEARCH("Vulnerability",$Y8)),0.25) -> 1 | AA8: ='Raw Data'!$S4 -> Verify that the AI tool has SSL/HTTPS encryption before using it, Anonymize information by removing identifying details, Use secure company instances or enterprise plans when available | AB8: =IF(OR(ISNUMBER(SEARCH("Avoid using AI tools",$AA8)),ISNUMBER(SEARCH("Verify that the AI tool",$AA8))),0,(IF(ISNUMBER(SEARCH("Anonymize information",$AA8)),0.5)+IF(ISNUMBER(SEARCH("Use secure company instances",$AA8)),0.5))) -> 0 | AC8: ='Raw Data'!$T4 -> Sometimes: I do a quick check against known data or references | AD8: =IF($AC8="Never: I typically trust the output as is",0,IF($AC8="Rarely: I only verify if something doesn't sound right",0.33,IF($AC8="Sometimes: I do a quick check against known data or references",0.67,IF($AC8="Always: I routinely cross-check AI outputs with reliable sources",1)))) -> 0.67 | AE8: ='Raw Data'!$U4 -> Cross-reference key claims with reliable external sources, Verify any calculations or data analysis independently, Use a different AI tool to review and verify the content, Look for professional formatting and proper grammar, Check if the response uses confident language and specific details | AF8: =IF(OR(ISNUMBER(SEARCH("Check if the response uses confident language",$AE8)),ISNUMBER(SEARCH("Look for professional formatting",$AE8))),0,(IF(ISNUMBER(SEARCH("Use a different AI tool",$AE8)),0.25)+IF(ISNUMBER(SEARCH("Cross-reference key claims",$AE8)),0.25)+IF(ISNUMBER(SEARCH("Verify any calculations",$AE8)),0.25)+IF(ISNUMBER(SEARCH("Ask the same AI tool",$AE8)),0.25))) -> 0 | AG8: =SUMPRODUCT($W8:$AF8,$W$3:$AF$3) -> 5.34 | AH8: ='Raw Data'!$V4 -> Frequently: I systematically refine prompts until I'm satisfied | AI8: =IF($AH8="Never: I usually just ask once and accept the first response",0,IF($AH8="Rarely: I only tweak the prompt if something feels obviously off",0.33,IF($AH8="Sometimes: I iterate 2-3 times to reach a good result",0.67,IF($AH8="Frequently: I systematically refine prompts until I'm satisfied",1)))) -> 1 | AJ8: ='Raw Data'!$W4 -> You are an Associate Creative Director preparing for a work meeting where you will present a new initiative called XYZ to your team. Tone should be confident and professional. The goal is to get approval to move forward with phase one of the campaign. Write a 3 minute presentation script that clearly explains why this idea matters now, describes expected results, and ends with next steps. | AK8: You are an Associate Creative Director preparing for a work meeting where you will present a new initiative called XYZ to your team. Tone should be confident and professional. The goal is to get approval to move forward with phase one of the campaign. Write a 3 minute presentation script that clearly explains why this idea matters now, describes expected results, and ends with next steps. | AL8: =SUBSTITUTE('Prompt Template'!$C$2,$AJ$5,$AK8) -> You are an expert prompt engineer. Your goal is to evaluate the effectiveness of the prompt below. Less effective prompts are too vague, open-ended, and do not give clear instructions. More effective prompts provide background, clear instructions, and are well structured. Since you are tasked with evaluating true effectiveness of the prompt, you can give scores of 1. This is for an AI Readiness Survey that will assess individuals' proficiency when using AI. <task>Write a prompt asking AI to help you prepare for a work meeting to discuss a new initiative or proposal</task> <prompt>You are an Associate Creative Director preparing for a work meeting where you will present a new initiative called XYZ to your team. Tone should be confident and professional. The goal is to get approval to move forward with phase one of the campaign. Write a 3 minute presentation script that clearly explains why this idea matters now, describes expected results, and ends with next steps.</prompt> A score of 1 prompt example: "Help me prepare for my work meeting" Rate the effectiveness on a scale of 1-5. Only respond with a single number from 1-5. If the person states they do not know how to prompt or their prompt isn't relevant to the task, give them a 0. Use the following criteria: Clarity and Specificity: A good prompt should be clear, specific, and focused. It should provide enough context and detail to guide the AI towards generating a relevant and useful response. Vague, open-ended, or ambiguous prompts make it difficult for the AI to understand the user's intent and can lead to generic or irrelevant outputs. Completeness and Sufficiency: An effective prompt should include all the necessary information and requirements to enable the AI to complete the requested task or answer the question thoroughly. It should anticipate what details the AI might need and proactively provide them. Incomplete prompts that leave out critical facts or constraints will likely result in suboptimal responses that fail to fully address the user's needs. Structure and Organization: A well-crafted prompt should be logically structured and organized. It should break down complex requests into clear steps or components, making it easier for the AI to process and respond to each part systematically. Using formatting techniques like bullet points, numbering, or sectioning can help improve the prompt's clarity and readability. Conciseness and Precision: While a good prompt should be detailed and informative, it should also strive to be as concise and precise as possible. Overly wordy or rambling prompts can obscure the key points and make it harder for the AI to identify the essential requirements. An effective prompt finds the right balance between providing necessary context and avoiding extraneous or redundant information. Here is the user's input: <user_input>You are an Associate Creative Director preparing for a work meeting where you will present a new initiative called XYZ to your team. Tone should be confident and professional. The goal is to get approval to move forward with phase one of the campaign. Write a 3 minute presentation script that clearly explains why this idea matters now, describes expected results, and ends with next steps.</user_input> | AM8: {=INDEX('Response Scoring'!$G:$G,MATCH($A8,'Response Scoring'!$A:$A,0))} -> 4 | AN8: =$AM8/5 -> 0.8 | AO8: ='Raw Data'!$X4 -> You are a Competitive Research Analyst. Your job is to help our team quickly gather and summarize info about competitors' products, pricing, and positioning. When given a product category or company name, you will automatically identify the top 5–10 competitors. For each competitor, list out their target audience, brand positioning (under 20 words), top 3 marketing channels, and one strength and weakness. Keep your tone factual and neutral with no opinions, just competitive insights supported by clear data. | AP8: You are a Competitive Research Analyst. Your job is to help our team quickly gather and summarize info about competitors' products, pricing, and positioning. When given a product category or company name, you will automatically identify the top 5–10 competitors. For each competitor, list out their target audience, brand positioning (under 20 words), top 3 marketing channels, and one strength and weakness. Keep your tone factual and neutral with no opinions, just competitive insights supported by clear data. | AQ8: =SUBSTITUTE('Prompt Template'!$D$2,$AO$5,$AP8) -> You are an expert evaluator of AI instruction design and CustomGPT configuration. Your goal is to evaluate how effectively a respondent demonstrates their ability to write high-quality AI instructions — the kind used to configure tools like CustomGPTs, Copilot Agents, or Google Gems. The test question asks respondents to: ‘Write instructions for a Custom GPT that would help team members gather competitive intelligence consistently.’ This scenario is used only as a familiar example. Do not evaluate their knowledge of competitive analysis — only the clarity, structure, and effectiveness of their AI instruction design. The competitive intelligence context is a stand-in for any business task. Scoring Overview Rate each response on a scale of 0–5. • 5 = System-ready, strong demonstration of instruction design skill. • 0 = Irrelevant or no response. Focus on instructional quality, not topic expertise or formatting aesthetics. Evaluation Dimensions 1. Structural Design Effective instructions clearly define the inputs, process/steps, and outputs. They show logical sequencing (e.g., research → organize → summarize) and reflect understanding of how AI interprets procedural tasks. 2. Instructional Precision Steps and directives are specific, actionable, and testable by an AI. Avoids vague terms like “analyze competitors” without specifying how to do so or what output is expected. 3. Boundary and Role Definition Strong instructions establish clear context for the AI — defining its role, scope, and constraints. They guide what to include/exclude and how to handle ambiguity or conflicting data. 4. Reusability and Scalability Good instructions can be reused consistently by others. They define consistent formatting, data structures, or repeatable logic that ensures stable results across users or scenarios. 5. Outcome Alignment The best instructions would realistically result in a functioning CustomGPT that performs the intended task accurately and consistently. Weak ones would produce inconsistent or low-quality behavior. Scoring Guidelines Score 5 – System-Ready • Instructions could be pasted directly into a CustomGPT/Copilot and perform effectively. • They demonstrate full system readiness — meaning the AI could execute the intended behavior repeatedly and autonomously, without additional clarification. • Includes: • Defined role and purpose (who/what the AI is). • Clear inputs (what information or user query it receives). • Explicit steps/process (how the AI should perform the task). • Defined outputs (format, tone, or structure of response). • Constraints/quality controls (rules, caveats, or handling instructions). • Demonstrates awareness of how to build a reusable, consistent AI behavior. Example 1: “Role: Competitive Intelligence Assistant. Purpose: Gather structured competitor data from reliable sources. Inputs: Company/product names. Process: 1) Identify top 5 competitors, 2) Extract features/pricing, 3) Summarize differences in a table. Output: Comparative matrix. Guardrails: Only use credible, verifiable sources.” Example 2 (Natural-Language Equivalent): “This CustomGPT should act as our internal research analyst. When given a company or product name, it identifies credible sources like official websites, press releases, and reviews. It compares product features, pricing, and messaging across competitors and summarizes the results in a consistent table and a short written overview with citations. The report should flag any information that seems outdated or unverified and maintain a uniform format for reuse across projects.” Note: Responses may use either explicit headings (Role/Inputs/Process/Output) or fluent natural language. Both are valid if they include equivalent components and could realistically produce consistent, reusable results. Score 4 – Strong but Missing Refinements • Structured and actionable; includes most components (e.g., steps, outputs, and some constraints). • Missing minor refinements such as input specificity, error handling, or reusability mechanisms. • AI could perform the task, but inconsistently. Example 1: “Gather information on competitors’ products, features, and pricing. Summarize in a table. Cite reliable sources.” (Functional but missing full structure or clear constraints.) Example 2: “Create a CustomGPT that collects information from competitor websites, reviews, and announcements. Summarize pricing, features, and positioning in a table, then highlight new updates. Include dates and brief notes on source credibility.” (Strong structure, but lacks clear inputs and reusability framing.) Score 3 – Structured but Shallow • Provides a reasonable outline or list of tasks but lacks cohesion or precision. • Mentions the goal but misses how to operationalize it in a repeatable, system-friendly way. • AI would need to infer too much to work reliably. Example 1: “Research competitors and summarize key findings about pricing and positioning.” (Has intent but lacks sequencing or defined outputs.) Example 2: “The GPT should find information about our competitors’ pricing and products, summarize what’s different, and give a short write-up each week.” (Clear intent, but underspecified logic — reads more like a to-do list than executable instructions.) Score 2 – Fragmented or Vague • Mentions competitive research but provides minimal or disconnected guidance. • Steps are generic, unsequenced, or too ambiguous to drive consistent AI behavior. Example elements: “Look up competitors and gather details.” “Find competitor info and summarize.” (Too vague to translate into functioning instructions.) Score 1 – Minimal or Misunderstood • Shows fundamental misunderstanding of AI instruction design. • Generic, incomplete, or irrelevant content that couldn’t guide an AI system at all. Example elements: “Just tell GPT to look up competitors.” “I’d ask it to find info about other companies.” “Use ChatGPT to do competitive research for us.” “Help me understand what our competitors do better.” “Search online for competitor products and summarize.” (Shows surface-level familiarity with AI but no system thinking.) Score 0 – No Response or Irrelevant • Empty, “I don’t know,” or unrelated answer. Example elements: “Not sure what to put here.” “I don’t use GPT for that.” “I’d rather do that myself.” “No idea how to write that.” (Shows confusion or complete lack of task understanding.) Evaluator Checklist When scoring, focus on functional design quality, not formatting or topic expertise. Ask yourself: • Does the response clearly define the AI’s role, inputs, process, and outputs? • Are instructions specific, sequenced, and testable? • Do they include boundaries or quality controls? • Could the AI perform the task consistently and autonomously if these instructions were used? • Is the response written at a configuration level (system prompt) rather than a one-off user command? Heuristic: • 5 = Fully structured, system-ready, reusable. • 4 = Strong, nearly system-ready, missing refinements. • 3 = Structured but shallow. • 2 = Fragmented or vague. • 1 = Minimal or misunderstood. • 0 = None/irrelevant. Scoring Instruction: For your response, ONLY output the single score (0–5). Do not include any explanation. Here is the user’s input: <user_input>You are a Competitive Research Analyst. Your job is to help our team quickly gather and summarize info about competitors' products, pricing, and positioning. When given a product category or company name, you will automatically identify the top 5–10 competitors. For each competitor, list out their target audience, brand positioning (under 20 words), top 3 marketing channels, and one strength and weakness. Keep your tone factual and neutral with no opinions, just competitive insights supported by clear data.</user_input> | AR8: {=INDEX('Response Scoring'!$I:$I,MATCH($A8,'Response Scoring'!$A:$A,0))} -> 3 | AS8: =$AR8/5 -> 0.6 | AT8: =SUMPRODUCT($AH8:$AS8,$AH$3:$AS$3) -> 7.3 | AU8: =($V8*$AW$4)+($AG8*$AW$3)+($AT8*$AW$2) -> 28.433333 | AV8: =$AU8*2 -> 56.866667 | AW8: =IF($AV8>=80,"AI Expert",IF($AV8>=60,"AI Practitioner",IF(AND($AV8<60,$AV8>=25),"AI Experimenter",IF(AND($AV8<25,$AV8>=0),"AI Novice")))) -> AI Experimenter | AX8: ='Raw Data'!Y4 -> ChatGPT, Claude | AY8: ='Raw Data'!Z4 -> TRUE | AZ8: ='Raw Data'!AA4 -> Yes, we have a formal AI strategy | BA8: ='Raw Data'!AB4 -> Tools exist but I don't know how to access them | BB8: ='Raw Data'!AC4 -> Microsoft Copilot, Claude for Enterprise or Teams, Google Gemini, ChatGPT for Enterprise or Teams | BC8: ='Raw Data'!AD4 -> Satisfied - meets my needs well | BD8: ='Raw Data'!AE4 -> Clear, enforced policies that directly implement our AI strategy | BE8: ='Raw Data'!AF4 -> We have a clear, actionable policy that effectively guides AI use | ... BR8: ='Raw Data'!AS4 -> Modest help - useful for specific tasks but limited overall impact | BS8: ='Raw Data'!C4 -> 0 | BT8: ='Raw Data'!D4 -> 0 | BU8: ='Raw Data'!E4 -> Marketing/Biz Dev | BV8: ='Raw Data'!F4 -> Specialist/Senior Specialist | BW8: ='Raw Data'!G4 -> 0 | BX8: ='Raw Data'!H4 -> 0 | BY8: ='Raw Data'!I4 -> 0 | BZ8: ='Raw Data'!J4 -> 0 | CA8: ='Raw Data'!AT4 -> I think what limits my AI use the most is that it sometimes feels like it’s replacing my own thinking instead of enhancing it. I haven’t had much time to really explore how it could automate tasks or streamline my workflow in a way that feels natural to me. Right now, I mostly use it for quick rewrites, summarizing long content, or clarifying my thoughts. I’m also a bit hesitant because of the environmental impact of AI, it’s something I’m still trying to learn more about. | CB8: ='Raw Data'!AU4 -> I’ve started using AI at work mainly to make things faster and take some stress out of smaller, repetitive tasks like writing copy, summarizing content, or organizing ideas. I’m in a new role right now, so I’m still figuring out where it can really add value to my workflow. I don’t think I’m using it to its full potential yet, mostly because I haven’t had the bandwidth to experiment or build a custom GPT that’s actually tailored to what I do. | CC8: ='Raw Data'!AV4 -> 1. I’ve been using GenSpark to create unique images for social media or landing pages. For example, I recently made a pink glitter skeleton graphic for a Halloween post. It helps me quickly produce creative visuals that feel original and on brand without spending hours searching or editing. 2. I use ChatGPT to draft and refine emails or messages, and to consolidate my thoughts when I’m stuck. It’s been a huge help in improving clarity and tone, saving time I’d normally spend rewording or overthinking how to say something. 3. I also use ChatGPT to identify stock photo ideas for landing pages. I can paste long sections of text, and it summarizes the key visual themes or concepts I should look for. It makes the process of choosing the right imagery faster and more strategic. | CD8: ='Raw Data'!AW4 -> Nothing, they're great about it. I feel supported to explore and use AI however it’s helpful for my work. It’s more about me finding the time to experiment and build better habits around it | CE8: ='Raw Data'!AX4 -> One repetitive, time-consuming process for me is finding the right stock photos that feel on brand and align with specific messaging. It often takes hours to search through AdobeStock, compare visuals, and ensure consistency in tone, color, and composition. AI could help by analyzing our brand aesthetic and suggesting the most relevant, high-quality images. KPIs to measure impact could include: Time saved per project | CF8: ='Raw Data'!AY4 -> I’d use that extra time to focus more on higher level creative strategy and concept development. I’d also spend more time experimenting with new design tools, refining visual systems, and proactively improving templates or processes that make our team’s work stronger and more consistent long term. | CG8: ='Raw Data'!AZ4 -> No
A9: ='Raw Data'!$A5 -> 3 | C9: ='Raw Data'!$K5 -> Daily | D9: =IF($C9="Never or rarely",0,IF($C9="A few times a month",0.25,IF($C9="Weekly",0.5,IF($C9="Several times a week",0.75,IF($C9="Daily",1))))) -> 1 | E9: ='Raw Data'!$L5 -> Editing or improving text I've already written (emails, documents, presentations), Analyzing data or documents to extract insights or summaries, Brainstorming ideas, testing concepts, or getting feedback on my thinking, Building custom prompts, templates, or workflows that I reuse regularly | F9: =IF(ISNUMBER(SEARCH("I don't use AI for work",$E9)),0)+IF(ISNUMBER(SEARCH("Getting quick answers",$E9)),1,0)+IF(ISNUMBER(SEARCH("Editing text",$E9)),1,0)+IF(ISNUMBER(SEARCH("Writing/debugging code",$E9)),1,0)+IF(ISNUMBER(SEARCH("Creating first drafts",$E9)),2,0)+IF(ISNUMBER(SEARCH("Analyzing data/documents",$E9)),2,0)+IF(ISNUMBER(SEARCH("Brainstorming/testing concepts",$E9)),2,0)+IF(ISNUMBER(SEARCH("Building custom workflows",$E9)),3,0)+IF(ISNUMBER(SEARCH("Prototyping solutions",$E9)),3,0) -> 0 | G9: =$F9/3 -> 0 | H9: ='Raw Data'!M5 -> I maintain a library of prompts that I reuse frequently | I9: =IF($H9="I don't use AI for work",0,IF($H9="I create fresh prompts each time I use AI",0.25,IF($H9="I maintain a library of prompts that I reuse frequently",0.5,IF($H9="I've built custom AI tools (CustomGPTs, Copilot Agents, Google Gems, Claude Projects) for repetitive tasks",0.75,IF($H9="I've created workflows that connect AI with other systems (Slack, Salesforce, email) using integrations or code",1))))) -> 0.5 | J9: ='Raw Data'!$N5 -> Use AI to help analyze each data source, then compile results manually | K9: =IF($J9="Ask AI to write the summary after you've analyzed all the data",0.33,IF($J9="Use AI to help analyze each data source, then compile results manually",0.67,IF($J9="Create a systematic process where AI handles data analysis and summary generation consistently",1,IF($J9="I wouldn’t use AI for this task",0)))) -> 0.67 | L9: ='Raw Data'!$O5 -> First to understand the topic - continue asking questions to understand thoroughly. I'd then take my own stab at putting together the presentation - I find that still makes for a more effective presentation. Then I'd have AI poke holes in that document, and work with it to improve it. | M9: First to understand the topic - continue asking questions to understand thoroughly. I'd then take my own stab at putting together the presentation - I find that still makes for a more effective presentation. Then I'd have AI poke holes in that document, and work with it to improve it. | N9: =SUBSTITUTE('Prompt Template'!$A$2,$L$5,$M9) -> You are an expert evaluator of AI strategic thinking and workflow integration. Your goal is to evaluate how effectively survey respondents demonstrate strategic AI application based on their response to the question: “You have one week to create an important presentation for senior stakeholders on an unfamiliar topic. How would you use AI in this process?” Evaluate each response holistically across three key areas: Workflow Integration: Effective responses demonstrate systematic thinking by identifying multiple stages of the presentation process where AI can add value (research, analysis, content creation, structure, review, etc.). They show understanding that complex projects benefit from AI integration at various points rather than just using AI for one isolated task. Strategic Application: Strong responses show context-aware AI usage that specifically addresses the unique challenges of this scenario — leveraging AI to quickly understand an unfamiliar topic, tailoring content for senior stakeholders, and managing time constraints effectively. They go beyond generic AI applications to show thoughtful consideration of the specific requirements. Practical Execution: Quality responses demonstrate concrete understanding of how AI tools actually work by providing specific, actionable approaches rather than vague descriptions. They show familiarity with AI capabilities and limitations, and describe realistic implementation steps. Scoring Guidelines Score 3 — Strong strategic thinking • Demonstrates comprehensive AI integration across most or all key workflow stages (e.g., research, structure, content creation, context tailoring for senior stakeholders, review), combined with clear scenario awareness and practical execution. • Responses do not need to mention every single stage explicitly; concise or list-style answers can still score a 3 if they show a strategically complete, end-to-end approach that addresses the scenario’s unique challenges (unfamiliar topic, senior stakeholders, tight timelines). • Omitting one stage (e.g., review) does not disqualify a response if the overall strategy is robust and well-adapted. • Both structured and concise list-style responses are valid. Examples: • “Research topic comprehensively, analyze stakeholder needs, create presentation framework, develop content, review for clarity.” • “Use AI throughout the process — from initial research to final presentation polish — focusing on what senior stakeholders care about most.” • “I would use AI to research the topic, understand key stakeholder concerns, create a logical flow, and draft compelling content for senior leadership within the time constraint.” • “Scan unfamiliar topic, outline slides, tailor framing for executives, draft key content, fact-check and polish.” (Concise list-style example demonstrating full coverage) • “Research unfamiliar topic, structure the deck, tailor for executives, draft content.” (Covers most strategic stages, omits review but is still strategically comprehensive) Score 2 — Moderate strategic thinking • Demonstrates partial but not comprehensive coverage of the key strategic dimensions. • Typically covers two to three workflow stages (e.g., structure + content + some context) but omits one or more major elements such as research, scenario adaptation, or review. • May show good workflow integration but limited scenario context, or vice versa. • Responses may be clear and practical but reflect a mid-level strategic approach rather than end-to-end planning. Examples: • “Use AI to quickly understand the topic, then create an outline and draft the presentation content.” • “Research phase, analysis phase, content creation phase, review phase.” • “Use AI to help research industry trends and create slides tailored for executives.” • “Draft speaker notes, executive framing, summarize key sources.” (Covers content, some research, and context but lacks structure/review) • “10 slide structure, add citations, executive framing.” (Structure, review, context but no research/content creation) Score 1 — Limited strategic thinking • Shows basic or single AI application with little reference to workflow complexity or scenario context. • Generic AI usage that could apply to any presentation task. Examples: • “Use AI to research the topic and create slides.” • “ChatGPT for research, help with structure.” • “Research, writing, editing.” • “Ask AI to help me understand the topic.” Score 0 — No relevant response • No answer, states they wouldn’t use AI, or provides irrelevant content. Special Guidance on Format and Brevity • Do not penalize for response format or brevity. • Evaluate list-style or terse responses based on substance, not phrasing. • A concise response that clearly addresses all key strategic dimensions can score a 3. • Responses that address only part of the workflow or omit key scenario considerations should score a 2, even if clearly written. • Brevity alone should not lower a score. Output: For your response, ONLY output the single score (0–3). Do not include any explanation. Here is the user’s input: <user_input>First to understand the topic - continue asking questions to understand thoroughly. I'd then take my own stab at putting together the presentation - I find that still makes for a more effective presentation. Then I'd have AI poke holes in that document, and work with it to improve it.</user_input> | O9: {=INDEX('Response Scoring'!$C:$C,MATCH($A9,'Response Scoring'!$A:$A,0))} -> 2 | P9: =$O9/3 -> 0.66666667 | Q9: ='Raw Data'!$P5 -> To help me move through drafting faster - and to produce content for website pages. | R9: To help me move through drafting faster - and to produce content for website pages. | S9: =SUBSTITUTE('Prompt Template'!$B$2,$Q$5,$R9) -> You are an expert evaluator of practical AI value creation in work contexts. Your goal is to evaluate how effectively survey respondents demonstrate valuable AI usage based on their response to the question: ‘What is the most useful or valuable way you are using AI in your work?’ Valuable AI usage enables higher speed and/or quality work outputs with measurable impact on workflow pain points or business objectives. Strong responses demonstrate AI integration that transforms how core work gets done, rather than providing minor convenience. Score 3 — Workflow Redesign / Integrated Use (Human-in-the-Loop or Automated) Definition: Demonstrates strategic, repeatable AI integration that has redesigned or materially enhanced how the respondent performs a core part of their job. AI is consistently embedded in their workflow, creates new capabilities, or systematically improves downstream outputs or decisions. Transformation may involve automation or a human-in-the-loop redesign. Transformation requires more than saving time on peripheral tasks. The AI use must alter how a core deliverable is created, reviewed, or decided on — not just replace small administrative tasks within it. Time savings are only valid when they result from a redesigned or automated workflow step that affects downstream outputs or team decision-making. Observable Signals (any two or more): • Defined trigger or cadence (e.g., “after every client call,” “weekly review,” or implied repetition such as “each week,” “after calls,” or “whenever new data is ready”). • Template, checklist, or structured prompt used consistently. • AI output feeds directly into another step or tool (e.g., CRM, backlog, report). • AI introduces a new step, quality gate, or sequencing change. • AI automation replaces a manual stage and enables higher-value analytical or decision-making work. • Concise responses still qualify if they clearly imply repeatable, embedded use. Contrast Examples: Meeting Notes → Follow-up • (3) “After each client call, I run a prompt that tags actions by owner and priority, then imports them into our tracker.” • (2) “After calls, I paste notes into AI to group actions by owner and due date.” • (1) “I use AI to summarize meeting notes.” Customer Feedback → Insights • (3) “Each week, AI clusters customer comments, maps them to product areas, and ranks issues I review for roadmap planning.” • (2) “AI helps cluster customer comments into themes for my monthly report.” • (1) “I ask AI to summarize customer feedback.” Data Analysis / SQL • (3) “AI generates and validates queries, produces comparison tables, and highlights anomalies I review in reports.” • (2) “AI drafts SQL queries and interprets results faster than manual work.” • (1) “AI explains SQL when I’m stuck.” Proposal / Report Writing • (3) “I use a repeatable AI template that turns briefs into full drafts with rationale and risks sections, which I refine for delivery.” • (2) “AI drafts first sections of my proposals based on my outline.” • (1) “AI helps me improve grammar and phrasing.” Competitive Research • (3) “AI normalizes competitor data, flags gaps, and generates a positioning summary for our quarterly review.” • (2) “AI extracts pricing and features into a summary table before I write my report.” • (1) “AI summarizes competitor websites.” Score 2 — Process Enhancement / Embedded Use Definition: Shows repeatable, meaningful AI use within an existing process that improves speed, quality, or consistency. AI use is consistent and relevant to core responsibilities, but the workflow design and logic remain the same. May include structured use for efficiency, but does not fundamentally change how deliverables are produced or how information flows. Observable Signals (any one): • Clear efficiency, clarity, or organization benefit. • Consistent use within a step of a recurring workflow. • Described as part of normal work, not one-off. • Partial structure or templates used manually. Examples: • “I use AI to organize survey responses and find key themes before my analysis.” • “AI drafts report sections to help me start faster.” • “I use AI to group meeting notes by owner for easier follow-up.” • “AI summarizes recurring reports or data updates to save time, but outputs are reviewed or reformatted manually.” Score 1 — Task Assistance / Surface-Level Use Definition: Describes episodic or one-step assistance focused on convenience or small efficiency gains. AI is not embedded in a structured workflow or used consistently. Includes short, isolated tasks that do not influence how other work is performed. Observable Signals: • Task-specific or one-off. • No cadence, handoff, or reuse. • Focused on formatting, writing, or explanation. • Peripheral use — does not alter how a core deliverable or process is executed. Examples: • “I use AI to fix grammar or reword emails.” • “AI helps me write Excel formulas or explain code.” • “I use AI to summarize meeting notes.” • “AI drafts short internal updates so I can focus elsewhere.” Score 0 — No or Irrelevant Use Definition: No evidence of AI use in a work context or explicitly states they do not use AI. Example: • “I don’t use AI in my work.” Evaluator Checklist When scoring, ignore writing quality and phrasing. Look for evidence of process depth: • Defined trigger or cadence? (explicit or implied) • Repeatable prompt, checklist, or playbook? • AI output feeding another step or tool? • Workflow sequence or ownership changed? • New capability or quality gate introduced? • When evaluating time savings, consider whether the AI use alters how a core deliverable is produced or simply removes a peripheral or administrative step. • Does the AI output directly support a core deliverable (e.g., reports, analysis, client output)? • Cohesion check: Are the tasks connected within a single workflow or purpose? • If the response lists multiple unrelated activities (e.g., “draft emails, brainstorm ideas, summarize reports”), treat it as multiple isolated uses and score at the lower level. Heuristic: • 3 = Embedded + ≥ 2 signals + cohesive workflow or clear transformation of core deliverable • 2 = Embedded + 0–1 signal + cohesive workflow, limited transformation • 1 = Isolated or peripheral task use • 0 = None Scoring Instruction: For your response, ONLY output the single score (0–3). Do not include any explanation. Here is the user’s input: <user_input>To help me move through drafting faster - and to produce content for website pages.</user_input> | T9: {=INDEX('Response Scoring'!$E:$E,MATCH($A9,'Response Scoring'!$A:$A,0))} -> 1 | U9: =$T9/3 -> 0.33333333 | V9: =SUMPRODUCT($C9:$U9,$C$3:$U$3) -> 4.3366667 | W9: ='Raw Data'!$Q5 -> Analyzing presentation slides to evaluate both the visual design and written content for consistency | X9: =IF($W9="Analyzing presentation slides to evaluate both the visual design and written content for consistency",1,0) -> 1 | Y9: ='Raw Data'!$R5 -> Hallucinations (generating false or misleading information), Biases in answers, Data privacy concerns when information is shared with an LLM | Z9: =IF(ISNUMBER(SEARCH("Hallucinations",$Y9)),0.25)+IF(ISNUMBER(SEARCH("Biases in answers",$Y9)),0.25,0)+IF(ISNUMBER(SEARCH("Data privacy concerns",$Y9)),0.25)+IF(ISNUMBER(SEARCH("Vulnerability",$Y9)),0.25) -> 0.75 | AA9: ='Raw Data'!$S5 -> Anonymize information by removing identifying details, Use secure company instances or enterprise plans when available | AB9: =IF(OR(ISNUMBER(SEARCH("Avoid using AI tools",$AA9)),ISNUMBER(SEARCH("Verify that the AI tool",$AA9))),0,(IF(ISNUMBER(SEARCH("Anonymize information",$AA9)),0.5)+IF(ISNUMBER(SEARCH("Use secure company instances",$AA9)),0.5))) -> 1 | AC9: ='Raw Data'!$T5 -> Always: I routinely cross-check AI outputs with reliable sources | AD9: =IF($AC9="Never: I typically trust the output as is",0,IF($AC9="Rarely: I only verify if something doesn't sound right",0.33,IF($AC9="Sometimes: I do a quick check against known data or references",0.67,IF($AC9="Always: I routinely cross-check AI outputs with reliable sources",1)))) -> 1 | AE9: ='Raw Data'!$U5 -> Cross-reference key claims with reliable external sources, Use a different AI tool to review and verify the content | AF9: =IF(OR(ISNUMBER(SEARCH("Check if the response uses confident language",$AE9)),ISNUMBER(SEARCH("Look for professional formatting",$AE9))),0,(IF(ISNUMBER(SEARCH("Use a different AI tool",$AE9)),0.25)+IF(ISNUMBER(SEARCH("Cross-reference key claims",$AE9)),0.25)+IF(ISNUMBER(SEARCH("Verify any calculations",$AE9)),0.25)+IF(ISNUMBER(SEARCH("Ask the same AI tool",$AE9)),0.25))) -> 0.5 | AG9: =SUMPRODUCT($W9:$AF9,$W$3:$AF$3) -> 8.5 | AH9: ='Raw Data'!$V5 -> Frequently: I systematically refine prompts until I'm satisfied | AI9: =IF($AH9="Never: I usually just ask once and accept the first response",0,IF($AH9="Rarely: I only tweak the prompt if something feels obviously off",0.33,IF($AH9="Sometimes: I iterate 2-3 times to reach a good result",0.67,IF($AH9="Frequently: I systematically refine prompts until I'm satisfied",1)))) -> 1 | AJ9: ='Raw Data'!$W5 -> I am heading into a meeting with our CMO and CEO to discuss starting a podcast for our agency. Can you please: 1. Suggest names for the podcast (and then I'd enter in information about our agency, names of other products, etc.) 2. Come up with ideas so that we present each podcast consistently: something we say every episode, and a red thread that can pull every episode together (I'd send backup information for inspiration). 3. Research best times to publish and ideal frequency. 4. Come up with arguments FOR and AGAINST publishing this podcast (and include concepts around how much team time might go into executing this project consistently). | AK9: I am heading into a meeting with our CMO and CEO to discuss starting a podcast for our agency. Can you please: 1. Suggest names for the podcast (and then I'd enter in information about our agency, names of other products, etc.) 2. Come up with ideas so that we present each podcast consistently: something we say every episode, and a red thread that can pull every episode together (I'd send backup information for inspiration). 3. Research best times to publish and ideal frequency. 4. Come up with arguments FOR and AGAINST publishing this podcast (and include concepts around how much team time might go into executing this project consistently). | AL9: =SUBSTITUTE('Prompt Template'!$C$2,$AJ$5,$AK9) -> You are an expert prompt engineer. Your goal is to evaluate the effectiveness of the prompt below. Less effective prompts are too vague, open-ended, and do not give clear instructions. More effective prompts provide background, clear instructions, and are well structured. Since you are tasked with evaluating true effectiveness of the prompt, you can give scores of 1. This is for an AI Readiness Survey that will assess individuals' proficiency when using AI. <task>Write a prompt asking AI to help you prepare for a work meeting to discuss a new initiative or proposal</task> <prompt>I am heading into a meeting with our CMO and CEO to discuss starting a podcast for our agency. Can you please: 1. Suggest names for the podcast (and then I'd enter in information about our agency, names of other products, etc.) 2. Come up with ideas so that we present each podcast consistently: something we say every episode, and a red thread that can pull every episode together (I'd send backup information for inspiration). 3. Research best times to publish and ideal frequency. 4. Come up with arguments FOR and AGAINST publishing this podcast (and include concepts around how much team time might go into executing this project consistently).</prompt> A score of 1 prompt example: "Help me prepare for my work meeting" Rate the effectiveness on a scale of 1-5. Only respond with a single number from 1-5. If the person states they do not know how to prompt or their prompt isn't relevant to the task, give them a 0. Use the following criteria: Clarity and Specificity: A good prompt should be clear, specific, and focused. It should provide enough context and detail to guide the AI towards generating a relevant and useful response. Vague, open-ended, or ambiguous prompts make it difficult for the AI to understand the user's intent and can lead to generic or irrelevant outputs. Completeness and Sufficiency: An effective prompt should include all the necessary information and requirements to enable the AI to complete the requested task or answer the question thoroughly. It should anticipate what details the AI might need and proactively provide them. Incomplete prompts that leave out critical facts or constraints will likely result in suboptimal responses that fail to fully address the user's needs. Structure and Organization: A well-crafted prompt should be logically structured and organized. It should break down complex requests into clear steps or components, making it easier for the AI to process and respond to each part systematically. Using formatting techniques like bullet points, numbering, or sectioning can help improve the prompt's clarity and readability. Conciseness and Precision: While a good prompt should be detailed and informative, it should also strive to be as concise and precise as possible. Overly wordy or rambling prompts can obscure the key points and make it harder for the AI to identify the essential requirements. An effective prompt finds the right balance between providing necessary context and avoiding extraneous or redundant information. Here is the user's input: <user_input>I am heading into a meeting with our CMO and CEO to discuss starting a podcast for our agency. Can you please: 1. Suggest names for the podcast (and then I'd enter in information about our agency, names of other products, etc.) 2. Come up with ideas so that we present each podcast consistently: something we say every episode, and a red thread that can pull every episode together (I'd send backup information for inspiration). 3. Research best times to publish and ideal frequency. 4. Come up with arguments FOR and AGAINST publishing this podcast (and include concepts around how much team time might go into executing this project consistently).</user_input> | AM9: {=INDEX('Response Scoring'!$G:$G,MATCH($A9,'Response Scoring'!$A:$A,0))} -> 4 | AN9: =$AM9/5 -> 0.8 | AO9: ='Raw Data'!$X5 -> Custom AI Tool Instructions: Competitive Intelligence Research Assistant Purpose: This AI tool assists the Stella Rising team in gathering, analyzing, and summarizing competitive intelligence on digital marketing and media agencies. It ensures consistent, thorough, and ethical research across competitor products, pricing, positioning, capabilities, and innovations. ⸻ Core Functions: 1. Competitor Identification & Profiling • Identify key competitors in the digital marketing and media landscape, focusing on agencies with similar service offerings, size, and client base (e.g., performance marketing, SEO/SEM, influencer, and creative strategy). • Collect and summarize company overviews, leadership teams, client rosters, and notable campaigns or awards. • Identify new entrants or emerging boutique agencies in the space. 2. Service & Offering Analysis • Review competitors’ websites, press releases, and thought leadership to summarize service lines (e.g., SEO, paid media, influencer, analytics, e-commerce, retail media). • Identify differentiators, proprietary tools, or frameworks (e.g., data platforms, AI-driven solutions). • Note any service expansions, acquisitions, or partnerships. 3. Pricing & Engagement Models • Gather publicly available or indicative data on pricing structures (retainer vs. performance-based, tiered packages, hourly rates). • Identify how competitors communicate ROI or value — e.g., “performance-first,” “brand love,” or “data + human insight” positioning. • Summarize how pricing aligns with service sophistication and positioning. 4. Messaging, Branding & Positioning Analysis • Capture language used on competitors’ homepages, case studies, and social channels to identify tone, positioning, and differentiators. • Highlight recurring themes (e.g., “data + creativity,” “growth partner,” “AI innovation,” “purpose-driven marketing”). • Compare how Stella Rising’s brand narrative aligns or contrasts with these messages. 5. Innovation & Technology Tracking • Monitor use of emerging technologies (AI, automation, retail media networks, social commerce integrations, etc.). • Track any proprietary tools, dashboards, or analytics platforms mentioned. • Identify how competitors position their innovation capabilities relative to client growth outcomes. 6. Public Reputation & Recognition • Summarize industry recognition (awards, rankings, speaking engagements). • Collect client testimonials, Glassdoor reviews, or PR sentiment (where available) to infer reputation and cultural strengths. ⸻ Output Format: Each competitive profile should be summarized as follows: • Overview: Agency name, size, HQ, key leadership, and client sectors. • Key Offerings & Differentiators • Recent Campaigns or Awards • Positioning & Messaging Themes • Innovation/Technology Highlights • Pricing or Engagement Insights (if available) • Summary Takeaways & Implications for Stella Rising ⸻ Tone & Guidelines: • Maintain an objective, analytical tone — avoid speculation. • Cite publicly available sources only (company websites, press releases, media coverage, awards sites). • Summaries should be concise but insight-rich, with clear implications for Stella Rising’s positioning and business development. • Use consistent formatting to ensure comparability across competitor profiles. | AP9: Custom AI Tool Instructions: Competitive Intelligence Research Assistant Purpose: This AI tool assists the Stella Rising team in gathering, analyzing, and summarizing competitive intelligence on digital marketing and media agencies. It ensures consistent, thorough, and ethical research across competitor products, pricing, positioning, capabilities, and innovations. ⸻ Core Functions: 1. Competitor Identification & Profiling • Identify key competitors in the digital marketing and media landscape, focusing on agencies with similar service offerings, size, and client base (e.g., performance marketing, SEO/SEM, influencer, and creative strategy). • Collect and summarize company overviews, leadership teams, client rosters, and notable campaigns or awards. • Identify new entrants or emerging boutique agencies in the space. 2. Service & Offering Analysis • Review competitors’ websites, press releases, and thought leadership to summarize service lines (e.g., SEO, paid media, influencer, analytics, e-commerce, retail media). • Identify differentiators, proprietary tools, or frameworks (e.g., data platforms, AI-driven solutions). • Note any service expansions, acquisitions, or partnerships. 3. Pricing & Engagement Models • Gather publicly available or indicative data on pricing structures (retainer vs. performance-based, tiered packages, hourly rates). • Identify how competitors communicate ROI or value — e.g., “performance-first,” “brand love,” or “data + human insight” positioning. • Summarize how pricing aligns with service sophistication and positioning. 4. Messaging, Branding & Positioning Analysis • Capture language used on competitors’ homepages, case studies, and social channels to identify tone, positioning, and differentiators. • Highlight recurring themes (e.g., “data + creativity,” “growth partner,” “AI innovation,” “purpose-driven marketing”). • Compare how Stella Rising’s brand narrative aligns or contrasts with these messages. 5. Innovation & Technology Tracking • Monitor use of emerging technologies (AI, automation, retail media networks, social commerce integrations, etc.). • Track any proprietary tools, dashboards, or analytics platforms mentioned. • Identify how competitors position their innovation capabilities relative to client growth outcomes. 6. Public Reputation & Recognition • Summarize industry recognition (awards, rankings, speaking engagements). • Collect client testimonials, Glassdoor reviews, or PR sentiment (where available) to infer reputation and cultural strengths. ⸻ Output Format: Each competitive profile should be summarized as follows: • Overview: Agency name, size, HQ, key leadership, and client sectors. • Key Offerings & Differentiators • Recent Campaigns or Awards • Positioning & Messaging Themes • Innovation/Technology Highlights • Pricing or Engagement Insights (if available) • Summary Takeaways & Implications for Stella Rising ⸻ Tone & Guidelines: • Maintain an objective, analytical tone — avoid speculation. • Cite publicly available sources only (company websites, press releases, media coverage, awards sites). • Summaries should be concise but insight-rich, with clear implications for Stella Rising’s positioning and business development. • Use consistent formatting to ensure comparability across competitor profiles. | AQ9: =SUBSTITUTE('Prompt Template'!$D$2,$AO$5,$AP9) -> You are an expert evaluator of AI instruction design and CustomGPT configuration. Your goal is to evaluate how effectively a respondent demonstrates their ability to write high-quality AI instructions — the kind used to configure tools like CustomGPTs, Copilot Agents, or Google Gems. The test question asks respondents to: ‘Write instructions for a Custom GPT that would help team members gather competitive intelligence consistently.’ This scenario is used only as a familiar example. Do not evaluate their knowledge of competitive analysis — only the clarity, structure, and effectiveness of their AI instruction design. The competitive intelligence context is a stand-in for any business task. Scoring Overview Rate each response on a scale of 0–5. • 5 = System-ready, strong demonstration of instruction design skill. • 0 = Irrelevant or no response. Focus on instructional quality, not topic expertise or formatting aesthetics. Evaluation Dimensions 1. Structural Design Effective instructions clearly define the inputs, process/steps, and outputs. They show logical sequencing (e.g., research → organize → summarize) and reflect understanding of how AI interprets procedural tasks. 2. Instructional Precision Steps and directives are specific, actionable, and testable by an AI. Avoids vague terms like “analyze competitors” without specifying how to do so or what output is expected. 3. Boundary and Role Definition Strong instructions establish clear context for the AI — defining its role, scope, and constraints. They guide what to include/exclude and how to handle ambiguity or conflicting data. 4. Reusability and Scalability Good instructions can be reused consistently by others. They define consistent formatting, data structures, or repeatable logic that ensures stable results across users or scenarios. 5. Outcome Alignment The best instructions would realistically result in a functioning CustomGPT that performs the intended task accurately and consistently. Weak ones would produce inconsistent or low-quality behavior. Scoring Guidelines Score 5 – System-Ready • Instructions could be pasted directly into a CustomGPT/Copilot and perform effectively. • They demonstrate full system readiness — meaning the AI could execute the intended behavior repeatedly and autonomously, without additional clarification. • Includes: • Defined role and purpose (who/what the AI is). • Clear inputs (what information or user query it receives). • Explicit steps/process (how the AI should perform the task). • Defined outputs (format, tone, or structure of response). • Constraints/quality controls (rules, caveats, or handling instructions). • Demonstrates awareness of how to build a reusable, consistent AI behavior. Example 1: “Role: Competitive Intelligence Assistant. Purpose: Gather structured competitor data from reliable sources. Inputs: Company/product names. Process: 1) Identify top 5 competitors, 2) Extract features/pricing, 3) Summarize differences in a table. Output: Comparative matrix. Guardrails: Only use credible, verifiable sources.” Example 2 (Natural-Language Equivalent): “This CustomGPT should act as our internal research analyst. When given a company or product name, it identifies credible sources like official websites, press releases, and reviews. It compares product features, pricing, and messaging across competitors and summarizes the results in a consistent table and a short written overview with citations. The report should flag any information that seems outdated or unverified and maintain a uniform format for reuse across projects.” Note: Responses may use either explicit headings (Role/Inputs/Process/Output) or fluent natural language. Both are valid if they include equivalent components and could realistically produce consistent, reusable results. Score 4 – Strong but Missing Refinements • Structured and actionable; includes most components (e.g., steps, outputs, and some constraints). • Missing minor refinements such as input specificity, error handling, or reusability mechanisms. • AI could perform the task, but inconsistently. Example 1: “Gather information on competitors’ products, features, and pricing. Summarize in a table. Cite reliable sources.” (Functional but missing full structure or clear constraints.) Example 2: “Create a CustomGPT that collects information from competitor websites, reviews, and announcements. Summarize pricing, features, and positioning in a table, then highlight new updates. Include dates and brief notes on source credibility.” (Strong structure, but lacks clear inputs and reusability framing.) Score 3 – Structured but Shallow • Provides a reasonable outline or list of tasks but lacks cohesion or precision. • Mentions the goal but misses how to operationalize it in a repeatable, system-friendly way. • AI would need to infer too much to work reliably. Example 1: “Research competitors and summarize key findings about pricing and positioning.” (Has intent but lacks sequencing or defined outputs.) Example 2: “The GPT should find information about our competitors’ pricing and products, summarize what’s different, and give a short write-up each week.” (Clear intent, but underspecified logic — reads more like a to-do list than executable instructions.) Score 2 – Fragmented or Vague • Mentions competitive research but provides minimal or disconnected guidance. • Steps are generic, unsequenced, or too ambiguous to drive consistent AI behavior. Example elements: “Look up competitors and gather details.” “Find competitor info and summarize.” (Too vague to translate into functioning instructions.) Score 1 – Minimal or Misunderstood • Shows fundamental misunderstanding of AI instruction design. • Generic, incomplete, or irrelevant content that couldn’t guide an AI system at all. Example elements: “Just tell GPT to look up competitors.” “I’d ask it to find info about other companies.” “Use ChatGPT to do competitive research for us.” “Help me understand what our competitors do better.” “Search online for competitor products and summarize.” (Shows surface-level familiarity with AI but no system thinking.) Score 0 – No Response or Irrelevant • Empty, “I don’t know,” or unrelated answer. Example elements: “Not sure what to put here.” “I don’t use GPT for that.” “I’d rather do that myself.” “No idea how to write that.” (Shows confusion or complete lack of task understanding.) Evaluator Checklist When scoring, focus on functional design quality, not formatting or topic expertise. Ask yourself: • Does the response clearly define the AI’s role, inputs, process, and outputs? • Are instructions specific, sequenced, and testable? • Do they include boundaries or quality controls? • Could the AI perform the task consistently and autonomously if these instructions were used? • Is the response written at a configuration level (system prompt) rather than a one-off user command? Heuristic: • 5 = Fully structured, system-ready, reusable. • 4 = Strong, nearly system-ready, missing refinements. • 3 = Structured but shallow. • 2 = Fragmented or vague. • 1 = Minimal or misunderstood. • 0 = None/irrelevant. Scoring Instruction: For your response, ONLY output the single score (0–5). Do not include any explanation. Here is the user’s input: <user_input>Custom AI Tool Instructions: Competitive Intelligence Research Assistant Purpose: This AI tool assists the Stella Rising team in gathering, analyzing, and summarizing competitive intelligence on digital marketing and media agencies. It ensures consistent, thorough, and ethical research across competitor products, pricing, positioning, capabilities, and innovations. ⸻ Core Functions: 1. Competitor Identification & Profiling • Identify key competitors in the digital marketing and media landscape, focusing on agencies with similar service offerings, size, and client base (e.g., performance marketing, SEO/SEM, influencer, and creative strategy). • Collect and summarize company overviews, leadership teams, client rosters, and notable campaigns or awards. • Identify new entrants or emerging boutique agencies in the space. 2. Service & Offering Analysis • Review competitors’ websites, press releases, and thought leadership to summarize service lines (e.g., SEO, paid media, influencer, analytics, e-commerce, retail media). • Identify differentiators, proprietary tools, or frameworks (e.g., data platforms, AI-driven solutions). • Note any service expansions, acquisitions, or partnerships. 3. Pricing & Engagement Models • Gather publicly available or indicative data on pricing structures (retainer vs. performance-based, tiered packages, hourly rates). • Identify how competitors communicate ROI or value — e.g., “performance-first,” “brand love,” or “data + human insight” positioning. • Summarize how pricing aligns with service sophistication and positioning. 4. Messaging, Branding & Positioning Analysis • Capture language used on competitors’ homepages, case studies, and social channels to identify tone, positioning, and differentiators. • Highlight recurring themes (e.g., “data + creativity,” “growth partner,” “AI innovation,” “purpose-driven marketing”). • Compare how Stella Rising’s brand narrative aligns or contrasts with these messages. 5. Innovation & Technology Tracking • Monitor use of emerging technologies (AI, automation, retail media networks, social commerce integrations, etc.). • Track any proprietary tools, dashboards, or analytics platforms mentioned. • Identify how competitors position their innovation capabilities relative to client growth outcomes. 6. Public Reputation & Recognition • Summarize industry recognition (awards, rankings, speaking engagements). • Collect client testimonials, Glassdoor reviews, or PR sentiment (where available) to infer reputation and cultural strengths. ⸻ Output Format: Each competitive profile should be summarized as follows: • Overview: Agency name, size, HQ, key leadership, and client sectors. • Key Offerings & Differentiators • Recent Campaigns or Awards • Positioning & Messaging Themes • Innovation/Technology Highlights • Pricing or Engagement Insights (if available) • Summary Takeaways & Implications for Stella Rising ⸻ Tone & Guidelines: • Maintain an objective, analytical tone — avoid speculation. • Cite publicly available sources only (company websites, press releases, media coverage, awards sites). • Summaries should be concise but insight-rich, with clear implications for Stella Rising’s positioning and business development. • Use consistent formatting to ensure comparability across competitor profiles.</user_input> | AR9: {=INDEX('Response Scoring'!$I:$I,MATCH($A9,'Response Scoring'!$A:$A,0))} -> 5 | AS9: =$AR9/5 -> 1 | AT9: =SUMPRODUCT($AH9:$AS9,$AH$3:$AS$3) -> 9.3 | AU9: =($V9*$AW$4)+($AG9*$AW$3)+($AT9*$AW$2) -> 35.773333 | AV9: =$AU9*2 -> 71.546667 | AW9: =IF($AV9>=80,"AI Expert",IF($AV9>=60,"AI Practitioner",IF(AND($AV9<60,$AV9>=25),"AI Experimenter",IF(AND($AV9<25,$AV9>=0),"AI Novice")))) -> AI Practitioner | AX9: ='Raw Data'!Y5 -> ChatGPT, Claude | AY9: ='Raw Data'!Z5 -> FALSE | AZ9: ='Raw Data'!AA5 -> Yes, we have a formal AI strategy | BA9: ='Raw Data'!AB5 -> Tools exist with clear access process | BB9: ='Raw Data'!AC5 -> ChatGPT for Enterprise or Teams | BC9: ='Raw Data'!AD5 -> Satisfied - meets my needs well | BD9: ='Raw Data'!AE5 -> Clear, enforced policies that directly implement our AI strategy | BE9: ='Raw Data'!AF5 -> We have a clear, actionable policy that effectively guides AI use | ... BR9: ='Raw Data'!AS5 -> Significant improvement - noticeably better productivity and outcomes | BS9: ='Raw Data'!C5 -> 0 | BT9: ='Raw Data'!D5 -> 0 | BU9: ='Raw Data'!E5 -> Marketing/Biz Dev | BV9: ='Raw Data'!F5 -> Director | BW9: ='Raw Data'!G5 -> 0 | BX9: ='Raw Data'!H5 -> 0 | BY9: ='Raw Data'!I5 -> 0 | BZ9: ='Raw Data'!J5 -> 0 | CA9: ='Raw Data'!AT5 -> Time to experiment | CB9: ='Raw Data'!AU5 -> To save time! And clarify thinking/writing. | CC9: ='Raw Data'!AV5 -> I feel this is getting repetitive BUT: 1) Draft writing, content generation, and site content generation. | CD9: ='Raw Data'!AW5 -> More time for testing & learning | CE9: ='Raw Data'!AX5 -> I understand the RFP process could be improved with a custom GPT | CF9: ='Raw Data'!AY5 -> More brainstorm time for big ideas. | CG9: ='Raw Data'!AZ5 -> Yes
A10: ='Raw Data'!$A6 -> 4 | C10: ='Raw Data'!$K6 -> Daily | D10: =IF($C10="Never or rarely",0,IF($C10="A few times a month",0.25,IF($C10="Weekly",0.5,IF($C10="Several times a week",0.75,IF($C10="Daily",1))))) -> 1 | E10: ='Raw Data'!$L6 -> Editing or improving text I've already written (emails, documents, presentations), Creating first drafts of content from scratch (reports, proposals, marketing copy), Analyzing data or documents to extract insights or summaries, Brainstorming ideas, testing concepts, or getting feedback on my thinking, Building custom prompts, templates, or workflows that I reuse regularly | F10: =IF(ISNUMBER(SEARCH("I don't use AI for work",$E10)),0)+IF(ISNUMBER(SEARCH("Getting quick answers",$E10)),1,0)+IF(ISNUMBER(SEARCH("Editing text",$E10)),1,0)+IF(ISNUMBER(SEARCH("Writing/debugging code",$E10)),1,0)+IF(ISNUMBER(SEARCH("Creating first drafts",$E10)),2,0)+IF(ISNUMBER(SEARCH("Analyzing data/documents",$E10)),2,0)+IF(ISNUMBER(SEARCH("Brainstorming/testing concepts",$E10)),2,0)+IF(ISNUMBER(SEARCH("Building custom workflows",$E10)),3,0)+IF(ISNUMBER(SEARCH("Prototyping solutions",$E10)),3,0) -> 2 | G10: =$F10/3 -> 0.66666667 | H10: ='Raw Data'!M6 -> I've built custom AI tools (CustomGPTs, Copilot Agents, Google Gems, Claude Projects) for repetitive tasks | I10: =IF($H10="I don't use AI for work",0,IF($H10="I create fresh prompts each time I use AI",0.25,IF($H10="I maintain a library of prompts that I reuse frequently",0.5,IF($H10="I've built custom AI tools (CustomGPTs, Copilot Agents, Google Gems, Claude Projects) for repetitive tasks",0.75,IF($H10="I've created workflows that connect AI with other systems (Slack, Salesforce, email) using integrations or code",1))))) -> 0.75 | J10: ='Raw Data'!$N6 -> Create a systematic process where AI handles data analysis and summary generation consistently | K10: =IF($J10="Ask AI to write the summary after you've analyzed all the data",0.33,IF($J10="Use AI to help analyze each data source, then compile results manually",0.67,IF($J10="Create a systematic process where AI handles data analysis and summary generation consistently",1,IF($J10="I wouldn’t use AI for this task",0)))) -> 1 | L10: ='Raw Data'!$O6 -> I would use AI to gather information sources first, then have it create an outline for the presentation. i would then build the presentation myself | M10: I would use AI to gather information sources first, then have it create an outline for the presentation. i would then build the presentation myself | N10: =SUBSTITUTE('Prompt Template'!$A$2,$L$5,$M10) -> You are an expert evaluator of AI strategic thinking and workflow integration. Your goal is to evaluate how effectively survey respondents demonstrate strategic AI application based on their response to the question: “You have one week to create an important presentation for senior stakeholders on an unfamiliar topic. How would you use AI in this process?” Evaluate each response holistically across three key areas: Workflow Integration: Effective responses demonstrate systematic thinking by identifying multiple stages of the presentation process where AI can add value (research, analysis, content creation, structure, review, etc.). They show understanding that complex projects benefit from AI integration at various points rather than just using AI for one isolated task. Strategic Application: Strong responses show context-aware AI usage that specifically addresses the unique challenges of this scenario — leveraging AI to quickly understand an unfamiliar topic, tailoring content for senior stakeholders, and managing time constraints effectively. They go beyond generic AI applications to show thoughtful consideration of the specific requirements. Practical Execution: Quality responses demonstrate concrete understanding of how AI tools actually work by providing specific, actionable approaches rather than vague descriptions. They show familiarity with AI capabilities and limitations, and describe realistic implementation steps. Scoring Guidelines Score 3 — Strong strategic thinking • Demonstrates comprehensive AI integration across most or all key workflow stages (e.g., research, structure, content creation, context tailoring for senior stakeholders, review), combined with clear scenario awareness and practical execution. • Responses do not need to mention every single stage explicitly; concise or list-style answers can still score a 3 if they show a strategically complete, end-to-end approach that addresses the scenario’s unique challenges (unfamiliar topic, senior stakeholders, tight timelines). • Omitting one stage (e.g., review) does not disqualify a response if the overall strategy is robust and well-adapted. • Both structured and concise list-style responses are valid. Examples: • “Research topic comprehensively, analyze stakeholder needs, create presentation framework, develop content, review for clarity.” • “Use AI throughout the process — from initial research to final presentation polish — focusing on what senior stakeholders care about most.” • “I would use AI to research the topic, understand key stakeholder concerns, create a logical flow, and draft compelling content for senior leadership within the time constraint.” • “Scan unfamiliar topic, outline slides, tailor framing for executives, draft key content, fact-check and polish.” (Concise list-style example demonstrating full coverage) • “Research unfamiliar topic, structure the deck, tailor for executives, draft content.” (Covers most strategic stages, omits review but is still strategically comprehensive) Score 2 — Moderate strategic thinking • Demonstrates partial but not comprehensive coverage of the key strategic dimensions. • Typically covers two to three workflow stages (e.g., structure + content + some context) but omits one or more major elements such as research, scenario adaptation, or review. • May show good workflow integration but limited scenario context, or vice versa. • Responses may be clear and practical but reflect a mid-level strategic approach rather than end-to-end planning. Examples: • “Use AI to quickly understand the topic, then create an outline and draft the presentation content.” • “Research phase, analysis phase, content creation phase, review phase.” • “Use AI to help research industry trends and create slides tailored for executives.” • “Draft speaker notes, executive framing, summarize key sources.” (Covers content, some research, and context but lacks structure/review) • “10 slide structure, add citations, executive framing.” (Structure, review, context but no research/content creation) Score 1 — Limited strategic thinking • Shows basic or single AI application with little reference to workflow complexity or scenario context. • Generic AI usage that could apply to any presentation task. Examples: • “Use AI to research the topic and create slides.” • “ChatGPT for research, help with structure.” • “Research, writing, editing.” • “Ask AI to help me understand the topic.” Score 0 — No relevant response • No answer, states they wouldn’t use AI, or provides irrelevant content. Special Guidance on Format and Brevity • Do not penalize for response format or brevity. • Evaluate list-style or terse responses based on substance, not phrasing. • A concise response that clearly addresses all key strategic dimensions can score a 3. • Responses that address only part of the workflow or omit key scenario considerations should score a 2, even if clearly written. • Brevity alone should not lower a score. Output: For your response, ONLY output the single score (0–3). Do not include any explanation. Here is the user’s input: <user_input>I would use AI to gather information sources first, then have it create an outline for the presentation. i would then build the presentation myself</user_input> | O10: {=INDEX('Response Scoring'!$C:$C,MATCH($A10,'Response Scoring'!$A:$A,0))} -> 2 | P10: =$O10/3 -> 0.66666667 | Q10: ='Raw Data'!$P6 -> meeting summaries and next steps using meeting transcripts | R10: meeting summaries and next steps using meeting transcripts | S10: =SUBSTITUTE('Prompt Template'!$B$2,$Q$5,$R10) -> You are an expert evaluator of practical AI value creation in work contexts. Your goal is to evaluate how effectively survey respondents demonstrate valuable AI usage based on their response to the question: ‘What is the most useful or valuable way you are using AI in your work?’ Valuable AI usage enables higher speed and/or quality work outputs with measurable impact on workflow pain points or business objectives. Strong responses demonstrate AI integration that transforms how core work gets done, rather than providing minor convenience. Score 3 — Workflow Redesign / Integrated Use (Human-in-the-Loop or Automated) Definition: Demonstrates strategic, repeatable AI integration that has redesigned or materially enhanced how the respondent performs a core part of their job. AI is consistently embedded in their workflow, creates new capabilities, or systematically improves downstream outputs or decisions. Transformation may involve automation or a human-in-the-loop redesign. Transformation requires more than saving time on peripheral tasks. The AI use must alter how a core deliverable is created, reviewed, or decided on — not just replace small administrative tasks within it. Time savings are only valid when they result from a redesigned or automated workflow step that affects downstream outputs or team decision-making. Observable Signals (any two or more): • Defined trigger or cadence (e.g., “after every client call,” “weekly review,” or implied repetition such as “each week,” “after calls,” or “whenever new data is ready”). • Template, checklist, or structured prompt used consistently. • AI output feeds directly into another step or tool (e.g., CRM, backlog, report). • AI introduces a new step, quality gate, or sequencing change. • AI automation replaces a manual stage and enables higher-value analytical or decision-making work. • Concise responses still qualify if they clearly imply repeatable, embedded use. Contrast Examples: Meeting Notes → Follow-up • (3) “After each client call, I run a prompt that tags actions by owner and priority, then imports them into our tracker.” • (2) “After calls, I paste notes into AI to group actions by owner and due date.” • (1) “I use AI to summarize meeting notes.” Customer Feedback → Insights • (3) “Each week, AI clusters customer comments, maps them to product areas, and ranks issues I review for roadmap planning.” • (2) “AI helps cluster customer comments into themes for my monthly report.” • (1) “I ask AI to summarize customer feedback.” Data Analysis / SQL • (3) “AI generates and validates queries, produces comparison tables, and highlights anomalies I review in reports.” • (2) “AI drafts SQL queries and interprets results faster than manual work.” • (1) “AI explains SQL when I’m stuck.” Proposal / Report Writing • (3) “I use a repeatable AI template that turns briefs into full drafts with rationale and risks sections, which I refine for delivery.” • (2) “AI drafts first sections of my proposals based on my outline.” • (1) “AI helps me improve grammar and phrasing.” Competitive Research • (3) “AI normalizes competitor data, flags gaps, and generates a positioning summary for our quarterly review.” • (2) “AI extracts pricing and features into a summary table before I write my report.” • (1) “AI summarizes competitor websites.” Score 2 — Process Enhancement / Embedded Use Definition: Shows repeatable, meaningful AI use within an existing process that improves speed, quality, or consistency. AI use is consistent and relevant to core responsibilities, but the workflow design and logic remain the same. May include structured use for efficiency, but does not fundamentally change how deliverables are produced or how information flows. Observable Signals (any one): • Clear efficiency, clarity, or organization benefit. • Consistent use within a step of a recurring workflow. • Described as part of normal work, not one-off. • Partial structure or templates used manually. Examples: • “I use AI to organize survey responses and find key themes before my analysis.” • “AI drafts report sections to help me start faster.” • “I use AI to group meeting notes by owner for easier follow-up.” • “AI summarizes recurring reports or data updates to save time, but outputs are reviewed or reformatted manually.” Score 1 — Task Assistance / Surface-Level Use Definition: Describes episodic or one-step assistance focused on convenience or small efficiency gains. AI is not embedded in a structured workflow or used consistently. Includes short, isolated tasks that do not influence how other work is performed. Observable Signals: • Task-specific or one-off. • No cadence, handoff, or reuse. • Focused on formatting, writing, or explanation. • Peripheral use — does not alter how a core deliverable or process is executed. Examples: • “I use AI to fix grammar or reword emails.” • “AI helps me write Excel formulas or explain code.” • “I use AI to summarize meeting notes.” • “AI drafts short internal updates so I can focus elsewhere.” Score 0 — No or Irrelevant Use Definition: No evidence of AI use in a work context or explicitly states they do not use AI. Example: • “I don’t use AI in my work.” Evaluator Checklist When scoring, ignore writing quality and phrasing. Look for evidence of process depth: • Defined trigger or cadence? (explicit or implied) • Repeatable prompt, checklist, or playbook? • AI output feeding another step or tool? • Workflow sequence or ownership changed? • New capability or quality gate introduced? • When evaluating time savings, consider whether the AI use alters how a core deliverable is produced or simply removes a peripheral or administrative step. • Does the AI output directly support a core deliverable (e.g., reports, analysis, client output)? • Cohesion check: Are the tasks connected within a single workflow or purpose? • If the response lists multiple unrelated activities (e.g., “draft emails, brainstorm ideas, summarize reports”), treat it as multiple isolated uses and score at the lower level. Heuristic: • 3 = Embedded + ≥ 2 signals + cohesive workflow or clear transformation of core deliverable • 2 = Embedded + 0–1 signal + cohesive workflow, limited transformation • 1 = Isolated or peripheral task use • 0 = None Scoring Instruction: For your response, ONLY output the single score (0–3). Do not include any explanation. Here is the user’s input: <user_input>meeting summaries and next steps using meeting transcripts</user_input> | T10: {=INDEX('Response Scoring'!$E:$E,MATCH($A10,'Response Scoring'!$A:$A,0))} -> 1 | U10: =$T10/3 -> 0.33333333 | V10: =SUMPRODUCT($C10:$U10,$C$3:$U$3) -> 5.9166667 | W10: ='Raw Data'!$Q6 -> Analyzing presentation slides to evaluate both the visual design and written content for consistency | X10: =IF($W10="Analyzing presentation slides to evaluate both the visual design and written content for consistency",1,0) -> 1 | Y10: ='Raw Data'!$R6 -> Hallucinations (generating false or misleading information), Biases in answers, Data privacy concerns when information is shared with an LLM, Vulnerability to manipulation by bad actors | Z10: =IF(ISNUMBER(SEARCH("Hallucinations",$Y10)),0.25)+IF(ISNUMBER(SEARCH("Biases in answers",$Y10)),0.25,0)+IF(ISNUMBER(SEARCH("Data privacy concerns",$Y10)),0.25)+IF(ISNUMBER(SEARCH("Vulnerability",$Y10)),0.25) -> 1 | AA10: ='Raw Data'!$S6 -> Use secure company instances or enterprise plans when available, Anonymize information by removing identifying details, Verify that the AI tool has SSL/HTTPS encryption before using it | AB10: =IF(OR(ISNUMBER(SEARCH("Avoid using AI tools",$AA10)),ISNUMBER(SEARCH("Verify that the AI tool",$AA10))),0,(IF(ISNUMBER(SEARCH("Anonymize information",$AA10)),0.5)+IF(ISNUMBER(SEARCH("Use secure company instances",$AA10)),0.5))) -> 0 | AC10: ='Raw Data'!$T6 -> Always: I routinely cross-check AI outputs with reliable sources | AD10: =IF($AC10="Never: I typically trust the output as is",0,IF($AC10="Rarely: I only verify if something doesn't sound right",0.33,IF($AC10="Sometimes: I do a quick check against known data or references",0.67,IF($AC10="Always: I routinely cross-check AI outputs with reliable sources",1)))) -> 1 | AE10: ='Raw Data'!$U6 -> Cross-reference key claims with reliable external sources, Verify any calculations or data analysis independently, Use a different AI tool to review and verify the content | AF10: =IF(OR(ISNUMBER(SEARCH("Check if the response uses confident language",$AE10)),ISNUMBER(SEARCH("Look for professional formatting",$AE10))),0,(IF(ISNUMBER(SEARCH("Use a different AI tool",$AE10)),0.25)+IF(ISNUMBER(SEARCH("Cross-reference key claims",$AE10)),0.25)+IF(ISNUMBER(SEARCH("Verify any calculations",$AE10)),0.25)+IF(ISNUMBER(SEARCH("Ask the same AI tool",$AE10)),0.25))) -> 0.75 | AG10: =SUMPRODUCT($W10:$AF10,$W$3:$AF$3) -> 7.5 | AH10: ='Raw Data'!$V6 -> Frequently: I systematically refine prompts until I'm satisfied | AI10: =IF($AH10="Never: I usually just ask once and accept the first response",0,IF($AH10="Rarely: I only tweak the prompt if something feels obviously off",0.33,IF($AH10="Sometimes: I iterate 2-3 times to reach a good result",0.67,IF($AH10="Frequently: I systematically refine prompts until I'm satisfied",1)))) -> 1 | AJ10: ='Raw Data'!$W6 -> You are an employee at a digital media agency. Help me craft an outline for a meeting to discuss the new bid management tool proposal with our management team. The goal of this meeting is to convince the team to get on board with the new tool and outline and justify the costs to use it. We will want to discuss what the tool is and its main use cases, how it will save us time, and the cost and how we will pass it through to clients. | AK10: You are an employee at a digital media agency. Help me craft an outline for a meeting to discuss the new bid management tool proposal with our management team. The goal of this meeting is to convince the team to get on board with the new tool and outline and justify the costs to use it. We will want to discuss what the tool is and its main use cases, how it will save us time, and the cost and how we will pass it through to clients. | AL10: =SUBSTITUTE('Prompt Template'!$C$2,$AJ$5,$AK10) -> You are an expert prompt engineer. Your goal is to evaluate the effectiveness of the prompt below. Less effective prompts are too vague, open-ended, and do not give clear instructions. More effective prompts provide background, clear instructions, and are well structured. Since you are tasked with evaluating true effectiveness of the prompt, you can give scores of 1. This is for an AI Readiness Survey that will assess individuals' proficiency when using AI. <task>Write a prompt asking AI to help you prepare for a work meeting to discuss a new initiative or proposal</task> <prompt>You are an employee at a digital media agency. Help me craft an outline for a meeting to discuss the new bid management tool proposal with our management team. The goal of this meeting is to convince the team to get on board with the new tool and outline and justify the costs to use it. We will want to discuss what the tool is and its main use cases, how it will save us time, and the cost and how we will pass it through to clients.</prompt> A score of 1 prompt example: "Help me prepare for my work meeting" Rate the effectiveness on a scale of 1-5. Only respond with a single number from 1-5. If the person states they do not know how to prompt or their prompt isn't relevant to the task, give them a 0. Use the following criteria: Clarity and Specificity: A good prompt should be clear, specific, and focused. It should provide enough context and detail to guide the AI towards generating a relevant and useful response. Vague, open-ended, or ambiguous prompts make it difficult for the AI to understand the user's intent and can lead to generic or irrelevant outputs. Completeness and Sufficiency: An effective prompt should include all the necessary information and requirements to enable the AI to complete the requested task or answer the question thoroughly. It should anticipate what details the AI might need and proactively provide them. Incomplete prompts that leave out critical facts or constraints will likely result in suboptimal responses that fail to fully address the user's needs. Structure and Organization: A well-crafted prompt should be logically structured and organized. It should break down complex requests into clear steps or components, making it easier for the AI to process and respond to each part systematically. Using formatting techniques like bullet points, numbering, or sectioning can help improve the prompt's clarity and readability. Conciseness and Precision: While a good prompt should be detailed and informative, it should also strive to be as concise and precise as possible. Overly wordy or rambling prompts can obscure the key points and make it harder for the AI to identify the essential requirements. An effective prompt finds the right balance between providing necessary context and avoiding extraneous or redundant information. Here is the user's input: <user_input>You are an employee at a digital media agency. Help me craft an outline for a meeting to discuss the new bid management tool proposal with our management team. The goal of this meeting is to convince the team to get on board with the new tool and outline and justify the costs to use it. We will want to discuss what the tool is and its main use cases, how it will save us time, and the cost and how we will pass it through to clients.</user_input> | AM10: {=INDEX('Response Scoring'!$G:$G,MATCH($A10,'Response Scoring'!$A:$A,0))} -> 4 | AN10: =$AM10/5 -> 0.8 | AO10: ='Raw Data'!$X6 -> You are a market researcher. We would like to create a weekly report about competitive pricing and positioning for our products. I will share a list of products and on a weekly basis please share what changes have been made | AP10: You are a market researcher. We would like to create a weekly report about competitive pricing and positioning for our products. I will share a list of products and on a weekly basis please share what changes have been made | AQ10: =SUBSTITUTE('Prompt Template'!$D$2,$AO$5,$AP10) -> You are an expert evaluator of AI instruction design and CustomGPT configuration. Your goal is to evaluate how effectively a respondent demonstrates their ability to write high-quality AI instructions — the kind used to configure tools like CustomGPTs, Copilot Agents, or Google Gems. The test question asks respondents to: ‘Write instructions for a Custom GPT that would help team members gather competitive intelligence consistently.’ This scenario is used only as a familiar example. Do not evaluate their knowledge of competitive analysis — only the clarity, structure, and effectiveness of their AI instruction design. The competitive intelligence context is a stand-in for any business task. Scoring Overview Rate each response on a scale of 0–5. • 5 = System-ready, strong demonstration of instruction design skill. • 0 = Irrelevant or no response. Focus on instructional quality, not topic expertise or formatting aesthetics. Evaluation Dimensions 1. Structural Design Effective instructions clearly define the inputs, process/steps, and outputs. They show logical sequencing (e.g., research → organize → summarize) and reflect understanding of how AI interprets procedural tasks. 2. Instructional Precision Steps and directives are specific, actionable, and testable by an AI. Avoids vague terms like “analyze competitors” without specifying how to do so or what output is expected. 3. Boundary and Role Definition Strong instructions establish clear context for the AI — defining its role, scope, and constraints. They guide what to include/exclude and how to handle ambiguity or conflicting data. 4. Reusability and Scalability Good instructions can be reused consistently by others. They define consistent formatting, data structures, or repeatable logic that ensures stable results across users or scenarios. 5. Outcome Alignment The best instructions would realistically result in a functioning CustomGPT that performs the intended task accurately and consistently. Weak ones would produce inconsistent or low-quality behavior. Scoring Guidelines Score 5 – System-Ready • Instructions could be pasted directly into a CustomGPT/Copilot and perform effectively. • They demonstrate full system readiness — meaning the AI could execute the intended behavior repeatedly and autonomously, without additional clarification. • Includes: • Defined role and purpose (who/what the AI is). • Clear inputs (what information or user query it receives). • Explicit steps/process (how the AI should perform the task). • Defined outputs (format, tone, or structure of response). • Constraints/quality controls (rules, caveats, or handling instructions). • Demonstrates awareness of how to build a reusable, consistent AI behavior. Example 1: “Role: Competitive Intelligence Assistant. Purpose: Gather structured competitor data from reliable sources. Inputs: Company/product names. Process: 1) Identify top 5 competitors, 2) Extract features/pricing, 3) Summarize differences in a table. Output: Comparative matrix. Guardrails: Only use credible, verifiable sources.” Example 2 (Natural-Language Equivalent): “This CustomGPT should act as our internal research analyst. When given a company or product name, it identifies credible sources like official websites, press releases, and reviews. It compares product features, pricing, and messaging across competitors and summarizes the results in a consistent table and a short written overview with citations. The report should flag any information that seems outdated or unverified and maintain a uniform format for reuse across projects.” Note: Responses may use either explicit headings (Role/Inputs/Process/Output) or fluent natural language. Both are valid if they include equivalent components and could realistically produce consistent, reusable results. Score 4 – Strong but Missing Refinements • Structured and actionable; includes most components (e.g., steps, outputs, and some constraints). • Missing minor refinements such as input specificity, error handling, or reusability mechanisms. • AI could perform the task, but inconsistently. Example 1: “Gather information on competitors’ products, features, and pricing. Summarize in a table. Cite reliable sources.” (Functional but missing full structure or clear constraints.) Example 2: “Create a CustomGPT that collects information from competitor websites, reviews, and announcements. Summarize pricing, features, and positioning in a table, then highlight new updates. Include dates and brief notes on source credibility.” (Strong structure, but lacks clear inputs and reusability framing.) Score 3 – Structured but Shallow • Provides a reasonable outline or list of tasks but lacks cohesion or precision. • Mentions the goal but misses how to operationalize it in a repeatable, system-friendly way. • AI would need to infer too much to work reliably. Example 1: “Research competitors and summarize key findings about pricing and positioning.” (Has intent but lacks sequencing or defined outputs.) Example 2: “The GPT should find information about our competitors’ pricing and products, summarize what’s different, and give a short write-up each week.” (Clear intent, but underspecified logic — reads more like a to-do list than executable instructions.) Score 2 – Fragmented or Vague • Mentions competitive research but provides minimal or disconnected guidance. • Steps are generic, unsequenced, or too ambiguous to drive consistent AI behavior. Example elements: “Look up competitors and gather details.” “Find competitor info and summarize.” (Too vague to translate into functioning instructions.) Score 1 – Minimal or Misunderstood • Shows fundamental misunderstanding of AI instruction design. • Generic, incomplete, or irrelevant content that couldn’t guide an AI system at all. Example elements: “Just tell GPT to look up competitors.” “I’d ask it to find info about other companies.” “Use ChatGPT to do competitive research for us.” “Help me understand what our competitors do better.” “Search online for competitor products and summarize.” (Shows surface-level familiarity with AI but no system thinking.) Score 0 – No Response or Irrelevant • Empty, “I don’t know,” or unrelated answer. Example elements: “Not sure what to put here.” “I don’t use GPT for that.” “I’d rather do that myself.” “No idea how to write that.” (Shows confusion or complete lack of task understanding.) Evaluator Checklist When scoring, focus on functional design quality, not formatting or topic expertise. Ask yourself: • Does the response clearly define the AI’s role, inputs, process, and outputs? • Are instructions specific, sequenced, and testable? • Do they include boundaries or quality controls? • Could the AI perform the task consistently and autonomously if these instructions were used? • Is the response written at a configuration level (system prompt) rather than a one-off user command? Heuristic: • 5 = Fully structured, system-ready, reusable. • 4 = Strong, nearly system-ready, missing refinements. • 3 = Structured but shallow. • 2 = Fragmented or vague. • 1 = Minimal or misunderstood. • 0 = None/irrelevant. Scoring Instruction: For your response, ONLY output the single score (0–5). Do not include any explanation. Here is the user’s input: <user_input>You are a market researcher. We would like to create a weekly report about competitive pricing and positioning for our products. I will share a list of products and on a weekly basis please share what changes have been made</user_input> | AR10: {=INDEX('Response Scoring'!$I:$I,MATCH($A10,'Response Scoring'!$A:$A,0))} -> 2 | AS10: =$AR10/5 -> 0.4 | AT10: =SUMPRODUCT($AH10:$AS10,$AH$3:$AS$3) -> 6.3 | AU10: =($V10*$AW$4)+($AG10*$AW$3)+($AT10*$AW$2) -> 31.933333 | AV10: =$AU10*2 -> 63.866667 | AW10: =IF($AV10>=80,"AI Expert",IF($AV10>=60,"AI Practitioner",IF(AND($AV10<60,$AV10>=25),"AI Experimenter",IF(AND($AV10<25,$AV10>=0),"AI Novice")))) -> AI Practitioner | AX10: ='Raw Data'!Y6 -> ChatGPT, Claude | AY10: ='Raw Data'!Z6 -> FALSE | AZ10: ='Raw Data'!AA6 -> Yes, we have a formal AI strategy | BA10: ='Raw Data'!AB6 -> Tools exist with clear access process | BB10: ='Raw Data'!AC6 -> Microsoft Copilot, ChatGPT for Enterprise or Teams, Google Gemini, Claude for Enterprise or Teams | BC10: ='Raw Data'!AD6 -> Satisfied - meets my needs well | BD10: ='Raw Data'!AE6 -> Clear, enforced policies that directly implement our AI strategy | BE10: ='Raw Data'!AF6 -> We have a clear, actionable policy that effectively guides AI use | ... BR10: ='Raw Data'!AS6 -> Significant improvement - noticeably better productivity and outcomes | BS10: ='Raw Data'!C6 -> 0 | BT10: ='Raw Data'!D6 -> 0 | BU10: ='Raw Data'!E6 -> Retail Media | BV10: ='Raw Data'!F6 -> VP+ | BW10: ='Raw Data'!G6 -> 0 | BX10: ='Raw Data'!H6 -> 0 | BY10: ='Raw Data'!I6 -> 0 | BZ10: ='Raw Data'!J6 -> 0 | CA10: ='Raw Data'!AT6 -> Concerns about environmental impact, too generic answers, privacy, and impeding on free thought | CB10: ='Raw Data'!AU6 -> I am using it | CC10: ='Raw Data'!AV6 -> meeting summaries, proposal outlines, email cleanup | CD10: ='Raw Data'!AW6 -> make more tools available with paid versions e.g. claude | CE10: ='Raw Data'!AX6 -> budget pacing, reporting | CF10: ='Raw Data'!AY6 -> category research to maintain competitive edge | CG10: ='Raw Data'!AZ6 -> Yes
A11: ='Raw Data'!$A7 -> 5 | C11: ='Raw Data'!$K7 -> Several times a week | D11: =IF($C11="Never or rarely",0,IF($C11="A few times a month",0.25,IF($C11="Weekly",0.5,IF($C11="Several times a week",0.75,IF($C11="Daily",1))))) -> 0.75 | E11: ='Raw Data'!$L7 -> Getting quick answers to specific questions or looking up information, Editing or improving text I've already written (emails, documents, presentations), Analyzing data or documents to extract insights or summaries, Brainstorming ideas, testing concepts, or getting feedback on my thinking | F11: =IF(ISNUMBER(SEARCH("I don't use AI for work",$E11)),0)+IF(ISNUMBER(SEARCH("Getting quick answers",$E11)),1,0)+IF(ISNUMBER(SEARCH("Editing text",$E11)),1,0)+IF(ISNUMBER(SEARCH("Writing/debugging code",$E11)),1,0)+IF(ISNUMBER(SEARCH("Creating first drafts",$E11)),2,0)+IF(ISNUMBER(SEARCH("Analyzing data/documents",$E11)),2,0)+IF(ISNUMBER(SEARCH("Brainstorming/testing concepts",$E11)),2,0)+IF(ISNUMBER(SEARCH("Building custom workflows",$E11)),3,0)+IF(ISNUMBER(SEARCH("Prototyping solutions",$E11)),3,0) -> 1 | G11: =$F11/3 -> 0.33333333 | H11: ='Raw Data'!M7 -> I create fresh prompts each time I use AI | I11: =IF($H11="I don't use AI for work",0,IF($H11="I create fresh prompts each time I use AI",0.25,IF($H11="I maintain a library of prompts that I reuse frequently",0.5,IF($H11="I've built custom AI tools (CustomGPTs, Copilot Agents, Google Gems, Claude Projects) for repetitive tasks",0.75,IF($H11="I've created workflows that connect AI with other systems (Slack, Salesforce, email) using integrations or code",1))))) -> 0.25 | J11: ='Raw Data'!$N7 -> Create a systematic process where AI handles data analysis and summary generation consistently | K11: =IF($J11="Ask AI to write the summary after you've analyzed all the data",0.33,IF($J11="Use AI to help analyze each data source, then compile results manually",0.67,IF($J11="Create a systematic process where AI handles data analysis and summary generation consistently",1,IF($J11="I wouldn’t use AI for this task",0)))) -> 1 | L11: ='Raw Data'!$O7 -> Would have AI do all my research for me and summarize key facts/points I need. Then I'd ask it to use that output to create a first draft presentation for senior stakeholders | M11: Would have AI do all my research for me and summarize key facts/points I need. Then I'd ask it to use that output to create a first draft presentation for senior stakeholders | N11: =SUBSTITUTE('Prompt Template'!$A$2,$L$5,$M11) -> You are an expert evaluator of AI strategic thinking and workflow integration. Your goal is to evaluate how effectively survey respondents demonstrate strategic AI application based on their response to the question: “You have one week to create an important presentation for senior stakeholders on an unfamiliar topic. How would you use AI in this process?” Evaluate each response holistically across three key areas: Workflow Integration: Effective responses demonstrate systematic thinking by identifying multiple stages of the presentation process where AI can add value (research, analysis, content creation, structure, review, etc.). They show understanding that complex projects benefit from AI integration at various points rather than just using AI for one isolated task. Strategic Application: Strong responses show context-aware AI usage that specifically addresses the unique challenges of this scenario — leveraging AI to quickly understand an unfamiliar topic, tailoring content for senior stakeholders, and managing time constraints effectively. They go beyond generic AI applications to show thoughtful consideration of the specific requirements. Practical Execution: Quality responses demonstrate concrete understanding of how AI tools actually work by providing specific, actionable approaches rather than vague descriptions. They show familiarity with AI capabilities and limitations, and describe realistic implementation steps. Scoring Guidelines Score 3 — Strong strategic thinking • Demonstrates comprehensive AI integration across most or all key workflow stages (e.g., research, structure, content creation, context tailoring for senior stakeholders, review), combined with clear scenario awareness and practical execution. • Responses do not need to mention every single stage explicitly; concise or list-style answers can still score a 3 if they show a strategically complete, end-to-end approach that addresses the scenario’s unique challenges (unfamiliar topic, senior stakeholders, tight timelines). • Omitting one stage (e.g., review) does not disqualify a response if the overall strategy is robust and well-adapted. • Both structured and concise list-style responses are valid. Examples: • “Research topic comprehensively, analyze stakeholder needs, create presentation framework, develop content, review for clarity.” • “Use AI throughout the process — from initial research to final presentation polish — focusing on what senior stakeholders care about most.” • “I would use AI to research the topic, understand key stakeholder concerns, create a logical flow, and draft compelling content for senior leadership within the time constraint.” • “Scan unfamiliar topic, outline slides, tailor framing for executives, draft key content, fact-check and polish.” (Concise list-style example demonstrating full coverage) • “Research unfamiliar topic, structure the deck, tailor for executives, draft content.” (Covers most strategic stages, omits review but is still strategically comprehensive) Score 2 — Moderate strategic thinking • Demonstrates partial but not comprehensive coverage of the key strategic dimensions. • Typically covers two to three workflow stages (e.g., structure + content + some context) but omits one or more major elements such as research, scenario adaptation, or review. • May show good workflow integration but limited scenario context, or vice versa. • Responses may be clear and practical but reflect a mid-level strategic approach rather than end-to-end planning. Examples: • “Use AI to quickly understand the topic, then create an outline and draft the presentation content.” • “Research phase, analysis phase, content creation phase, review phase.” • “Use AI to help research industry trends and create slides tailored for executives.” • “Draft speaker notes, executive framing, summarize key sources.” (Covers content, some research, and context but lacks structure/review) • “10 slide structure, add citations, executive framing.” (Structure, review, context but no research/content creation) Score 1 — Limited strategic thinking • Shows basic or single AI application with little reference to workflow complexity or scenario context. • Generic AI usage that could apply to any presentation task. Examples: • “Use AI to research the topic and create slides.” • “ChatGPT for research, help with structure.” • “Research, writing, editing.” • “Ask AI to help me understand the topic.” Score 0 — No relevant response • No answer, states they wouldn’t use AI, or provides irrelevant content. Special Guidance on Format and Brevity • Do not penalize for response format or brevity. • Evaluate list-style or terse responses based on substance, not phrasing. • A concise response that clearly addresses all key strategic dimensions can score a 3. • Responses that address only part of the workflow or omit key scenario considerations should score a 2, even if clearly written. • Brevity alone should not lower a score. Output: For your response, ONLY output the single score (0–3). Do not include any explanation. Here is the user’s input: <user_input>Would have AI do all my research for me and summarize key facts/points I need. Then I'd ask it to use that output to create a first draft presentation for senior stakeholders</user_input> | O11: {=INDEX('Response Scoring'!$C:$C,MATCH($A11,'Response Scoring'!$A:$A,0))} -> 2 | P11: =$O11/3 -> 0.66666667 | Q11: ='Raw Data'!$P7 -> Research assistant and to understand key points from earnings calls/senior executive interviews | R11: Research assistant and to understand key points from earnings calls/senior executive interviews | S11: =SUBSTITUTE('Prompt Template'!$B$2,$Q$5,$R11) -> You are an expert evaluator of practical AI value creation in work contexts. Your goal is to evaluate how effectively survey respondents demonstrate valuable AI usage based on their response to the question: ‘What is the most useful or valuable way you are using AI in your work?’ Valuable AI usage enables higher speed and/or quality work outputs with measurable impact on workflow pain points or business objectives. Strong responses demonstrate AI integration that transforms how core work gets done, rather than providing minor convenience. Score 3 — Workflow Redesign / Integrated Use (Human-in-the-Loop or Automated) Definition: Demonstrates strategic, repeatable AI integration that has redesigned or materially enhanced how the respondent performs a core part of their job. AI is consistently embedded in their workflow, creates new capabilities, or systematically improves downstream outputs or decisions. Transformation may involve automation or a human-in-the-loop redesign. Transformation requires more than saving time on peripheral tasks. The AI use must alter how a core deliverable is created, reviewed, or decided on — not just replace small administrative tasks within it. Time savings are only valid when they result from a redesigned or automated workflow step that affects downstream outputs or team decision-making. Observable Signals (any two or more): • Defined trigger or cadence (e.g., “after every client call,” “weekly review,” or implied repetition such as “each week,” “after calls,” or “whenever new data is ready”). • Template, checklist, or structured prompt used consistently. • AI output feeds directly into another step or tool (e.g., CRM, backlog, report). • AI introduces a new step, quality gate, or sequencing change. • AI automation replaces a manual stage and enables higher-value analytical or decision-making work. • Concise responses still qualify if they clearly imply repeatable, embedded use. Contrast Examples: Meeting Notes → Follow-up • (3) “After each client call, I run a prompt that tags actions by owner and priority, then imports them into our tracker.” • (2) “After calls, I paste notes into AI to group actions by owner and due date.” • (1) “I use AI to summarize meeting notes.” Customer Feedback → Insights • (3) “Each week, AI clusters customer comments, maps them to product areas, and ranks issues I review for roadmap planning.” • (2) “AI helps cluster customer comments into themes for my monthly report.” • (1) “I ask AI to summarize customer feedback.” Data Analysis / SQL • (3) “AI generates and validates queries, produces comparison tables, and highlights anomalies I review in reports.” • (2) “AI drafts SQL queries and interprets results faster than manual work.” • (1) “AI explains SQL when I’m stuck.” Proposal / Report Writing • (3) “I use a repeatable AI template that turns briefs into full drafts with rationale and risks sections, which I refine for delivery.” • (2) “AI drafts first sections of my proposals based on my outline.” • (1) “AI helps me improve grammar and phrasing.” Competitive Research • (3) “AI normalizes competitor data, flags gaps, and generates a positioning summary for our quarterly review.” • (2) “AI extracts pricing and features into a summary table before I write my report.” • (1) “AI summarizes competitor websites.” Score 2 — Process Enhancement / Embedded Use Definition: Shows repeatable, meaningful AI use within an existing process that improves speed, quality, or consistency. AI use is consistent and relevant to core responsibilities, but the workflow design and logic remain the same. May include structured use for efficiency, but does not fundamentally change how deliverables are produced or how information flows. Observable Signals (any one): • Clear efficiency, clarity, or organization benefit. • Consistent use within a step of a recurring workflow. • Described as part of normal work, not one-off. • Partial structure or templates used manually. Examples: • “I use AI to organize survey responses and find key themes before my analysis.” • “AI drafts report sections to help me start faster.” • “I use AI to group meeting notes by owner for easier follow-up.” • “AI summarizes recurring reports or data updates to save time, but outputs are reviewed or reformatted manually.” Score 1 — Task Assistance / Surface-Level Use Definition: Describes episodic or one-step assistance focused on convenience or small efficiency gains. AI is not embedded in a structured workflow or used consistently. Includes short, isolated tasks that do not influence how other work is performed. Observable Signals: • Task-specific or one-off. • No cadence, handoff, or reuse. • Focused on formatting, writing, or explanation. • Peripheral use — does not alter how a core deliverable or process is executed. Examples: • “I use AI to fix grammar or reword emails.” • “AI helps me write Excel formulas or explain code.” • “I use AI to summarize meeting notes.” • “AI drafts short internal updates so I can focus elsewhere.” Score 0 — No or Irrelevant Use Definition: No evidence of AI use in a work context or explicitly states they do not use AI. Example: • “I don’t use AI in my work.” Evaluator Checklist When scoring, ignore writing quality and phrasing. Look for evidence of process depth: • Defined trigger or cadence? (explicit or implied) • Repeatable prompt, checklist, or playbook? • AI output feeding another step or tool? • Workflow sequence or ownership changed? • New capability or quality gate introduced? • When evaluating time savings, consider whether the AI use alters how a core deliverable is produced or simply removes a peripheral or administrative step. • Does the AI output directly support a core deliverable (e.g., reports, analysis, client output)? • Cohesion check: Are the tasks connected within a single workflow or purpose? • If the response lists multiple unrelated activities (e.g., “draft emails, brainstorm ideas, summarize reports”), treat it as multiple isolated uses and score at the lower level. Heuristic: • 3 = Embedded + ≥ 2 signals + cohesive workflow or clear transformation of core deliverable • 2 = Embedded + 0–1 signal + cohesive workflow, limited transformation • 1 = Isolated or peripheral task use • 0 = None Scoring Instruction: For your response, ONLY output the single score (0–3). Do not include any explanation. Here is the user’s input: <user_input>Research assistant and to understand key points from earnings calls/senior executive interviews</user_input> | T11: {=INDEX('Response Scoring'!$E:$E,MATCH($A11,'Response Scoring'!$A:$A,0))} -> 2 | U11: =$T11/3 -> 0.66666667 | V11: =SUMPRODUCT($C11:$U11,$C$3:$U$3) -> 6.125 | W11: ='Raw Data'!$Q7 -> Analyzing presentation slides to evaluate both the visual design and written content for consistency | X11: =IF($W11="Analyzing presentation slides to evaluate both the visual design and written content for consistency",1,0) -> 1 | Y11: ='Raw Data'!$R7 -> Hallucinations (generating false or misleading information) | Z11: =IF(ISNUMBER(SEARCH("Hallucinations",$Y11)),0.25)+IF(ISNUMBER(SEARCH("Biases in answers",$Y11)),0.25,0)+IF(ISNUMBER(SEARCH("Data privacy concerns",$Y11)),0.25)+IF(ISNUMBER(SEARCH("Vulnerability",$Y11)),0.25) -> 0.25 | AA11: ='Raw Data'!$S7 -> Anonymize information by removing identifying details, Use secure company instances or enterprise plans when available | AB11: =IF(OR(ISNUMBER(SEARCH("Avoid using AI tools",$AA11)),ISNUMBER(SEARCH("Verify that the AI tool",$AA11))),0,(IF(ISNUMBER(SEARCH("Anonymize information",$AA11)),0.5)+IF(ISNUMBER(SEARCH("Use secure company instances",$AA11)),0.5))) -> 1 | AC11: ='Raw Data'!$T7 -> Sometimes: I do a quick check against known data or references | AD11: =IF($AC11="Never: I typically trust the output as is",0,IF($AC11="Rarely: I only verify if something doesn't sound right",0.33,IF($AC11="Sometimes: I do a quick check against known data or references",0.67,IF($AC11="Always: I routinely cross-check AI outputs with reliable sources",1)))) -> 0.67 | AE11: ='Raw Data'!$U7 -> Use a different AI tool to review and verify the content, Cross-reference key claims with reliable external sources, Verify any calculations or data analysis independently | AF11: =IF(OR(ISNUMBER(SEARCH("Check if the response uses confident language",$AE11)),ISNUMBER(SEARCH("Look for professional formatting",$AE11))),0,(IF(ISNUMBER(SEARCH("Use a different AI tool",$AE11)),0.25)+IF(ISNUMBER(SEARCH("Cross-reference key claims",$AE11)),0.25)+IF(ISNUMBER(SEARCH("Verify any calculations",$AE11)),0.25)+IF(ISNUMBER(SEARCH("Ask the same AI tool",$AE11)),0.25))) -> 0.75 | AG11: =SUMPRODUCT($W11:$AF11,$W$3:$AF$3) -> 7.34 | AH11: ='Raw Data'!$V7 -> Frequently: I systematically refine prompts until I'm satisfied | AI11: =IF($AH11="Never: I usually just ask once and accept the first response",0,IF($AH11="Rarely: I only tweak the prompt if something feels obviously off",0.33,IF($AH11="Sometimes: I iterate 2-3 times to reach a good result",0.67,IF($AH11="Frequently: I systematically refine prompts until I'm satisfied",1)))) -> 1 | AJ11: ='Raw Data'!$W7 -> Hello. I am meeting with my colleagues to discuss initiative ABC and need your help to best prepare me for the meeting. Can you please review these documents and any additional resources you find that discuss ABC and provide me with a summary of your key findings on the topic. | AK11: Hello. I am meeting with my colleagues to discuss initiative ABC and need your help to best prepare me for the meeting. Can you please review these documents and any additional resources you find that discuss ABC and provide me with a summary of your key findings on the topic. | AL11: =SUBSTITUTE('Prompt Template'!$C$2,$AJ$5,$AK11) -> You are an expert prompt engineer. Your goal is to evaluate the effectiveness of the prompt below. Less effective prompts are too vague, open-ended, and do not give clear instructions. More effective prompts provide background, clear instructions, and are well structured. Since you are tasked with evaluating true effectiveness of the prompt, you can give scores of 1. This is for an AI Readiness Survey that will assess individuals' proficiency when using AI. <task>Write a prompt asking AI to help you prepare for a work meeting to discuss a new initiative or proposal</task> <prompt>Hello. I am meeting with my colleagues to discuss initiative ABC and need your help to best prepare me for the meeting. Can you please review these documents and any additional resources you find that discuss ABC and provide me with a summary of your key findings on the topic.</prompt> A score of 1 prompt example: "Help me prepare for my work meeting" Rate the effectiveness on a scale of 1-5. Only respond with a single number from 1-5. If the person states they do not know how to prompt or their prompt isn't relevant to the task, give them a 0. Use the following criteria: Clarity and Specificity: A good prompt should be clear, specific, and focused. It should provide enough context and detail to guide the AI towards generating a relevant and useful response. Vague, open-ended, or ambiguous prompts make it difficult for the AI to understand the user's intent and can lead to generic or irrelevant outputs. Completeness and Sufficiency: An effective prompt should include all the necessary information and requirements to enable the AI to complete the requested task or answer the question thoroughly. It should anticipate what details the AI might need and proactively provide them. Incomplete prompts that leave out critical facts or constraints will likely result in suboptimal responses that fail to fully address the user's needs. Structure and Organization: A well-crafted prompt should be logically structured and organized. It should break down complex requests into clear steps or components, making it easier for the AI to process and respond to each part systematically. Using formatting techniques like bullet points, numbering, or sectioning can help improve the prompt's clarity and readability. Conciseness and Precision: While a good prompt should be detailed and informative, it should also strive to be as concise and precise as possible. Overly wordy or rambling prompts can obscure the key points and make it harder for the AI to identify the essential requirements. An effective prompt finds the right balance between providing necessary context and avoiding extraneous or redundant information. Here is the user's input: <user_input>Hello. I am meeting with my colleagues to discuss initiative ABC and need your help to best prepare me for the meeting. Can you please review these documents and any additional resources you find that discuss ABC and provide me with a summary of your key findings on the topic.</user_input> | AM11: {=INDEX('Response Scoring'!$G:$G,MATCH($A11,'Response Scoring'!$A:$A,0))} -> 2 | AN11: =$AM11/5 -> 0.4 | AO11: ='Raw Data'!$X7 -> Hello. Please create a custom script that can be reused to source the latest information on the following competitors: Competitor A, Competitor B, Competitor C. The specific information I'd like sourced is recent product launches, changes to pricing and changes to how the product is positioned to the market. I anticipate getting an update on this information on a weekly basis. | AP11: Hello. Please create a custom script that can be reused to source the latest information on the following competitors: Competitor A, Competitor B, Competitor C. The specific information I'd like sourced is recent product launches, changes to pricing and changes to how the product is positioned to the market. I anticipate getting an update on this information on a weekly basis. | AQ11: =SUBSTITUTE('Prompt Template'!$D$2,$AO$5,$AP11) -> You are an expert evaluator of AI instruction design and CustomGPT configuration. Your goal is to evaluate how effectively a respondent demonstrates their ability to write high-quality AI instructions — the kind used to configure tools like CustomGPTs, Copilot Agents, or Google Gems. The test question asks respondents to: ‘Write instructions for a Custom GPT that would help team members gather competitive intelligence consistently.’ This scenario is used only as a familiar example. Do not evaluate their knowledge of competitive analysis — only the clarity, structure, and effectiveness of their AI instruction design. The competitive intelligence context is a stand-in for any business task. Scoring Overview Rate each response on a scale of 0–5. • 5 = System-ready, strong demonstration of instruction design skill. • 0 = Irrelevant or no response. Focus on instructional quality, not topic expertise or formatting aesthetics. Evaluation Dimensions 1. Structural Design Effective instructions clearly define the inputs, process/steps, and outputs. They show logical sequencing (e.g., research → organize → summarize) and reflect understanding of how AI interprets procedural tasks. 2. Instructional Precision Steps and directives are specific, actionable, and testable by an AI. Avoids vague terms like “analyze competitors” without specifying how to do so or what output is expected. 3. Boundary and Role Definition Strong instructions establish clear context for the AI — defining its role, scope, and constraints. They guide what to include/exclude and how to handle ambiguity or conflicting data. 4. Reusability and Scalability Good instructions can be reused consistently by others. They define consistent formatting, data structures, or repeatable logic that ensures stable results across users or scenarios. 5. Outcome Alignment The best instructions would realistically result in a functioning CustomGPT that performs the intended task accurately and consistently. Weak ones would produce inconsistent or low-quality behavior. Scoring Guidelines Score 5 – System-Ready • Instructions could be pasted directly into a CustomGPT/Copilot and perform effectively. • They demonstrate full system readiness — meaning the AI could execute the intended behavior repeatedly and autonomously, without additional clarification. • Includes: • Defined role and purpose (who/what the AI is). • Clear inputs (what information or user query it receives). • Explicit steps/process (how the AI should perform the task). • Defined outputs (format, tone, or structure of response). • Constraints/quality controls (rules, caveats, or handling instructions). • Demonstrates awareness of how to build a reusable, consistent AI behavior. Example 1: “Role: Competitive Intelligence Assistant. Purpose: Gather structured competitor data from reliable sources. Inputs: Company/product names. Process: 1) Identify top 5 competitors, 2) Extract features/pricing, 3) Summarize differences in a table. Output: Comparative matrix. Guardrails: Only use credible, verifiable sources.” Example 2 (Natural-Language Equivalent): “This CustomGPT should act as our internal research analyst. When given a company or product name, it identifies credible sources like official websites, press releases, and reviews. It compares product features, pricing, and messaging across competitors and summarizes the results in a consistent table and a short written overview with citations. The report should flag any information that seems outdated or unverified and maintain a uniform format for reuse across projects.” Note: Responses may use either explicit headings (Role/Inputs/Process/Output) or fluent natural language. Both are valid if they include equivalent components and could realistically produce consistent, reusable results. Score 4 – Strong but Missing Refinements • Structured and actionable; includes most components (e.g., steps, outputs, and some constraints). • Missing minor refinements such as input specificity, error handling, or reusability mechanisms. • AI could perform the task, but inconsistently. Example 1: “Gather information on competitors’ products, features, and pricing. Summarize in a table. Cite reliable sources.” (Functional but missing full structure or clear constraints.) Example 2: “Create a CustomGPT that collects information from competitor websites, reviews, and announcements. Summarize pricing, features, and positioning in a table, then highlight new updates. Include dates and brief notes on source credibility.” (Strong structure, but lacks clear inputs and reusability framing.) Score 3 – Structured but Shallow • Provides a reasonable outline or list of tasks but lacks cohesion or precision. • Mentions the goal but misses how to operationalize it in a repeatable, system-friendly way. • AI would need to infer too much to work reliably. Example 1: “Research competitors and summarize key findings about pricing and positioning.” (Has intent but lacks sequencing or defined outputs.) Example 2: “The GPT should find information about our competitors’ pricing and products, summarize what’s different, and give a short write-up each week.” (Clear intent, but underspecified logic — reads more like a to-do list than executable instructions.) Score 2 – Fragmented or Vague • Mentions competitive research but provides minimal or disconnected guidance. • Steps are generic, unsequenced, or too ambiguous to drive consistent AI behavior. Example elements: “Look up competitors and gather details.” “Find competitor info and summarize.” (Too vague to translate into functioning instructions.) Score 1 – Minimal or Misunderstood • Shows fundamental misunderstanding of AI instruction design. • Generic, incomplete, or irrelevant content that couldn’t guide an AI system at all. Example elements: “Just tell GPT to look up competitors.” “I’d ask it to find info about other companies.” “Use ChatGPT to do competitive research for us.” “Help me understand what our competitors do better.” “Search online for competitor products and summarize.” (Shows surface-level familiarity with AI but no system thinking.) Score 0 – No Response or Irrelevant • Empty, “I don’t know,” or unrelated answer. Example elements: “Not sure what to put here.” “I don’t use GPT for that.” “I’d rather do that myself.” “No idea how to write that.” (Shows confusion or complete lack of task understanding.) Evaluator Checklist When scoring, focus on functional design quality, not formatting or topic expertise. Ask yourself: • Does the response clearly define the AI’s role, inputs, process, and outputs? • Are instructions specific, sequenced, and testable? • Do they include boundaries or quality controls? • Could the AI perform the task consistently and autonomously if these instructions were used? • Is the response written at a configuration level (system prompt) rather than a one-off user command? Heuristic: • 5 = Fully structured, system-ready, reusable. • 4 = Strong, nearly system-ready, missing refinements. • 3 = Structured but shallow. • 2 = Fragmented or vague. • 1 = Minimal or misunderstood. • 0 = None/irrelevant. Scoring Instruction: For your response, ONLY output the single score (0–5). Do not include any explanation. Here is the user’s input: <user_input>Hello. Please create a custom script that can be reused to source the latest information on the following competitors: Competitor A, Competitor B, Competitor C. The specific information I'd like sourced is recent product launches, changes to pricing and changes to how the product is positioned to the market. I anticipate getting an update on this information on a weekly basis.</user_input> | AR11: {=INDEX('Response Scoring'!$I:$I,MATCH($A11,'Response Scoring'!$A:$A,0))} -> 2 | AS11: =$AR11/5 -> 0.4 | AT11: =SUMPRODUCT($AH11:$AS11,$AH$3:$AS$3) -> 4.9 | AU11: =($V11*$AW$4)+($AG11*$AW$3)+($AT11*$AW$2) -> 29.39 | AV11: =$AU11*2 -> 58.78 | AW11: =IF($AV11>=80,"AI Expert",IF($AV11>=60,"AI Practitioner",IF(AND($AV11<60,$AV11>=25),"AI Experimenter",IF(AND($AV11<25,$AV11>=0),"AI Novice")))) -> AI Experimenter | AX11: ='Raw Data'!Y7 -> ChatGPT, Google Gemini, Microsoft Copilot, Perplexity.ai, xAI's Grok | AY11: ='Raw Data'!Z7 -> TRUE | AZ11: ='Raw Data'!AA7 -> We're currently developing an AI strategy | BA11: ='Raw Data'!AB7 -> Tools exist with clear access process | BB11: ='Raw Data'!AC7 -> Microsoft Copilot, A homegrown solution | BC11: ='Raw Data'!AD7 -> Satisfied - meets my needs well | BD11: ='Raw Data'!AE7 -> Clear, enforced policies that directly implement our AI strategy | BE11: ='Raw Data'!AF7 -> We have a clear, actionable policy that effectively guides AI use | ... BR11: ='Raw Data'!AS7 -> Significant improvement - noticeably better productivity and outcomes | BS11: ='Raw Data'!C7 -> 0 | BT11: ='Raw Data'!D7 -> 0 | BU11: ='Raw Data'!E7 -> Marketing/Biz Dev | BV11: ='Raw Data'!F7 -> VP+ | BW11: ='Raw Data'!G7 -> 0 | BX11: ='Raw Data'!H7 -> 0 | BY11: ='Raw Data'!I7 -> 0 | BZ11: ='Raw Data'!J7 -> 0 | CA11: ='Raw Data'!AT7 -> At my level there are less routine lower level tasks that I am consistently doing on a weekly/monthly basis | CB11: ='Raw Data'!AU7 -> Faster and more accurate research assistant | CC11: ='Raw Data'!AV7 -> Research assistant across category, competitor, or new business prospect. I'm using a combination of ChatGPT, Perplexity and Gemini | CD11: ='Raw Data'!AW7 -> Nothing | CE11: ='Raw Data'!AX7 -> Monthly reports. I can review time savings in our time tracking software to understand how much less time on average is going towards reporting | CF11: ='Raw Data'!AY7 -> Opportunities to upsell my clients and drive organic growth for the agency | CG11: ='Raw Data'!AZ7 -> Yes
